Workbook

Sheet rajal cluster icd10_web20260922
A1: Cluster Type | B1: Cluster Code | C1: Cluster Description | D1: ICD-10 Code | E1: ICD-10 Description
A2: PDC | B2: D11AA | C2: Nervous system infection | D2: ="A06.6" -> A06.6 | E2: Amoebic brain abscess
A3: PDC | B3: D11AA | C3: Nervous system infection | D3: ="A17.0" -> A17.0 | E3: Tuberculous meningitis
A4: PDC | B4: D11AA | C4: Nervous system infection | D4: ="A17.1" -> A17.1 | E4: Meningeal tuberculoma
A5: PDC | B5: D11AA | C5: Nervous system infection | D5: ="A17.8" -> A17.8 | E5: Other tuberculosis of nervous system
A6: PDC | B6: D11AA | C6: Nervous system infection | D6: ="A17.9" -> A17.9 | E6: Tuberculosis of nervous system unspecified
A7: PDC | B7: D11AA | C7: Nervous system infection | D7: ="A32.1" -> A32.1 | E7: Listerial meningitis and meningoencephalitis
A8: PDC | B8: D11AA | C8: Nervous system infection | D8: ="A39.0" -> A39.0 | E8: Meningococcal meningitis
A9: PDC | B9: D11AA | C9: Nervous system infection | D9: ="A50.4" -> A50.4 | E9: Late congenital neurosyphilis [juvenile neurosyphilis]
A10: PDC | B10: D11AA | C10: Nervous system infection | D10: ="A52.1" -> A52.1 | E10: Symptomatic neurosyphilis
A11: PDC | B11: D11AA | C11: Nervous system infection | D11: ="A52.2" -> A52.2 | E11: Asymptomatic neurosyphilis
A12: PDC | B12: D11AA | C12: Nervous system infection | D12: ="A52.3" -> A52.3 | E12: Neurosyphilis, unspecified
A13: PDC | B13: D11AA | C13: Nervous system infection | D13: ="A80.0" -> A80.0 | E13: Acute paralytic poliomyelitis, vaccine-associated
A14: PDC | B14: D11AA | C14: Nervous system infection | D14: ="A80.1" -> A80.1 | E14: Acute paralytic poliomyelitis, wild virus, imported
A15: PDC | B15: D11AA | C15: Nervous system infection | D15: ="A80.2" -> A80.2 | E15: Acute paralytic poliomyelitis, wild virus, indigenous
A16: PDC | B16: D11AA | C16: Nervous system infection | D16: ="A80.3" -> A80.3 | E16: Acute paralytic poliomyelitis, other and unspecified
A17: PDC | B17: D11AA | C17: Nervous system infection | D17: ="A80.9" -> A80.9 | E17: Acute poliomyelitis, unspecified
A18: PDC | B18: D11AA | C18: Nervous system infection | D18: ="A81.0" -> A81.0 | E18: Creutzfeldt-jakob disease
A19: PDC | B19: D11AA | C19: Nervous system infection | D19: ="A81.1" -> A81.1 | E19: Subacute sclerosing panencephalitis
A20: PDC | B20: D11AA | C20: Nervous system infection | D20: ="A81.2" -> A81.2 | E20: Progressive multifocal leukoencephalopathy
A21: PDC | B21: D11AA | C21: Nervous system infection | D21: ="A81.8" -> A81.8 | E21: Other atypical virus infections of central nervous system
A22: PDC | B22: D11AA | C22: Nervous system infection | D22: ="A81.9" -> A81.9 | E22: Atypical virus infection of central nervous system, unspecified
A23: PDC | B23: D11AA | C23: Nervous system infection | D23: ="A82.0" -> A82.0 | E23: Sylvatic rabies
A24: PDC | B24: D11AA | C24: Nervous system infection | D24: ="A82.1" -> A82.1 | E24: Urban rabies
A25: PDC | B25: D11AA | C25: Nervous system infection | D25: ="A82.9" -> A82.9 | E25: Rabies, unspecified
A26: PDC | B26: D11AA | C26: Nervous system infection | D26: ="A83.0" -> A83.0 | E26: Japanese encephalitis
A27: PDC | B27: D11AA | C27: Nervous system infection | D27: ="A83.1" -> A83.1 | E27: Western equine encephalitis
A28: PDC | B28: D11AA | C28: Nervous system infection | D28: ="A83.2" -> A83.2 | E28: Eastern equine encephalitis
A29: PDC | B29: D11AA | C29: Nervous system infection | D29: ="A83.3" -> A83.3 | E29: St louis encephalitis
A30: PDC | B30: D11AA | C30: Nervous system infection | D30: ="A83.4" -> A83.4 | E30: Australian encephalitis
A31: PDC | B31: D11AA | C31: Nervous system infection | D31: ="A83.5" -> A83.5 | E31: California encephalitis
A32: PDC | B32: D11AA | C32: Nervous system infection | D32: ="A83.6" -> A83.6 | E32: Rocio virus disease
A33: PDC | B33: D11AA | C33: Nervous system infection | D33: ="A83.8" -> A83.8 | E33: Other mosquito-borne viral encephalitis
A34: PDC | B34: D11AA | C34: Nervous system infection | D34: ="A83.9" -> A83.9 | E34: Mosquito-borne viral encephalitis, unspecified
A35: PDC | B35: D11AA | C35: Nervous system infection | D35: ="A84.0" -> A84.0 | E35: Far east tick-born enceph-russn spring-summ enceph
A36: PDC | B36: D11AA | C36: Nervous system infection | D36: ="A84.1" -> A84.1 | E36: Central european tick-borne encephalitis
A37: PDC | B37: D11AA | C37: Nervous system infection | D37: ="A84.8" -> A84.8 | E37: Other tick-borne viral encephalitis
A38: PDC | B38: D11AA | C38: Nervous system infection | D38: ="A84.9" -> A84.9 | E38: Tick-borne viral encephalitis, unspecified
A39: PDC | B39: D11AA | C39: Nervous system infection | D39: ="A85.0" -> A85.0 | E39: Enteroviral encephalitis
A40: PDC | B40: D11AA | C40: Nervous system infection | D40: ="A85.1" -> A85.1 | E40: Adenoviral encephalitis
A41: PDC | B41: D11AA | C41: Nervous system infection | D41: ="A85.2" -> A85.2 | E41: Arthropod-borne viral encephalitis, unspecified
A42: PDC | B42: D11AA | C42: Nervous system infection | D42: ="A85.8" -> A85.8 | E42: Other specified viral encephalitis
A43: PDC | B43: D11AA | C43: Nervous system infection | D43: ="A86" -> A86 | E43: Unspecified viral encephalitis
A44: PDC | B44: D11AA | C44: Nervous system infection | D44: ="A87.0" -> A87.0 | E44: Enteroviral meningitis
A45: PDC | B45: D11AA | C45: Nervous system infection | D45: ="A87.1" -> A87.1 | E45: Adenoviral meningitis
A46: PDC | B46: D11AA | C46: Nervous system infection | D46: ="A87.2" -> A87.2 | E46: Lymphocytic choriomeningitis
A47: PDC | B47: D11AA | C47: Nervous system infection | D47: ="A87.8" -> A87.8 | E47: Other viral meningitis
A48: PDC | B48: D11AA | C48: Nervous system infection | D48: ="A87.9" -> A87.9 | E48: Viral meningitis, unspecified
A49: PDC | B49: D11AA | C49: Nervous system infection | D49: ="A88.0" -> A88.0 | E49: Enteroviral exanthematous fever [boston exanthem]
A50: PDC | B50: D11AA | C50: Nervous system infection | D50: ="A88.1" -> A88.1 | E50: Epidemic vertigo
A51: PDC | B51: D11AA | C51: Nervous system infection | D51: ="A88.8" -> A88.8 | E51: Other specified viral infections of central nervous system
A52: PDC | B52: D11AA | C52: Nervous system infection | D52: ="A89" -> A89 | E52: Unspecified viral infection of central nervous system
A53: PDC | B53: D11AA | C53: Nervous system infection | D53: ="A92.2" -> A92.2 | E53: Venezuelan equine fever
A54: PDC | B54: D11AA | C54: Nervous system infection | D54: ="B00.3" -> B00.3 | E54: Herpesviral meningitis
A55: PDC | B55: D11AA | C55: Nervous system infection | D55: ="B00.4" -> B00.4 | E55: Herpesviral encephalitis
A56: PDC | B56: D11AA | C56: Nervous system infection | D56: ="B01.0" -> B01.0 | E56: Varicella meningitis
A57: PDC | B57: D11AA | C57: Nervous system infection | D57: ="B01.1" -> B01.1 | E57: Varicella encephalitis
A58: PDC | B58: D11AA | C58: Nervous system infection | D58: ="B02.0" -> B02.0 | E58: Zoster encephalitis
A59: PDC | B59: D11AA | C59: Nervous system infection | D59: ="B02.1" -> B02.1 | E59: Zoster meningitis
A60: PDC | B60: D11AA | C60: Nervous system infection | D60: ="B02.2" -> B02.2 | E60: Zoster with other nervous system involvement
A61: PDC | B61: D11AA | C61: Nervous system infection | D61: ="B05.0" -> B05.0 | E61: Measles complicated by encephalitis
A62: PDC | B62: D11AA | C62: Nervous system infection | D62: ="B05.1" -> B05.1 | E62: Measles complicated by meningitis
A63: PDC | B63: D11AA | C63: Nervous system infection | D63: ="B06.0" -> B06.0 | E63: Rubella with neurological complications
A64: PDC | B64: D11AA | C64: Nervous system infection | D64: ="B26.1" -> B26.1 | E64: Mumps meningitis
A65: PDC | B65: D11AA | C65: Nervous system infection | D65: ="B26.2" -> B26.2 | E65: Mumps encephalitis
A66: PDC | B66: D11AA | C66: Nervous system infection | D66: ="B37.5" -> B37.5 | E66: Candidal meningitis
A67: PDC | B67: D11AA | C67: Nervous system infection | D67: ="B38.4" -> B38.4 | E67: Coccidioidomycosis meningitis
A68: PDC | B68: D11AA | C68: Nervous system infection | D68: ="B43.1" -> B43.1 | E68: Phaeomycotic brain abscess
A69: PDC | B69: D11AA | C69: Nervous system infection | D69: ="B45.1" -> B45.1 | E69: Cerebral cryptococcosis
A70: PDC | B70: D11AA | C70: Nervous system infection | D70: ="B46.1" -> B46.1 | E70: Rhinocerebral mucormycosis
A71: PDC | B71: D11AA | C71: Nervous system infection | D71: ="B57.4" -> B57.4 | E71: Chagas' disease (chronic) with nervous system involvement
A72: PDC | B72: D11AA | C72: Nervous system infection | D72: ="B58.2" -> B58.2 | E72: Toxoplasma meningoencephalitis
A73: PDC | B73: D11AA | C73: Nervous system infection | D73: ="B69.0" -> B69.0 | E73: Cysticercosis of central nervous system
A74: PDC | B74: D11AA | C74: Nervous system infection | D74: ="B83.10" -> B83.10 | E74: Gnathostomiasis of central nervous system (IM)
A75: PDC | B75: D11AA | C75: Nervous system infection | D75: ="G00.0" -> G00.0 | E75: Haemophilus meningitis
A76: PDC | B76: D11AA | C76: Nervous system infection | D76: ="G00.1" -> G00.1 | E76: Pneumococcal meningitis
A77: PDC | B77: D11AA | C77: Nervous system infection | D77: ="G00.2" -> G00.2 | E77: Streptococcal meningitis
A78: PDC | B78: D11AA | C78: Nervous system infection | D78: ="G00.3" -> G00.3 | E78: Staphylococcal meningitis
A79: PDC | B79: D11AA | C79: Nervous system infection | D79: ="G00.8" -> G00.8 | E79: Other bacterial meningitis
A80: PDC | B80: D11AA | C80: Nervous system infection | D80: ="G00.9" -> G00.9 | E80: Bacterial meningitis, unspecified
A81: PDC | B81: D11AA | C81: Nervous system infection | D81: ="G03.0" -> G03.0 | E81: Nonpyogenic meningitis
A82: PDC | B82: D11AA | C82: Nervous system infection | D82: ="G03.1" -> G03.1 | E82: Chronic meningitis
A83: PDC | B83: D11AA | C83: Nervous system infection | D83: ="G03.2" -> G03.2 | E83: Benign recurrent meningitis [mollaret]
A84: PDC | B84: D11AA | C84: Nervous system infection | D84: ="G03.8" -> G03.8 | E84: Meningitis due to other specified causes
A85: PDC | B85: D11AA | C85: Nervous system infection | D85: ="G03.9" -> G03.9 | E85: Meningitis, unspecified
A86: PDC | B86: D11AA | C86: Nervous system infection | D86: ="G04.0" -> G04.0 | E86: Acute disseminated encephalitis
A87: PDC | B87: D11AA | C87: Nervous system infection | D87: ="G04.1" -> G04.1 | E87: Tropical spastic paraplegia
A88: PDC | B88: D11AA | C88: Nervous system infection | D88: ="G04.2" -> G04.2 | E88: Bacterial meningoencephalitis and meningomyelitis nec
A89: PDC | B89: D11AA | C89: Nervous system infection | D89: ="G04.3" -> G04.3 | E89: Viral transverse myelitis, unspecified (IM)
A90: PDC | B90: D11AA | C90: Nervous system infection | D90: ="G04.8" -> G04.8 | E90: Other encephalitis, myelitis and encephalomyelitis
A91: PDC | B91: D11AA | C91: Nervous system infection | D91: ="G04.81" -> G04.81 | E91: Autoimmune encephalitis (IM)
A92: PDC | B92: D11AA | C92: Nervous system infection | D92: ="G04.9" -> G04.9 | E92: Encephalitis, myelitis and encephalomyelitis, unspecified
A93: PDC | B93: D11AA | C93: Nervous system infection | D93: ="G06.0" -> G06.0 | E93: Intracranial abscess and granuloma
A94: PDC | B94: D11AA | C94: Nervous system infection | D94: ="G06.1" -> G06.1 | E94: Intraspinal abscess and granuloma
A95: PDC | B95: D11AA | C95: Nervous system infection | D95: ="G06.2" -> G06.2 | E95: Extradural and subdural abscess, unspecified
A96: PDC | B96: D11AA | C96: Nervous system infection | D96: ="G08" -> G08 | E96: Intracranial and intraspinal phlebitis and thrombophlebitis
A97: PDC | B97: D11AB | C97: Nervous System Neoplasm | D97: ="C70.0" -> C70.0 | E97: Malignant neoplasm, cerebral meninges
A98: PDC | B98: D11AB | C98: Nervous System Neoplasm | D98: ="C70.1" -> C70.1 | E98: Malignant neoplasm, spinal meninges
A99: PDC | B99: D11AB | C99: Nervous System Neoplasm | D99: ="C70.9" -> C70.9 | E99: Malignant neoplasm, meninges, unspecified
A100: PDC | B100: D11AB | C100: Nervous System Neoplasm | D100: ="C71.0" -> C71.0 | E100: Malignant neoplasm, cerebrum, except lobes and ventricles
...

Sheet rajal cluster icd9cm_web2026092
A1: Cluster Type | B1: Cluster Code | C1: Cluster Description | D1: ICD-9-CM Code | E1: ICD-9-CM Description
A2: PDC | B2: P11KC | C2: Extracranial Vessel Proc. | D2: ="88.41" -> 88.41 | E2: Arteriography of cerebral arteries
A3: PDC | B3: P11KA | C3: Other Nervous System Major Proc. | D3: ="01.13" -> 01.13 | E3: Closed [percutaneous] [needle] biopsy of brain
A4: PDC | B4: P11KA | C4: Other Nervous System Major Proc. | D4: ="01.6" -> 01.6 | E4: Excision of lesion of skull
A5: PDC | B5: P11KA | C5: Other Nervous System Major Proc. | D5: ="02.02" -> 02.02 | E5: Elevation of skull fracture fragments
A6: PDC | B6: P11KA | C6: Other Nervous System Major Proc. | D6: ="02.41" -> 02.41 | E6: Irrigation and exploration of ventricular shunt
A7: PDC | B7: P11KA | C7: Other Nervous System Major Proc. | D7: ="02.43" -> 02.43 | E7: Removal of ventricular shunt
A8: PDC | B8: P11KA | C8: Other Nervous System Major Proc. | D8: ="02.96" -> 02.96 | E8: Insertion of sphenoidal electrodes
A9: PDC | B9: P11KA | C9: Other Nervous System Major Proc. | D9: ="03.21" -> 03.21 | E9: Percutaneous chordotomy
A10: PDC | B10: P11KA | C10: Other Nervous System Major Proc. | D10: ="03.32" -> 03.32 | E10: Biopsy of spinal cord or spinal meninges
A11: PDC | B11: P11KA | C11: Other Nervous System Major Proc. | D11: ="03.94" -> 03.94 | E11: Removal of spinal neurostimulator lead(s)
A12: PDC | B12: P11KA | C12: Other Nervous System Major Proc. | D12: ="03.99" -> 03.99 | E12: Other operations on spinal cord and spinal canal structures
A13: PDC | B13: P11KA | C13: Other Nervous System Major Proc. | D13: ="04.05" -> 04.05 | E13: Gasserian ganglionectomy
A14: PDC | B14: P11KA | C14: Other Nervous System Major Proc. | D14: ="04.06" -> 04.06 | E14: Other cranial or peripheral ganglionectomy
A15: PDC | B15: P11KA | C15: Other Nervous System Major Proc. | D15: ="04.07" -> 04.07 | E15: Other excision or avulsion of cranial and peripheral nerves
A16: PDC | B16: P11KA | C16: Other Nervous System Major Proc. | D16: ="04.3" -> 04.3 | E16: Suture of cranial and peripheral nerves
A17: PDC | B17: P11KA | C17: Other Nervous System Major Proc. | D17: ="04.42" -> 04.42 | E17: Other cranial nerve decompression
A18: PDC | B18: P11KA | C18: Other Nervous System Major Proc. | D18: ="04.49" -> 04.49 | E18: Other peripheral nerve or ganglion decompression or lysis of adhesions
A19: PDC | B19: P11KD | C19: Release of Carpal/Tarsal Tunnel | D19: ="04.43" -> 04.43 | E19: Release of carpal tunnel
A20: PDC | B20: P11KD | C20: Release of Carpal/Tarsal Tunnel | D20: ="04.44" -> 04.44 | E20: Release of tarsal tunnel
A21: PDC | B21: P11KP | C21: Other Nervous System Minor Proc. | D21: ="01.01" -> 01.01 | E21: Cisternal puncture
A22: PDC | B22: P11KP | C22: Other Nervous System Minor Proc. | D22: ="01.09" -> 01.09 | E22: Other cranial puncture
A23: PDC | B23: P11KP | C23: Other Nervous System Minor Proc. | D23: ="01.11" -> 01.11 | E23: Closed [percutaneous] [needle] biopsy of cerebral meninges
A24: PDC | B24: P11KP | C24: Other Nervous System Minor Proc. | D24: ="03.8" -> 03.8 | E24: Injection of destructive agent into spinal canal
A25: PDC | B25: P11KP | C25: Other Nervous System Minor Proc. | D25: ="03.90" -> 03.90 | E25: Insertion of catheter into spinal canal for infusion of therapeutic or palliative substances
A26: PDC | B26: P11KP | C26: Other Nervous System Minor Proc. | D26: ="03.91" -> 03.91 | E26: Injection of anesthetic into spinal canal for analgesia
A27: PDC | B27: P11KP | C27: Other Nervous System Minor Proc. | D27: ="03.92" -> 03.92 | E27: Injection of other agent into spinal canal
A28: PDC | B28: P11KP | C28: Other Nervous System Minor Proc. | D28: ="03.95" -> 03.95 | E28: Spinal blood patch
A29: PDC | B29: P11KP | C29: Other Nervous System Minor Proc. | D29: ="04.11" -> 04.11 | E29: Closed [percutaneous] [needle] biopsy of cranial or peripheral nerve or ganglion
A30: PDC | B30: P11KP | C30: Other Nervous System Minor Proc. | D30: ="04.91" -> 04.91 | E30: Neurectasis
A31: PDC | B31: P11KP | C31: Other Nervous System Minor Proc. | D31: ="04.99" -> 04.99 | E31: Other operations on cranial and peripheral nerves
A32: PDC | B32: P11KP | C32: Other Nervous System Minor Proc. | D32: ="05.0" -> 05.0 | E32: Division of sympathetic nerve or ganglion
A33: PDC | B33: P11KP | C33: Other Nervous System Minor Proc. | D33: ="05.11" -> 05.11 | E33: Biopsy of sympathetic nerve or ganglion
A34: PDC | B34: P11KP | C34: Other Nervous System Minor Proc. | D34: ="05.9" -> 05.9 | E34: Other operations on nervous system
A35: PDC | B35: P11KP | C35: Other Nervous System Minor Proc. | D35: ="83.91" -> 83.91 | E35: Lysis of adhesions of muscle, tendon, fascia, and bursa
A36: PDC | B36: P11KP | C36: Other Nervous System Minor Proc. | D36: ="86.22" -> 86.22 | E36: Excisional debridement of wound, infection, or burn
A37: PDC | B37: P11KP | C37: Other Nervous System Minor Proc. | D37: ="94.28" -> 94.28 | E37: Transcranial magnetic stimulation (TMS) (IM)
A38: PDC | B38: P11KF | C38: Nervous System Other Diagnostic Proc. | D38: ="01.18" -> 01.18 | E38: Other diagnostic procedures on brain and cerebral meninges
A39: PDC | B39: P11KF | C39: Nervous System Other Diagnostic Proc. | D39: ="03.31" -> 03.31 | E39: Spinal tap
A40: PDC | B40: P11KF | C40: Nervous System Other Diagnostic Proc. | D40: ="03.39" -> 03.39 | E40: Other diagnostic procedures on spinal cord and spinal canal structures
A41: PDC | B41: P11KF | C41: Nervous System Other Diagnostic Proc. | D41: ="04.19" -> 04.19 | E41: Other diagnostic procedures on cranial and peripheral nerves and ganglia
A42: PDC | B42: P11KF | C42: Nervous System Other Diagnostic Proc. | D42: ="05.19" -> 05.19 | E42: Other diagnostic procedures on sympathetic nerves or ganglia
A43: PDC | B43: P11KM | C43: Electroencephalography (EEG) | D43: ="89.14" -> 89.14 | E43: Electroencephalogram
A44: PDC | B44: P11KM | C44: Electroencephalography (EEG) | D44: ="89.19" -> 89.19 | E44: Video and radio-telemetered electroencephalographic monitoring
A45: PDC | B45: P11KK | C45: Peripheral Nerve Injection Proc. | D45: ="04.80" -> 04.80 | E45: Peripheral nerve injection, not otherwise specified
A46: PDC | B46: P11KK | C46: Peripheral Nerve Injection Proc. | D46: ="04.81" -> 04.81 | E46: Injection of anesthetic into peripheral nerve for analgesia
A47: PDC | B47: P11KK | C47: Peripheral Nerve Injection Proc. | D47: ="04.89" -> 04.89 | E47: Injection of other agent, except neurolytic
A48: PDC | B48: P11KK | C48: Peripheral Nerve Injection Proc. | D48: ="05.31" -> 05.31 | E48: Injection of anesthetic into sympathetic nerve for analgesia
A49: PDC | B49: P11KK | C49: Peripheral Nerve Injection Proc. | D49: ="05.32" -> 05.32 | E49: Injection of neurolytic agent into sympathetic nerve
A50: AX | B50: 11PBX | C50: Diagnostic Proc. for Nervous System Neoplasms | D50: ="01.11" -> 01.11 | E50: Closed [percutaneous] [needle] biopsy of cerebral meninges
A51: AX | B51: 11PBX | C51: Diagnostic Proc. for Nervous System Neoplasms | D51: ="01.13" -> 01.13 | E51: Closed [percutaneous] [needle] biopsy of brain
A52: AX | B52: 11PBX | C52: Diagnostic Proc. for Nervous System Neoplasms | D52: ="04.11" -> 04.11 | E52: Closed [percutaneous] [needle] biopsy of cranial or peripheral nerve or ganglion
A53: AX | B53: 11PBX | C53: Diagnostic Proc. for Nervous System Neoplasms | D53: ="87.01" -> 87.01 | E53: Pneumoencephalogram
A54: AX | B54: 11PBX | C54: Diagnostic Proc. for Nervous System Neoplasms | D54: ="87.02" -> 87.02 | E54: Other contrast radiogram of brain and skull
A55: AX | B55: 11PBX | C55: Diagnostic Proc. for Nervous System Neoplasms | D55: ="87.03" -> 87.03 | E55: Computerized axial tomography of head
A56: AX | B56: 11PBX | C56: Diagnostic Proc. for Nervous System Neoplasms | D56: ="87.04" -> 87.04 | E56: Other tomography of head
A57: AX | B57: 11PBX | C57: Diagnostic Proc. for Nervous System Neoplasms | D57: ="87.05" -> 87.05 | E57: Contrast dacryocystogram
A58: AX | B58: 11PBX | C58: Diagnostic Proc. for Nervous System Neoplasms | D58: ="87.06" -> 87.06 | E58: Contrast radiogram of nasopharynx
A59: AX | B59: 11PBX | C59: Diagnostic Proc. for Nervous System Neoplasms | D59: ="87.14" -> 87.14 | E59: Contrast radiogram of orbit
A60: AX | B60: 11PBX | C60: Diagnostic Proc. for Nervous System Neoplasms | D60: ="87.15" -> 87.15 | E60: Contrast radiogram of sinus
A61: AX | B61: 11PBX | C61: Diagnostic Proc. for Nervous System Neoplasms | D61: ="87.21" -> 87.21 | E61: Contrast myelogram
A62: AX | B62: 11PBX | C62: Diagnostic Proc. for Nervous System Neoplasms | D62: ="87.41" -> 87.41 | E62: Computerized axial tomography of thorax
A63: AX | B63: 11PBX | C63: Diagnostic Proc. for Nervous System Neoplasms | D63: ="87.62" -> 87.62 | E63: Upper gi series
A64: AX | B64: 11PBX | C64: Diagnostic Proc. for Nervous System Neoplasms | D64: ="87.63" -> 87.63 | E64: Small bowel series
A65: AX | B65: 11PBX | C65: Diagnostic Proc. for Nervous System Neoplasms | D65: ="87.64" -> 87.64 | E65: Lower gi series
A66: AX | B66: 11PBX | C66: Diagnostic Proc. for Nervous System Neoplasms | D66: ="88.01" -> 88.01 | E66: Computerized axial tomography of abdomen
A67: AX | B67: 11PBX | C67: Diagnostic Proc. for Nervous System Neoplasms | D67: ="88.41" -> 88.41 | E67: Arteriography of cerebral arteries
A68: AX | B68: 11PBX | C68: Diagnostic Proc. for Nervous System Neoplasms | D68: ="88.61" -> 88.61 | E68: Phlebography of veins of head and neck using contrast material
A69: AX | B69: 11PBX | C69: Diagnostic Proc. for Nervous System Neoplasms | D69: ="88.71" -> 88.71 | E69: Diagnostic ultrasound of head and neck
A70: AX | B70: 11PBX | C70: Diagnostic Proc. for Nervous System Neoplasms | D70: ="88.76" -> 88.76 | E70: Diagnostic ultrasound of abdomen and retroperitoneum
A71: AX | B71: 11PBX | C71: Diagnostic Proc. for Nervous System Neoplasms | D71: ="88.91" -> 88.91 | E71: Magnetic resonance imaging of brain and brain stem
A72: AX | B72: 11PBX | C72: Diagnostic Proc. for Nervous System Neoplasms | D72: ="88.93" -> 88.93 | E72: Magnetic resonance imaging of spinal canal
A73: AX | B73: 11PBX | C73: Diagnostic Proc. for Nervous System Neoplasms | D73: ="88.94" -> 88.94 | E73: Magnetic resonance imaging of musculoskeletal
A74: AX | B74: 11PBX | C74: Diagnostic Proc. for Nervous System Neoplasms | D74: ="88.97" -> 88.97 | E74: Magnetic resonance imaging of other and unspecified sites
A75: AX | B75: 11PBX | C75: Diagnostic Proc. for Nervous System Neoplasms | D75: ="92.11" -> 92.11 | E75: Cerebral scan
A76: AX | B76: 11PBX | C76: Diagnostic Proc. for Nervous System Neoplasms | D76: ="92.12" -> 92.12 | E76: Scan of other sites of head
A77: AX | B77: 11PBX | C77: Diagnostic Proc. for Nervous System Neoplasms | D77: ="92.14" -> 92.14 | E77: Bone scan
A78: AX | B78: 11PBX | C78: Diagnostic Proc. for Nervous System Neoplasms | D78: ="92.18" -> 92.18 | E78: Total body scan
A79: AX | B79: 11PBX | C79: Diagnostic Proc. for Nervous System Neoplasms | D79: ="95.23" -> 95.23 | E79: Visual evoked potential [VEP]
A80: AX | B80: 11PBX | C80: Diagnostic Proc. for Nervous System Neoplasms | D80: ="95.25" -> 95.25 | E80: Electromyogram of eye [EMG]
A81: AX | B81: 11PBX | C81: Diagnostic Proc. for Nervous System Neoplasms | D81: ="95.41" -> 95.41 | E81: Audiometry
A82: AX | B82: 11PCX | C82: Plasmapheresis | D82: ="99.71" -> 99.71 | E82: Therapeutic plasmapheresis
A83: AX | B83: 11PDX | C83: Thrombolytic Agent Injection/Infusion | D83: ="99.10" -> 99.10 | E83: Injection or infusion of thrombolytic agent

Sheet ranap cluster icd10_web20260922
A1: Cluster Type | B1: Cluster Code | C1: Cluster Description | D1: ICD-10 Code | E1: ICD-10 Description
A2: PDC | B2: D11AA | C2: Nervous system infection | D2: ="A06.6" -> A06.6 | E2: Amoebic brain abscess
A3: PDC | B3: D11AA | C3: Nervous system infection | D3: ="A17.0" -> A17.0 | E3: Tuberculous meningitis
A4: PDC | B4: D11AA | C4: Nervous system infection | D4: ="A17.1" -> A17.1 | E4: Meningeal tuberculoma
A5: PDC | B5: D11AA | C5: Nervous system infection | D5: ="A17.8" -> A17.8 | E5: Other tuberculosis of nervous system
A6: PDC | B6: D11AA | C6: Nervous system infection | D6: ="A17.9" -> A17.9 | E6: Tuberculosis of nervous system unspecified
A7: PDC | B7: D11AA | C7: Nervous system infection | D7: ="A32.1" -> A32.1 | E7: Listerial meningitis and meningoencephalitis
A8: PDC | B8: D11AA | C8: Nervous system infection | D8: ="A39.0" -> A39.0 | E8: Meningococcal meningitis
A9: PDC | B9: D11AA | C9: Nervous system infection | D9: ="A50.4" -> A50.4 | E9: Late congenital neurosyphilis [juvenile neurosyphilis]
A10: PDC | B10: D11AA | C10: Nervous system infection | D10: ="A52.1" -> A52.1 | E10: Symptomatic neurosyphilis
A11: PDC | B11: D11AA | C11: Nervous system infection | D11: ="A52.2" -> A52.2 | E11: Asymptomatic neurosyphilis
A12: PDC | B12: D11AA | C12: Nervous system infection | D12: ="A52.3" -> A52.3 | E12: Neurosyphilis, unspecified
A13: PDC | B13: D11AA | C13: Nervous system infection | D13: ="A80.0" -> A80.0 | E13: Acute paralytic poliomyelitis, vaccine-associated
A14: PDC | B14: D11AA | C14: Nervous system infection | D14: ="A80.1" -> A80.1 | E14: Acute paralytic poliomyelitis, wild virus, imported
A15: PDC | B15: D11AA | C15: Nervous system infection | D15: ="A80.2" -> A80.2 | E15: Acute paralytic poliomyelitis, wild virus, indigenous
A16: PDC | B16: D11AA | C16: Nervous system infection | D16: ="A80.3" -> A80.3 | E16: Acute paralytic poliomyelitis, other and unspecified
A17: PDC | B17: D11AA | C17: Nervous system infection | D17: ="A80.9" -> A80.9 | E17: Acute poliomyelitis, unspecified
A18: PDC | B18: D11AA | C18: Nervous system infection | D18: ="A81.0" -> A81.0 | E18: Creutzfeldt-jakob disease
A19: PDC | B19: D11AA | C19: Nervous system infection | D19: ="A81.1" -> A81.1 | E19: Subacute sclerosing panencephalitis
A20: PDC | B20: D11AA | C20: Nervous system infection | D20: ="A81.2" -> A81.2 | E20: Progressive multifocal leukoencephalopathy
A21: PDC | B21: D11AA | C21: Nervous system infection | D21: ="A81.8" -> A81.8 | E21: Other atypical virus infections of central nervous system
A22: PDC | B22: D11AA | C22: Nervous system infection | D22: ="A81.9" -> A81.9 | E22: Atypical virus infection of central nervous system, unspecified
A23: PDC | B23: D11AA | C23: Nervous system infection | D23: ="A82.0" -> A82.0 | E23: Sylvatic rabies
A24: PDC | B24: D11AA | C24: Nervous system infection | D24: ="A82.1" -> A82.1 | E24: Urban rabies
A25: PDC | B25: D11AA | C25: Nervous system infection | D25: ="A82.9" -> A82.9 | E25: Rabies, unspecified
A26: PDC | B26: D11AA | C26: Nervous system infection | D26: ="A83.0" -> A83.0 | E26: Japanese encephalitis
A27: PDC | B27: D11AA | C27: Nervous system infection | D27: ="A83.1" -> A83.1 | E27: Western equine encephalitis
A28: PDC | B28: D11AA | C28: Nervous system infection | D28: ="A83.2" -> A83.2 | E28: Eastern equine encephalitis
A29: PDC | B29: D11AA | C29: Nervous system infection | D29: ="A83.3" -> A83.3 | E29: St louis encephalitis
A30: PDC | B30: D11AA | C30: Nervous system infection | D30: ="A83.4" -> A83.4 | E30: Australian encephalitis
A31: PDC | B31: D11AA | C31: Nervous system infection | D31: ="A83.5" -> A83.5 | E31: California encephalitis
A32: PDC | B32: D11AA | C32: Nervous system infection | D32: ="A83.6" -> A83.6 | E32: Rocio virus disease
A33: PDC | B33: D11AA | C33: Nervous system infection | D33: ="A83.8" -> A83.8 | E33: Other mosquito-borne viral encephalitis
A34: PDC | B34: D11AA | C34: Nervous system infection | D34: ="A83.9" -> A83.9 | E34: Mosquito-borne viral encephalitis, unspecified
A35: PDC | B35: D11AA | C35: Nervous system infection | D35: ="A84.0" -> A84.0 | E35: Far east tick-born enceph-russn spring-summ enceph
A36: PDC | B36: D11AA | C36: Nervous system infection | D36: ="A84.1" -> A84.1 | E36: Central european tick-borne encephalitis
A37: PDC | B37: D11AA | C37: Nervous system infection | D37: ="A84.8" -> A84.8 | E37: Other tick-borne viral encephalitis
A38: PDC | B38: D11AA | C38: Nervous system infection | D38: ="A84.9" -> A84.9 | E38: Tick-borne viral encephalitis, unspecified
A39: PDC | B39: D11AA | C39: Nervous system infection | D39: ="A85.0" -> A85.0 | E39: Enteroviral encephalitis
A40: PDC | B40: D11AA | C40: Nervous system infection | D40: ="A85.1" -> A85.1 | E40: Adenoviral encephalitis
A41: PDC | B41: D11AA | C41: Nervous system infection | D41: ="A85.2" -> A85.2 | E41: Arthropod-borne viral encephalitis, unspecified
A42: PDC | B42: D11AA | C42: Nervous system infection | D42: ="A85.8" -> A85.8 | E42: Other specified viral encephalitis
A43: PDC | B43: D11AA | C43: Nervous system infection | D43: ="A86" -> A86 | E43: Unspecified viral encephalitis
A44: PDC | B44: D11AA | C44: Nervous system infection | D44: ="A87.0" -> A87.0 | E44: Enteroviral meningitis
A45: PDC | B45: D11AA | C45: Nervous system infection | D45: ="A87.1" -> A87.1 | E45: Adenoviral meningitis
A46: PDC | B46: D11AA | C46: Nervous system infection | D46: ="A87.2" -> A87.2 | E46: Lymphocytic choriomeningitis
A47: PDC | B47: D11AA | C47: Nervous system infection | D47: ="A87.8" -> A87.8 | E47: Other viral meningitis
A48: PDC | B48: D11AA | C48: Nervous system infection | D48: ="A87.9" -> A87.9 | E48: Viral meningitis, unspecified
A49: PDC | B49: D11AA | C49: Nervous system infection | D49: ="A88.0" -> A88.0 | E49: Enteroviral exanthematous fever [boston exanthem]
A50: PDC | B50: D11AA | C50: Nervous system infection | D50: ="A88.1" -> A88.1 | E50: Epidemic vertigo
A51: PDC | B51: D11AA | C51: Nervous system infection | D51: ="A88.8" -> A88.8 | E51: Other specified viral infections of central nervous system
A52: PDC | B52: D11AA | C52: Nervous system infection | D52: ="A89" -> A89 | E52: Unspecified viral infection of central nervous system
A53: PDC | B53: D11AA | C53: Nervous system infection | D53: ="A92.2" -> A92.2 | E53: Venezuelan equine fever
A54: PDC | B54: D11AA | C54: Nervous system infection | D54: ="B00.3" -> B00.3 | E54: Herpesviral meningitis
A55: PDC | B55: D11AA | C55: Nervous system infection | D55: ="B00.4" -> B00.4 | E55: Herpesviral encephalitis
A56: PDC | B56: D11AA | C56: Nervous system infection | D56: ="B01.0" -> B01.0 | E56: Varicella meningitis
A57: PDC | B57: D11AA | C57: Nervous system infection | D57: ="B01.1" -> B01.1 | E57: Varicella encephalitis
A58: PDC | B58: D11AA | C58: Nervous system infection | D58: ="B02.0" -> B02.0 | E58: Zoster encephalitis
A59: PDC | B59: D11AA | C59: Nervous system infection | D59: ="B02.1" -> B02.1 | E59: Zoster meningitis
A60: PDC | B60: D11AA | C60: Nervous system infection | D60: ="B02.2" -> B02.2 | E60: Zoster with other nervous system involvement
A61: PDC | B61: D11AA | C61: Nervous system infection | D61: ="B05.0" -> B05.0 | E61: Measles complicated by encephalitis
A62: PDC | B62: D11AA | C62: Nervous system infection | D62: ="B05.1" -> B05.1 | E62: Measles complicated by meningitis
A63: PDC | B63: D11AA | C63: Nervous system infection | D63: ="B06.0" -> B06.0 | E63: Rubella with neurological complications
A64: PDC | B64: D11AA | C64: Nervous system infection | D64: ="B26.1" -> B26.1 | E64: Mumps meningitis
A65: PDC | B65: D11AA | C65: Nervous system infection | D65: ="B26.2" -> B26.2 | E65: Mumps encephalitis
A66: PDC | B66: D11AA | C66: Nervous system infection | D66: ="B37.5" -> B37.5 | E66: Candidal meningitis
A67: PDC | B67: D11AA | C67: Nervous system infection | D67: ="B38.4" -> B38.4 | E67: Coccidioidomycosis meningitis
A68: PDC | B68: D11AA | C68: Nervous system infection | D68: ="B43.1" -> B43.1 | E68: Phaeomycotic brain abscess
A69: PDC | B69: D11AA | C69: Nervous system infection | D69: ="B45.1" -> B45.1 | E69: Cerebral cryptococcosis
A70: PDC | B70: D11AA | C70: Nervous system infection | D70: ="B46.1" -> B46.1 | E70: Rhinocerebral mucormycosis
A71: PDC | B71: D11AA | C71: Nervous system infection | D71: ="B57.4" -> B57.4 | E71: Chagas' disease (chronic) with nervous system involvement
A72: PDC | B72: D11AA | C72: Nervous system infection | D72: ="B58.2" -> B58.2 | E72: Toxoplasma meningoencephalitis
A73: PDC | B73: D11AA | C73: Nervous system infection | D73: ="B69.0" -> B69.0 | E73: Cysticercosis of central nervous system
A74: PDC | B74: D11AA | C74: Nervous system infection | D74: ="B83.10" -> B83.10 | E74: Gnathostomiasis of central nervous system (IM)
A75: PDC | B75: D11AA | C75: Nervous system infection | D75: ="G00.0" -> G00.0 | E75: Haemophilus meningitis
A76: PDC | B76: D11AA | C76: Nervous system infection | D76: ="G00.1" -> G00.1 | E76: Pneumococcal meningitis
A77: PDC | B77: D11AA | C77: Nervous system infection | D77: ="G00.2" -> G00.2 | E77: Streptococcal meningitis
A78: PDC | B78: D11AA | C78: Nervous system infection | D78: ="G00.3" -> G00.3 | E78: Staphylococcal meningitis
A79: PDC | B79: D11AA | C79: Nervous system infection | D79: ="G00.8" -> G00.8 | E79: Other bacterial meningitis
A80: PDC | B80: D11AA | C80: Nervous system infection | D80: ="G00.9" -> G00.9 | E80: Bacterial meningitis, unspecified
A81: PDC | B81: D11AA | C81: Nervous system infection | D81: ="G03.0" -> G03.0 | E81: Nonpyogenic meningitis
A82: PDC | B82: D11AA | C82: Nervous system infection | D82: ="G03.1" -> G03.1 | E82: Chronic meningitis
A83: PDC | B83: D11AA | C83: Nervous system infection | D83: ="G03.2" -> G03.2 | E83: Benign recurrent meningitis [mollaret]
A84: PDC | B84: D11AA | C84: Nervous system infection | D84: ="G03.8" -> G03.8 | E84: Meningitis due to other specified causes
A85: PDC | B85: D11AA | C85: Nervous system infection | D85: ="G03.9" -> G03.9 | E85: Meningitis, unspecified
A86: PDC | B86: D11AA | C86: Nervous system infection | D86: ="G04.0" -> G04.0 | E86: Acute disseminated encephalitis
A87: PDC | B87: D11AA | C87: Nervous system infection | D87: ="G04.1" -> G04.1 | E87: Tropical spastic paraplegia
A88: PDC | B88: D11AA | C88: Nervous system infection | D88: ="G04.2" -> G04.2 | E88: Bacterial meningoencephalitis and meningomyelitis nec
A89: PDC | B89: D11AA | C89: Nervous system infection | D89: ="G04.3" -> G04.3 | E89: Viral transverse myelitis, unspecified (IM)
A90: PDC | B90: D11AA | C90: Nervous system infection | D90: ="G04.8" -> G04.8 | E90: Other encephalitis, myelitis and encephalomyelitis
A91: PDC | B91: D11AA | C91: Nervous system infection | D91: ="G04.81" -> G04.81 | E91: Autoimmune encephalitis (IM)
A92: PDC | B92: D11AA | C92: Nervous system infection | D92: ="G04.9" -> G04.9 | E92: Encephalitis, myelitis and encephalomyelitis, unspecified
A93: PDC | B93: D11AA | C93: Nervous system infection | D93: ="G06.0" -> G06.0 | E93: Intracranial abscess and granuloma
A94: PDC | B94: D11AA | C94: Nervous system infection | D94: ="G06.1" -> G06.1 | E94: Intraspinal abscess and granuloma
A95: PDC | B95: D11AA | C95: Nervous system infection | D95: ="G06.2" -> G06.2 | E95: Extradural and subdural abscess, unspecified
A96: PDC | B96: D11AA | C96: Nervous system infection | D96: ="G08" -> G08 | E96: Intracranial and intraspinal phlebitis and thrombophlebitis
A97: PDC | B97: D11AB | C97: Nervous System Neoplasm | D97: ="C70.0" -> C70.0 | E97: Malignant neoplasm, cerebral meninges
A98: PDC | B98: D11AB | C98: Nervous System Neoplasm | D98: ="C70.1" -> C70.1 | E98: Malignant neoplasm, spinal meninges
A99: PDC | B99: D11AB | C99: Nervous System Neoplasm | D99: ="C70.9" -> C70.9 | E99: Malignant neoplasm, meninges, unspecified
A100: PDC | B100: D11AB | C100: Nervous System Neoplasm | D100: ="C71.0" -> C71.0 | E100: Malignant neoplasm, cerebrum, except lobes and ventricles
...

Sheet ranap cluster icd9cm_web2026092
A1: Cluster Type | B1: Cluster Code | C1: Cluster Description | D1: ICD-9-CM Code | E1: ICD-9-CM Description
A2: PDC | B2: P11AA | C2: Endovascular Procedures for Neurologic Diseases | D2: ="00.62" -> 00.62 | E2: Percutaneous angioplasty or atherectomy of intracranial vessel(s)
A3: PDC | B3: P11AA | C3: Endovascular Procedures for Neurologic Diseases | D3: ="38.52" -> 38.52 | E3: Ligation and stripping of varicose veins, other vessels of head and neck
A4: PDC | B4: P11AA | C4: Endovascular Procedures for Neurologic Diseases | D4: ="38.7" -> 38.7 | E4: Interruption vena cava
A5: PDC | B5: P11AA | C5: Endovascular Procedures for Neurologic Diseases | D5: ="38.82" -> 38.82 | E5: Other surgical occlusion of vessels, other vessels of head and neck
A6: PDC | B6: P11AA | C6: Endovascular Procedures for Neurologic Diseases | D6: ="39.72" -> 39.72 | E6: Endovascular embolization or occlusion of head and neck vessels
A7: PDC | B7: P11AA | C7: Endovascular Procedures for Neurologic Diseases | D7: ="39.74" -> 39.74 | E7: Endovascular removal of obstruction from head and neck vessel(s)
A8: PDC | B8: P11AA | C8: Endovascular Procedures for Neurologic Diseases | D8: ="39.75" -> 39.75 | E8: Endovascular embolization or occlusion of vessel(s) of head or neck using bare coils
A9: PDC | B9: P11AA | C9: Endovascular Procedures for Neurologic Diseases | D9: ="39.76" -> 39.76 | E9: Endovascular embolization or occlusion of vessel(s) of head or neck using bioactive coils
A10: PDC | B10: P11AA | C10: Endovascular Procedures for Neurologic Diseases | D10: ="39.81" -> 39.81 | E10: Implantation or replacement of carotid sinus stimulation device, total system (IM)
A11: PDC | B11: P11AA | C11: Endovascular Procedures for Neurologic Diseases | D11: ="39.82" -> 39.82 | E11: Implantation or replacement of carotid sinus stimulation lead(s) only (IM)
A12: PDC | B12: P11AA | C12: Endovascular Procedures for Neurologic Diseases | D12: ="39.83" -> 39.83 | E12: Implantation or replacement of carotid sinus stimulation pulse generator only (IM)
A13: PDC | B13: P11AA | C13: Endovascular Procedures for Neurologic Diseases | D13: ="39.84" -> 39.84 | E13: Revision of carotid sinus stimulation lead(s) only (IM)
A14: PDC | B14: P11AA | C14: Endovascular Procedures for Neurologic Diseases | D14: ="39.85" -> 39.85 | E14: Revision of carotid sinus stimulation pulse generator (IM)
A15: PDC | B15: P11AA | C15: Endovascular Procedures for Neurologic Diseases | D15: ="39.86" -> 39.86 | E15: Removal of carotid sinus stimulation device, total system (IM)
A16: PDC | B16: P11AA | C16: Endovascular Procedures for Neurologic Diseases | D16: ="39.87" -> 39.87 | E16: Removal of carotid sinus stimulation lead(s) only (IM)
A17: PDC | B17: P11AA | C17: Endovascular Procedures for Neurologic Diseases | D17: ="39.88" -> 39.88 | E17: Removal of carotid sinus stimulation pulse generator only (IM)
A18: PDC | B18: P11AA | C18: Endovascular Procedures for Neurologic Diseases | D18: ="39.89" -> 39.89 | E18: Other operations on carotid body, carotid sinus and other vascular bodies (IM)
A19: PDC | B19: P11AB | C19: Complex Spinal Procedures | D19: ="03.4" -> 03.4 | E19: Excision or destruction of lesion of spinal cord or spinal meninges
A20: PDC | B20: P11AB | C20: Complex Spinal Procedures | D20: ="03.52" -> 03.52 | E20: Repair of spinal myelomeningocele
A21: PDC | B21: P11AB | C21: Complex Spinal Procedures | D21: ="03.99" -> 03.99 | E21: Other operations on spinal cord and spinal canal structures
A22: PDC | B22: P11AB | C22: Complex Spinal Procedures | D22: ="81.00" -> 81.00 | E22: Spinal fusion, not otherwise specified
A23: PDC | B23: P11AB | C23: Complex Spinal Procedures | D23: ="81.01" -> 81.01 | E23: Atlas-axis spinal fusion
A24: PDC | B24: P11AB | C24: Complex Spinal Procedures | D24: ="81.02" -> 81.02 | E24: Other cervical fusion of the anterior column, anterior technique
A25: PDC | B25: P11AB | C25: Complex Spinal Procedures | D25: ="81.03" -> 81.03 | E25: Other cervical fusion of the posterior column, posterior technique
A26: PDC | B26: P11AB | C26: Complex Spinal Procedures | D26: ="81.04" -> 81.04 | E26: Dorsal and dorsolumbar fusion of the anterior column, anterior technique
A27: PDC | B27: P11AB | C27: Complex Spinal Procedures | D27: ="81.05" -> 81.05 | E27: Dorsal and dorsolumbar fusion of the posterior column, posterior technique
A28: PDC | B28: P11AB | C28: Complex Spinal Procedures | D28: ="81.06" -> 81.06 | E28: Lumbar and lumbosacral fusion of the anterior column, anterior technique
A29: PDC | B29: P11AB | C29: Complex Spinal Procedures | D29: ="81.07" -> 81.07 | E29: Lumbar and lumbosacral fusion of the posterior column, posterior technique
A30: PDC | B30: P11AB | C30: Complex Spinal Procedures | D30: ="81.08" -> 81.08 | E30: Lumbar and lumbosacral fusion of the anterior column, posterior technique
A31: PDC | B31: P11AB | C31: Complex Spinal Procedures | D31: ="81.30" -> 81.30 | E31: Refusion of spine, not otherwise specified
A32: PDC | B32: P11AB | C32: Complex Spinal Procedures | D32: ="81.31" -> 81.31 | E32: Refusion of atlas-axis spine
A33: PDC | B33: P11AB | C33: Complex Spinal Procedures | D33: ="81.32" -> 81.32 | E33: Refusion of other cervical spine, anterior column, anterior technique
A34: PDC | B34: P11AB | C34: Complex Spinal Procedures | D34: ="81.33" -> 81.33 | E34: Refusion of other cervical spine, posterior column, posterior technique
A35: PDC | B35: P11AB | C35: Complex Spinal Procedures | D35: ="81.34" -> 81.34 | E35: Refusion of dorsal and dorsolumbar spine, anterior column, anterior technique
A36: PDC | B36: P11AB | C36: Complex Spinal Procedures | D36: ="81.35" -> 81.35 | E36: Refusion of dorsal and dorsolumbar spine, posterior column, posterior technique
A37: PDC | B37: P11AB | C37: Complex Spinal Procedures | D37: ="81.36" -> 81.36 | E37: Refusion of lumbar and lumbosacral spine, anterior column, anterior technique
A38: PDC | B38: P11AB | C38: Complex Spinal Procedures | D38: ="81.37" -> 81.37 | E38: Refusion of lumbar and lumbosacral spine, posterior column, posterior technique
A39: PDC | B39: P11AB | C39: Complex Spinal Procedures | D39: ="81.38" -> 81.38 | E39: Refusion of lumbar and lumbosacral spine, anterior column, posterior technique
A40: PDC | B40: P11AB | C40: Complex Spinal Procedures | D40: ="81.39" -> 81.39 | E40: Refusion of spine, not elsewhere classified
A41: PDC | B41: P11AB | C41: Complex Spinal Procedures | D41: ="84.60" -> 84.60 | E41: Insertion of spinal disc prosthesis, not otherwise specified
A42: PDC | B42: P11AB | C42: Complex Spinal Procedures | D42: ="84.61" -> 84.61 | E42: Insertion of partial spinal disc prosthesis, cervical
A43: PDC | B43: P11AB | C43: Complex Spinal Procedures | D43: ="84.62" -> 84.62 | E43: Insertion of total spinal disc prosthesis, cervical
A44: PDC | B44: P11AB | C44: Complex Spinal Procedures | D44: ="84.63" -> 84.63 | E44: Insertion of spinal disc prosthesis, thoracic
A45: PDC | B45: P11AB | C45: Complex Spinal Procedures | D45: ="84.64" -> 84.64 | E45: Insertion of partial spinal disc prosthesis, lumbosacral
A46: PDC | B46: P11AB | C46: Complex Spinal Procedures | D46: ="84.65" -> 84.65 | E46: Insertion of total spinal disc prosthesis, lumbosacral
A47: PDC | B47: P11AB | C47: Complex Spinal Procedures | D47: ="84.66" -> 84.66 | E47: Revision or replacement of artificial spinal disc prosthesis, cervical
A48: PDC | B48: P11AB | C48: Complex Spinal Procedures | D48: ="84.67" -> 84.67 | E48: Revision or replacement of artificial spinal disc prosthesis, thoracic
A49: PDC | B49: P11AB | C49: Complex Spinal Procedures | D49: ="84.68" -> 84.68 | E49: Revision or replacement of artificial spinal disc prosthesis, lumbosacral
A50: PDC | B50: P11AB | C50: Complex Spinal Procedures | D50: ="84.69" -> 84.69 | E50: Revision or replacement of artificial spinal disc prosthesis, not otherwise specified
A51: PDC | B51: P11AC | C51: Complex Craniotomy Procedures | D51: ="01.41" -> 01.41 | E51: Operations on thalamus
A52: PDC | B52: P11AC | C52: Complex Craniotomy Procedures | D52: ="01.42" -> 01.42 | E52: Operations on globus pallidus
A53: PDC | B53: P11AC | C53: Complex Craniotomy Procedures | D53: ="04.01" -> 04.01 | E53: Excision of acoustic neuroma
A54: PDC | B54: P11AC | C54: Complex Craniotomy Procedures | D54: ="17.61" -> 17.61 | E54: Laser interstitial thermal therapy [LITT] of lesion or tissue of brain under guidance
A55: PDC | B55: P11AC | C55: Complex Craniotomy Procedures | D55: ="17.62" -> 17.62 | E55: Laser interstitial thermal therapy [LITT] of lesion or tissue of head and neck under guidance
A56: PDC | B56: P11AD | C56: Ventricular System Procedures | D56: ="01.02" -> 01.02 | E56: Ventriculopuncture through previously implanted catheter
A57: PDC | B57: P11AD | C57: Ventricular System Procedures | D57: ="02.2" -> 02.2 | E57: Ventriculostomy
A58: PDC | B58: P11AD | C58: Ventricular System Procedures | D58: ="02.20" -> 02.20 | E58: Endoscopic ventriculostomy (IM)
A59: PDC | B59: P11AD | C59: Ventricular System Procedures | D59: ="02.31" -> 02.31 | E59: Ventricular shunt to structure in head and neck
A60: PDC | B60: P11AD | C60: Ventricular System Procedures | D60: ="02.32" -> 02.32 | E60: Ventricular shunt to circulatory system
A61: PDC | B61: P11AD | C61: Ventricular System Procedures | D61: ="02.33" -> 02.33 | E61: Ventricular shunt to thoracic cavity
A62: PDC | B62: P11AD | C62: Ventricular System Procedures | D62: ="02.34" -> 02.34 | E62: Ventricular shunt to abdominal cavity and organs
A63: PDC | B63: P11AD | C63: Ventricular System Procedures | D63: ="02.35" -> 02.35 | E63: Ventricular shunt to urinary system
A64: PDC | B64: P11AD | C64: Ventricular System Procedures | D64: ="02.39" -> 02.39 | E64: Other operations to establish drainage of ventricle
A65: PDC | B65: P11AD | C65: Ventricular System Procedures | D65: ="02.41" -> 02.41 | E65: Irrigation and exploration of ventricular shunt
A66: PDC | B66: P11AD | C66: Ventricular System Procedures | D66: ="02.42" -> 02.42 | E66: Replacement of ventricular shunt
A67: PDC | B67: P11AD | C67: Ventricular System Procedures | D67: ="02.43" -> 02.43 | E67: Removal of ventricular shunt
A68: PDC | B68: P11AD | C68: Ventricular System Procedures | D68: ="54.95" -> 54.95 | E68: Incision of peritoneum
A69: PDC | B69: P11AE | C69: Moderate Craniotomy Procedures | D69: ="01.13" -> 01.13 | E69: Closed [percutaneous] [needle] biopsy of brain
A70: PDC | B70: P11AE | C70: Moderate Craniotomy Procedures | D70: ="01.17" -> 01.17 | E70: Brain temperature monitoring
A71: PDC | B71: P11AE | C71: Moderate Craniotomy Procedures | D71: ="01.23" -> 01.23 | E71: Reopening of craniotomy site
A72: PDC | B72: P11AE | C72: Moderate Craniotomy Procedures | D72: ="01.39" -> 01.39 | E72: Other incision of brain
A73: PDC | B73: P11AE | C73: Moderate Craniotomy Procedures | D73: ="01.51" -> 01.51 | E73: Excision of lesion or tissue of cerebral meninges
A74: PDC | B74: P11AE | C74: Moderate Craniotomy Procedures | D74: ="01.52" -> 01.52 | E74: Hemispherectomy
A75: PDC | B75: P11AE | C75: Moderate Craniotomy Procedures | D75: ="01.53" -> 01.53 | E75: Lobectomy of brain
A76: PDC | B76: P11AE | C76: Moderate Craniotomy Procedures | D76: ="01.59" -> 01.59 | E76: Other excision or destruction of lesion or tissue of brain
A77: PDC | B77: P11AE | C77: Moderate Craniotomy Procedures | D77: ="02.01" -> 02.01 | E77: Opening of cranial suture
A78: PDC | B78: P11AE | C78: Moderate Craniotomy Procedures | D78: ="02.14" -> 02.14 | E78: Choroid plexectomy
A79: PDC | B79: P11AE | C79: Moderate Craniotomy Procedures | D79: ="02.92" -> 02.92 | E79: Repair of brain
A80: PDC | B80: P11AE | C80: Moderate Craniotomy Procedures | D80: ="02.99" -> 02.99 | E80: Other operations on skull, brain, and cerebral meninges
A81: PDC | B81: P11AE | C81: Moderate Craniotomy Procedures | D81: ="04.05" -> 04.05 | E81: Gasserian ganglionectomy
A82: PDC | B82: P11AE | C82: Moderate Craniotomy Procedures | D82: ="04.41" -> 04.41 | E82: Decompression of trigeminal nerve root
A83: PDC | B83: P11AE | C83: Moderate Craniotomy Procedures | D83: ="04.42" -> 04.42 | E83: Other cranial nerve decompression
A84: PDC | B84: P11AE | C84: Moderate Craniotomy Procedures | D84: ="04.421" -> 04.421 | E84: Decompression of facial nerve with or without graft (IM)
A85: PDC | B85: P11AE | C85: Moderate Craniotomy Procedures | D85: ="07.13" -> 07.13 | E85: Biopsy of pituitary gland, transfrontal approach
A86: PDC | B86: P11AE | C86: Moderate Craniotomy Procedures | D86: ="07.14" -> 07.14 | E86: Biopsy of pituitary gland, transsphenoidal approach
A87: PDC | B87: P11AE | C87: Moderate Craniotomy Procedures | D87: ="07.15" -> 07.15 | E87: Biopsy of pituitary gland, unspecified approach
A88: PDC | B88: P11AE | C88: Moderate Craniotomy Procedures | D88: ="07.17" -> 07.17 | E88: Biopsy of pineal gland
A89: PDC | B89: P11AE | C89: Moderate Craniotomy Procedures | D89: ="07.51" -> 07.51 | E89: Exploration of pineal field
A90: PDC | B90: P11AE | C90: Moderate Craniotomy Procedures | D90: ="07.52" -> 07.52 | E90: Incision of pineal gland
A91: PDC | B91: P11AE | C91: Moderate Craniotomy Procedures | D91: ="07.53" -> 07.53 | E91: Partial excision of pineal gland
A92: PDC | B92: P11AE | C92: Moderate Craniotomy Procedures | D92: ="07.54" -> 07.54 | E92: Total excision of pineal gland
A93: PDC | B93: P11AE | C93: Moderate Craniotomy Procedures | D93: ="07.59" -> 07.59 | E93: Other operations on pineal gland
A94: PDC | B94: P11AE | C94: Moderate Craniotomy Procedures | D94: ="07.61" -> 07.61 | E94: Partial excision of pituitary gland, transfrontal approach
A95: PDC | B95: P11AE | C95: Moderate Craniotomy Procedures | D95: ="07.62" -> 07.62 | E95: Partial excision of pituitary gland, transsphenoidal approach
A96: PDC | B96: P11AE | C96: Moderate Craniotomy Procedures | D96: ="07.63" -> 07.63 | E96: Partial excision of pituitary gland, unspecified approach
A97: PDC | B97: P11AE | C97: Moderate Craniotomy Procedures | D97: ="07.64" -> 07.64 | E97: Total excision of pituitary gland, transfrontal approach
A98: PDC | B98: P11AE | C98: Moderate Craniotomy Procedures | D98: ="07.65" -> 07.65 | E98: Total excision of pituitary gland, transsphenoidal approach
A99: PDC | B99: P11AE | C99: Moderate Craniotomy Procedures | D99: ="07.68" -> 07.68 | E99: Total excision of pituitary gland, other specified approach
A100: PDC | B100: P11AE | C100: Moderate Craniotomy Procedures | D100: ="07.69" -> 07.69 | E100: Total excision of pituitary gland, unspecified approach
...

Sheet ranap clusters obsolete
A1: Cluster Type | B1: Cluster Code | C1: Cluster Description | D1: ICD-9-CM Code | E1: ICD-9-CM Description | F1: Grade | G1: IM | H1: New Cluster Description | I1: new PDC | J1: jumlah kasus | K1: mean_billing | L1: p25 | M1: p50 | N1: p75 | O1: p90 | P1: total | Q1: Keterangan | R1: 8037060
A2: PDC | B2: P11AC | C2: Endovascular Procedures for Neurologic Diseases | D2: 00.62 | E2: Percutaneous angioplasty or atherectomy of intracranial vessel(s) | F2: =VLOOKUP($D2,proc!$A:$D,3,FALSE) -> 3 | G2: =VLOOKUP($D2,proc!$A:$D,4,FALSE) -> 0 | H2: Endovascular Proc. for Neurologic Diseases | J2: =VLOOKUP($D2,'prosedur-2025'!$A:$H,3,FALSE) -> 120 | K2: =VLOOKUP($D2,'prosedur-2025'!$A:$H,4,FALSE) -> 78497963 | L2: =VLOOKUP($D2,'prosedur-2025'!$A:$H,5,FALSE) -> 31029390 | M2: =VLOOKUP($D2,'prosedur-2025'!$A:$H,6,FALSE) -> 49040723 | N2: =VLOOKUP($D2,'prosedur-2025'!$A:$H,7,FALSE) -> 88993193 | O2: =VLOOKUP($D2,'prosedur-2025'!$A:$H,8,FALSE) -> 153022000 | P2: =J2*K2 -> 9419755502
A3: PDC | B3: P11AC | C3: Endovascular Procedures for Neurologic Diseases | D3: 38.52 | E3: Ligation and stripping of varicose veins, other vessels of head and neck | F3: =VLOOKUP($D3,proc!$A:$D,3,FALSE) -> 0 | G3: =VLOOKUP($D3,proc!$A:$D,4,FALSE) -> 0 | H3: Endovascular Proc. for Neurologic Diseases | J3: =VLOOKUP($D3,'prosedur-2025'!$A:$H,3,FALSE) -> 33 | K3: =VLOOKUP($D3,'prosedur-2025'!$A:$H,4,FALSE) -> 21821658 | L3: =VLOOKUP($D3,'prosedur-2025'!$A:$H,5,FALSE) -> 7330331 | M3: =VLOOKUP($D3,'prosedur-2025'!$A:$H,6,FALSE) -> 13625695 | N3: =VLOOKUP($D3,'prosedur-2025'!$A:$H,7,FALSE) -> 22771045 | O3: =VLOOKUP($D3,'prosedur-2025'!$A:$H,8,FALSE) -> 55892400 | P3: =J3*K3 -> 720114702
A4: PDC | B4: P11AC | C4: Endovascular Procedures for Neurologic Diseases | D4: 38.7 | E4: Interruption vena cava | F4: =VLOOKUP($D4,proc!$A:$D,3,FALSE) -> 5 | G4: =VLOOKUP($D4,proc!$A:$D,4,FALSE) -> 0 | H4: Endovascular Proc. for Neurologic Diseases | J4: =VLOOKUP($D4,'prosedur-2025'!$A:$H,3,FALSE) -> 121 | K4: =VLOOKUP($D4,'prosedur-2025'!$A:$H,4,FALSE) -> 67670327 | L4: =VLOOKUP($D4,'prosedur-2025'!$A:$H,5,FALSE) -> 29852859 | M4: =VLOOKUP($D4,'prosedur-2025'!$A:$H,6,FALSE) -> 58105112 | N4: =VLOOKUP($D4,'prosedur-2025'!$A:$H,7,FALSE) -> 92598541 | O4: =VLOOKUP($D4,'prosedur-2025'!$A:$H,8,FALSE) -> 135912123 | P4: =J4*K4 -> 8188109584
A5: PDC | B5: P11AC | C5: Endovascular Procedures for Neurologic Diseases | D5: 38.82 | E5: Other surgical occlusion of vessels, other vessels of head and neck | F5: =VLOOKUP($D5,proc!$A:$D,3,FALSE) -> 4 | G5: =VLOOKUP($D5,proc!$A:$D,4,FALSE) -> 0 | H5: Endovascular Proc. for Neurologic Diseases | J5: =VLOOKUP($D5,'prosedur-2025'!$A:$H,3,FALSE) -> 434 | K5: =VLOOKUP($D5,'prosedur-2025'!$A:$H,4,FALSE) -> 48032893 | L5: =VLOOKUP($D5,'prosedur-2025'!$A:$H,5,FALSE) -> 10435277 | M5: =VLOOKUP($D5,'prosedur-2025'!$A:$H,6,FALSE) -> 22179491 | N5: =VLOOKUP($D5,'prosedur-2025'!$A:$H,7,FALSE) -> 61098522 | O5: =VLOOKUP($D5,'prosedur-2025'!$A:$H,8,FALSE) -> 123946351 | P5: =J5*K5 -> 20846275429
A6: PDC | B6: P11AC | C6: Endovascular Procedures for Neurologic Diseases | D6: 39.72 | E6: Endovascular embolization or occlusion of head and neck vessels | F6: =VLOOKUP($D6,proc!$A:$D,3,FALSE) -> 6 | G6: =VLOOKUP($D6,proc!$A:$D,4,FALSE) -> 0 | H6: Endovascular Proc. for Neurologic Diseases | J6: =VLOOKUP($D6,'prosedur-2025'!$A:$H,3,FALSE) -> 339 | K6: =VLOOKUP($D6,'prosedur-2025'!$A:$H,4,FALSE) -> 77422054 | L6: =VLOOKUP($D6,'prosedur-2025'!$A:$H,5,FALSE) -> 34528674 | M6: =VLOOKUP($D6,'prosedur-2025'!$A:$H,6,FALSE) -> 59125877 | N6: =VLOOKUP($D6,'prosedur-2025'!$A:$H,7,FALSE) -> 99036851 | O6: =VLOOKUP($D6,'prosedur-2025'!$A:$H,8,FALSE) -> 162366954 | P6: =J6*K6 -> 26246076412
A7: PDC | B7: P11AC | C7: Endovascular Procedures for Neurologic Diseases | D7: 39.74 | E7: Endovascular removal of obstruction from head and neck vessel(s) | F7: =VLOOKUP($D7,proc!$A:$D,3,FALSE) -> 5 | G7: =VLOOKUP($D7,proc!$A:$D,4,FALSE) -> 0 | H7: Endovascular Proc. for Neurologic Diseases | J7: =VLOOKUP($D7,'prosedur-2025'!$A:$H,3,FALSE) -> 412 | K7: =VLOOKUP($D7,'prosedur-2025'!$A:$H,4,FALSE) -> 1.1316846e+08 | L7: =VLOOKUP($D7,'prosedur-2025'!$A:$H,5,FALSE) -> 61273050 | M7: =VLOOKUP($D7,'prosedur-2025'!$A:$H,6,FALSE) -> 97611950 | N7: =VLOOKUP($D7,'prosedur-2025'!$A:$H,7,FALSE) -> 139420700 | O7: =VLOOKUP($D7,'prosedur-2025'!$A:$H,8,FALSE) -> 193880000 | P7: =J7*K7 -> 46625405734
A8: PDC | B8: P11AC | C8: Endovascular Procedures for Neurologic Diseases | D8: 39.75 | E8: Endovascular embolization or occlusion of vessel(s) of head or neck using bare coils | F8: =VLOOKUP($D8,proc!$A:$D,3,FALSE) -> 5 | G8: =VLOOKUP($D8,proc!$A:$D,4,FALSE) -> 0 | H8: Endovascular Proc. for Neurologic Diseases | J8: =VLOOKUP($D8,'prosedur-2025'!$A:$H,3,FALSE) -> 820 | K8: =VLOOKUP($D8,'prosedur-2025'!$A:$H,4,FALSE) -> 1.2139781e+08 | L8: =VLOOKUP($D8,'prosedur-2025'!$A:$H,5,FALSE) -> 72539060 | M8: =VLOOKUP($D8,'prosedur-2025'!$A:$H,6,FALSE) -> 100933007 | N8: =VLOOKUP($D8,'prosedur-2025'!$A:$H,7,FALSE) -> 144954100 | O8: =VLOOKUP($D8,'prosedur-2025'!$A:$H,8,FALSE) -> 207161425 | P8: =J8*K8 -> 99546207534
A9: PDC | B9: P11AC | C9: Endovascular Procedures for Neurologic Diseases | D9: 39.76 | E9: Endovascular embolization or occlusion of vessel(s) of head or neck using bioactive coils | F9: =VLOOKUP($D9,proc!$A:$D,3,FALSE) -> 5 | G9: =VLOOKUP($D9,proc!$A:$D,4,FALSE) -> 0 | H9: Endovascular Proc. for Neurologic Diseases | J9: =VLOOKUP($D9,'prosedur-2025'!$A:$H,3,FALSE) -> 25 | K9: =VLOOKUP($D9,'prosedur-2025'!$A:$H,4,FALSE) -> 73873294 | L9: =VLOOKUP($D9,'prosedur-2025'!$A:$H,5,FALSE) -> 46871484 | M9: =VLOOKUP($D9,'prosedur-2025'!$A:$H,6,FALSE) -> 62436689 | N9: =VLOOKUP($D9,'prosedur-2025'!$A:$H,7,FALSE) -> 95671460 | O9: =VLOOKUP($D9,'prosedur-2025'!$A:$H,8,FALSE) -> 147131046 | P9: =J9*K9 -> 1846832339
A10: PDC | B10: P11AC | C10: Endovascular Procedures for Neurologic Diseases | D10: 39.81 | E10: Implantation or replacement of carotid sinus stimulation device, total system (IM) | F10: =VLOOKUP($D10,proc!$A:$D,3,FALSE) -> 4 | G10: =VLOOKUP($D10,proc!$A:$D,4,FALSE) -> 1 | H10: Endovascular Proc. for Neurologic Diseases | J10: =VLOOKUP($D10,'prosedur-2025'!$A:$H,3,FALSE) -> 3 | K10: =VLOOKUP($D10,'prosedur-2025'!$A:$H,4,FALSE) -> 66396559 | L10: =VLOOKUP($D10,'prosedur-2025'!$A:$H,5,FALSE) -> 13113019 | M10: =VLOOKUP($D10,'prosedur-2025'!$A:$H,6,FALSE) -> 55660455 | N10: =VLOOKUP($D10,'prosedur-2025'!$A:$H,7,FALSE) -> 130416204 | O10: =VLOOKUP($D10,'prosedur-2025'!$A:$H,8,FALSE) -> 130416204 | P10: =J10*K10 -> 199189678
A11: PDC | B11: P11AC | C11: Endovascular Procedures for Neurologic Diseases | D11: 39.82 | E11: Implantation or replacement of carotid sinus stimulation lead(s) only (IM) | F11: =VLOOKUP($D11,proc!$A:$D,3,FALSE) -> 4 | G11: =VLOOKUP($D11,proc!$A:$D,4,FALSE) -> 1 | H11: Endovascular Proc. for Neurologic Diseases | J11: =VLOOKUP($D11,'prosedur-2025'!$A:$H,3,FALSE) -> 3 | K11: =VLOOKUP($D11,'prosedur-2025'!$A:$H,4,FALSE) -> 22003947 | L11: =VLOOKUP($D11,'prosedur-2025'!$A:$H,5,FALSE) -> 2830922 | M11: =VLOOKUP($D11,'prosedur-2025'!$A:$H,6,FALSE) -> 23146200 | N11: =VLOOKUP($D11,'prosedur-2025'!$A:$H,7,FALSE) -> 40034720 | O11: =VLOOKUP($D11,'prosedur-2025'!$A:$H,8,FALSE) -> 40034720 | P11: =J11*K11 -> 66011842
A12: PDC | B12: P11AC | C12: Endovascular Procedures for Neurologic Diseases | D12: 39.83 | E12: Implantation or replacement of carotid sinus stimulation pulse generator only (IM) | F12: =VLOOKUP($D12,proc!$A:$D,3,FALSE) -> 4 | G12: =VLOOKUP($D12,proc!$A:$D,4,FALSE) -> 1 | H12: Endovascular Proc. for Neurologic Diseases | J12: =VLOOKUP($D12,'prosedur-2025'!$A:$H,3,FALSE) -> 21 | K12: =VLOOKUP($D12,'prosedur-2025'!$A:$H,4,FALSE) -> 61165163 | L12: =VLOOKUP($D12,'prosedur-2025'!$A:$H,5,FALSE) -> 24235442 | M12: =VLOOKUP($D12,'prosedur-2025'!$A:$H,6,FALSE) -> 50697300 | N12: =VLOOKUP($D12,'prosedur-2025'!$A:$H,7,FALSE) -> 81533763 | O12: =VLOOKUP($D12,'prosedur-2025'!$A:$H,8,FALSE) -> 143177942 | P12: =J12*K12 -> 1284468416
A13: PDC | B13: P11AC | C13: Endovascular Procedures for Neurologic Diseases | D13: 39.84 | E13: Revision of carotid sinus stimulation lead(s) only (IM) | F13: =VLOOKUP($D13,proc!$A:$D,3,FALSE) -> 4 | G13: =VLOOKUP($D13,proc!$A:$D,4,FALSE) -> 1 | H13: Endovascular Proc. for Neurologic Diseases
A14: PDC | B14: P11AC | C14: Endovascular Procedures for Neurologic Diseases | D14: 39.85 | E14: Revision of carotid sinus stimulation pulse generator (IM) | F14: =VLOOKUP($D14,proc!$A:$D,3,FALSE) -> 4 | G14: =VLOOKUP($D14,proc!$A:$D,4,FALSE) -> 1 | H14: Endovascular Proc. for Neurologic Diseases | J14: =VLOOKUP($D14,'prosedur-2025'!$A:$H,3,FALSE) -> 19 | K14: =VLOOKUP($D14,'prosedur-2025'!$A:$H,4,FALSE) -> 33694355 | L14: =VLOOKUP($D14,'prosedur-2025'!$A:$H,5,FALSE) -> 11539385 | M14: =VLOOKUP($D14,'prosedur-2025'!$A:$H,6,FALSE) -> 17995946 | N14: =VLOOKUP($D14,'prosedur-2025'!$A:$H,7,FALSE) -> 46867900 | O14: =VLOOKUP($D14,'prosedur-2025'!$A:$H,8,FALSE) -> 106980599 | P14: =J14*K14 -> 640192748
A15: PDC | B15: P11AC | C15: Endovascular Procedures for Neurologic Diseases | D15: 39.86 | E15: Removal of carotid sinus stimulation device, total system (IM) | F15: =VLOOKUP($D15,proc!$A:$D,3,FALSE) -> 4 | G15: =VLOOKUP($D15,proc!$A:$D,4,FALSE) -> 1 | H15: Endovascular Proc. for Neurologic Diseases
A16: PDC | B16: P11AC | C16: Endovascular Procedures for Neurologic Diseases | D16: 39.87 | E16: Removal of carotid sinus stimulation lead(s) only (IM) | F16: =VLOOKUP($D16,proc!$A:$D,3,FALSE) -> 4 | G16: =VLOOKUP($D16,proc!$A:$D,4,FALSE) -> 1 | H16: Endovascular Proc. for Neurologic Diseases | J16: =VLOOKUP($D16,'prosedur-2025'!$A:$H,3,FALSE) -> 9 | K16: =VLOOKUP($D16,'prosedur-2025'!$A:$H,4,FALSE) -> 45263476 | L16: =VLOOKUP($D16,'prosedur-2025'!$A:$H,5,FALSE) -> 12766300 | M16: =VLOOKUP($D16,'prosedur-2025'!$A:$H,6,FALSE) -> 27068225 | N16: =VLOOKUP($D16,'prosedur-2025'!$A:$H,7,FALSE) -> 76887394 | O16: =VLOOKUP($D16,'prosedur-2025'!$A:$H,8,FALSE) -> 113466738 | P16: =J16*K16 -> 407371283
A17: PDC | B17: P11AC | C17: Endovascular Procedures for Neurologic Diseases | D17: 39.88 | E17: Removal of carotid sinus stimulation pulse generator only (IM) | F17: =VLOOKUP($D17,proc!$A:$D,3,FALSE) -> 4 | G17: =VLOOKUP($D17,proc!$A:$D,4,FALSE) -> 1 | H17: Endovascular Proc. for Neurologic Diseases | J17: =VLOOKUP($D17,'prosedur-2025'!$A:$H,3,FALSE) -> 4 | K17: =VLOOKUP($D17,'prosedur-2025'!$A:$H,4,FALSE) -> 80759175 | L17: =VLOOKUP($D17,'prosedur-2025'!$A:$H,5,FALSE) -> 27335689 | M17: =VLOOKUP($D17,'prosedur-2025'!$A:$H,6,FALSE) -> 59070224 | N17: =VLOOKUP($D17,'prosedur-2025'!$A:$H,7,FALSE) -> 62839575 | O17: =VLOOKUP($D17,'prosedur-2025'!$A:$H,8,FALSE) -> 173791213 | P17: =J17*K17 -> 323036701
A18: PDC | B18: P11AC | C18: Endovascular Procedures for Neurologic Diseases | D18: 39.89 | E18: Other operations on carotid body, carotid sinus and other vascular bodies (IM) | F18: =VLOOKUP($D18,proc!$A:$D,3,FALSE) -> 4 | G18: =VLOOKUP($D18,proc!$A:$D,4,FALSE) -> 1 | H18: Endovascular Proc. for Neurologic Diseases | J18: =VLOOKUP($D18,'prosedur-2025'!$A:$H,3,FALSE) -> 6 | K18: =VLOOKUP($D18,'prosedur-2025'!$A:$H,4,FALSE) -> 30687575 | L18: =VLOOKUP($D18,'prosedur-2025'!$A:$H,5,FALSE) -> 8104487 | M18: =VLOOKUP($D18,'prosedur-2025'!$A:$H,6,FALSE) -> 27889516 | N18: =VLOOKUP($D18,'prosedur-2025'!$A:$H,7,FALSE) -> 34947067 | O18: =VLOOKUP($D18,'prosedur-2025'!$A:$H,8,FALSE) -> 76434965 | P18: =J18*K18 -> 184125448
A19: PDC | B19: P11AD | C19: Complex Spinal Procedures | D19: 03.01 | E19: Removal of foreign body from spinal canal | F19: =VLOOKUP($D19,proc!$A:$D,3,FALSE) -> 5 | G19: =VLOOKUP($D19,proc!$A:$D,4,FALSE) -> 0 | H19: Moderate Spinal Proc. | J19: =VLOOKUP($D19,'prosedur-2025'!$A:$H,3,FALSE) -> 12 | K19: =VLOOKUP($D19,'prosedur-2025'!$A:$H,4,FALSE) -> 68030011 | L19: =VLOOKUP($D19,'prosedur-2025'!$A:$H,5,FALSE) -> 37169810 | M19: =VLOOKUP($D19,'prosedur-2025'!$A:$H,6,FALSE) -> 47495894 | N19: =VLOOKUP($D19,'prosedur-2025'!$A:$H,7,FALSE) -> 86573446 | O19: =VLOOKUP($D19,'prosedur-2025'!$A:$H,8,FALSE) -> 91434374 | P19: =J19*K19 -> 816360130
A20: PDC | B20: P11AD | C20: Complex Spinal Procedures | D20: 03.02 | E20: Reopening of laminectomy site | F20: =VLOOKUP($D20,proc!$A:$D,3,FALSE) -> 5 | G20: =VLOOKUP($D20,proc!$A:$D,4,FALSE) -> 0 | H20: Moderate Spinal Proc. | J20: =VLOOKUP($D20,'prosedur-2025'!$A:$H,3,FALSE) -> 226 | K20: =VLOOKUP($D20,'prosedur-2025'!$A:$H,4,FALSE) -> 58748393 | L20: =VLOOKUP($D20,'prosedur-2025'!$A:$H,5,FALSE) -> 27898024 | M20: =VLOOKUP($D20,'prosedur-2025'!$A:$H,6,FALSE) -> 46204400 | N20: =VLOOKUP($D20,'prosedur-2025'!$A:$H,7,FALSE) -> 74596310 | O20: =VLOOKUP($D20,'prosedur-2025'!$A:$H,8,FALSE) -> 122337966 | P20: =J20*K20 -> 13277136710
A21: PDC | B21: P11AD | C21: Complex Spinal Procedures | D21: 03.09 | E21: Other exploration and decompression of spinal canal | F21: =VLOOKUP($D21,proc!$A:$D,3,FALSE) -> 5 | G21: =VLOOKUP($D21,proc!$A:$D,4,FALSE) -> 0 | H21: Moderate Spinal Proc. | J21: =VLOOKUP($D21,'prosedur-2025'!$A:$H,3,FALSE) -> 9293 | K21: =VLOOKUP($D21,'prosedur-2025'!$A:$H,4,FALSE) -> 59760268 | L21: =VLOOKUP($D21,'prosedur-2025'!$A:$H,5,FALSE) -> 35810933 | M21: =VLOOKUP($D21,'prosedur-2025'!$A:$H,6,FALSE) -> 51791394 | N21: =VLOOKUP($D21,'prosedur-2025'!$A:$H,7,FALSE) -> 72016486 | O21: =VLOOKUP($D21,'prosedur-2025'!$A:$H,8,FALSE) -> 102710378 | P21: =J21*K21 -> 555352166212
A22: PDC | B22: P11AD | C22: Complex Spinal Procedures | D22: 03.21 | E22: Percutaneous chordotomy | F22: =VLOOKUP($D22,proc!$A:$D,3,FALSE) -> 4 | G22: =VLOOKUP($D22,proc!$A:$D,4,FALSE) -> 0 | H22: Moderate Spinal Proc. | J22: =VLOOKUP($D22,'prosedur-2025'!$A:$H,3,FALSE) -> 2 | K22: =VLOOKUP($D22,'prosedur-2025'!$A:$H,4,FALSE) -> 62128059 | L22: =VLOOKUP($D22,'prosedur-2025'!$A:$H,5,FALSE) -> 10275818 | M22: =VLOOKUP($D22,'prosedur-2025'!$A:$H,6,FALSE) -> 10275818 | N22: =VLOOKUP($D22,'prosedur-2025'!$A:$H,7,FALSE) -> 113980300 | O22: =VLOOKUP($D22,'prosedur-2025'!$A:$H,8,FALSE) -> 113980300 | P22: =J22*K22 -> 124256118
A23: PDC | B23: P11AD | C23: Complex Spinal Procedures | D23: 03.29 | E23: Other chordotomy | F23: =VLOOKUP($D23,proc!$A:$D,3,FALSE) -> 4 | G23: =VLOOKUP($D23,proc!$A:$D,4,FALSE) -> 0 | H23: Moderate Spinal Proc. | J23: =VLOOKUP($D23,'prosedur-2025'!$A:$H,3,FALSE) -> 14 | K23: =VLOOKUP($D23,'prosedur-2025'!$A:$H,4,FALSE) -> 56094480 | L23: =VLOOKUP($D23,'prosedur-2025'!$A:$H,5,FALSE) -> 17227265 | M23: =VLOOKUP($D23,'prosedur-2025'!$A:$H,6,FALSE) -> 58180620 | N23: =VLOOKUP($D23,'prosedur-2025'!$A:$H,7,FALSE) -> 88350158 | O23: =VLOOKUP($D23,'prosedur-2025'!$A:$H,8,FALSE) -> 97786657 | P23: =J23*K23 -> 785322726
A24: PDC | B24: P11AD | C24: Complex Spinal Procedures | D24: 03.4 | E24: Excision or destruction of lesion of spinal cord or spinal meninges | F24: =VLOOKUP($D24,proc!$A:$D,3,FALSE) -> 6 | G24: =VLOOKUP($D24,proc!$A:$D,4,FALSE) -> 0 | H24: Complex Spinal Proc. | J24: =VLOOKUP($D24,'prosedur-2025'!$A:$H,3,FALSE) -> 969 | K24: =VLOOKUP($D24,'prosedur-2025'!$A:$H,4,FALSE) -> 80259541 | L24: =VLOOKUP($D24,'prosedur-2025'!$A:$H,5,FALSE) -> 37570498 | M24: =VLOOKUP($D24,'prosedur-2025'!$A:$H,6,FALSE) -> 67611921 | N24: =VLOOKUP($D24,'prosedur-2025'!$A:$H,7,FALSE) -> 98550892 | O24: =VLOOKUP($D24,'prosedur-2025'!$A:$H,8,FALSE) -> 159266167 | P24: =J24*K24 -> 77771495627
A25: PDC | B25: P11AD | C25: Complex Spinal Procedures | D25: 03.51 | E25: Repair of spinal meningocele | F25: =VLOOKUP($D25,proc!$A:$D,3,FALSE) -> 5 | G25: =VLOOKUP($D25,proc!$A:$D,4,FALSE) -> 0 | H25: Moderate Spinal Proc. | J25: =VLOOKUP($D25,'prosedur-2025'!$A:$H,3,FALSE) -> 82 | K25: =VLOOKUP($D25,'prosedur-2025'!$A:$H,4,FALSE) -> 68166626 | L25: =VLOOKUP($D25,'prosedur-2025'!$A:$H,5,FALSE) -> 32504489 | M25: =VLOOKUP($D25,'prosedur-2025'!$A:$H,6,FALSE) -> 57467984 | N25: =VLOOKUP($D25,'prosedur-2025'!$A:$H,7,FALSE) -> 89998640 | O25: =VLOOKUP($D25,'prosedur-2025'!$A:$H,8,FALSE) -> 119390219 | P25: =J25*K25 -> 5589663365
A26: PDC | B26: P11AD | C26: Complex Spinal Procedures | D26: 03.52 | E26: Repair of spinal myelomeningocele | F26: =VLOOKUP($D26,proc!$A:$D,3,FALSE) -> 5 | G26: =VLOOKUP($D26,proc!$A:$D,4,FALSE) -> 0 | H26: Complex Spinal Proc. | J26: =VLOOKUP($D26,'prosedur-2025'!$A:$H,3,FALSE) -> 101 | K26: =VLOOKUP($D26,'prosedur-2025'!$A:$H,4,FALSE) -> 68653256 | L26: =VLOOKUP($D26,'prosedur-2025'!$A:$H,5,FALSE) -> 32601013 | M26: =VLOOKUP($D26,'prosedur-2025'!$A:$H,6,FALSE) -> 50170854 | N26: =VLOOKUP($D26,'prosedur-2025'!$A:$H,7,FALSE) -> 82461979 | O26: =VLOOKUP($D26,'prosedur-2025'!$A:$H,8,FALSE) -> 143505352 | P26: =J26*K26 -> 6933978859
A27: PDC | B27: P11AD | C27: Complex Spinal Procedures | D27: 03.53 | E27: Repair of vertebral fracture | F27: =VLOOKUP($D27,proc!$A:$D,3,FALSE) -> 5 | G27: =VLOOKUP($D27,proc!$A:$D,4,FALSE) -> 0 | H27: Moderate Spinal Proc. | J27: =VLOOKUP($D27,'prosedur-2025'!$A:$H,3,FALSE) -> 109 | K27: =VLOOKUP($D27,'prosedur-2025'!$A:$H,4,FALSE) -> 74716957 | L27: =VLOOKUP($D27,'prosedur-2025'!$A:$H,5,FALSE) -> 52512103 | M27: =VLOOKUP($D27,'prosedur-2025'!$A:$H,6,FALSE) -> 71569867 | N27: =VLOOKUP($D27,'prosedur-2025'!$A:$H,7,FALSE) -> 93427650 | O27: =VLOOKUP($D27,'prosedur-2025'!$A:$H,8,FALSE) -> 133643976 | P27: =J27*K27 -> 8144148286
... A30: PDC | B30: P11AD | C30: Complex Spinal Procedures | D30: 03.71 | E30: Spinal subarachnoid-peritoneal shunt | F30: =VLOOKUP($D30,proc!$A:$D,3,FALSE) -> 4 | G30: =VLOOKUP($D30,proc!$A:$D,4,FALSE) -> 0 | H30: Moderate Spinal Proc. | J30: =VLOOKUP($D30,'prosedur-2025'!$A:$H,3,FALSE) -> 11 | K30: =VLOOKUP($D30,'prosedur-2025'!$A:$H,4,FALSE) -> 61719059 | L30: =VLOOKUP($D30,'prosedur-2025'!$A:$H,5,FALSE) -> 30268917 | M30: =VLOOKUP($D30,'prosedur-2025'!$A:$H,6,FALSE) -> 49767972 | N30: =VLOOKUP($D30,'prosedur-2025'!$A:$H,7,FALSE) -> 82947747 | O30: =VLOOKUP($D30,'prosedur-2025'!$A:$H,8,FALSE) -> 92224400 | P30: =J30*K30 -> 678909647
A31: PDC | B31: P11AD | C31: Complex Spinal Procedures | D31: 03.72 | E31: Spinal subarachnoid-ureteral shunt | F31: =VLOOKUP($D31,proc!$A:$D,3,FALSE) -> 4 | G31: =VLOOKUP($D31,proc!$A:$D,4,FALSE) -> 0 | H31: Moderate Spinal Proc.
A32: PDC | B32: P11AD | C32: Complex Spinal Procedures | D32: 03.79 | E32: Other shunt of spinal theca | F32: =VLOOKUP($D32,proc!$A:$D,3,FALSE) -> 4 | G32: =VLOOKUP($D32,proc!$A:$D,4,FALSE) -> 0 | H32: Moderate Spinal Proc. | J32: =VLOOKUP($D32,'prosedur-2025'!$A:$H,3,FALSE) -> 28 | K32: =VLOOKUP($D32,'prosedur-2025'!$A:$H,4,FALSE) -> 86356199 | L32: =VLOOKUP($D32,'prosedur-2025'!$A:$H,5,FALSE) -> 50049275 | M32: =VLOOKUP($D32,'prosedur-2025'!$A:$H,6,FALSE) -> 87553186 | N32: =VLOOKUP($D32,'prosedur-2025'!$A:$H,7,FALSE) -> 118772842 | O32: =VLOOKUP($D32,'prosedur-2025'!$A:$H,8,FALSE) -> 144357842 | P32: =J32*K32 -> 2417973559
A33: PDC | B33: P11AD | C33: Complex Spinal Procedures | D33: 03.93 | E33: Implantation or replacement of spinal neurostimulator lead(s) | F33: =VLOOKUP($D33,proc!$A:$D,3,FALSE) -> 2 | G33: =VLOOKUP($D33,proc!$A:$D,4,FALSE) -> 0 | H33: Neuromodulation | J33: =VLOOKUP($D33,'prosedur-2025'!$A:$H,3,FALSE) -> 4 | K33: =VLOOKUP($D33,'prosedur-2025'!$A:$H,4,FALSE) -> 62796968 | L33: =VLOOKUP($D33,'prosedur-2025'!$A:$H,5,FALSE) -> 21537047 | M33: =VLOOKUP($D33,'prosedur-2025'!$A:$H,6,FALSE) -> 58677511 | N33: =VLOOKUP($D33,'prosedur-2025'!$A:$H,7,FALSE) -> 72113063 | O33: =VLOOKUP($D33,'prosedur-2025'!$A:$H,8,FALSE) -> 98860250 | P33: =J33*K33 -> 251187871
A34: PDC | B34: P11AD | C34: Complex Spinal Procedures | D34: 03.97 | E34: Revision of spinal thecal shunt | F34: =VLOOKUP($D34,proc!$A:$D,3,FALSE) -> 4 | G34: =VLOOKUP($D34,proc!$A:$D,4,FALSE) -> 0 | H34: Moderate Spinal Proc. | J34: =VLOOKUP($D34,'prosedur-2025'!$A:$H,3,FALSE) -> 4 | K34: =VLOOKUP($D34,'prosedur-2025'!$A:$H,4,FALSE) -> 37675131 | L34: =VLOOKUP($D34,'prosedur-2025'!$A:$H,5,FALSE) -> 6034823 | M34: =VLOOKUP($D34,'prosedur-2025'!$A:$H,6,FALSE) -> 6176764 | N34: =VLOOKUP($D34,'prosedur-2025'!$A:$H,7,FALSE) -> 23281087 | O34: =VLOOKUP($D34,'prosedur-2025'!$A:$H,8,FALSE) -> 115207850 | P34: =J34*K34 -> 150700524
A35: PDC | B35: P11AD | C35: Complex Spinal Procedures | D35: 03.99 | E35: Other operations on spinal cord and spinal canal structures | F35: =VLOOKUP($D35,proc!$A:$D,3,FALSE) -> 3 | G35: =VLOOKUP($D35,proc!$A:$D,4,FALSE) -> 0 | H35: Complex Spinal Proc. | J35: =VLOOKUP($D35,'prosedur-2025'!$A:$H,3,FALSE) -> 43 | K35: =VLOOKUP($D35,'prosedur-2025'!$A:$H,4,FALSE) -> 67769438 | L35: =VLOOKUP($D35,'prosedur-2025'!$A:$H,5,FALSE) -> 28286512 | M35: =VLOOKUP($D35,'prosedur-2025'!$A:$H,6,FALSE) -> 54070788 | N35: =VLOOKUP($D35,'prosedur-2025'!$A:$H,7,FALSE) -> 90470150 | O35: =VLOOKUP($D35,'prosedur-2025'!$A:$H,8,FALSE) -> 121648571 | P35: =J35*K35 -> 2914085816
A36: PDC | B36: P11AD | C36: Complex Spinal Procedures | D36: 77.81 | E36: Other partial ostectomy, scapula, clavicle, and thorax [ribs and sternum] | F36: =VLOOKUP($D36,proc!$A:$D,3,FALSE) -> 3 | G36: =VLOOKUP($D36,proc!$A:$D,4,FALSE) -> 0 | H36: Moderate Spinal Proc. | J36: =VLOOKUP($D36,'prosedur-2025'!$A:$H,3,FALSE) -> 121 | K36: =VLOOKUP($D36,'prosedur-2025'!$A:$H,4,FALSE) -> 38161526 | L36: =VLOOKUP($D36,'prosedur-2025'!$A:$H,5,FALSE) -> 8518840 | M36: =VLOOKUP($D36,'prosedur-2025'!$A:$H,6,FALSE) -> 15333076 | N36: =VLOOKUP($D36,'prosedur-2025'!$A:$H,7,FALSE) -> 32317948 | O36: =VLOOKUP($D36,'prosedur-2025'!$A:$H,8,FALSE) -> 102633976 | P36: =J36*K36 -> 4617544641
A37: PDC | B37: P11AD | C37: Complex Spinal Procedures | D37: 77.91 | E37: Total ostectomy, scapula, clavicle, and thorax [ribs and sternum] | F37: =VLOOKUP($D37,proc!$A:$D,3,FALSE) -> 5 | G37: =VLOOKUP($D37,proc!$A:$D,4,FALSE) -> 0 | H37: Moderate Spinal Proc. | J37: =VLOOKUP($D37,'prosedur-2025'!$A:$H,3,FALSE) -> 61 | K37: =VLOOKUP($D37,'prosedur-2025'!$A:$H,4,FALSE) -> 48177048 | L37: =VLOOKUP($D37,'prosedur-2025'!$A:$H,5,FALSE) -> 15263017 | M37: =VLOOKUP($D37,'prosedur-2025'!$A:$H,6,FALSE) -> 30053842 | N37: =VLOOKUP($D37,'prosedur-2025'!$A:$H,7,FALSE) -> 63933300 | O37: =VLOOKUP($D37,'prosedur-2025'!$A:$H,8,FALSE) -> 112482408 | P37: =J37*K37 -> 2938799910
A38: PDC | B38: P11AD | C38: Complex Spinal Procedures | D38: 80.55 | E38: Microdissectomy (endoscopic/microscopic) (IM) | F38: =VLOOKUP($D38,proc!$A:$D,3,FALSE) -> 4 | G38: =VLOOKUP($D38,proc!$A:$D,4,FALSE) -> 1 | H38: Moderate Spinal Proc.
A39: PDC | B39: P11AD | C39: Complex Spinal Procedures | D39: 81.00 | E39: Spinal fusion, not otherwise specified | F39: =VLOOKUP($D39,proc!$A:$D,3,FALSE) -> 5 | G39: =VLOOKUP($D39,proc!$A:$D,4,FALSE) -> 0 | H39: Complex Spinal Proc. | J39: =VLOOKUP($D39,'prosedur-2025'!$A:$H,3,FALSE) -> 1528 | K39: =VLOOKUP($D39,'prosedur-2025'!$A:$H,4,FALSE) -> 65674909 | L39: =VLOOKUP($D39,'prosedur-2025'!$A:$H,5,FALSE) -> 49936194 | M39: =VLOOKUP($D39,'prosedur-2025'!$A:$H,6,FALSE) -> 61234300 | N39: =VLOOKUP($D39,'prosedur-2025'!$A:$H,7,FALSE) -> 74515004 | O39: =VLOOKUP($D39,'prosedur-2025'!$A:$H,8,FALSE) -> 97919911 | P39: =J39*K39 -> 100351260453
A40: PDC | B40: P11AD | C40: Complex Spinal Procedures | D40: 81.01 | E40: Atlas-axis spinal fusion | F40: =VLOOKUP($D40,proc!$A:$D,3,FALSE) -> 6 | G40: =VLOOKUP($D40,proc!$A:$D,4,FALSE) -> 0 | H40: Complex Spinal Proc. | J40: =VLOOKUP($D40,'prosedur-2025'!$A:$H,3,FALSE) -> 27 | K40: =VLOOKUP($D40,'prosedur-2025'!$A:$H,4,FALSE) -> 1.2467283e+08 | L40: =VLOOKUP($D40,'prosedur-2025'!$A:$H,5,FALSE) -> 52639588 | M40: =VLOOKUP($D40,'prosedur-2025'!$A:$H,6,FALSE) -> 87551311 | N40: =VLOOKUP($D40,'prosedur-2025'!$A:$H,7,FALSE) -> 115964551 | O40: =VLOOKUP($D40,'prosedur-2025'!$A:$H,8,FALSE) -> 208639207 | P40: =J40*K40 -> 3366166364
A41: PDC | B41: P11AD | C41: Complex Spinal Procedures | D41: 81.02 | E41: Other cervical fusion of the anterior column, anterior technique | F41: =VLOOKUP($D41,proc!$A:$D,3,FALSE) -> 5 | G41: =VLOOKUP($D41,proc!$A:$D,4,FALSE) -> 0 | H41: Complex Spinal Proc. | J41: =VLOOKUP($D41,'prosedur-2025'!$A:$H,3,FALSE) -> 1124 | K41: =VLOOKUP($D41,'prosedur-2025'!$A:$H,4,FALSE) -> 81393964 | L41: =VLOOKUP($D41,'prosedur-2025'!$A:$H,5,FALSE) -> 49774876 | M41: =VLOOKUP($D41,'prosedur-2025'!$A:$H,6,FALSE) -> 68684800 | N41: =VLOOKUP($D41,'prosedur-2025'!$A:$H,7,FALSE) -> 97992005 | O41: =VLOOKUP($D41,'prosedur-2025'!$A:$H,8,FALSE) -> 141735725 | P41: =J41*K41 -> 91486815900
A42: PDC | B42: P11AD | C42: Complex Spinal Procedures | D42: 81.03 | E42: Other cervical fusion of the posterior column, posterior technique | F42: =VLOOKUP($D42,proc!$A:$D,3,FALSE) -> 5 | G42: =VLOOKUP($D42,proc!$A:$D,4,FALSE) -> 0 | H42: Complex Spinal Proc. | J42: =VLOOKUP($D42,'prosedur-2025'!$A:$H,3,FALSE) -> 875 | K42: =VLOOKUP($D42,'prosedur-2025'!$A:$H,4,FALSE) -> 94529035 | L42: =VLOOKUP($D42,'prosedur-2025'!$A:$H,5,FALSE) -> 56619127 | M42: =VLOOKUP($D42,'prosedur-2025'!$A:$H,6,FALSE) -> 78073992 | N42: =VLOOKUP($D42,'prosedur-2025'!$A:$H,7,FALSE) -> 110993428 | O42: =VLOOKUP($D42,'prosedur-2025'!$A:$H,8,FALSE) -> 160154433 | P42: =J42*K42 -> 82712905872
A43: PDC | B43: P11AD | C43: Complex Spinal Procedures | D43: 81.04 | E43: Dorsal and dorsolumbar fusion of the anterior column, anterior technique | F43: =VLOOKUP($D43,proc!$A:$D,3,FALSE) -> 5 | G43: =VLOOKUP($D43,proc!$A:$D,4,FALSE) -> 0 | H43: Complex Spinal Proc. | J43: =VLOOKUP($D43,'prosedur-2025'!$A:$H,3,FALSE) -> 156 | K43: =VLOOKUP($D43,'prosedur-2025'!$A:$H,4,FALSE) -> 62574827 | L43: =VLOOKUP($D43,'prosedur-2025'!$A:$H,5,FALSE) -> 38373771 | M43: =VLOOKUP($D43,'prosedur-2025'!$A:$H,6,FALSE) -> 47165305 | N43: =VLOOKUP($D43,'prosedur-2025'!$A:$H,7,FALSE) -> 72615200 | O43: =VLOOKUP($D43,'prosedur-2025'!$A:$H,8,FALSE) -> 122341412 | P43: =J43*K43 -> 9761672970
A44: PDC | B44: P11AD | C44: Complex Spinal Procedures | D44: 81.05 | E44: Dorsal and dorsolumbar fusion of the posterior column, posterior technique | F44: =VLOOKUP($D44,proc!$A:$D,3,FALSE) -> 5 | G44: =VLOOKUP($D44,proc!$A:$D,4,FALSE) -> 0 | H44: Complex Spinal Proc. | J44: =VLOOKUP($D44,'prosedur-2025'!$A:$H,3,FALSE) -> 3213 | K44: =VLOOKUP($D44,'prosedur-2025'!$A:$H,4,FALSE) -> 84793189 | L44: =VLOOKUP($D44,'prosedur-2025'!$A:$H,5,FALSE) -> 53141009 | M44: =VLOOKUP($D44,'prosedur-2025'!$A:$H,6,FALSE) -> 77159544 | N44: =VLOOKUP($D44,'prosedur-2025'!$A:$H,7,FALSE) -> 109024391 | O44: =VLOOKUP($D44,'prosedur-2025'!$A:$H,8,FALSE) -> 133632798 | P44: =J44*K44 -> 272440516704
A45: PDC | B45: P11AD | C45: Complex Spinal Procedures | D45: 81.06 | E45: Lumbar and lumbosacral fusion of the anterior column, anterior technique | F45: =VLOOKUP($D45,proc!$A:$D,3,FALSE) -> 5 | G45: =VLOOKUP($D45,proc!$A:$D,4,FALSE) -> 0 | H45: Complex Spinal Proc. | J45: =VLOOKUP($D45,'prosedur-2025'!$A:$H,3,FALSE) -> 517 | K45: =VLOOKUP($D45,'prosedur-2025'!$A:$H,4,FALSE) -> 68693105 | L45: =VLOOKUP($D45,'prosedur-2025'!$A:$H,5,FALSE) -> 46359588 | M45: =VLOOKUP($D45,'prosedur-2025'!$A:$H,6,FALSE) -> 61443163 | N45: =VLOOKUP($D45,'prosedur-2025'!$A:$H,7,FALSE) -> 85773937 | O45: =VLOOKUP($D45,'prosedur-2025'!$A:$H,8,FALSE) -> 107636330 | P45: =J45*K45 -> 35514335204
A46: PDC | B46: P11AD | C46: Complex Spinal Procedures | D46: 81.07 | E46: Lumbar and lumbosacral fusion of the posterior column, posterior technique | F46: =VLOOKUP($D46,proc!$A:$D,3,FALSE) -> 5 | G46: =VLOOKUP($D46,proc!$A:$D,4,FALSE) -> 0 | H46: Complex Spinal Proc. | J46: =VLOOKUP($D46,'prosedur-2025'!$A:$H,3,FALSE) -> 431 | K46: =VLOOKUP($D46,'prosedur-2025'!$A:$H,4,FALSE) -> 57943673 | L46: =VLOOKUP($D46,'prosedur-2025'!$A:$H,5,FALSE) -> 35822500 | M46: =VLOOKUP($D46,'prosedur-2025'!$A:$H,6,FALSE) -> 50244990 | N46: =VLOOKUP($D46,'prosedur-2025'!$A:$H,7,FALSE) -> 70447761 | O46: =VLOOKUP($D46,'prosedur-2025'!$A:$H,8,FALSE) -> 105761272 | P46: =J46*K46 -> 24973723210
A47: PDC | B47: P11AD | C47: Complex Spinal Procedures | D47: 81.08 | E47: Lumbar and lumbosacral fusion of the anterior column, posterior technique | F47: =VLOOKUP($D47,proc!$A:$D,3,FALSE) -> 5 | G47: =VLOOKUP($D47,proc!$A:$D,4,FALSE) -> 0 | H47: Complex Spinal Proc. | J47: =VLOOKUP($D47,'prosedur-2025'!$A:$H,3,FALSE) -> 8521 | K47: =VLOOKUP($D47,'prosedur-2025'!$A:$H,4,FALSE) -> 67689416 | L47: =VLOOKUP($D47,'prosedur-2025'!$A:$H,5,FALSE) -> 46180007 | M47: =VLOOKUP($D47,'prosedur-2025'!$A:$H,6,FALSE) -> 58731728 | N47: =VLOOKUP($D47,'prosedur-2025'!$A:$H,7,FALSE) -> 78160513 | O47: =VLOOKUP($D47,'prosedur-2025'!$A:$H,8,FALSE) -> 109551144 | P47: =J47*K47 -> 576781509548
A48: PDC | B48: P11AD | C48: Complex Spinal Procedures | D48: 81.30 | E48: Refusion of spine, not otherwise specified | F48: =VLOOKUP($D48,proc!$A:$D,3,FALSE) -> 5 | G48: =VLOOKUP($D48,proc!$A:$D,4,FALSE) -> 0 | H48: Complex Spinal Proc. | J48: =VLOOKUP($D48,'prosedur-2025'!$A:$H,3,FALSE) -> 35 | K48: =VLOOKUP($D48,'prosedur-2025'!$A:$H,4,FALSE) -> 70318241 | L48: =VLOOKUP($D48,'prosedur-2025'!$A:$H,5,FALSE) -> 54490054 | M48: =VLOOKUP($D48,'prosedur-2025'!$A:$H,6,FALSE) -> 75165616 | N48: =VLOOKUP($D48,'prosedur-2025'!$A:$H,7,FALSE) -> 86883828 | O48: =VLOOKUP($D48,'prosedur-2025'!$A:$H,8,FALSE) -> 92794264 | P48: =J48*K48 -> 2461138422
A49: PDC | B49: P11AD | C49: Complex Spinal Procedures | D49: 81.31 | E49: Refusion of atlas-axis spine | F49: =VLOOKUP($D49,proc!$A:$D,3,FALSE) -> 5 | G49: =VLOOKUP($D49,proc!$A:$D,4,FALSE) -> 0 | H49: Complex Spinal Proc.
A50: PDC | B50: P11AD | C50: Complex Spinal Procedures | D50: 81.32 | E50: Refusion of other cervical spine, anterior column, anterior technique | F50: =VLOOKUP($D50,proc!$A:$D,3,FALSE) -> 5 | G50: =VLOOKUP($D50,proc!$A:$D,4,FALSE) -> 0 | H50: Complex Spinal Proc. | J50: =VLOOKUP($D50,'prosedur-2025'!$A:$H,3,FALSE) -> 12 | K50: =VLOOKUP($D50,'prosedur-2025'!$A:$H,4,FALSE) -> 93542328 | L50: =VLOOKUP($D50,'prosedur-2025'!$A:$H,5,FALSE) -> 59016369 | M50: =VLOOKUP($D50,'prosedur-2025'!$A:$H,6,FALSE) -> 86014412 | N50: =VLOOKUP($D50,'prosedur-2025'!$A:$H,7,FALSE) -> 94265770 | O50: =VLOOKUP($D50,'prosedur-2025'!$A:$H,8,FALSE) -> 139788621 | P50: =J50*K50 -> 1122507935
A51: PDC | B51: P11AD | C51: Complex Spinal Procedures | D51: 81.33 | E51: Refusion of other cervical spine, posterior column, posterior technique | F51: =VLOOKUP($D51,proc!$A:$D,3,FALSE) -> 5 | G51: =VLOOKUP($D51,proc!$A:$D,4,FALSE) -> 0 | H51: Complex Spinal Proc. | J51: =VLOOKUP($D51,'prosedur-2025'!$A:$H,3,FALSE) -> 15 | K51: =VLOOKUP($D51,'prosedur-2025'!$A:$H,4,FALSE) -> 62730194 | L51: =VLOOKUP($D51,'prosedur-2025'!$A:$H,5,FALSE) -> 26799353 | M51: =VLOOKUP($D51,'prosedur-2025'!$A:$H,6,FALSE) -> 62937527 | N51: =VLOOKUP($D51,'prosedur-2025'!$A:$H,7,FALSE) -> 95353673 | O51: =VLOOKUP($D51,'prosedur-2025'!$A:$H,8,FALSE) -> 99702768 | P51: =J51*K51 -> 940952905
A52: PDC | B52: P11AD | C52: Complex Spinal Procedures | D52: 81.34 | E52: Refusion of dorsal and dorsolumbar spine, anterior column, anterior technique | F52: =VLOOKUP($D52,proc!$A:$D,3,FALSE) -> 5 | G52: =VLOOKUP($D52,proc!$A:$D,4,FALSE) -> 0 | H52: Complex Spinal Proc. | J52: =VLOOKUP($D52,'prosedur-2025'!$A:$H,3,FALSE) -> 7 | K52: =VLOOKUP($D52,'prosedur-2025'!$A:$H,4,FALSE) -> 1.1739956e+08 | L52: =VLOOKUP($D52,'prosedur-2025'!$A:$H,5,FALSE) -> 9003207 | M52: =VLOOKUP($D52,'prosedur-2025'!$A:$H,6,FALSE) -> 111904600 | N52: =VLOOKUP($D52,'prosedur-2025'!$A:$H,7,FALSE) -> 125308086 | O52: =VLOOKUP($D52,'prosedur-2025'!$A:$H,8,FALSE) -> 350784753 | P52: =J52*K52 -> 821796938
A53: PDC | B53: P11AD | C53: Complex Spinal Procedures | D53: 81.35 | E53: Refusion of dorsal and dorsolumbar spine, posterior column, posterior technique | F53: =VLOOKUP($D53,proc!$A:$D,3,FALSE) -> 5 | G53: =VLOOKUP($D53,proc!$A:$D,4,FALSE) -> 0 | H53: Complex Spinal Proc. | J53: =VLOOKUP($D53,'prosedur-2025'!$A:$H,3,FALSE) -> 185 | K53: =VLOOKUP($D53,'prosedur-2025'!$A:$H,4,FALSE) -> 91375186 | L53: =VLOOKUP($D53,'prosedur-2025'!$A:$H,5,FALSE) -> 71476844 | M53: =VLOOKUP($D53,'prosedur-2025'!$A:$H,6,FALSE) -> 92485620 | N53: =VLOOKUP($D53,'prosedur-2025'!$A:$H,7,FALSE) -> 108187010 | O53: =VLOOKUP($D53,'prosedur-2025'!$A:$H,8,FALSE) -> 124520887 | P53: =J53*K53 -> 16904409480
A54: PDC | B54: P11AD | C54: Complex Spinal Procedures | D54: 81.36 | E54: Refusion of lumbar and lumbosacral spine, anterior column, anterior technique | F54: =VLOOKUP($D54,proc!$A:$D,3,FALSE) -> 5 | G54: =VLOOKUP($D54,proc!$A:$D,4,FALSE) -> 0 | H54: Complex Spinal Proc. | J54: =VLOOKUP($D54,'prosedur-2025'!$A:$H,3,FALSE) -> 14 | K54: =VLOOKUP($D54,'prosedur-2025'!$A:$H,4,FALSE) -> 74601905 | L54: =VLOOKUP($D54,'prosedur-2025'!$A:$H,5,FALSE) -> 48056191 | M54: =VLOOKUP($D54,'prosedur-2025'!$A:$H,6,FALSE) -> 78794765 | N54: =VLOOKUP($D54,'prosedur-2025'!$A:$H,7,FALSE) -> 100591222 | O54: =VLOOKUP($D54,'prosedur-2025'!$A:$H,8,FALSE) -> 107748085 | P54: =J54*K54 -> 1044426669
A55: PDC | B55: P11AD | C55: Complex Spinal Procedures | D55: 81.37 | E55: Refusion of lumbar and lumbosacral spine, posterior column, posterior technique | F55: =VLOOKUP($D55,proc!$A:$D,3,FALSE) -> 5 | G55: =VLOOKUP($D55,proc!$A:$D,4,FALSE) -> 0 | H55: Complex Spinal Proc. | J55: =VLOOKUP($D55,'prosedur-2025'!$A:$H,3,FALSE) -> 9 | K55: =VLOOKUP($D55,'prosedur-2025'!$A:$H,4,FALSE) -> 1.0575249e+08 | L55: =VLOOKUP($D55,'prosedur-2025'!$A:$H,5,FALSE) -> 98390202 | M55: =VLOOKUP($D55,'prosedur-2025'!$A:$H,6,FALSE) -> 109876684 | N55: =VLOOKUP($D55,'prosedur-2025'!$A:$H,7,FALSE) -> 148569122 | O55: =VLOOKUP($D55,'prosedur-2025'!$A:$H,8,FALSE) -> 150380731 | P55: =J55*K55 -> 951772405
A56: PDC | B56: P11AD | C56: Complex Spinal Procedures | D56: 81.38 | E56: Refusion of lumbar and lumbosacral spine, anterior column, posterior technique | F56: =VLOOKUP($D56,proc!$A:$D,3,FALSE) -> 5 | G56: =VLOOKUP($D56,proc!$A:$D,4,FALSE) -> 0 | H56: Complex Spinal Proc. | J56: =VLOOKUP($D56,'prosedur-2025'!$A:$H,3,FALSE) -> 135 | K56: =VLOOKUP($D56,'prosedur-2025'!$A:$H,4,FALSE) -> 76730268 | L56: =VLOOKUP($D56,'prosedur-2025'!$A:$H,5,FALSE) -> 45214948 | M56: =VLOOKUP($D56,'prosedur-2025'!$A:$H,6,FALSE) -> 85161186 | N56: =VLOOKUP($D56,'prosedur-2025'!$A:$H,7,FALSE) -> 104323910 | O56: =VLOOKUP($D56,'prosedur-2025'!$A:$H,8,FALSE) -> 126089406 | P56: =J56*K56 -> 10358586246
A57: PDC | B57: P11AD | C57: Complex Spinal Procedures | D57: 81.39 | E57: Refusion of spine, not elsewhere classified | F57: =VLOOKUP($D57,proc!$A:$D,3,FALSE) -> 4 | G57: =VLOOKUP($D57,proc!$A:$D,4,FALSE) -> 0 | H57: Complex Spinal Proc. | J57: =VLOOKUP($D57,'prosedur-2025'!$A:$H,3,FALSE) -> 68 | K57: =VLOOKUP($D57,'prosedur-2025'!$A:$H,4,FALSE) -> 76808456 | L57: =VLOOKUP($D57,'prosedur-2025'!$A:$H,5,FALSE) -> 51487642 | M57: =VLOOKUP($D57,'prosedur-2025'!$A:$H,6,FALSE) -> 77173066 | N57: =VLOOKUP($D57,'prosedur-2025'!$A:$H,7,FALSE) -> 94742454 | O57: =VLOOKUP($D57,'prosedur-2025'!$A:$H,8,FALSE) -> 105626015 | P57: =J57*K57 -> 5222974975
A58: PDC | B58: P11AD | C58: Complex Spinal Procedures | D58: 81.66 | E58: Percutaneous vertebral augmentation | F58: =VLOOKUP($D58,proc!$A:$D,3,FALSE) -> 4 | G58: =VLOOKUP($D58,proc!$A:$D,4,FALSE) -> 0 | H58: Moderate Spinal Proc. | J58: =VLOOKUP($D58,'prosedur-2025'!$A:$H,3,FALSE) -> 666 | K58: =VLOOKUP($D58,'prosedur-2025'!$A:$H,4,FALSE) -> 47065309 | L58: =VLOOKUP($D58,'prosedur-2025'!$A:$H,5,FALSE) -> 31525400 | M58: =VLOOKUP($D58,'prosedur-2025'!$A:$H,6,FALSE) -> 42013112 | N58: =VLOOKUP($D58,'prosedur-2025'!$A:$H,7,FALSE) -> 57545001 | O58: =VLOOKUP($D58,'prosedur-2025'!$A:$H,8,FALSE) -> 75413325 | P58: =J58*K58 -> 31345495792
A59: PDC | B59: P11AD | C59: Complex Spinal Procedures | D59: 84.59 | E59: Insertion of other spinal devices | F59: =VLOOKUP($D59,proc!$A:$D,3,FALSE) -> 0 | G59: =VLOOKUP($D59,proc!$A:$D,4,FALSE) -> 0 | H59: Moderate Spinal Proc. | J59: =VLOOKUP($D59,'prosedur-2025'!$A:$H,3,FALSE) -> 88 | K59: =VLOOKUP($D59,'prosedur-2025'!$A:$H,4,FALSE) -> 63971686 | L59: =VLOOKUP($D59,'prosedur-2025'!$A:$H,5,FALSE) -> 34988684 | M59: =VLOOKUP($D59,'prosedur-2025'!$A:$H,6,FALSE) -> 44652176 | N59: =VLOOKUP($D59,'prosedur-2025'!$A:$H,7,FALSE) -> 70382521 | O59: =VLOOKUP($D59,'prosedur-2025'!$A:$H,8,FALSE) -> 128858971 | P59: =J59*K59 -> 5629508395
A60: PDC | B60: P11AD | C60: Complex Spinal Procedures | D60: 84.60 | E60: Insertion of spinal disc prosthesis, not otherwise specified | F60: =VLOOKUP($D60,proc!$A:$D,3,FALSE) -> 3 | G60: =VLOOKUP($D60,proc!$A:$D,4,FALSE) -> 0 | H60: Complex Spinal Proc. | J60: =VLOOKUP($D60,'prosedur-2025'!$A:$H,3,FALSE) -> 4 | K60: =VLOOKUP($D60,'prosedur-2025'!$A:$H,4,FALSE) -> 94201396 | L60: =VLOOKUP($D60,'prosedur-2025'!$A:$H,5,FALSE) -> 14919275 | M60: =VLOOKUP($D60,'prosedur-2025'!$A:$H,6,FALSE) -> 54528657 | N60: =VLOOKUP($D60,'prosedur-2025'!$A:$H,7,FALSE) -> 125025777 | O60: =VLOOKUP($D60,'prosedur-2025'!$A:$H,8,FALSE) -> 182331876 | P60: =J60*K60 -> 376805585
A61: PDC | B61: P11AD | C61: Complex Spinal Procedures | D61: 84.61 | E61: Insertion of partial spinal disc prosthesis, cervical | F61: =VLOOKUP($D61,proc!$A:$D,3,FALSE) -> 3 | G61: =VLOOKUP($D61,proc!$A:$D,4,FALSE) -> 0 | H61: Complex Spinal Proc. | J61: =VLOOKUP($D61,'prosedur-2025'!$A:$H,3,FALSE) -> 6 | K61: =VLOOKUP($D61,'prosedur-2025'!$A:$H,4,FALSE) -> 116184758 | L61: =VLOOKUP($D61,'prosedur-2025'!$A:$H,5,FALSE) -> 79665771 | M61: =VLOOKUP($D61,'prosedur-2025'!$A:$H,6,FALSE) -> 83597661 | N61: =VLOOKUP($D61,'prosedur-2025'!$A:$H,7,FALSE) -> 118980329 | O61: =VLOOKUP($D61,'prosedur-2025'!$A:$H,8,FALSE) -> 247386247 | P61: =J61*K61 -> 697108548
... A92: PDC | B92: P11AB | C92: Complex Craniotomy | D92: 02.93 | E92: Implantation or replacement of intracranial neurostimulator lead(s) | F92: =VLOOKUP($D92,proc!$A:$D,3,FALSE) -> 5 | G92: =VLOOKUP($D92,proc!$A:$D,4,FALSE) -> 0 | H92: Neuromodulation | J92: =VLOOKUP($D92,'prosedur-2025'!$A:$H,3,FALSE) -> 12 | K92: =VLOOKUP($D92,'prosedur-2025'!$A:$H,4,FALSE) -> 1.2191113e+08 | L92: =VLOOKUP($D92,'prosedur-2025'!$A:$H,5,FALSE) -> 18882640 | M92: =VLOOKUP($D92,'prosedur-2025'!$A:$H,6,FALSE) -> 36337421 | N92: =VLOOKUP($D92,'prosedur-2025'!$A:$H,7,FALSE) -> 170459548 | O92: =VLOOKUP($D92,'prosedur-2025'!$A:$H,8,FALSE) -> 287488076 | P92: =J92*K92 -> 1462933521
A93: PDC | B93: P11AB | C93: Complex Craniotomy | D93: 02.930 | E93: Implantation of neurostimulator lead into vagus nerve (IM) | F93: =VLOOKUP($D93,proc!$A:$D,3,FALSE) -> 5 | G93: =VLOOKUP($D93,proc!$A:$D,4,FALSE) -> 1 | H93: Neuromodulation
A94: PDC | B94: P11AB | C94: Complex Craniotomy | D94: 02.99 | E94: Other operations on skull, brain, and cerebral meninges | F94: =VLOOKUP($D94,proc!$A:$D,3,FALSE) -> 3 | G94: =VLOOKUP($D94,proc!$A:$D,4,FALSE) -> 0 | H94: Moderate Craniotomy Proc. | J94: =VLOOKUP($D94,'prosedur-2025'!$A:$H,3,FALSE) -> 30 | K94: =VLOOKUP($D94,'prosedur-2025'!$A:$H,4,FALSE) -> 49249925 | L94: =VLOOKUP($D94,'prosedur-2025'!$A:$H,5,FALSE) -> 26648275 | M94: =VLOOKUP($D94,'prosedur-2025'!$A:$H,6,FALSE) -> 42055366 | N94: =VLOOKUP($D94,'prosedur-2025'!$A:$H,7,FALSE) -> 54957500 | O94: =VLOOKUP($D94,'prosedur-2025'!$A:$H,8,FALSE) -> 108253753 | P94: =J94*K94 -> 1477497747
A95: PDC | B95: P11AB | C95: Complex Craniotomy | D95: 04.01 | E95: Excision of acoustic neuroma | F95: =VLOOKUP($D95,proc!$A:$D,3,FALSE) -> 6 | G95: =VLOOKUP($D95,proc!$A:$D,4,FALSE) -> 0 | H95: Complex Craniotomy Proc. | J95: =VLOOKUP($D95,'prosedur-2025'!$A:$H,3,FALSE) -> 5 | K95: =VLOOKUP($D95,'prosedur-2025'!$A:$H,4,FALSE) -> 46698548 | L95: =VLOOKUP($D95,'prosedur-2025'!$A:$H,5,FALSE) -> 46150857 | M95: =VLOOKUP($D95,'prosedur-2025'!$A:$H,6,FALSE) -> 46327667 | N95: =VLOOKUP($D95,'prosedur-2025'!$A:$H,7,FALSE) -> 48290169 | O95: =VLOOKUP($D95,'prosedur-2025'!$A:$H,8,FALSE) -> 54698318 | P95: =J95*K95 -> 233492738
A96: PDC | B96: P11AB | C96: Complex Craniotomy | D96: 04.41 | E96: Decompression of trigeminal nerve root | F96: =VLOOKUP($D96,proc!$A:$D,3,FALSE) -> 5 | G96: =VLOOKUP($D96,proc!$A:$D,4,FALSE) -> 0 | H96: Moderate Craniotomy Proc. | J96: =VLOOKUP($D96,'prosedur-2025'!$A:$H,3,FALSE) -> 210 | K96: =VLOOKUP($D96,'prosedur-2025'!$A:$H,4,FALSE) -> 84551426 | L96: =VLOOKUP($D96,'prosedur-2025'!$A:$H,5,FALSE) -> 36683138 | M96: =VLOOKUP($D96,'prosedur-2025'!$A:$H,6,FALSE) -> 58685750 | N96: =VLOOKUP($D96,'prosedur-2025'!$A:$H,7,FALSE) -> 137485045 | O96: =VLOOKUP($D96,'prosedur-2025'!$A:$H,8,FALSE) -> 176289774 | P96: =J96*K96 -> 17755799499
A97: PDC | B97: P11AB | C97: Complex Craniotomy | D97: 07.13 | E97: Biopsy of pituitary gland, transfrontal approach | F97: =VLOOKUP($D97,proc!$A:$D,3,FALSE) -> 6 | G97: =VLOOKUP($D97,proc!$A:$D,4,FALSE) -> 0 | H97: Moderate Craniotomy Proc. | J97: =VLOOKUP($D97,'prosedur-2025'!$A:$H,3,FALSE) -> 1 | K97: =VLOOKUP($D97,'prosedur-2025'!$A:$H,4,FALSE) -> 56515553 | L97: =VLOOKUP($D97,'prosedur-2025'!$A:$H,5,FALSE) -> 56515553 | M97: =VLOOKUP($D97,'prosedur-2025'!$A:$H,6,FALSE) -> 56515553 | N97: =VLOOKUP($D97,'prosedur-2025'!$A:$H,7,FALSE) -> 56515553 | O97: =VLOOKUP($D97,'prosedur-2025'!$A:$H,8,FALSE) -> 56515553 | P97: =J97*K97 -> 56515553
A98: PDC | B98: P11AB | C98: Complex Craniotomy | D98: 07.14 | E98: Biopsy of pituitary gland, transsphenoidal approach | F98: =VLOOKUP($D98,proc!$A:$D,3,FALSE) -> 6 | G98: =VLOOKUP($D98,proc!$A:$D,4,FALSE) -> 0 | H98: Moderate Craniotomy Proc. | J98: =VLOOKUP($D98,'prosedur-2025'!$A:$H,3,FALSE) -> 48 | K98: =VLOOKUP($D98,'prosedur-2025'!$A:$H,4,FALSE) -> 1.8190223e+08 | L98: =VLOOKUP($D98,'prosedur-2025'!$A:$H,5,FALSE) -> 120711693 | M98: =VLOOKUP($D98,'prosedur-2025'!$A:$H,6,FALSE) -> 211809342 | N98: =VLOOKUP($D98,'prosedur-2025'!$A:$H,7,FALSE) -> 228962314 | O98: =VLOOKUP($D98,'prosedur-2025'!$A:$H,8,FALSE) -> 243577663 | P98: =J98*K98 -> 8731307242
A99: PDC | B99: P11AB | C99: Complex Craniotomy | D99: 07.15 | E99: Biopsy of pituitary gland, unspecified approach | F99: =VLOOKUP($D99,proc!$A:$D,3,FALSE) -> 6 | G99: =VLOOKUP($D99,proc!$A:$D,4,FALSE) -> 0 | H99: Moderate Craniotomy Proc. | J99: =VLOOKUP($D99,'prosedur-2025'!$A:$H,3,FALSE) -> 9 | K99: =VLOOKUP($D99,'prosedur-2025'!$A:$H,4,FALSE) -> 49564209 | L99: =VLOOKUP($D99,'prosedur-2025'!$A:$H,5,FALSE) -> 43981561 | M99: =VLOOKUP($D99,'prosedur-2025'!$A:$H,6,FALSE) -> 48923455 | N99: =VLOOKUP($D99,'prosedur-2025'!$A:$H,7,FALSE) -> 54309575 | O99: =VLOOKUP($D99,'prosedur-2025'!$A:$H,8,FALSE) -> 59210601 | P99: =J99*K99 -> 446077885
A100: PDC | B100: P11AB | C100: Complex Craniotomy | D100: 07.17 | E100: Biopsy of pineal gland | F100: =VLOOKUP($D100,proc!$A:$D,3,FALSE) -> 5 | G100: =VLOOKUP($D100,proc!$A:$D,4,FALSE) -> 0 | H100: Moderate Craniotomy Proc. | J100: =VLOOKUP($D100,'prosedur-2025'!$A:$H,3,FALSE) -> 5 | K100: =VLOOKUP($D100,'prosedur-2025'!$A:$H,4,FALSE) -> 61004076 | L100: =VLOOKUP($D100,'prosedur-2025'!$A:$H,5,FALSE) -> 34733055 | M100: =VLOOKUP($D100,'prosedur-2025'!$A:$H,6,FALSE) -> 56500654 | N100: =VLOOKUP($D100,'prosedur-2025'!$A:$H,7,FALSE) -> 65622425 | O100: =VLOOKUP($D100,'prosedur-2025'!$A:$H,8,FALSE) -> 113760502 | P100: =J100*K100 -> 305020381
A101: PDC | B101: P11AB | C101: Complex Craniotomy | D101: 07.51 | E101: Exploration of pineal field | F101: =VLOOKUP($D101,proc!$A:$D,3,FALSE) -> 6 | G101: =VLOOKUP($D101,proc!$A:$D,4,FALSE) -> 0 | H101: Moderate Craniotomy Proc. | J101: =VLOOKUP($D101,'prosedur-2025'!$A:$H,3,FALSE) -> 1 | K101: =VLOOKUP($D101,'prosedur-2025'!$A:$H,4,FALSE) -> 9699277 | L101: =VLOOKUP($D101,'prosedur-2025'!$A:$H,5,FALSE) -> 9699277 | M101: =VLOOKUP($D101,'prosedur-2025'!$A:$H,6,FALSE) -> 9699277 | N101: =VLOOKUP($D101,'prosedur-2025'!$A:$H,7,FALSE) -> 9699277 | O101: =VLOOKUP($D101,'prosedur-2025'!$A:$H,8,FALSE) -> 9699277 | P101: =J101*K101 -> 9699277
A102: PDC | B102: P11AB | C102: Complex Craniotomy | D102: 07.52 | E102: Incision of pineal gland | F102: =VLOOKUP($D102,proc!$A:$D,3,FALSE) -> 6 | G102: =VLOOKUP($D102,proc!$A:$D,4,FALSE) -> 0 | H102: Moderate Craniotomy Proc.
A103: PDC | B103: P11AB | C103: Complex Craniotomy | D103: 07.53 | E103: Partial excision of pineal gland | F103: =VLOOKUP($D103,proc!$A:$D,3,FALSE) -> 6 | G103: =VLOOKUP($D103,proc!$A:$D,4,FALSE) -> 0 | H103: Moderate Craniotomy Proc. | J103: =VLOOKUP($D103,'prosedur-2025'!$A:$H,3,FALSE) -> 5 | K103: =VLOOKUP($D103,'prosedur-2025'!$A:$H,4,FALSE) -> 76397121 | L103: =VLOOKUP($D103,'prosedur-2025'!$A:$H,5,FALSE) -> 76986850 | M103: =VLOOKUP($D103,'prosedur-2025'!$A:$H,6,FALSE) -> 78960194 | N103: =VLOOKUP($D103,'prosedur-2025'!$A:$H,7,FALSE) -> 81671388 | O103: =VLOOKUP($D103,'prosedur-2025'!$A:$H,8,FALSE) -> 83248369 | P103: =J103*K103 -> 381985607
A104: PDC | B104: P11AB | C104: Complex Craniotomy | D104: 07.54 | E104: Total excision of pineal gland | F104: =VLOOKUP($D104,proc!$A:$D,3,FALSE) -> 6 | G104: =VLOOKUP($D104,proc!$A:$D,4,FALSE) -> 0 | H104: Moderate Craniotomy Proc.
A105: PDC | B105: P11AB | C105: Complex Craniotomy | D105: 07.59 | E105: Other operations on pineal gland | F105: =VLOOKUP($D105,proc!$A:$D,3,FALSE) -> 6 | G105: =VLOOKUP($D105,proc!$A:$D,4,FALSE) -> 0 | H105: Moderate Craniotomy Proc. | J105: =VLOOKUP($D105,'prosedur-2025'!$A:$H,3,FALSE) -> 1 | K105: =VLOOKUP($D105,'prosedur-2025'!$A:$H,4,FALSE) -> 88311491 | L105: =VLOOKUP($D105,'prosedur-2025'!$A:$H,5,FALSE) -> 88311491 | M105: =VLOOKUP($D105,'prosedur-2025'!$A:$H,6,FALSE) -> 88311491 | N105: =VLOOKUP($D105,'prosedur-2025'!$A:$H,7,FALSE) -> 88311491 | O105: =VLOOKUP($D105,'prosedur-2025'!$A:$H,8,FALSE) -> 88311491 | P105: =J105*K105 -> 88311491
A106: PDC | B106: P11AB | C106: Complex Craniotomy | D106: 07.61 | E106: Partial excision of pituitary gland, transfrontal approach | F106: =VLOOKUP($D106,proc!$A:$D,3,FALSE) -> 6 | G106: =VLOOKUP($D106,proc!$A:$D,4,FALSE) -> 0 | H106: Moderate Craniotomy Proc. | J106: =VLOOKUP($D106,'prosedur-2025'!$A:$H,3,FALSE) -> 10 | K106: =VLOOKUP($D106,'prosedur-2025'!$A:$H,4,FALSE) -> 73125733 | L106: =VLOOKUP($D106,'prosedur-2025'!$A:$H,5,FALSE) -> 35111306 | M106: =VLOOKUP($D106,'prosedur-2025'!$A:$H,6,FALSE) -> 58448080 | N106: =VLOOKUP($D106,'prosedur-2025'!$A:$H,7,FALSE) -> 104387331 | O106: =VLOOKUP($D106,'prosedur-2025'!$A:$H,8,FALSE) -> 118798384 | P106: =J106*K106 -> 731257327 | Q106: di IDRG Endocrine, Nutritional and Metabolic Diseases and Disorders (MDC) Pituitary and Thymus Proc. (DRG)
A107: PDC | B107: P11AB | C107: Complex Craniotomy | D107: 07.62 | E107: Partial excision of pituitary gland, transsphenoidal approach | F107: =VLOOKUP($D107,proc!$A:$D,3,FALSE) -> 6 | G107: =VLOOKUP($D107,proc!$A:$D,4,FALSE) -> 0 | H107: Moderate Craniotomy Proc. | J107: =VLOOKUP($D107,'prosedur-2025'!$A:$H,3,FALSE) -> 159 | K107: =VLOOKUP($D107,'prosedur-2025'!$A:$H,4,FALSE) -> 1.4017225e+08 | L107: =VLOOKUP($D107,'prosedur-2025'!$A:$H,5,FALSE) -> 73132025 | M107: =VLOOKUP($D107,'prosedur-2025'!$A:$H,6,FALSE) -> 114861226 | N107: =VLOOKUP($D107,'prosedur-2025'!$A:$H,7,FALSE) -> 217110036 | O107: =VLOOKUP($D107,'prosedur-2025'!$A:$H,8,FALSE) -> 243283766 | P107: =J107*K107 -> 22287387010 | Q107: di IDRG Endocrine, Nutritional and Metabolic Diseases and Disorders (MDC) Pituitary and Thymus Proc. (DRG)
A108: PDC | B108: P11AB | C108: Complex Craniotomy | D108: 07.63 | E108: Partial excision of pituitary gland, unspecified approach | F108: =VLOOKUP($D108,proc!$A:$D,3,FALSE) -> 6 | G108: =VLOOKUP($D108,proc!$A:$D,4,FALSE) -> 0 | H108: Moderate Craniotomy Proc. | J108: =VLOOKUP($D108,'prosedur-2025'!$A:$H,3,FALSE) -> 23 | K108: =VLOOKUP($D108,'prosedur-2025'!$A:$H,4,FALSE) -> 71469804 | L108: =VLOOKUP($D108,'prosedur-2025'!$A:$H,5,FALSE) -> 45435400 | M108: =VLOOKUP($D108,'prosedur-2025'!$A:$H,6,FALSE) -> 54309575 | N108: =VLOOKUP($D108,'prosedur-2025'!$A:$H,7,FALSE) -> 90803701 | O108: =VLOOKUP($D108,'prosedur-2025'!$A:$H,8,FALSE) -> 126078524 | P108: =J108*K108 -> 1643805486 | Q108: di IDRG Endocrine, Nutritional and Metabolic Diseases and Disorders (MDC) Pituitary and Thymus Proc. (DRG)
A109: PDC | B109: P11AB | C109: Complex Craniotomy | D109: 07.64 | E109: Total excision of pituitary gland, transfrontal approach | F109: =VLOOKUP($D109,proc!$A:$D,3,FALSE) -> 6 | G109: =VLOOKUP($D109,proc!$A:$D,4,FALSE) -> 0 | H109: Moderate Craniotomy Proc. | J109: =VLOOKUP($D109,'prosedur-2025'!$A:$H,3,FALSE) -> 15 | K109: =VLOOKUP($D109,'prosedur-2025'!$A:$H,4,FALSE) -> 94875677 | L109: =VLOOKUP($D109,'prosedur-2025'!$A:$H,5,FALSE) -> 28157212 | M109: =VLOOKUP($D109,'prosedur-2025'!$A:$H,6,FALSE) -> 95930390 | N109: =VLOOKUP($D109,'prosedur-2025'!$A:$H,7,FALSE) -> 114518699 | O109: =VLOOKUP($D109,'prosedur-2025'!$A:$H,8,FALSE) -> 218943764 | P109: =J109*K109 -> 1423135148 | Q109: di IDRG Endocrine, Nutritional and Metabolic Diseases and Disorders (MDC) Pituitary and Thymus Proc. (DRG)
A110: PDC | B110: P11AB | C110: Complex Craniotomy | D110: 07.65 | E110: Total excision of pituitary gland, transsphenoidal approach | F110: =VLOOKUP($D110,proc!$A:$D,3,FALSE) -> 6 | G110: =VLOOKUP($D110,proc!$A:$D,4,FALSE) -> 0 | H110: Moderate Craniotomy Proc. | J110: =VLOOKUP($D110,'prosedur-2025'!$A:$H,3,FALSE) -> 150 | K110: =VLOOKUP($D110,'prosedur-2025'!$A:$H,4,FALSE) -> 95595091 | L110: =VLOOKUP($D110,'prosedur-2025'!$A:$H,5,FALSE) -> 63362506 | M110: =VLOOKUP($D110,'prosedur-2025'!$A:$H,6,FALSE) -> 85654492 | N110: =VLOOKUP($D110,'prosedur-2025'!$A:$H,7,FALSE) -> 111943701 | O110: =VLOOKUP($D110,'prosedur-2025'!$A:$H,8,FALSE) -> 140273000 | P110: =J110*K110 -> 14339263719 | Q110: di IDRG Endocrine, Nutritional and Metabolic Diseases and Disorders (MDC) Pituitary and Thymus Proc. (DRG)
A111: PDC | B111: P11AB | C111: Complex Craniotomy | D111: 07.68 | E111: Total excision of pituitary gland, other specified approach | F111: =VLOOKUP($D111,proc!$A:$D,3,FALSE) -> 6 | G111: =VLOOKUP($D111,proc!$A:$D,4,FALSE) -> 0 | H111: Moderate Craniotomy Proc. | J111: =VLOOKUP($D111,'prosedur-2025'!$A:$H,3,FALSE) -> 6 | K111: =VLOOKUP($D111,'prosedur-2025'!$A:$H,4,FALSE) -> 98062115 | L111: =VLOOKUP($D111,'prosedur-2025'!$A:$H,5,FALSE) -> 76490631 | M111: =VLOOKUP($D111,'prosedur-2025'!$A:$H,6,FALSE) -> 79380920 | N111: =VLOOKUP($D111,'prosedur-2025'!$A:$H,7,FALSE) -> 139470719 | O111: =VLOOKUP($D111,'prosedur-2025'!$A:$H,8,FALSE) -> 147130260 | P111: =J111*K111 -> 588372688 | Q111: di IDRG Endocrine, Nutritional and Metabolic Diseases and Disorders (MDC) Pituitary and Thymus Proc. (DRG)
A112: PDC | B112: P11AB | C112: Complex Craniotomy | D112: 07.69 | E112: Total excision of pituitary gland, unspecified approach | F112: =VLOOKUP($D112,proc!$A:$D,3,FALSE) -> 6 | G112: =VLOOKUP($D112,proc!$A:$D,4,FALSE) -> 0 | H112: Moderate Craniotomy Proc. | J112: =VLOOKUP($D112,'prosedur-2025'!$A:$H,3,FALSE) -> 22 | K112: =VLOOKUP($D112,'prosedur-2025'!$A:$H,4,FALSE) -> 83043520 | L112: =VLOOKUP($D112,'prosedur-2025'!$A:$H,5,FALSE) -> 39900217 | M112: =VLOOKUP($D112,'prosedur-2025'!$A:$H,6,FALSE) -> 68653527 | N112: =VLOOKUP($D112,'prosedur-2025'!$A:$H,7,FALSE) -> 93597601 | O112: =VLOOKUP($D112,'prosedur-2025'!$A:$H,8,FALSE) -> 186000150 | P112: =J112*K112 -> 1826957432 | Q112: di IDRG Endocrine, Nutritional and Metabolic Diseases and Disorders (MDC) Pituitary and Thymus Proc. (DRG)
A113: PDC | B113: P11AB | C113: Complex Craniotomy | D113: 07.71 | E113: Exploration of pituitary fossa | F113: =VLOOKUP($D113,proc!$A:$D,3,FALSE) -> 6 | G113: =VLOOKUP($D113,proc!$A:$D,4,FALSE) -> 0 | H113: Moderate Craniotomy Proc. | J113: =VLOOKUP($D113,'prosedur-2025'!$A:$H,3,FALSE) -> 1 | K113: =VLOOKUP($D113,'prosedur-2025'!$A:$H,4,FALSE) -> 93539090 | L113: =VLOOKUP($D113,'prosedur-2025'!$A:$H,5,FALSE) -> 93539090 | M113: =VLOOKUP($D113,'prosedur-2025'!$A:$H,6,FALSE) -> 93539090 | N113: =VLOOKUP($D113,'prosedur-2025'!$A:$H,7,FALSE) -> 93539090 | O113: =VLOOKUP($D113,'prosedur-2025'!$A:$H,8,FALSE) -> 93539090 | P113: =J113*K113 -> 93539090 | Q113: di IDRG Endocrine, Nutritional and Metabolic Diseases and Disorders (MDC) Pituitary and Thymus Proc. (DRG)
A114: PDC | B114: P11AB | C114: Complex Craniotomy | D114: 07.72 | E114: Incision of pituitary gland | F114: =VLOOKUP($D114,proc!$A:$D,3,FALSE) -> 6 | G114: =VLOOKUP($D114,proc!$A:$D,4,FALSE) -> 0 | H114: Moderate Craniotomy Proc. | J114: =VLOOKUP($D114,'prosedur-2025'!$A:$H,3,FALSE) -> 5 | K114: =VLOOKUP($D114,'prosedur-2025'!$A:$H,4,FALSE) -> 85378441 | L114: =VLOOKUP($D114,'prosedur-2025'!$A:$H,5,FALSE) -> 50017843 | M114: =VLOOKUP($D114,'prosedur-2025'!$A:$H,6,FALSE) -> 79380920 | N114: =VLOOKUP($D114,'prosedur-2025'!$A:$H,7,FALSE) -> 126787100 | O114: =VLOOKUP($D114,'prosedur-2025'!$A:$H,8,FALSE) -> 131029468 | P114: =J114*K114 -> 426892207 | Q114: di IDRG Endocrine, Nutritional and Metabolic Diseases and Disorders (MDC) Pituitary and Thymus Proc. (DRG)
A115: PDC | B115: P11AB | C115: Complex Craniotomy | D115: 07.79 | E115: Other operations on hypophysis | F115: =VLOOKUP($D115,proc!$A:$D,3,FALSE) -> 6 | G115: =VLOOKUP($D115,proc!$A:$D,4,FALSE) -> 0 | H115: Moderate Craniotomy Proc. | J115: =VLOOKUP($D115,'prosedur-2025'!$A:$H,3,FALSE) -> 2 | K115: =VLOOKUP($D115,'prosedur-2025'!$A:$H,4,FALSE) -> 52394033 | L115: =VLOOKUP($D115,'prosedur-2025'!$A:$H,5,FALSE) -> 13382449 | M115: =VLOOKUP($D115,'prosedur-2025'!$A:$H,6,FALSE) -> 13382449 | N115: =VLOOKUP($D115,'prosedur-2025'!$A:$H,7,FALSE) -> 91405617 | O115: =VLOOKUP($D115,'prosedur-2025'!$A:$H,8,FALSE) -> 91405617 | P115: =J115*K115 -> 104788066 | Q115: di IDRG Endocrine, Nutritional and Metabolic Diseases and Disorders (MDC) Pituitary and Thymus Proc. (DRG)
A116: PDC | B116: P11AF | C116: Ventricular System Procedures | D116: 01.02 | E116: Ventriculopuncture through previously implanted catheter | F116: =VLOOKUP($D116,proc!$A:$D,3,FALSE) -> 0 | G116: =VLOOKUP($D116,proc!$A:$D,4,FALSE) -> 0 | H116: Ventricular System Proc. | J116: =VLOOKUP($D116,'prosedur-2025'!$A:$H,3,FALSE) -> 78 | K116: =VLOOKUP($D116,'prosedur-2025'!$A:$H,4,FALSE) -> 99329817 | L116: =VLOOKUP($D116,'prosedur-2025'!$A:$H,5,FALSE) -> 17269648 | M116: =VLOOKUP($D116,'prosedur-2025'!$A:$H,6,FALSE) -> 71886054 | N116: =VLOOKUP($D116,'prosedur-2025'!$A:$H,7,FALSE) -> 135437757 | O116: =VLOOKUP($D116,'prosedur-2025'!$A:$H,8,FALSE) -> 258782162 | P116: =J116*K116 -> 7747725696
A117: PDC | B117: P11AF | C117: Ventricular System Procedures | D117: 01.10 | E117: Intracranial pressure monitoring | F117: =VLOOKUP($D117,proc!$A:$D,3,FALSE) -> 0 | G117: =VLOOKUP($D117,proc!$A:$D,4,FALSE) -> 0 | H117: Simple Craniotomy Proc. | J117: =VLOOKUP($D117,'prosedur-2025'!$A:$H,3,FALSE) -> 162 | K117: =VLOOKUP($D117,'prosedur-2025'!$A:$H,4,FALSE) -> 81369168 | L117: =VLOOKUP($D117,'prosedur-2025'!$A:$H,5,FALSE) -> 44007000 | M117: =VLOOKUP($D117,'prosedur-2025'!$A:$H,6,FALSE) -> 68061550 | N117: =VLOOKUP($D117,'prosedur-2025'!$A:$H,7,FALSE) -> 101397714 | O117: =VLOOKUP($D117,'prosedur-2025'!$A:$H,8,FALSE) -> 144267639 | P117: =J117*K117 -> 13181805199
A118: PDC | B118: P11AF | C118: Ventricular System Procedures | D118: 01.11 | E118: Closed [percutaneous] [needle] biopsy of cerebral meninges | F118: =VLOOKUP($D118,proc!$A:$D,3,FALSE) -> 0 | G118: =VLOOKUP($D118,proc!$A:$D,4,FALSE) -> 0 | H118: Simple Craniotomy Proc. | J118: =VLOOKUP($D118,'prosedur-2025'!$A:$H,3,FALSE) -> 17 | K118: =VLOOKUP($D118,'prosedur-2025'!$A:$H,4,FALSE) -> 70802456 | L118: =VLOOKUP($D118,'prosedur-2025'!$A:$H,5,FALSE) -> 40231606 | M118: =VLOOKUP($D118,'prosedur-2025'!$A:$H,6,FALSE) -> 60338026 | N118: =VLOOKUP($D118,'prosedur-2025'!$A:$H,7,FALSE) -> 88869861 | O118: =VLOOKUP($D118,'prosedur-2025'!$A:$H,8,FALSE) -> 149341125 | P118: =J118*K118 -> 1203641746
A119: PDC | B119: P11AF | C119: Ventricular System Procedures | D119: 02.2 | E119: Ventriculostomy | F119: =VLOOKUP($D119,proc!$A:$D,3,FALSE) -> 5 | G119: =VLOOKUP($D119,proc!$A:$D,4,FALSE) -> 0 | H119: Ventricular System Proc. | J119: =VLOOKUP($D119,'prosedur-2025'!$A:$H,3,FALSE) -> 2023 | K119: =VLOOKUP($D119,'prosedur-2025'!$A:$H,4,FALSE) -> 94591092 | L119: =VLOOKUP($D119,'prosedur-2025'!$A:$H,5,FALSE) -> 43090378 | M119: =VLOOKUP($D119,'prosedur-2025'!$A:$H,6,FALSE) -> 66553382 | N119: =VLOOKUP($D119,'prosedur-2025'!$A:$H,7,FALSE) -> 113539160 | O119: =VLOOKUP($D119,'prosedur-2025'!$A:$H,8,FALSE) -> 182337200 | P119: =J119*K119 -> 191357778820
A120: PDC | B120: P11AF | C120: Ventricular System Procedures | D120: 02.20 | E120: Endoscopic ventriculostomy (IM) | F120: =VLOOKUP($D120,proc!$A:$D,3,FALSE) -> 5 | G120: =VLOOKUP($D120,proc!$A:$D,4,FALSE) -> 1 | H120: Ventricular System Proc.
A121: PDC | B121: P11AF | C121: Ventricular System Procedures | D121: 02.31 | E121: Ventricular shunt to structure in head and neck | F121: =VLOOKUP($D121,proc!$A:$D,3,FALSE) -> 5 | G121: =VLOOKUP($D121,proc!$A:$D,4,FALSE) -> 0 | H121: Ventricular System Proc. | J121: =VLOOKUP($D121,'prosedur-2025'!$A:$H,3,FALSE) -> 1878 | K121: =VLOOKUP($D121,'prosedur-2025'!$A:$H,4,FALSE) -> 63822179 | L121: =VLOOKUP($D121,'prosedur-2025'!$A:$H,5,FALSE) -> 34891590 | M121: =VLOOKUP($D121,'prosedur-2025'!$A:$H,6,FALSE) -> 51804096 | N121: =VLOOKUP($D121,'prosedur-2025'!$A:$H,7,FALSE) -> 76161688 | O121: =VLOOKUP($D121,'prosedur-2025'!$A:$H,8,FALSE) -> 119207123 | P121: =J121*K121 -> 119858052782
A122: PDC | B122: P11AF | C122: Ventricular System Procedures | D122: 02.32 | E122: Ventricular shunt to circulatory system | F122: =VLOOKUP($D122,proc!$A:$D,3,FALSE) -> 5 | G122: =VLOOKUP($D122,proc!$A:$D,4,FALSE) -> 0 | H122: Ventricular System Proc. | J122: =VLOOKUP($D122,'prosedur-2025'!$A:$H,3,FALSE) -> 314 | K122: =VLOOKUP($D122,'prosedur-2025'!$A:$H,4,FALSE) -> 1.1670652e+08 | L122: =VLOOKUP($D122,'prosedur-2025'!$A:$H,5,FALSE) -> 54713451 | M122: =VLOOKUP($D122,'prosedur-2025'!$A:$H,6,FALSE) -> 81656095 | N122: =VLOOKUP($D122,'prosedur-2025'!$A:$H,7,FALSE) -> 171237317 | O122: =VLOOKUP($D122,'prosedur-2025'!$A:$H,8,FALSE) -> 245327943 | P122: =J122*K122 -> 36645846274
A123: PDC | B123: P11AF | C123: Ventricular System Procedures | D123: 02.33 | E123: Ventricular shunt to thoracic cavity | F123: =VLOOKUP($D123,proc!$A:$D,3,FALSE) -> 5 | G123: =VLOOKUP($D123,proc!$A:$D,4,FALSE) -> 0 | H123: Ventricular System Proc. | J123: =VLOOKUP($D123,'prosedur-2025'!$A:$H,3,FALSE) -> 11 | K123: =VLOOKUP($D123,'prosedur-2025'!$A:$H,4,FALSE) -> 84342354 | L123: =VLOOKUP($D123,'prosedur-2025'!$A:$H,5,FALSE) -> 57643742 | M123: =VLOOKUP($D123,'prosedur-2025'!$A:$H,6,FALSE) -> 83664102 | N123: =VLOOKUP($D123,'prosedur-2025'!$A:$H,7,FALSE) -> 117112030 | O123: =VLOOKUP($D123,'prosedur-2025'!$A:$H,8,FALSE) -> 118314046 | P123: =J123*K123 -> 927765893
A124: PDC | B124: P11AF | C124: Ventricular System Procedures | D124: 02.34 | E124: Ventricular shunt to abdominal cavity and organs | F124: =VLOOKUP($D124,proc!$A:$D,3,FALSE) -> 5 | G124: =VLOOKUP($D124,proc!$A:$D,4,FALSE) -> 0 | H124: Ventricular System Proc. | J124: =VLOOKUP($D124,'prosedur-2025'!$A:$H,3,FALSE) -> 13108 | K124: =VLOOKUP($D124,'prosedur-2025'!$A:$H,4,FALSE) -> 74957648 | L124: =VLOOKUP($D124,'prosedur-2025'!$A:$H,5,FALSE) -> 34357232 | M124: =VLOOKUP($D124,'prosedur-2025'!$A:$H,6,FALSE) -> 53434087 | N124: =VLOOKUP($D124,'prosedur-2025'!$A:$H,7,FALSE) -> 86504609 | O124: =VLOOKUP($D124,'prosedur-2025'!$A:$H,8,FALSE) -> 143534937 | P124: =J124*K124 -> 982544850804
A125: PDC | B125: P11AF | C125: Ventricular System Procedures | D125: 02.35 | E125: Ventricular shunt to urinary system | F125: =VLOOKUP($D125,proc!$A:$D,3,FALSE) -> 5 | G125: =VLOOKUP($D125,proc!$A:$D,4,FALSE) -> 0 | H125: Ventricular System Proc. | J125: =VLOOKUP($D125,'prosedur-2025'!$A:$H,3,FALSE) -> 6 | K125: =VLOOKUP($D125,'prosedur-2025'!$A:$H,4,FALSE) -> 30898141 | L125: =VLOOKUP($D125,'prosedur-2025'!$A:$H,5,FALSE) -> 22619239 | M125: =VLOOKUP($D125,'prosedur-2025'!$A:$H,6,FALSE) -> 34473500 | N125: =VLOOKUP($D125,'prosedur-2025'!$A:$H,7,FALSE) -> 37063193 | O125: =VLOOKUP($D125,'prosedur-2025'!$A:$H,8,FALSE) -> 40066165 | P125: =J125*K125 -> 185388844
A126: PDC | B126: P11AF | C126: Ventricular System Procedures | D126: 02.39 | E126: Other operations to establish drainage of ventricle | F126: =VLOOKUP($D126,proc!$A:$D,3,FALSE) -> 5 | G126: =VLOOKUP($D126,proc!$A:$D,4,FALSE) -> 0 | H126: Ventricular System Proc. | J126: =VLOOKUP($D126,'prosedur-2025'!$A:$H,3,FALSE) -> 4602 | K126: =VLOOKUP($D126,'prosedur-2025'!$A:$H,4,FALSE) -> 86828675 | L126: =VLOOKUP($D126,'prosedur-2025'!$A:$H,5,FALSE) -> 38661114 | M126: =VLOOKUP($D126,'prosedur-2025'!$A:$H,6,FALSE) -> 57376300 | N126: =VLOOKUP($D126,'prosedur-2025'!$A:$H,7,FALSE) -> 98611186 | O126: =VLOOKUP($D126,'prosedur-2025'!$A:$H,8,FALSE) -> 168717974 | P126: =J126*K126 -> 399585563036
A127: PDC | B127: P11AF | C127: Ventricular System Procedures | D127: 02.41 | E127: Irrigation and exploration of ventricular shunt | F127: =VLOOKUP($D127,proc!$A:$D,3,FALSE) -> 0 | G127: =VLOOKUP($D127,proc!$A:$D,4,FALSE) -> 0 | H127: Ventricular System Proc. | J127: =VLOOKUP($D127,'prosedur-2025'!$A:$H,3,FALSE) -> 59 | K127: =VLOOKUP($D127,'prosedur-2025'!$A:$H,4,FALSE) -> 113670059 | L127: =VLOOKUP($D127,'prosedur-2025'!$A:$H,5,FALSE) -> 30793730 | M127: =VLOOKUP($D127,'prosedur-2025'!$A:$H,6,FALSE) -> 76496464 | N127: =VLOOKUP($D127,'prosedur-2025'!$A:$H,7,FALSE) -> 141401193 | O127: =VLOOKUP($D127,'prosedur-2025'!$A:$H,8,FALSE) -> 264663544 | P127: =J127*K127 -> 6706533483
A128: PDC | B128: P11AF | C128: Ventricular System Procedures | D128: 02.42 | E128: Replacement of ventricular shunt | F128: =VLOOKUP($D128,proc!$A:$D,3,FALSE) -> 5 | G128: =VLOOKUP($D128,proc!$A:$D,4,FALSE) -> 0 | H128: Ventricular System Proc. | J128: =VLOOKUP($D128,'prosedur-2025'!$A:$H,3,FALSE) -> 1231 | K128: =VLOOKUP($D128,'prosedur-2025'!$A:$H,4,FALSE) -> 72192376 | L128: =VLOOKUP($D128,'prosedur-2025'!$A:$H,5,FALSE) -> 26241292 | M128: =VLOOKUP($D128,'prosedur-2025'!$A:$H,6,FALSE) -> 45374358 | N128: =VLOOKUP($D128,'prosedur-2025'!$A:$H,7,FALSE) -> 84282812 | O128: =VLOOKUP($D128,'prosedur-2025'!$A:$H,8,FALSE) -> 149641471 | P128: =J128*K128 -> 88868815407
A129: PDC | B129: P11AF | C129: Ventricular System Procedures | D129: 02.43 | E129: Removal of ventricular shunt | F129: =VLOOKUP($D129,proc!$A:$D,3,FALSE) -> 5 | G129: =VLOOKUP($D129,proc!$A:$D,4,FALSE) -> 0 | H129: Ventricular System Proc. | J129: =VLOOKUP($D129,'prosedur-2025'!$A:$H,3,FALSE) -> 545 | K129: =VLOOKUP($D129,'prosedur-2025'!$A:$H,4,FALSE) -> 83850248 | L129: =VLOOKUP($D129,'prosedur-2025'!$A:$H,5,FALSE) -> 27431297 | M129: =VLOOKUP($D129,'prosedur-2025'!$A:$H,6,FALSE) -> 48863691 | N129: =VLOOKUP($D129,'prosedur-2025'!$A:$H,7,FALSE) -> 96869391 | O129: =VLOOKUP($D129,'prosedur-2025'!$A:$H,8,FALSE) -> 176749827 | P129: =J129*K129 -> 45698385288
A130: PDC | B130: P11AF | C130: Ventricular System Procedures | D130: 54.95 | E130: Incision of peritoneum | F130: =VLOOKUP($D130,proc!$A:$D,3,FALSE) -> 4 | G130: =VLOOKUP($D130,proc!$A:$D,4,FALSE) -> 0 | H130: Ventricular System Proc. | J130: =VLOOKUP($D130,'prosedur-2025'!$A:$H,3,FALSE) -> 462 | K130: =VLOOKUP($D130,'prosedur-2025'!$A:$H,4,FALSE) -> 48506017 | L130: =VLOOKUP($D130,'prosedur-2025'!$A:$H,5,FALSE) -> 17666816 | M130: =VLOOKUP($D130,'prosedur-2025'!$A:$H,6,FALSE) -> 31421173 | N130: =VLOOKUP($D130,'prosedur-2025'!$A:$H,7,FALSE) -> 52547678 | O130: =VLOOKUP($D130,'prosedur-2025'!$A:$H,8,FALSE) -> 85961545 | P130: =J130*K130 -> 22409779889
A131: PDC | B131: P11AE | C131: Simple Craniotomy | D131: 01.15 | E131: Biopsy of skull | F131: =VLOOKUP($D131,proc!$A:$D,3,FALSE) -> 4 | G131: =VLOOKUP($D131,proc!$A:$D,4,FALSE) -> 0 | H131: Simple Craniotomy Proc. | J131: =VLOOKUP($D131,'prosedur-2025'!$A:$H,3,FALSE) -> 81 | K131: =VLOOKUP($D131,'prosedur-2025'!$A:$H,4,FALSE) -> 35277169 | L131: =VLOOKUP($D131,'prosedur-2025'!$A:$H,5,FALSE) -> 12325242 | M131: =VLOOKUP($D131,'prosedur-2025'!$A:$H,6,FALSE) -> 27146402 | N131: =VLOOKUP($D131,'prosedur-2025'!$A:$H,7,FALSE) -> 46216100 | O131: =VLOOKUP($D131,'prosedur-2025'!$A:$H,8,FALSE) -> 68443679 | P131: =J131*K131 -> 2857450714
A132: PDC | B132: P11AE | C132: Simple Craniotomy | D132: 01.16 | E132: Intracranial oxygen monitoring | F132: =VLOOKUP($D132,proc!$A:$D,3,FALSE) -> 0 | G132: =VLOOKUP($D132,proc!$A:$D,4,FALSE) -> 0 | H132: Simple Craniotomy Proc. | J132: =VLOOKUP($D132,'prosedur-2025'!$A:$H,3,FALSE) -> 4 | K132: =VLOOKUP($D132,'prosedur-2025'!$A:$H,4,FALSE) -> 25536192 | L132: =VLOOKUP($D132,'prosedur-2025'!$A:$H,5,FALSE) -> 5657318 | M132: =VLOOKUP($D132,'prosedur-2025'!$A:$H,6,FALSE) -> 7481087 | N132: =VLOOKUP($D132,'prosedur-2025'!$A:$H,7,FALSE) -> 28056577 | O132: =VLOOKUP($D132,'prosedur-2025'!$A:$H,8,FALSE) -> 60949786 | P132: =J132*K132 -> 102144768
...

Sheet Sheet8
A1: ICD | B1: Deskripsi ICD | C1: PDC
A2: A06.6 | B2: Amoebic brain abscess | C2: PDC D11AA Nervous system infection
A3: A17.0 | B3: Tuberculous meningitis | C3: PDC D11AA Nervous system infection
A4: A17.1 | B4: Meningeal tuberculoma | C4: PDC D11AA Nervous system infection
A5: A17.8 | B5: Other tuberculosis of nervous system | C5: PDC D11AA Nervous system infection
A6: A17.9 | B6: Tuberculosis of nervous system unspecified | C6: PDC D11AA Nervous system infection
A7: A32.1 | B7: Listerial meningitis and meningoencephalitis | C7: PDC D11AA Nervous system infection
A8: A39.0 | B8: Meningococcal meningitis | C8: PDC D11AA Nervous system infection
A9: A50.4 | B9: Late congenital neurosyphilis [juvenile neurosyphilis] | C9: PDC D11AA Nervous system infection
A10: A52.1 | B10: Symptomatic neurosyphilis | C10: PDC D11AA Nervous system infection
A11: A52.2 | B11: Asymptomatic neurosyphilis | C11: PDC D11AA Nervous system infection
A12: A52.3 | B12: Neurosyphilis, unspecified | C12: PDC D11AA Nervous system infection
... A796: Z90.0 | B796: Acquired absence of part of head and neck | C796: PDC D11AV Gangguan Penyakit Sistem Persarafan Lain-lain
A797: ="00.62" -> 00.62 | B797: Percutaneous angioplasty or atherectomy of intracranial vessel(s) | C797: PDC P11AA Endovascular Procedures for Neurologic Diseases
A798: 38.52 | B798: Ligation and stripping of varicose veins, other vessels of head and neck | C798: PDC P11AA Endovascular Procedures for Neurologic Diseases
A799: 38.7 | B799: Interruption vena cava | C799: PDC P11AA Endovascular Procedures for Neurologic Diseases
A800: 38.82 | B800: Other surgical occlusion of vessels, other vessels of head and neck | C800: PDC P11AA Endovascular Procedures for Neurologic Diseases
A801: 39.72 | B801: Endovascular embolization or occlusion of head and neck vessels | C801: PDC P11AA Endovascular Procedures for Neurologic Diseases
A802: 39.74 | B802: Endovascular removal of obstruction from head and neck vessel(s) | C802: PDC P11AA Endovascular Procedures for Neurologic Diseases
A803: 39.75 | B803: Endovascular embolization or occlusion of vessel(s) of head or neck using bare coils | C803: PDC P11AA Endovascular Procedures for Neurologic Diseases
A804: 39.76 | B804: Endovascular embolization or occlusion of vessel(s) of head or neck using bioactive coils | C804: PDC P11AA Endovascular Procedures for Neurologic Diseases
A805: 39.81 | B805: Implantation or replacement of carotid sinus stimulation device, total system (IM) | C805: PDC P11AA Endovascular Procedures for Neurologic Diseases
A806: 39.82 | B806: Implantation or replacement of carotid sinus stimulation lead(s) only (IM) | C806: PDC P11AA Endovascular Procedures for Neurologic Diseases
A807: 39.83 | B807: Implantation or replacement of carotid sinus stimulation pulse generator only (IM) | C807: PDC P11AA Endovascular Procedures for Neurologic Diseases
A808: 39.84 | B808: Revision of carotid sinus stimulation lead(s) only (IM) | C808: PDC P11AA Endovascular Procedures for Neurologic Diseases
A809: 39.85 | B809: Revision of carotid sinus stimulation pulse generator (IM) | C809: PDC P11AA Endovascular Procedures for Neurologic Diseases
... A813: 39.89 | B813: Other operations on carotid body, carotid sinus and other vascular bodies (IM) | C813: PDC P11AA Endovascular Procedures for Neurologic Diseases
A814: ="03.4" -> 03.4 | B814: Excision or destruction of lesion of spinal cord or spinal meninges | C814: PDC P11AB Complex Spinal Procedures
A815: ="03.52" -> 03.52 | B815: Repair of spinal myelomeningocele | C815: PDC P11AB Complex Spinal Procedures
A816: ="03.99" -> 03.99 | B816: Other operations on spinal cord and spinal canal structures | C816: PDC P11AB Complex Spinal Procedures
A817: 81 | B817: Spinal fusion, not otherwise specified | C817: PDC P11AB Complex Spinal Procedures
A818: 81.01 | B818: Atlas-axis spinal fusion | C818: PDC P11AB Complex Spinal Procedures
A819: 81.02 | B819: Other cervical fusion of the anterior column, anterior technique | C819: PDC P11AB Complex Spinal Procedures
A820: 81.03 | B820: Other cervical fusion of the posterior column, posterior technique | C820: PDC P11AB Complex Spinal Procedures
A821: 81.04 | B821: Dorsal and dorsolumbar fusion of the anterior column, anterior technique | C821: PDC P11AB Complex Spinal Procedures
A822: 81.05 | B822: Dorsal and dorsolumbar fusion of the posterior column, posterior technique | C822: PDC P11AB Complex Spinal Procedures
A823: 81.06 | B823: Lumbar and lumbosacral fusion of the anterior column, anterior technique | C823: PDC P11AB Complex Spinal Procedures
A824: 81.07 | B824: Lumbar and lumbosacral fusion of the posterior column, posterior technique | C824: PDC P11AB Complex Spinal Procedures
A825: 81.08 | B825: Lumbar and lumbosacral fusion of the anterior column, posterior technique | C825: PDC P11AB Complex Spinal Procedures
A826: 81.3 | B826: Refusion of spine, not otherwise specified | C826: PDC P11AB Complex Spinal Procedures
A827: 81.31 | B827: Refusion of atlas-axis spine | C827: PDC P11AB Complex Spinal Procedures
A828: 81.32 | B828: Refusion of other cervical spine, anterior column, anterior technique | C828: PDC P11AB Complex Spinal Procedures
... A845: 84.69 | B845: Revision or replacement of artificial spinal disc prosthesis, not otherwise specified | C845: PDC P11AB Complex Spinal Procedures
A846: ="01.41" -> 01.41 | B846: Operations on thalamus | C846: PDC P11AC Complex Craniotomy Procedures
A847: ="01.42" -> 01.42 | B847: Operations on globus pallidus | C847: PDC P11AC Complex Craniotomy Procedures
A848: ="04.01" -> 04.01 | B848: Excision of acoustic neuroma | C848: PDC P11AC Complex Craniotomy Procedures
A849: 17.61 | B849: Laser interstitial thermal therapy [LITT] of lesion or tissue of brain under guidance | C849: PDC P11AC Complex Craniotomy Procedures
A850: 17.62 | B850: Laser interstitial thermal therapy [LITT] of lesion or tissue of head and neck under guidance | C850: PDC P11AC Complex Craniotomy Procedures
A851: ="01.02" -> 01.02 | B851: Ventriculopuncture through previously implanted catheter | C851: PDC P11AD Ventricular System Procedures
A852: ="02.2" -> 02.2 | B852: Ventriculostomy | C852: PDC P11AD Ventricular System Procedures
A853: ="02.20" -> 02.20 | B853: Endoscopic ventriculostomy (IM) | C853: PDC P11AD Ventricular System Procedures
A854: ="02.31" -> 02.31 | B854: Ventricular shunt to structure in head and neck | C854: PDC P11AD Ventricular System Procedures
A855: ="02.32" -> 02.32 | B855: Ventricular shunt to circulatory system | C855: PDC P11AD Ventricular System Procedures
A856: ="02.33" -> 02.33 | B856: Ventricular shunt to thoracic cavity | C856: PDC P11AD Ventricular System Procedures
A857: ="02.34" -> 02.34 | B857: Ventricular shunt to abdominal cavity and organs | C857: PDC P11AD Ventricular System Procedures
A858: ="02.35" -> 02.35 | B858: Ventricular shunt to urinary system | C858: PDC P11AD Ventricular System Procedures
A859: ="02.39" -> 02.39 | B859: Other operations to establish drainage of ventricle | C859: PDC P11AD Ventricular System Procedures
A860: ="02.41" -> 02.41 | B860: Irrigation and exploration of ventricular shunt | C860: PDC P11AD Ventricular System Procedures
A861: ="02.42" -> 02.42 | B861: Replacement of ventricular shunt | C861: PDC P11AD Ventricular System Procedures
A862: ="02.43" -> 02.43 | B862: Removal of ventricular shunt | C862: PDC P11AD Ventricular System Procedures
A863: 54.95 | B863: Incision of peritoneum | C863: PDC P11AD Ventricular System Procedures
A864: ="01.13" -> 01.13 | B864: Closed [percutaneous] [needle] biopsy of brain | C864: PDC P11AE Moderate Craniotomy Procedures
A865: ="01.17" -> 01.17 | B865: Brain temperature monitoring | C865: PDC P11AE Moderate Craniotomy Procedures
A866: ="01.23" -> 01.23 | B866: Reopening of craniotomy site | C866: PDC P11AE Moderate Craniotomy Procedures
A867: ="01.39" -> 01.39 | B867: Other incision of brain | C867: PDC P11AE Moderate Craniotomy Procedures
A868: ="01.51" -> 01.51 | B868: Excision of lesion or tissue of cerebral meninges | C868: PDC P11AE Moderate Craniotomy Procedures
A869: ="01.52" -> 01.52 | B869: Hemispherectomy | C869: PDC P11AE Moderate Craniotomy Procedures
A870: ="01.53" -> 01.53 | B870: Lobectomy of brain | C870: PDC P11AE Moderate Craniotomy Procedures
A871: ="01.59" -> 01.59 | B871: Other excision or destruction of lesion or tissue of brain | C871: PDC P11AE Moderate Craniotomy Procedures
A872: ="02.01" -> 02.01 | B872: Opening of cranial suture | C872: PDC P11AE Moderate Craniotomy Procedures
A873: ="02.14" -> 02.14 | B873: Choroid plexectomy | C873: PDC P11AE Moderate Craniotomy Procedures
A874: ="02.92" -> 02.92 | B874: Repair of brain | C874: PDC P11AE Moderate Craniotomy Procedures
A875: ="02.99" -> 02.99 | B875: Other operations on skull, brain, and cerebral meninges | C875: PDC P11AE Moderate Craniotomy Procedures
A876: ="04.05" -> 04.05 | B876: Gasserian ganglionectomy | C876: PDC P11AE Moderate Craniotomy Procedures
A877: ="04.41" -> 04.41 | B877: Decompression of trigeminal nerve root | C877: PDC P11AE Moderate Craniotomy Procedures
A878: ="04.42" -> 04.42 | B878: Other cranial nerve decompression | C878: PDC P11AE Moderate Craniotomy Procedures
A879: ="04.421" -> 04.421 | B879: Decompression of facial nerve with or without graft (IM) | C879: PDC P11AE Moderate Craniotomy Procedures
A880: ="07.13" -> 07.13 | B880: Biopsy of pituitary gland, transfrontal approach | C880: PDC P11AE Moderate Craniotomy Procedures
A881: ="07.14" -> 07.14 | B881: Biopsy of pituitary gland, transsphenoidal approach | C881: PDC P11AE Moderate Craniotomy Procedures
A882: ="07.15" -> 07.15 | B882: Biopsy of pituitary gland, unspecified approach | C882: PDC P11AE Moderate Craniotomy Procedures
A883: ="07.17" -> 07.17 | B883: Biopsy of pineal gland | C883: PDC P11AE Moderate Craniotomy Procedures
A884: ="07.51" -> 07.51 | B884: Exploration of pineal field | C884: PDC P11AE Moderate Craniotomy Procedures
A885: ="07.52" -> 07.52 | B885: Incision of pineal gland | C885: PDC P11AE Moderate Craniotomy Procedures
A886: ="07.53" -> 07.53 | B886: Partial excision of pineal gland | C886: PDC P11AE Moderate Craniotomy Procedures
A887: ="07.54" -> 07.54 | B887: Total excision of pineal gland | C887: PDC P11AE Moderate Craniotomy Procedures
A888: ="07.59" -> 07.59 | B888: Other operations on pineal gland | C888: PDC P11AE Moderate Craniotomy Procedures
A889: ="07.61" -> 07.61 | B889: Partial excision of pituitary gland, transfrontal approach | C889: PDC P11AE Moderate Craniotomy Procedures
A890: ="07.62" -> 07.62 | B890: Partial excision of pituitary gland, transsphenoidal approach | C890: PDC P11AE Moderate Craniotomy Procedures
A891: ="07.63" -> 07.63 | B891: Partial excision of pituitary gland, unspecified approach | C891: PDC P11AE Moderate Craniotomy Procedures
A892: ="07.64" -> 07.64 | B892: Total excision of pituitary gland, transfrontal approach | C892: PDC P11AE Moderate Craniotomy Procedures
A893: ="07.65" -> 07.65 | B893: Total excision of pituitary gland, transsphenoidal approach | C893: PDC P11AE Moderate Craniotomy Procedures
A894: ="07.68" -> 07.68 | B894: Total excision of pituitary gland, other specified approach | C894: PDC P11AE Moderate Craniotomy Procedures
A895: ="07.69" -> 07.69 | B895: Total excision of pituitary gland, unspecified approach | C895: PDC P11AE Moderate Craniotomy Procedures
A896: ="07.71" -> 07.71 | B896: Exploration of pituitary fossa | C896: PDC P11AE Moderate Craniotomy Procedures
A897: ="07.72" -> 07.72 | B897: Incision of pituitary gland | C897: PDC P11AE Moderate Craniotomy Procedures
A898: ="07.79" -> 07.79 | B898: Other operations on hypophysis | C898: PDC P11AE Moderate Craniotomy Procedures
A899: ="01.10" -> 01.10 | B899: Intracranial pressure monitoring | C899: PDC P11AF Simple Craniotomy Procedures
A900: ="01.11" -> 01.11 | B900: Closed [percutaneous] [needle] biopsy of cerebral meninges | C900: PDC P11AF Simple Craniotomy Procedures
A901: ="01.12" -> 01.12 | B901: Open biopsy of cerebral meninges | C901: PDC P11AF Simple Craniotomy Procedures
A902: ="01.14" -> 01.14 | B902: Open biopsy of brain | C902: PDC P11AF Simple Craniotomy Procedures
...

Sheet ranap clusters (ICD 9)
A1: Cluster Type | B1: Cluster Code | C1: Cluster Description | D1: ICD-9-CM Code | E1: ICD-9-CM Description | F1: Grade | G1: IM | H1: ICD-9-CM no dot | I1: New Cluster Description | J1: New Cluster Code | K1: jumlah kasus | L1: mean_billing | M1: p25 | N1: p50 | O1: p75 | P1: p90 | Q1: total | R1: Keterangan | S1: Action | T1: ICD-9 Code | U1: ICD 10 | V1: Deskripsi ICD 10 | W1: code | X1: mdc | Y1: pdc | Z1: ptd | AA1: description | AB1: catatan upload | AC1: ax | AD1: code | AE1: cl
A2: PDC | B2: P11AC | C2: Endovascular Procedures for Neurologic Diseases | D2: 00.62 | E2: Percutaneous angioplasty or atherectomy of intracranial vessel(s) | F2: =VLOOKUP($D2,proc!$A:$D,3,FALSE) -> 3 | G2: =VLOOKUP($D2,proc!$A:$D,4,FALSE) -> 0 | H2: 0062 | I2: #N/A | J2: #N/A | K2: =VLOOKUP($D2,'prosedur-2025'!$A:$H,3,FALSE) -> 120 | L2: =VLOOKUP($D2,'prosedur-2025'!$A:$H,4,FALSE) -> 78497963 | M2: =VLOOKUP($D2,'prosedur-2025'!$A:$H,5,FALSE) -> 31029390 | N2: =VLOOKUP($D2,'prosedur-2025'!$A:$H,6,FALSE) -> 49040723 | O2: =VLOOKUP($D2,'prosedur-2025'!$A:$H,7,FALSE) -> 88993193 | P2: =VLOOKUP($D2,'prosedur-2025'!$A:$H,8,FALSE) -> 153022000 | Q2: =K2*L2 -> 9419755502 | R2: sudah ada rumah baru PTA Cerebral (CK) | S2: drop
A3: PDC | B3: P11AC | C3: Endovascular Procedures for Neurologic Diseases | D3: 38.52 | E3: Ligation and stripping of varicose veins, other vessels of head and neck | F3: =VLOOKUP($D3,proc!$A:$D,3,FALSE) -> 0 | G3: =VLOOKUP($D3,proc!$A:$D,4,FALSE) -> 0 | H3: =SUBSTITUTE(D3,".","") -> 3852 | I3: Endovascular Proc. for Neurologic Diseases | J3: =VLOOKUP(H3,'upload c51prpdc'!A:C,3,FALSE) -> P11AA | K3: =VLOOKUP($D3,'prosedur-2025'!$A:$H,3,FALSE) -> 33 | L3: =VLOOKUP($D3,'prosedur-2025'!$A:$H,4,FALSE) -> 21821658 | M3: =VLOOKUP($D3,'prosedur-2025'!$A:$H,5,FALSE) -> 7330331 | N3: =VLOOKUP($D3,'prosedur-2025'!$A:$H,6,FALSE) -> 13625695 | O3: =VLOOKUP($D3,'prosedur-2025'!$A:$H,7,FALSE) -> 22771045 | P3: =VLOOKUP($D3,'prosedur-2025'!$A:$H,8,FALSE) -> 55892400 | Q3: =K3*L3 -> 720114702 | T3: =TEXT(VALUE(D3),"00.00") -> 38.52 | W3: =H3 -> 3852 | X3: 11 | Y3: =J3 -> P11AA | Z3: 1 | AA3: =I3 -> Endovascular Proc. for Neurologic Diseases
A4: PDC | B4: P11AC | C4: Endovascular Procedures for Neurologic Diseases | D4: 38.7 | E4: Interruption vena cava | F4: =VLOOKUP($D4,proc!$A:$D,3,FALSE) -> 5 | G4: =VLOOKUP($D4,proc!$A:$D,4,FALSE) -> 0 | H4: =SUBSTITUTE(D4,".","") -> 387 | I4: Endovascular Proc. for Neurologic Diseases | J4: =VLOOKUP(H4,'upload c51prpdc'!A:C,3,FALSE) -> P11AA | K4: =VLOOKUP($D4,'prosedur-2025'!$A:$H,3,FALSE) -> 121 | L4: =VLOOKUP($D4,'prosedur-2025'!$A:$H,4,FALSE) -> 67670327 | M4: =VLOOKUP($D4,'prosedur-2025'!$A:$H,5,FALSE) -> 29852859 | N4: =VLOOKUP($D4,'prosedur-2025'!$A:$H,6,FALSE) -> 58105112 | O4: =VLOOKUP($D4,'prosedur-2025'!$A:$H,7,FALSE) -> 92598541 | P4: =VLOOKUP($D4,'prosedur-2025'!$A:$H,8,FALSE) -> 135912123 | Q4: =K4*L4 -> 8188109584 | T4: =TEXT(VALUE(D4),"00.00") -> 38.70 | W4: =H4 -> 387 | X4: 11 | Y4: =J4 -> P11AA | Z4: 1 | AA4: =I4 -> Endovascular Proc. for Neurologic Diseases
A5: PDC | B5: P11AC | C5: Endovascular Procedures for Neurologic Diseases | D5: 38.82 | E5: Other surgical occlusion of vessels, other vessels of head and neck | F5: =VLOOKUP($D5,proc!$A:$D,3,FALSE) -> 4 | G5: =VLOOKUP($D5,proc!$A:$D,4,FALSE) -> 0 | H5: =SUBSTITUTE(D5,".","") -> 3882 | I5: Endovascular Proc. for Neurologic Diseases | J5: =VLOOKUP(H5,'upload c51prpdc'!A:C,3,FALSE) -> P11AA | K5: =VLOOKUP($D5,'prosedur-2025'!$A:$H,3,FALSE) -> 434 | L5: =VLOOKUP($D5,'prosedur-2025'!$A:$H,4,FALSE) -> 48032893 | M5: =VLOOKUP($D5,'prosedur-2025'!$A:$H,5,FALSE) -> 10435277 | N5: =VLOOKUP($D5,'prosedur-2025'!$A:$H,6,FALSE) -> 22179491 | O5: =VLOOKUP($D5,'prosedur-2025'!$A:$H,7,FALSE) -> 61098522 | P5: =VLOOKUP($D5,'prosedur-2025'!$A:$H,8,FALSE) -> 123946351 | Q5: =K5*L5 -> 20846275429 | T5: =TEXT(VALUE(D5),"00.00") -> 38.82 | W5: =H5 -> 3882 | X5: 11 | Y5: =J5 -> P11AA | Z5: 1 | AA5: =I5 -> Endovascular Proc. for Neurologic Diseases
A6: PDC | B6: P11AC | C6: Endovascular Procedures for Neurologic Diseases | D6: 39.72 | E6: Endovascular embolization or occlusion of head and neck vessels | F6: =VLOOKUP($D6,proc!$A:$D,3,FALSE) -> 6 | G6: =VLOOKUP($D6,proc!$A:$D,4,FALSE) -> 0 | H6: =SUBSTITUTE(D6,".","") -> 3972 | I6: Endovascular Proc. for Neurologic Diseases | J6: =VLOOKUP(H6,'upload c51prpdc'!A:C,3,FALSE) -> P11AA | K6: =VLOOKUP($D6,'prosedur-2025'!$A:$H,3,FALSE) -> 339 | L6: =VLOOKUP($D6,'prosedur-2025'!$A:$H,4,FALSE) -> 77422054 | M6: =VLOOKUP($D6,'prosedur-2025'!$A:$H,5,FALSE) -> 34528674 | N6: =VLOOKUP($D6,'prosedur-2025'!$A:$H,6,FALSE) -> 59125877 | O6: =VLOOKUP($D6,'prosedur-2025'!$A:$H,7,FALSE) -> 99036851 | P6: =VLOOKUP($D6,'prosedur-2025'!$A:$H,8,FALSE) -> 162366954 | Q6: =K6*L6 -> 26246076412 | T6: =TEXT(VALUE(D6),"00.00") -> 39.72 | W6: =H6 -> 3972 | X6: 11 | Y6: =J6 -> P11AA | Z6: 1 | AA6: =I6 -> Endovascular Proc. for Neurologic Diseases
A7: PDC | D7: 39.720 | E7: Endovascular repair or occlusion of head and neck vessels with detachable balloon (IM) | F7: 6 | G7: 1 | H7: =SUBSTITUTE(D7,".","") -> 39720 | I7: Endovascular Proc. for Neurologic Diseases | J7: P11AA | W7: =H7 -> 39720 | X7: 11 | Y7: =J7 -> P11AA | Z7: 1 | AA7: =I7 -> Endovascular Proc. for Neurologic Diseases
A8: PDC | B8: P11AC | C8: Endovascular Procedures for Neurologic Diseases | D8: 39.74 | E8: Endovascular removal of obstruction from head and neck vessel(s) | F8: =VLOOKUP($D8,proc!$A:$D,3,FALSE) -> 5 | G8: =VLOOKUP($D8,proc!$A:$D,4,FALSE) -> 0 | H8: =SUBSTITUTE(D8,".","") -> 3974 | I8: Endovascular Proc. for Neurologic Diseases | J8: =VLOOKUP(H8,'upload c51prpdc'!A:C,3,FALSE) -> P11AA | K8: =VLOOKUP($D8,'prosedur-2025'!$A:$H,3,FALSE) -> 412 | L8: =VLOOKUP($D8,'prosedur-2025'!$A:$H,4,FALSE) -> 1.1316846e+08 | M8: =VLOOKUP($D8,'prosedur-2025'!$A:$H,5,FALSE) -> 61273050 | N8: =VLOOKUP($D8,'prosedur-2025'!$A:$H,6,FALSE) -> 97611950 | O8: =VLOOKUP($D8,'prosedur-2025'!$A:$H,7,FALSE) -> 139420700 | P8: =VLOOKUP($D8,'prosedur-2025'!$A:$H,8,FALSE) -> 193880000 | Q8: =K8*L8 -> 46625405734 | T8: =TEXT(VALUE(D8),"00.00") -> 39.74 | W8: =H8 -> 3974 | X8: 11 | Y8: =J8 -> P11AA | Z8: 1 | AA8: =I8 -> Endovascular Proc. for Neurologic Diseases
A9: PDC | B9: P11AC | C9: Endovascular Procedures for Neurologic Diseases | D9: 39.75 | E9: Endovascular embolization or occlusion of vessel(s) of head or neck using bare coils | F9: =VLOOKUP($D9,proc!$A:$D,3,FALSE) -> 5 | G9: =VLOOKUP($D9,proc!$A:$D,4,FALSE) -> 0 | H9: =SUBSTITUTE(D9,".","") -> 3975 | I9: Endovascular Proc. for Neurologic Diseases | J9: =VLOOKUP(H9,'upload c51prpdc'!A:C,3,FALSE) -> P11AA | K9: =VLOOKUP($D9,'prosedur-2025'!$A:$H,3,FALSE) -> 820 | L9: =VLOOKUP($D9,'prosedur-2025'!$A:$H,4,FALSE) -> 1.2139781e+08 | M9: =VLOOKUP($D9,'prosedur-2025'!$A:$H,5,FALSE) -> 72539060 | N9: =VLOOKUP($D9,'prosedur-2025'!$A:$H,6,FALSE) -> 100933007 | O9: =VLOOKUP($D9,'prosedur-2025'!$A:$H,7,FALSE) -> 144954100 | P9: =VLOOKUP($D9,'prosedur-2025'!$A:$H,8,FALSE) -> 207161425 | Q9: =K9*L9 -> 99546207534 | T9: =TEXT(VALUE(D9),"00.00") -> 39.75 | W9: =H9 -> 3975 | X9: 11 | Y9: =J9 -> P11AA | Z9: 1 | AA9: =I9 -> Endovascular Proc. for Neurologic Diseases
A10: PDC | B10: P11AC | C10: Endovascular Procedures for Neurologic Diseases | D10: 39.76 | E10: Endovascular embolization or occlusion of vessel(s) of head or neck using bioactive coils | F10: =VLOOKUP($D10,proc!$A:$D,3,FALSE) -> 5 | G10: =VLOOKUP($D10,proc!$A:$D,4,FALSE) -> 0 | H10: =SUBSTITUTE(D10,".","") -> 3976 | I10: Endovascular Proc. for Neurologic Diseases | J10: =VLOOKUP(H10,'upload c51prpdc'!A:C,3,FALSE) -> P11AA | K10: =VLOOKUP($D10,'prosedur-2025'!$A:$H,3,FALSE) -> 25 | L10: =VLOOKUP($D10,'prosedur-2025'!$A:$H,4,FALSE) -> 73873294 | M10: =VLOOKUP($D10,'prosedur-2025'!$A:$H,5,FALSE) -> 46871484 | N10: =VLOOKUP($D10,'prosedur-2025'!$A:$H,6,FALSE) -> 62436689 | O10: =VLOOKUP($D10,'prosedur-2025'!$A:$H,7,FALSE) -> 95671460 | P10: =VLOOKUP($D10,'prosedur-2025'!$A:$H,8,FALSE) -> 147131046 | Q10: =K10*L10 -> 1846832339 | T10: =TEXT(VALUE(D10),"00.00") -> 39.76 | W10: =H10 -> 3976 | X10: 11 | Y10: =J10 -> P11AA | Z10: 1 | AA10: =I10 -> Endovascular Proc. for Neurologic Diseases
A11: PDC | B11: P11AC | C11: Endovascular Procedures for Neurologic Diseases | D11: 39.81 | E11: Implantation or replacement of carotid sinus stimulation device, total system (IM) | F11: =VLOOKUP($D11,proc!$A:$D,3,FALSE) -> 4 | G11: =VLOOKUP($D11,proc!$A:$D,4,FALSE) -> 1 | H11: =SUBSTITUTE(D11,".","") -> 3981 | I11: Endovascular Proc. for Neurologic Diseases | J11: =VLOOKUP(H11,'upload c51prpdc'!A:C,3,FALSE) -> P11AA | K11: =VLOOKUP($D11,'prosedur-2025'!$A:$H,3,FALSE) -> 3 | L11: =VLOOKUP($D11,'prosedur-2025'!$A:$H,4,FALSE) -> 66396559 | M11: =VLOOKUP($D11,'prosedur-2025'!$A:$H,5,FALSE) -> 13113019 | N11: =VLOOKUP($D11,'prosedur-2025'!$A:$H,6,FALSE) -> 55660455 | O11: =VLOOKUP($D11,'prosedur-2025'!$A:$H,7,FALSE) -> 130416204 | P11: =VLOOKUP($D11,'prosedur-2025'!$A:$H,8,FALSE) -> 130416204 | Q11: =K11*L11 -> 199189678 | T11: =TEXT(VALUE(D11),"00.00") -> 39.81 | W11: =H11 -> 3981 | X11: 11 | Y11: =J11 -> P11AA | Z11: 1 | AA11: =I11 -> Endovascular Proc. for Neurologic Diseases
A12: PDC | B12: P11AC | C12: Endovascular Procedures for Neurologic Diseases | D12: 39.82 | E12: Implantation or replacement of carotid sinus stimulation lead(s) only (IM) | F12: =VLOOKUP($D12,proc!$A:$D,3,FALSE) -> 4 | G12: =VLOOKUP($D12,proc!$A:$D,4,FALSE) -> 1 | H12: =SUBSTITUTE(D12,".","") -> 3982 | I12: Endovascular Proc. for Neurologic Diseases | J12: =VLOOKUP(H12,'upload c51prpdc'!A:C,3,FALSE) -> P11AA | K12: =VLOOKUP($D12,'prosedur-2025'!$A:$H,3,FALSE) -> 3 | L12: =VLOOKUP($D12,'prosedur-2025'!$A:$H,4,FALSE) -> 22003947 | M12: =VLOOKUP($D12,'prosedur-2025'!$A:$H,5,FALSE) -> 2830922 | N12: =VLOOKUP($D12,'prosedur-2025'!$A:$H,6,FALSE) -> 23146200 | O12: =VLOOKUP($D12,'prosedur-2025'!$A:$H,7,FALSE) -> 40034720 | P12: =VLOOKUP($D12,'prosedur-2025'!$A:$H,8,FALSE) -> 40034720 | Q12: =K12*L12 -> 66011842 | T12: =TEXT(VALUE(D12),"00.00") -> 39.82 | W12: =H12 -> 3982 | X12: 11 | Y12: =J12 -> P11AA | Z12: 1 | AA12: =I12 -> Endovascular Proc. for Neurologic Diseases
A13: PDC | B13: P11AC | C13: Endovascular Procedures for Neurologic Diseases | D13: 39.83 | E13: Implantation or replacement of carotid sinus stimulation pulse generator only (IM) | F13: =VLOOKUP($D13,proc!$A:$D,3,FALSE) -> 4 | G13: =VLOOKUP($D13,proc!$A:$D,4,FALSE) -> 1 | H13: =SUBSTITUTE(D13,".","") -> 3983 | I13: Endovascular Proc. for Neurologic Diseases | J13: =VLOOKUP(H13,'upload c51prpdc'!A:C,3,FALSE) -> P11AA | K13: =VLOOKUP($D13,'prosedur-2025'!$A:$H,3,FALSE) -> 21 | L13: =VLOOKUP($D13,'prosedur-2025'!$A:$H,4,FALSE) -> 61165163 | M13: =VLOOKUP($D13,'prosedur-2025'!$A:$H,5,FALSE) -> 24235442 | N13: =VLOOKUP($D13,'prosedur-2025'!$A:$H,6,FALSE) -> 50697300 | O13: =VLOOKUP($D13,'prosedur-2025'!$A:$H,7,FALSE) -> 81533763 | P13: =VLOOKUP($D13,'prosedur-2025'!$A:$H,8,FALSE) -> 143177942 | Q13: =K13*L13 -> 1284468416 | T13: =TEXT(VALUE(D13),"00.00") -> 39.83 | W13: =H13 -> 3983 | X13: 11 | Y13: =J13 -> P11AA | Z13: 1 | AA13: =I13 -> Endovascular Proc. for Neurologic Diseases
A14: PDC | B14: P11AC | C14: Endovascular Procedures for Neurologic Diseases | D14: 39.84 | E14: Revision of carotid sinus stimulation lead(s) only (IM) | F14: =VLOOKUP($D14,proc!$A:$D,3,FALSE) -> 4 | G14: =VLOOKUP($D14,proc!$A:$D,4,FALSE) -> 1 | H14: =SUBSTITUTE(D14,".","") -> 3984 | I14: Endovascular Proc. for Neurologic Diseases | J14: =VLOOKUP(H14,'upload c51prpdc'!A:C,3,FALSE) -> P11AA | T14: =TEXT(VALUE(D14),"00.00") -> 39.84 | W14: =H14 -> 3984 | X14: 11 | Y14: =J14 -> P11AA | Z14: 1 | AA14: =I14 -> Endovascular Proc. for Neurologic Diseases
A15: PDC | B15: P11AC | C15: Endovascular Procedures for Neurologic Diseases | D15: 39.85 | E15: Revision of carotid sinus stimulation pulse generator (IM) | F15: =VLOOKUP($D15,proc!$A:$D,3,FALSE) -> 4 | G15: =VLOOKUP($D15,proc!$A:$D,4,FALSE) -> 1 | H15: =SUBSTITUTE(D15,".","") -> 3985 | I15: Endovascular Proc. for Neurologic Diseases | J15: =VLOOKUP(H15,'upload c51prpdc'!A:C,3,FALSE) -> P11AA | K15: =VLOOKUP($D15,'prosedur-2025'!$A:$H,3,FALSE) -> 19 | L15: =VLOOKUP($D15,'prosedur-2025'!$A:$H,4,FALSE) -> 33694355 | M15: =VLOOKUP($D15,'prosedur-2025'!$A:$H,5,FALSE) -> 11539385 | N15: =VLOOKUP($D15,'prosedur-2025'!$A:$H,6,FALSE) -> 17995946 | O15: =VLOOKUP($D15,'prosedur-2025'!$A:$H,7,FALSE) -> 46867900 | P15: =VLOOKUP($D15,'prosedur-2025'!$A:$H,8,FALSE) -> 106980599 | Q15: =K15*L15 -> 640192748 | T15: =TEXT(VALUE(D15),"00.00") -> 39.85 | W15: =H15 -> 3985 | X15: 11 | Y15: =J15 -> P11AA | Z15: 1 | AA15: =I15 -> Endovascular Proc. for Neurologic Diseases
A16: PDC | B16: P11AC | C16: Endovascular Procedures for Neurologic Diseases | D16: 39.86 | E16: Removal of carotid sinus stimulation device, total system (IM) | F16: =VLOOKUP($D16,proc!$A:$D,3,FALSE) -> 4 | G16: =VLOOKUP($D16,proc!$A:$D,4,FALSE) -> 1 | H16: =SUBSTITUTE(D16,".","") -> 3986 | I16: Endovascular Proc. for Neurologic Diseases | J16: =VLOOKUP(H16,'upload c51prpdc'!A:C,3,FALSE) -> P11AA | T16: =TEXT(VALUE(D16),"00.00") -> 39.86 | W16: =H16 -> 3986 | X16: 11 | Y16: =J16 -> P11AA | Z16: 1 | AA16: =I16 -> Endovascular Proc. for Neurologic Diseases
A17: PDC | B17: P11AC | C17: Endovascular Procedures for Neurologic Diseases | D17: 39.87 | E17: Removal of carotid sinus stimulation lead(s) only (IM) | F17: =VLOOKUP($D17,proc!$A:$D,3,FALSE) -> 4 | G17: =VLOOKUP($D17,proc!$A:$D,4,FALSE) -> 1 | H17: =SUBSTITUTE(D17,".","") -> 3987 | I17: Endovascular Proc. for Neurologic Diseases | J17: =VLOOKUP(H17,'upload c51prpdc'!A:C,3,FALSE) -> P11AA | K17: =VLOOKUP($D17,'prosedur-2025'!$A:$H,3,FALSE) -> 9 | L17: =VLOOKUP($D17,'prosedur-2025'!$A:$H,4,FALSE) -> 45263476 | M17: =VLOOKUP($D17,'prosedur-2025'!$A:$H,5,FALSE) -> 12766300 | N17: =VLOOKUP($D17,'prosedur-2025'!$A:$H,6,FALSE) -> 27068225 | O17: =VLOOKUP($D17,'prosedur-2025'!$A:$H,7,FALSE) -> 76887394 | P17: =VLOOKUP($D17,'prosedur-2025'!$A:$H,8,FALSE) -> 113466738 | Q17: =K17*L17 -> 407371283 | T17: =TEXT(VALUE(D17),"00.00") -> 39.87 | W17: =H17 -> 3987 | X17: 11 | Y17: =J17 -> P11AA | Z17: 1 | AA17: =I17 -> Endovascular Proc. for Neurologic Diseases
A18: PDC | B18: P11AC | C18: Endovascular Procedures for Neurologic Diseases | D18: 39.88 | E18: Removal of carotid sinus stimulation pulse generator only (IM) | F18: =VLOOKUP($D18,proc!$A:$D,3,FALSE) -> 4 | G18: =VLOOKUP($D18,proc!$A:$D,4,FALSE) -> 1 | H18: =SUBSTITUTE(D18,".","") -> 3988 | I18: Endovascular Proc. for Neurologic Diseases | J18: =VLOOKUP(H18,'upload c51prpdc'!A:C,3,FALSE) -> P11AA | K18: =VLOOKUP($D18,'prosedur-2025'!$A:$H,3,FALSE) -> 4 | L18: =VLOOKUP($D18,'prosedur-2025'!$A:$H,4,FALSE) -> 80759175 | M18: =VLOOKUP($D18,'prosedur-2025'!$A:$H,5,FALSE) -> 27335689 | N18: =VLOOKUP($D18,'prosedur-2025'!$A:$H,6,FALSE) -> 59070224 | O18: =VLOOKUP($D18,'prosedur-2025'!$A:$H,7,FALSE) -> 62839575 | P18: =VLOOKUP($D18,'prosedur-2025'!$A:$H,8,FALSE) -> 173791213 | Q18: =K18*L18 -> 323036701 | T18: =TEXT(VALUE(D18),"00.00") -> 39.88 | W18: =H18 -> 3988 | X18: 11 | Y18: =J18 -> P11AA | Z18: 1 | AA18: =I18 -> Endovascular Proc. for Neurologic Diseases
A19: PDC | B19: P11AC | C19: Endovascular Procedures for Neurologic Diseases | D19: 39.89 | E19: Other operations on carotid body, carotid sinus and other vascular bodies (IM) | F19: =VLOOKUP($D19,proc!$A:$D,3,FALSE) -> 4 | G19: =VLOOKUP($D19,proc!$A:$D,4,FALSE) -> 1 | H19: =SUBSTITUTE(D19,".","") -> 3989 | I19: Endovascular Proc. for Neurologic Diseases | J19: =VLOOKUP(H19,'upload c51prpdc'!A:C,3,FALSE) -> P11AA | K19: =VLOOKUP($D19,'prosedur-2025'!$A:$H,3,FALSE) -> 6 | L19: =VLOOKUP($D19,'prosedur-2025'!$A:$H,4,FALSE) -> 30687575 | M19: =VLOOKUP($D19,'prosedur-2025'!$A:$H,5,FALSE) -> 8104487 | N19: =VLOOKUP($D19,'prosedur-2025'!$A:$H,6,FALSE) -> 27889516 | O19: =VLOOKUP($D19,'prosedur-2025'!$A:$H,7,FALSE) -> 34947067 | P19: =VLOOKUP($D19,'prosedur-2025'!$A:$H,8,FALSE) -> 76434965 | Q19: =K19*L19 -> 184125448 | T19: =TEXT(VALUE(D19),"00.00") -> 39.89 | W19: =H19 -> 3989 | X19: 11 | Y19: =J19 -> P11AA | Z19: 1 | AA19: =I19 -> Endovascular Proc. for Neurologic Diseases
A20: PDC | B20: P11AD | C20: Complex Spinal Procedures | D20: 03.01 | E20: Removal of foreign body from spinal canal | F20: =VLOOKUP($D20,proc!$A:$D,3,FALSE) -> 5 | G20: =VLOOKUP($D20,proc!$A:$D,4,FALSE) -> 0 | H20: =SUBSTITUTE(D20,".","") -> 0301 | I20: Moderate Spinal Proc. | J20: =VLOOKUP(H20,'upload c51prpdc'!A:C,3,FALSE) -> P11AJ | K20: =VLOOKUP($D20,'prosedur-2025'!$A:$H,3,FALSE) -> 12 | L20: =VLOOKUP($D20,'prosedur-2025'!$A:$H,4,FALSE) -> 68030011 | M20: =VLOOKUP($D20,'prosedur-2025'!$A:$H,5,FALSE) -> 37169810 | N20: =VLOOKUP($D20,'prosedur-2025'!$A:$H,6,FALSE) -> 47495894 | O20: =VLOOKUP($D20,'prosedur-2025'!$A:$H,7,FALSE) -> 86573446 | P20: =VLOOKUP($D20,'prosedur-2025'!$A:$H,8,FALSE) -> 91434374 | Q20: =K20*L20 -> 816360130 | T20: =TEXT(VALUE(D20),"00.00") -> 03.01 | W20: =H20 -> 0301 | X20: 11 | Y20: =J20 -> P11AJ | Z20: 1 | AA20: =I20 -> Moderate Spinal Proc.
A21: PDC | B21: P11AD | C21: Complex Spinal Procedures | D21: 03.02 | E21: Reopening of laminectomy site | F21: =VLOOKUP($D21,proc!$A:$D,3,FALSE) -> 5 | G21: =VLOOKUP($D21,proc!$A:$D,4,FALSE) -> 0 | H21: =SUBSTITUTE(D21,".","") -> 0302 | I21: Moderate Spinal Proc. | J21: =VLOOKUP(H21,'upload c51prpdc'!A:C,3,FALSE) -> P11AJ | K21: =VLOOKUP($D21,'prosedur-2025'!$A:$H,3,FALSE) -> 226 | L21: =VLOOKUP($D21,'prosedur-2025'!$A:$H,4,FALSE) -> 58748393 | M21: =VLOOKUP($D21,'prosedur-2025'!$A:$H,5,FALSE) -> 27898024 | N21: =VLOOKUP($D21,'prosedur-2025'!$A:$H,6,FALSE) -> 46204400 | O21: =VLOOKUP($D21,'prosedur-2025'!$A:$H,7,FALSE) -> 74596310 | P21: =VLOOKUP($D21,'prosedur-2025'!$A:$H,8,FALSE) -> 122337966 | Q21: =K21*L21 -> 13277136710 | T21: =TEXT(VALUE(D21),"00.00") -> 03.02 | W21: =H21 -> 0302 | X21: 11 | Y21: =J21 -> P11AJ | Z21: 1 | AA21: =I21 -> Moderate Spinal Proc.
A22: PDC | B22: P11AD | C22: Complex Spinal Procedures | D22: 03.09 | E22: Other exploration and decompression of spinal canal | F22: =VLOOKUP($D22,proc!$A:$D,3,FALSE) -> 5 | G22: =VLOOKUP($D22,proc!$A:$D,4,FALSE) -> 0 | H22: =SUBSTITUTE(D22,".","") -> 0309 | I22: Moderate Spinal Proc. | J22: =VLOOKUP(H22,'upload c51prpdc'!A:C,3,FALSE) -> P11AJ | K22: =VLOOKUP($D22,'prosedur-2025'!$A:$H,3,FALSE) -> 9293 | L22: =VLOOKUP($D22,'prosedur-2025'!$A:$H,4,FALSE) -> 59760268 | M22: =VLOOKUP($D22,'prosedur-2025'!$A:$H,5,FALSE) -> 35810933 | N22: =VLOOKUP($D22,'prosedur-2025'!$A:$H,6,FALSE) -> 51791394 | O22: =VLOOKUP($D22,'prosedur-2025'!$A:$H,7,FALSE) -> 72016486 | P22: =VLOOKUP($D22,'prosedur-2025'!$A:$H,8,FALSE) -> 102710378 | Q22: =K22*L22 -> 555352166212 | T22: =TEXT(VALUE(D22),"00.00") -> 03.09 | W22: =H22 -> 0309 | X22: 11 | Y22: =J22 -> P11AJ | Z22: 1 | AA22: =I22 -> Moderate Spinal Proc.
A23: PDC | B23: P11AD | C23: Complex Spinal Procedures | D23: 03.21 | E23: Percutaneous chordotomy | F23: =VLOOKUP($D23,proc!$A:$D,3,FALSE) -> 4 | G23: =VLOOKUP($D23,proc!$A:$D,4,FALSE) -> 0 | H23: =SUBSTITUTE(D23,".","") -> 0321 | I23: Moderate Spinal Proc. | J23: =VLOOKUP(H23,'upload c51prpdc'!A:C,3,FALSE) -> P11AJ | K23: =VLOOKUP($D23,'prosedur-2025'!$A:$H,3,FALSE) -> 2 | L23: =VLOOKUP($D23,'prosedur-2025'!$A:$H,4,FALSE) -> 62128059 | M23: =VLOOKUP($D23,'prosedur-2025'!$A:$H,5,FALSE) -> 10275818 | N23: =VLOOKUP($D23,'prosedur-2025'!$A:$H,6,FALSE) -> 10275818 | O23: =VLOOKUP($D23,'prosedur-2025'!$A:$H,7,FALSE) -> 113980300 | P23: =VLOOKUP($D23,'prosedur-2025'!$A:$H,8,FALSE) -> 113980300 | Q23: =K23*L23 -> 124256118 | T23: =TEXT(VALUE(D23),"00.00") -> 03.21 | W23: =H23 -> 0321 | X23: 11 | Y23: =J23 -> P11AJ | Z23: 1 | AA23: =I23 -> Moderate Spinal Proc.
A24: PDC | B24: P11AD | C24: Complex Spinal Procedures | D24: 03.29 | E24: Other chordotomy | F24: =VLOOKUP($D24,proc!$A:$D,3,FALSE) -> 4 | G24: =VLOOKUP($D24,proc!$A:$D,4,FALSE) -> 0 | H24: =SUBSTITUTE(D24,".","") -> 0329 | I24: Moderate Spinal Proc. | J24: =VLOOKUP(H24,'upload c51prpdc'!A:C,3,FALSE) -> P11AJ | K24: =VLOOKUP($D24,'prosedur-2025'!$A:$H,3,FALSE) -> 14 | L24: =VLOOKUP($D24,'prosedur-2025'!$A:$H,4,FALSE) -> 56094480 | M24: =VLOOKUP($D24,'prosedur-2025'!$A:$H,5,FALSE) -> 17227265 | N24: =VLOOKUP($D24,'prosedur-2025'!$A:$H,6,FALSE) -> 58180620 | O24: =VLOOKUP($D24,'prosedur-2025'!$A:$H,7,FALSE) -> 88350158 | P24: =VLOOKUP($D24,'prosedur-2025'!$A:$H,8,FALSE) -> 97786657 | Q24: =K24*L24 -> 785322726 | T24: =TEXT(VALUE(D24),"00.00") -> 03.29 | W24: =H24 -> 0329 | X24: 11 | Y24: =J24 -> P11AJ | Z24: 1 | AA24: =I24 -> Moderate Spinal Proc.
A25: PDC | B25: P11AD | C25: Complex Spinal Procedures | D25: 03.4 | E25: Excision or destruction of lesion of spinal cord or spinal meninges | F25: =VLOOKUP($D25,proc!$A:$D,3,FALSE) -> 6 | G25: =VLOOKUP($D25,proc!$A:$D,4,FALSE) -> 0 | H25: =SUBSTITUTE(D25,".","") -> 034 | I25: Complex Spinal Proc. | J25: =VLOOKUP(H25,'upload c51prpdc'!A:C,3,FALSE) -> P11AB | K25: =VLOOKUP($D25,'prosedur-2025'!$A:$H,3,FALSE) -> 969 | L25: =VLOOKUP($D25,'prosedur-2025'!$A:$H,4,FALSE) -> 80259541 | M25: =VLOOKUP($D25,'prosedur-2025'!$A:$H,5,FALSE) -> 37570498 | N25: =VLOOKUP($D25,'prosedur-2025'!$A:$H,6,FALSE) -> 67611921 | O25: =VLOOKUP($D25,'prosedur-2025'!$A:$H,7,FALSE) -> 98550892 | P25: =VLOOKUP($D25,'prosedur-2025'!$A:$H,8,FALSE) -> 159266167 | Q25: =K25*L25 -> 77771495627 | T25: =TEXT(VALUE(D25),"00.00") -> 03.40 | W25: =H25 -> 034 | X25: 11 | Y25: =J25 -> P11AB | Z25: 1 | AA25: =I25 -> Complex Spinal Proc.
A26: PDC | B26: P11AD | C26: Complex Spinal Procedures | D26: 03.51 | E26: Repair of spinal meningocele | F26: =VLOOKUP($D26,proc!$A:$D,3,FALSE) -> 5 | G26: =VLOOKUP($D26,proc!$A:$D,4,FALSE) -> 0 | H26: =SUBSTITUTE(D26,".","") -> 0351 | I26: Moderate Spinal Proc. | J26: =VLOOKUP(H26,'upload c51prpdc'!A:C,3,FALSE) -> P11AJ | K26: =VLOOKUP($D26,'prosedur-2025'!$A:$H,3,FALSE) -> 82 | L26: =VLOOKUP($D26,'prosedur-2025'!$A:$H,4,FALSE) -> 68166626 | M26: =VLOOKUP($D26,'prosedur-2025'!$A:$H,5,FALSE) -> 32504489 | N26: =VLOOKUP($D26,'prosedur-2025'!$A:$H,6,FALSE) -> 57467984 | O26: =VLOOKUP($D26,'prosedur-2025'!$A:$H,7,FALSE) -> 89998640 | P26: =VLOOKUP($D26,'prosedur-2025'!$A:$H,8,FALSE) -> 119390219 | Q26: =K26*L26 -> 5589663365 | T26: =TEXT(VALUE(D26),"00.00") -> 03.51 | W26: =H26 -> 0351 | X26: 11 | Y26: =J26 -> P11AJ | Z26: 1 | AA26: =I26 -> Moderate Spinal Proc.
A27: PDC | B27: P11AD | C27: Complex Spinal Procedures | D27: 03.52 | E27: Repair of spinal myelomeningocele | F27: =VLOOKUP($D27,proc!$A:$D,3,FALSE) -> 5 | G27: =VLOOKUP($D27,proc!$A:$D,4,FALSE) -> 0 | H27: =SUBSTITUTE(D27,".","") -> 0352 | I27: Complex Spinal Proc. | J27: =VLOOKUP(H27,'upload c51prpdc'!A:C,3,FALSE) -> P11AB | K27: =VLOOKUP($D27,'prosedur-2025'!$A:$H,3,FALSE) -> 101 | L27: =VLOOKUP($D27,'prosedur-2025'!$A:$H,4,FALSE) -> 68653256 | M27: =VLOOKUP($D27,'prosedur-2025'!$A:$H,5,FALSE) -> 32601013 | N27: =VLOOKUP($D27,'prosedur-2025'!$A:$H,6,FALSE) -> 50170854 | O27: =VLOOKUP($D27,'prosedur-2025'!$A:$H,7,FALSE) -> 82461979 | P27: =VLOOKUP($D27,'prosedur-2025'!$A:$H,8,FALSE) -> 143505352 | Q27: =K27*L27 -> 6933978859 | T27: =TEXT(VALUE(D27),"00.00") -> 03.52 | W27: =H27 -> 0352 | X27: 11 | Y27: =J27 -> P11AB | Z27: 1 | AA27: =I27 -> Complex Spinal Proc.
A28: PDC | B28: P11AD | C28: Complex Spinal Procedures | D28: 03.53 | E28: Repair of vertebral fracture | F28: =VLOOKUP($D28,proc!$A:$D,3,FALSE) -> 5 | G28: =VLOOKUP($D28,proc!$A:$D,4,FALSE) -> 0 | H28: =SUBSTITUTE(D28,".","") -> 0353 | I28: Moderate Spinal Proc. | J28: =VLOOKUP(H28,'upload c51prpdc'!A:C,3,FALSE) -> P11AJ | K28: =VLOOKUP($D28,'prosedur-2025'!$A:$H,3,FALSE) -> 109 | L28: =VLOOKUP($D28,'prosedur-2025'!$A:$H,4,FALSE) -> 74716957 | M28: =VLOOKUP($D28,'prosedur-2025'!$A:$H,5,FALSE) -> 52512103 | N28: =VLOOKUP($D28,'prosedur-2025'!$A:$H,6,FALSE) -> 71569867 | O28: =VLOOKUP($D28,'prosedur-2025'!$A:$H,7,FALSE) -> 93427650 | P28: =VLOOKUP($D28,'prosedur-2025'!$A:$H,8,FALSE) -> 133643976 | Q28: =K28*L28 -> 8144148286 | T28: =TEXT(VALUE(D28),"00.00") -> 03.53 | W28: =H28 -> 0353 | X28: 11 | Y28: =J28 -> P11AJ | Z28: 1 | AA28: =I28 -> Moderate Spinal Proc.
... A31: PDC | B31: P11AD | C31: Complex Spinal Procedures | D31: 03.71 | E31: Spinal subarachnoid-peritoneal shunt | F31: =VLOOKUP($D31,proc!$A:$D,3,FALSE) -> 4 | G31: =VLOOKUP($D31,proc!$A:$D,4,FALSE) -> 0 | H31: =SUBSTITUTE(D31,".","") -> 0371 | I31: Moderate Spinal Proc. | J31: =VLOOKUP(H31,'upload c51prpdc'!A:C,3,FALSE) -> P11AJ | K31: =VLOOKUP($D31,'prosedur-2025'!$A:$H,3,FALSE) -> 11 | L31: =VLOOKUP($D31,'prosedur-2025'!$A:$H,4,FALSE) -> 61719059 | M31: =VLOOKUP($D31,'prosedur-2025'!$A:$H,5,FALSE) -> 30268917 | N31: =VLOOKUP($D31,'prosedur-2025'!$A:$H,6,FALSE) -> 49767972 | O31: =VLOOKUP($D31,'prosedur-2025'!$A:$H,7,FALSE) -> 82947747 | P31: =VLOOKUP($D31,'prosedur-2025'!$A:$H,8,FALSE) -> 92224400 | Q31: =K31*L31 -> 678909647 | T31: =TEXT(VALUE(D31),"00.00") -> 03.71 | W31: =H31 -> 0371 | X31: 11 | Y31: =J31 -> P11AJ | Z31: 1 | AA31: =I31 -> Moderate Spinal Proc.
A32: PDC | B32: P11AD | C32: Complex Spinal Procedures | D32: 03.72 | E32: Spinal subarachnoid-ureteral shunt | F32: =VLOOKUP($D32,proc!$A:$D,3,FALSE) -> 4 | G32: =VLOOKUP($D32,proc!$A:$D,4,FALSE) -> 0 | H32: =SUBSTITUTE(D32,".","") -> 0372 | I32: Moderate Spinal Proc. | J32: =VLOOKUP(H32,'upload c51prpdc'!A:C,3,FALSE) -> P11AJ | T32: =TEXT(VALUE(D32),"00.00") -> 03.72 | W32: =H32 -> 0372 | X32: 11 | Y32: =J32 -> P11AJ | Z32: 1 | AA32: =I32 -> Moderate Spinal Proc.
A33: PDC | B33: P11AD | C33: Complex Spinal Procedures | D33: 03.79 | E33: Other shunt of spinal theca | F33: =VLOOKUP($D33,proc!$A:$D,3,FALSE) -> 4 | G33: =VLOOKUP($D33,proc!$A:$D,4,FALSE) -> 0 | H33: =SUBSTITUTE(D33,".","") -> 0379 | I33: Moderate Spinal Proc. | J33: =VLOOKUP(H33,'upload c51prpdc'!A:C,3,FALSE) -> P11AJ | K33: =VLOOKUP($D33,'prosedur-2025'!$A:$H,3,FALSE) -> 28 | L33: =VLOOKUP($D33,'prosedur-2025'!$A:$H,4,FALSE) -> 86356199 | M33: =VLOOKUP($D33,'prosedur-2025'!$A:$H,5,FALSE) -> 50049275 | N33: =VLOOKUP($D33,'prosedur-2025'!$A:$H,6,FALSE) -> 87553186 | O33: =VLOOKUP($D33,'prosedur-2025'!$A:$H,7,FALSE) -> 118772842 | P33: =VLOOKUP($D33,'prosedur-2025'!$A:$H,8,FALSE) -> 144357842 | Q33: =K33*L33 -> 2417973559 | T33: =TEXT(VALUE(D33),"00.00") -> 03.79 | W33: =H33 -> 0379 | X33: 11 | Y33: =J33 -> P11AJ | Z33: 1 | AA33: =I33 -> Moderate Spinal Proc.
A34: PDC | B34: P11AP | C34: Neuromodulation | D34: 03.93 | E34: Implantation or replacement of spinal neurostimulator lead(s) | F34: =VLOOKUP($D34,proc!$A:$D,3,FALSE) -> 2 | G34: =VLOOKUP($D34,proc!$A:$D,4,FALSE) -> 0 | H34: =SUBSTITUTE(D34,".","") -> 0393 | I34: Neuromodulation Proc. | J34: =VLOOKUP(H34,'upload c51prpdc'!A:C,3,FALSE) -> P11AP | K34: =VLOOKUP($D34,'prosedur-2025'!$A:$H,3,FALSE) -> 4 | L34: =VLOOKUP($D34,'prosedur-2025'!$A:$H,4,FALSE) -> 62796968 | M34: =VLOOKUP($D34,'prosedur-2025'!$A:$H,5,FALSE) -> 21537047 | N34: =VLOOKUP($D34,'prosedur-2025'!$A:$H,6,FALSE) -> 58677511 | O34: =VLOOKUP($D34,'prosedur-2025'!$A:$H,7,FALSE) -> 72113063 | P34: =VLOOKUP($D34,'prosedur-2025'!$A:$H,8,FALSE) -> 98860250 | Q34: =K34*L34 -> 251187871 | T34: =TEXT(VALUE(D34),"00.00") -> 03.93 | W34: =H34 -> 0393 | X34: 11 | Y34: =J34 -> P11AP | Z34: 1 | AA34: =I34 -> Neuromodulation Proc.
A35: PDC | B35: P11AP | C35: Neuromodulation | D35: 03.931 | E35: Implantation of spinal cord stimulator (SCS) lead (IM) | F35: 2 | G35: 1 | H35: =SUBSTITUTE(D35,".","") -> 03931 | I35: Neuromodulation Proc. | J35: P11AP | W35: =H35 -> 03931 | X35: 11 | Y35: =J35 -> P11AP | Z35: 1 | AA35: =I35 -> Neuromodulation Proc.
A36: PDC | B36: P11AD | C36: Complex Spinal Procedures | D36: 03.97 | E36: Revision of spinal thecal shunt | F36: =VLOOKUP($D36,proc!$A:$D,3,FALSE) -> 4 | G36: =VLOOKUP($D36,proc!$A:$D,4,FALSE) -> 0 | H36: =SUBSTITUTE(D36,".","") -> 0397 | I36: Moderate Spinal Proc. | J36: =VLOOKUP(H36,'upload c51prpdc'!A:C,3,FALSE) -> P11AJ | K36: =VLOOKUP($D36,'prosedur-2025'!$A:$H,3,FALSE) -> 4 | L36: =VLOOKUP($D36,'prosedur-2025'!$A:$H,4,FALSE) -> 37675131 | M36: =VLOOKUP($D36,'prosedur-2025'!$A:$H,5,FALSE) -> 6034823 | N36: =VLOOKUP($D36,'prosedur-2025'!$A:$H,6,FALSE) -> 6176764 | O36: =VLOOKUP($D36,'prosedur-2025'!$A:$H,7,FALSE) -> 23281087 | P36: =VLOOKUP($D36,'prosedur-2025'!$A:$H,8,FALSE) -> 115207850 | Q36: =K36*L36 -> 150700524 | T36: =TEXT(VALUE(D36),"00.00") -> 03.97 | W36: =H36 -> 0397 | X36: 11 | Y36: =J36 -> P11AJ | Z36: 1 | AA36: =I36 -> Moderate Spinal Proc.
A37: PDC | B37: P11AD | C37: Complex Spinal Procedures | D37: 03.99 | E37: Other operations on spinal cord and spinal canal structures | F37: =VLOOKUP($D37,proc!$A:$D,3,FALSE) -> 3 | G37: =VLOOKUP($D37,proc!$A:$D,4,FALSE) -> 0 | H37: =SUBSTITUTE(D37,".","") -> 0399 | I37: Complex Spinal Proc. | J37: =VLOOKUP(H37,'upload c51prpdc'!A:C,3,FALSE) -> P11AB | K37: =VLOOKUP($D37,'prosedur-2025'!$A:$H,3,FALSE) -> 43 | L37: =VLOOKUP($D37,'prosedur-2025'!$A:$H,4,FALSE) -> 67769438 | M37: =VLOOKUP($D37,'prosedur-2025'!$A:$H,5,FALSE) -> 28286512 | N37: =VLOOKUP($D37,'prosedur-2025'!$A:$H,6,FALSE) -> 54070788 | O37: =VLOOKUP($D37,'prosedur-2025'!$A:$H,7,FALSE) -> 90470150 | P37: =VLOOKUP($D37,'prosedur-2025'!$A:$H,8,FALSE) -> 121648571 | Q37: =K37*L37 -> 2914085816 | T37: =TEXT(VALUE(D37),"00.00") -> 03.99 | W37: =H37 -> 0399 | X37: 11 | Y37: =J37 -> P11AB | Z37: 1 | AA37: =I37 -> Complex Spinal Proc.
A38: PDC | B38: P11AD | C38: Complex Spinal Procedures | D38: 77.81 | E38: Other partial ostectomy, scapula, clavicle, and thorax [ribs and sternum] | F38: =VLOOKUP($D38,proc!$A:$D,3,FALSE) -> 3 | G38: =VLOOKUP($D38,proc!$A:$D,4,FALSE) -> 0 | H38: =SUBSTITUTE(D38,".","") -> 7781 | I38: Moderate Spinal Proc. | J38: =VLOOKUP(H38,'upload c51prpdc'!A:C,3,FALSE) -> P11AJ | K38: =VLOOKUP($D38,'prosedur-2025'!$A:$H,3,FALSE) -> 121 | L38: =VLOOKUP($D38,'prosedur-2025'!$A:$H,4,FALSE) -> 38161526 | M38: =VLOOKUP($D38,'prosedur-2025'!$A:$H,5,FALSE) -> 8518840 | N38: =VLOOKUP($D38,'prosedur-2025'!$A:$H,6,FALSE) -> 15333076 | O38: =VLOOKUP($D38,'prosedur-2025'!$A:$H,7,FALSE) -> 32317948 | P38: =VLOOKUP($D38,'prosedur-2025'!$A:$H,8,FALSE) -> 102633976 | Q38: =K38*L38 -> 4617544641 | T38: =TEXT(VALUE(D38),"00.00") -> 77.81 | W38: =H38 -> 7781 | X38: 11 | Y38: =J38 -> P11AJ | Z38: 1 | AA38: =I38 -> Moderate Spinal Proc.
A39: PDC | B39: P11AD | C39: Complex Spinal Procedures | D39: 77.91 | E39: Total ostectomy, scapula, clavicle, and thorax [ribs and sternum] | F39: =VLOOKUP($D39,proc!$A:$D,3,FALSE) -> 5 | G39: =VLOOKUP($D39,proc!$A:$D,4,FALSE) -> 0 | H39: =SUBSTITUTE(D39,".","") -> 7791 | I39: Moderate Spinal Proc. | J39: =VLOOKUP(H39,'upload c51prpdc'!A:C,3,FALSE) -> P11AJ | K39: =VLOOKUP($D39,'prosedur-2025'!$A:$H,3,FALSE) -> 61 | L39: =VLOOKUP($D39,'prosedur-2025'!$A:$H,4,FALSE) -> 48177048 | M39: =VLOOKUP($D39,'prosedur-2025'!$A:$H,5,FALSE) -> 15263017 | N39: =VLOOKUP($D39,'prosedur-2025'!$A:$H,6,FALSE) -> 30053842 | O39: =VLOOKUP($D39,'prosedur-2025'!$A:$H,7,FALSE) -> 63933300 | P39: =VLOOKUP($D39,'prosedur-2025'!$A:$H,8,FALSE) -> 112482408 | Q39: =K39*L39 -> 2938799910 | T39: =TEXT(VALUE(D39),"00.00") -> 77.91 | W39: =H39 -> 7791 | X39: 11 | Y39: =J39 -> P11AJ | Z39: 1 | AA39: =I39 -> Moderate Spinal Proc.
A40: PDC | B40: P11AD | C40: Complex Spinal Procedures | D40: 80.55 | E40: Microdissectomy (endoscopic/microscopic) (IM) | F40: =VLOOKUP($D40,proc!$A:$D,3,FALSE) -> 4 | G40: =VLOOKUP($D40,proc!$A:$D,4,FALSE) -> 1 | H40: =SUBSTITUTE(D40,".","") -> 8055 | I40: Moderate Spinal Proc. | J40: =VLOOKUP(H40,'upload c51prpdc'!A:C,3,FALSE) -> P11AJ | T40: =TEXT(VALUE(D40),"00.00") -> 80.55 | W40: =H40 -> 8055 | X40: 11 | Y40: =J40 -> P11AJ | Z40: 1 | AA40: =I40 -> Moderate Spinal Proc.
A41: PDC | B41: P11AD | C41: Complex Spinal Procedures | D41: 81.00 | E41: Spinal fusion, not otherwise specified | F41: =VLOOKUP($D41,proc!$A:$D,3,FALSE) -> 5 | G41: =VLOOKUP($D41,proc!$A:$D,4,FALSE) -> 0 | H41: =SUBSTITUTE(D41,".","") -> 8100 | I41: Complex Spinal Proc. | J41: =VLOOKUP(H41,'upload c51prpdc'!A:C,3,FALSE) -> P11AB | K41: =VLOOKUP($D41,'prosedur-2025'!$A:$H,3,FALSE) -> 1528 | L41: =VLOOKUP($D41,'prosedur-2025'!$A:$H,4,FALSE) -> 65674909 | M41: =VLOOKUP($D41,'prosedur-2025'!$A:$H,5,FALSE) -> 49936194 | N41: =VLOOKUP($D41,'prosedur-2025'!$A:$H,6,FALSE) -> 61234300 | O41: =VLOOKUP($D41,'prosedur-2025'!$A:$H,7,FALSE) -> 74515004 | P41: =VLOOKUP($D41,'prosedur-2025'!$A:$H,8,FALSE) -> 97919911 | Q41: =K41*L41 -> 100351260453 | T41: =TEXT(VALUE(D41),"00.00") -> 81.00 | W41: =H41 -> 8100 | X41: 11 | Y41: =J41 -> P11AB | Z41: 1 | AA41: =I41 -> Complex Spinal Proc.
A42: PDC | B42: P11AD | C42: Complex Spinal Procedures | D42: 81.01 | E42: Atlas-axis spinal fusion | F42: =VLOOKUP($D42,proc!$A:$D,3,FALSE) -> 6 | G42: =VLOOKUP($D42,proc!$A:$D,4,FALSE) -> 0 | H42: =SUBSTITUTE(D42,".","") -> 8101 | I42: Complex Spinal Proc. | J42: =VLOOKUP(H42,'upload c51prpdc'!A:C,3,FALSE) -> P11AB | K42: =VLOOKUP($D42,'prosedur-2025'!$A:$H,3,FALSE) -> 27 | L42: =VLOOKUP($D42,'prosedur-2025'!$A:$H,4,FALSE) -> 1.2467283e+08 | M42: =VLOOKUP($D42,'prosedur-2025'!$A:$H,5,FALSE) -> 52639588 | N42: =VLOOKUP($D42,'prosedur-2025'!$A:$H,6,FALSE) -> 87551311 | O42: =VLOOKUP($D42,'prosedur-2025'!$A:$H,7,FALSE) -> 115964551 | P42: =VLOOKUP($D42,'prosedur-2025'!$A:$H,8,FALSE) -> 208639207 | Q42: =K42*L42 -> 3366166364 | T42: =TEXT(VALUE(D42),"00.00") -> 81.01 | W42: =H42 -> 8101 | X42: 11 | Y42: =J42 -> P11AB | Z42: 1 | AA42: =I42 -> Complex Spinal Proc.
A43: PDC | B43: P11AD | C43: Complex Spinal Procedures | D43: 81.02 | E43: Other cervical fusion of the anterior column, anterior technique | F43: =VLOOKUP($D43,proc!$A:$D,3,FALSE) -> 5 | G43: =VLOOKUP($D43,proc!$A:$D,4,FALSE) -> 0 | H43: =SUBSTITUTE(D43,".","") -> 8102 | I43: Complex Spinal Proc. | J43: =VLOOKUP(H43,'upload c51prpdc'!A:C,3,FALSE) -> P11AB | K43: =VLOOKUP($D43,'prosedur-2025'!$A:$H,3,FALSE) -> 1124 | L43: =VLOOKUP($D43,'prosedur-2025'!$A:$H,4,FALSE) -> 81393964 | M43: =VLOOKUP($D43,'prosedur-2025'!$A:$H,5,FALSE) -> 49774876 | N43: =VLOOKUP($D43,'prosedur-2025'!$A:$H,6,FALSE) -> 68684800 | O43: =VLOOKUP($D43,'prosedur-2025'!$A:$H,7,FALSE) -> 97992005 | P43: =VLOOKUP($D43,'prosedur-2025'!$A:$H,8,FALSE) -> 141735725 | Q43: =K43*L43 -> 91486815900 | T43: =TEXT(VALUE(D43),"00.00") -> 81.02 | W43: =H43 -> 8102 | X43: 11 | Y43: =J43 -> P11AB | Z43: 1 | AA43: =I43 -> Complex Spinal Proc.
A44: PDC | B44: P11AD | C44: Complex Spinal Procedures | D44: 81.03 | E44: Other cervical fusion of the posterior column, posterior technique | F44: =VLOOKUP($D44,proc!$A:$D,3,FALSE) -> 5 | G44: =VLOOKUP($D44,proc!$A:$D,4,FALSE) -> 0 | H44: =SUBSTITUTE(D44,".","") -> 8103 | I44: Complex Spinal Proc. | J44: =VLOOKUP(H44,'upload c51prpdc'!A:C,3,FALSE) -> P11AB | K44: =VLOOKUP($D44,'prosedur-2025'!$A:$H,3,FALSE) -> 875 | L44: =VLOOKUP($D44,'prosedur-2025'!$A:$H,4,FALSE) -> 94529035 | M44: =VLOOKUP($D44,'prosedur-2025'!$A:$H,5,FALSE) -> 56619127 | N44: =VLOOKUP($D44,'prosedur-2025'!$A:$H,6,FALSE) -> 78073992 | O44: =VLOOKUP($D44,'prosedur-2025'!$A:$H,7,FALSE) -> 110993428 | P44: =VLOOKUP($D44,'prosedur-2025'!$A:$H,8,FALSE) -> 160154433 | Q44: =K44*L44 -> 82712905872 | T44: =TEXT(VALUE(D44),"00.00") -> 81.03 | W44: =H44 -> 8103 | X44: 11 | Y44: =J44 -> P11AB | Z44: 1 | AA44: =I44 -> Complex Spinal Proc.
A45: PDC | B45: P11AD | C45: Complex Spinal Procedures | D45: 81.04 | E45: Dorsal and dorsolumbar fusion of the anterior column, anterior technique | F45: =VLOOKUP($D45,proc!$A:$D,3,FALSE) -> 5 | G45: =VLOOKUP($D45,proc!$A:$D,4,FALSE) -> 0 | H45: =SUBSTITUTE(D45,".","") -> 8104 | I45: Complex Spinal Proc. | J45: =VLOOKUP(H45,'upload c51prpdc'!A:C,3,FALSE) -> P11AB | K45: =VLOOKUP($D45,'prosedur-2025'!$A:$H,3,FALSE) -> 156 | L45: =VLOOKUP($D45,'prosedur-2025'!$A:$H,4,FALSE) -> 62574827 | M45: =VLOOKUP($D45,'prosedur-2025'!$A:$H,5,FALSE) -> 38373771 | N45: =VLOOKUP($D45,'prosedur-2025'!$A:$H,6,FALSE) -> 47165305 | O45: =VLOOKUP($D45,'prosedur-2025'!$A:$H,7,FALSE) -> 72615200 | P45: =VLOOKUP($D45,'prosedur-2025'!$A:$H,8,FALSE) -> 122341412 | Q45: =K45*L45 -> 9761672970 | T45: =TEXT(VALUE(D45),"00.00") -> 81.04 | W45: =H45 -> 8104 | X45: 11 | Y45: =J45 -> P11AB | Z45: 1 | AA45: =I45 -> Complex Spinal Proc.
A46: PDC | B46: P11AD | C46: Complex Spinal Procedures | D46: 81.05 | E46: Dorsal and dorsolumbar fusion of the posterior column, posterior technique | F46: =VLOOKUP($D46,proc!$A:$D,3,FALSE) -> 5 | G46: =VLOOKUP($D46,proc!$A:$D,4,FALSE) -> 0 | H46: =SUBSTITUTE(D46,".","") -> 8105 | I46: Complex Spinal Proc. | J46: =VLOOKUP(H46,'upload c51prpdc'!A:C,3,FALSE) -> P11AB | K46: =VLOOKUP($D46,'prosedur-2025'!$A:$H,3,FALSE) -> 3213 | L46: =VLOOKUP($D46,'prosedur-2025'!$A:$H,4,FALSE) -> 84793189 | M46: =VLOOKUP($D46,'prosedur-2025'!$A:$H,5,FALSE) -> 53141009 | N46: =VLOOKUP($D46,'prosedur-2025'!$A:$H,6,FALSE) -> 77159544 | O46: =VLOOKUP($D46,'prosedur-2025'!$A:$H,7,FALSE) -> 109024391 | P46: =VLOOKUP($D46,'prosedur-2025'!$A:$H,8,FALSE) -> 133632798 | Q46: =K46*L46 -> 272440516704 | T46: =TEXT(VALUE(D46),"00.00") -> 81.05 | W46: =H46 -> 8105 | X46: 11 | Y46: =J46 -> P11AB | Z46: 1 | AA46: =I46 -> Complex Spinal Proc.
A47: PDC | B47: P11AD | C47: Complex Spinal Procedures | D47: 81.06 | E47: Lumbar and lumbosacral fusion of the anterior column, anterior technique | F47: =VLOOKUP($D47,proc!$A:$D,3,FALSE) -> 5 | G47: =VLOOKUP($D47,proc!$A:$D,4,FALSE) -> 0 | H47: =SUBSTITUTE(D47,".","") -> 8106 | I47: Complex Spinal Proc. | J47: =VLOOKUP(H47,'upload c51prpdc'!A:C,3,FALSE) -> P11AB | K47: =VLOOKUP($D47,'prosedur-2025'!$A:$H,3,FALSE) -> 517 | L47: =VLOOKUP($D47,'prosedur-2025'!$A:$H,4,FALSE) -> 68693105 | M47: =VLOOKUP($D47,'prosedur-2025'!$A:$H,5,FALSE) -> 46359588 | N47: =VLOOKUP($D47,'prosedur-2025'!$A:$H,6,FALSE) -> 61443163 | O47: =VLOOKUP($D47,'prosedur-2025'!$A:$H,7,FALSE) -> 85773937 | P47: =VLOOKUP($D47,'prosedur-2025'!$A:$H,8,FALSE) -> 107636330 | Q47: =K47*L47 -> 35514335204 | T47: =TEXT(VALUE(D47),"00.00") -> 81.06 | W47: =H47 -> 8106 | X47: 11 | Y47: =J47 -> P11AB | Z47: 1 | AA47: =I47 -> Complex Spinal Proc.
A48: PDC | B48: P11AD | C48: Complex Spinal Procedures | D48: 81.07 | E48: Lumbar and lumbosacral fusion of the posterior column, posterior technique | F48: =VLOOKUP($D48,proc!$A:$D,3,FALSE) -> 5 | G48: =VLOOKUP($D48,proc!$A:$D,4,FALSE) -> 0 | H48: =SUBSTITUTE(D48,".","") -> 8107 | I48: Complex Spinal Proc. | J48: =VLOOKUP(H48,'upload c51prpdc'!A:C,3,FALSE) -> P11AB | K48: =VLOOKUP($D48,'prosedur-2025'!$A:$H,3,FALSE) -> 431 | L48: =VLOOKUP($D48,'prosedur-2025'!$A:$H,4,FALSE) -> 57943673 | M48: =VLOOKUP($D48,'prosedur-2025'!$A:$H,5,FALSE) -> 35822500 | N48: =VLOOKUP($D48,'prosedur-2025'!$A:$H,6,FALSE) -> 50244990 | O48: =VLOOKUP($D48,'prosedur-2025'!$A:$H,7,FALSE) -> 70447761 | P48: =VLOOKUP($D48,'prosedur-2025'!$A:$H,8,FALSE) -> 105761272 | Q48: =K48*L48 -> 24973723210 | T48: =TEXT(VALUE(D48),"00.00") -> 81.07 | W48: =H48 -> 8107 | X48: 11 | Y48: =J48 -> P11AB | Z48: 1 | AA48: =I48 -> Complex Spinal Proc.
A49: PDC | B49: P11AD | C49: Complex Spinal Procedures | D49: 81.08 | E49: Lumbar and lumbosacral fusion of the anterior column, posterior technique | F49: =VLOOKUP($D49,proc!$A:$D,3,FALSE) -> 5 | G49: =VLOOKUP($D49,proc!$A:$D,4,FALSE) -> 0 | H49: =SUBSTITUTE(D49,".","") -> 8108 | I49: Complex Spinal Proc. | J49: =VLOOKUP(H49,'upload c51prpdc'!A:C,3,FALSE) -> P11AB | K49: =VLOOKUP($D49,'prosedur-2025'!$A:$H,3,FALSE) -> 8521 | L49: =VLOOKUP($D49,'prosedur-2025'!$A:$H,4,FALSE) -> 67689416 | M49: =VLOOKUP($D49,'prosedur-2025'!$A:$H,5,FALSE) -> 46180007 | N49: =VLOOKUP($D49,'prosedur-2025'!$A:$H,6,FALSE) -> 58731728 | O49: =VLOOKUP($D49,'prosedur-2025'!$A:$H,7,FALSE) -> 78160513 | P49: =VLOOKUP($D49,'prosedur-2025'!$A:$H,8,FALSE) -> 109551144 | Q49: =K49*L49 -> 576781509548 | T49: =TEXT(VALUE(D49),"00.00") -> 81.08 | W49: =H49 -> 8108 | X49: 11 | Y49: =J49 -> P11AB | Z49: 1 | AA49: =I49 -> Complex Spinal Proc.
A50: PDC | B50: P11AD | C50: Complex Spinal Procedures | D50: 81.30 | E50: Refusion of spine, not otherwise specified | F50: =VLOOKUP($D50,proc!$A:$D,3,FALSE) -> 5 | G50: =VLOOKUP($D50,proc!$A:$D,4,FALSE) -> 0 | H50: =SUBSTITUTE(D50,".","") -> 8130 | I50: Complex Spinal Proc. | J50: =VLOOKUP(H50,'upload c51prpdc'!A:C,3,FALSE) -> P11AB | K50: =VLOOKUP($D50,'prosedur-2025'!$A:$H,3,FALSE) -> 35 | L50: =VLOOKUP($D50,'prosedur-2025'!$A:$H,4,FALSE) -> 70318241 | M50: =VLOOKUP($D50,'prosedur-2025'!$A:$H,5,FALSE) -> 54490054 | N50: =VLOOKUP($D50,'prosedur-2025'!$A:$H,6,FALSE) -> 75165616 | O50: =VLOOKUP($D50,'prosedur-2025'!$A:$H,7,FALSE) -> 86883828 | P50: =VLOOKUP($D50,'prosedur-2025'!$A:$H,8,FALSE) -> 92794264 | Q50: =K50*L50 -> 2461138422 | T50: =TEXT(VALUE(D50),"00.00") -> 81.30 | W50: =H50 -> 8130 | X50: 11 | Y50: =J50 -> P11AB | Z50: 1 | AA50: =I50 -> Complex Spinal Proc.
A51: PDC | B51: P11AD | C51: Complex Spinal Procedures | D51: 81.31 | E51: Refusion of atlas-axis spine | F51: =VLOOKUP($D51,proc!$A:$D,3,FALSE) -> 5 | G51: =VLOOKUP($D51,proc!$A:$D,4,FALSE) -> 0 | H51: =SUBSTITUTE(D51,".","") -> 8131 | I51: Complex Spinal Proc. | J51: =VLOOKUP(H51,'upload c51prpdc'!A:C,3,FALSE) -> P11AB | T51: =TEXT(VALUE(D51),"00.00") -> 81.31 | W51: =H51 -> 8131 | X51: 11 | Y51: =J51 -> P11AB | Z51: 1 | AA51: =I51 -> Complex Spinal Proc.
A52: PDC | B52: P11AD | C52: Complex Spinal Procedures | D52: 81.32 | E52: Refusion of other cervical spine, anterior column, anterior technique | F52: =VLOOKUP($D52,proc!$A:$D,3,FALSE) -> 5 | G52: =VLOOKUP($D52,proc!$A:$D,4,FALSE) -> 0 | H52: =SUBSTITUTE(D52,".","") -> 8132 | I52: Complex Spinal Proc. | J52: =VLOOKUP(H52,'upload c51prpdc'!A:C,3,FALSE) -> P11AB | K52: =VLOOKUP($D52,'prosedur-2025'!$A:$H,3,FALSE) -> 12 | L52: =VLOOKUP($D52,'prosedur-2025'!$A:$H,4,FALSE) -> 93542328 | M52: =VLOOKUP($D52,'prosedur-2025'!$A:$H,5,FALSE) -> 59016369 | N52: =VLOOKUP($D52,'prosedur-2025'!$A:$H,6,FALSE) -> 86014412 | O52: =VLOOKUP($D52,'prosedur-2025'!$A:$H,7,FALSE) -> 94265770 | P52: =VLOOKUP($D52,'prosedur-2025'!$A:$H,8,FALSE) -> 139788621 | Q52: =K52*L52 -> 1122507935 | T52: =TEXT(VALUE(D52),"00.00") -> 81.32 | W52: =H52 -> 8132 | X52: 11 | Y52: =J52 -> P11AB | Z52: 1 | AA52: =I52 -> Complex Spinal Proc.
A53: PDC | B53: P11AD | C53: Complex Spinal Procedures | D53: 81.33 | E53: Refusion of other cervical spine, posterior column, posterior technique | F53: =VLOOKUP($D53,proc!$A:$D,3,FALSE) -> 5 | G53: =VLOOKUP($D53,proc!$A:$D,4,FALSE) -> 0 | H53: =SUBSTITUTE(D53,".","") -> 8133 | I53: Complex Spinal Proc. | J53: =VLOOKUP(H53,'upload c51prpdc'!A:C,3,FALSE) -> P11AB | K53: =VLOOKUP($D53,'prosedur-2025'!$A:$H,3,FALSE) -> 15 | L53: =VLOOKUP($D53,'prosedur-2025'!$A:$H,4,FALSE) -> 62730194 | M53: =VLOOKUP($D53,'prosedur-2025'!$A:$H,5,FALSE) -> 26799353 | N53: =VLOOKUP($D53,'prosedur-2025'!$A:$H,6,FALSE) -> 62937527 | O53: =VLOOKUP($D53,'prosedur-2025'!$A:$H,7,FALSE) -> 95353673 | P53: =VLOOKUP($D53,'prosedur-2025'!$A:$H,8,FALSE) -> 99702768 | Q53: =K53*L53 -> 940952905 | T53: =TEXT(VALUE(D53),"00.00") -> 81.33 | W53: =H53 -> 8133 | X53: 11 | Y53: =J53 -> P11AB | Z53: 1 | AA53: =I53 -> Complex Spinal Proc.
A54: PDC | B54: P11AD | C54: Complex Spinal Procedures | D54: 81.34 | E54: Refusion of dorsal and dorsolumbar spine, anterior column, anterior technique | F54: =VLOOKUP($D54,proc!$A:$D,3,FALSE) -> 5 | G54: =VLOOKUP($D54,proc!$A:$D,4,FALSE) -> 0 | H54: =SUBSTITUTE(D54,".","") -> 8134 | I54: Complex Spinal Proc. | J54: =VLOOKUP(H54,'upload c51prpdc'!A:C,3,FALSE) -> P11AB | K54: =VLOOKUP($D54,'prosedur-2025'!$A:$H,3,FALSE) -> 7 | L54: =VLOOKUP($D54,'prosedur-2025'!$A:$H,4,FALSE) -> 1.1739956e+08 | M54: =VLOOKUP($D54,'prosedur-2025'!$A:$H,5,FALSE) -> 9003207 | N54: =VLOOKUP($D54,'prosedur-2025'!$A:$H,6,FALSE) -> 111904600 | O54: =VLOOKUP($D54,'prosedur-2025'!$A:$H,7,FALSE) -> 125308086 | P54: =VLOOKUP($D54,'prosedur-2025'!$A:$H,8,FALSE) -> 350784753 | Q54: =K54*L54 -> 821796938 | T54: =TEXT(VALUE(D54),"00.00") -> 81.34 | W54: =H54 -> 8134 | X54: 11 | Y54: =J54 -> P11AB | Z54: 1 | AA54: =I54 -> Complex Spinal Proc.
A55: PDC | B55: P11AD | C55: Complex Spinal Procedures | D55: 81.35 | E55: Refusion of dorsal and dorsolumbar spine, posterior column, posterior technique | F55: =VLOOKUP($D55,proc!$A:$D,3,FALSE) -> 5 | G55: =VLOOKUP($D55,proc!$A:$D,4,FALSE) -> 0 | H55: =SUBSTITUTE(D55,".","") -> 8135 | I55: Complex Spinal Proc. | J55: =VLOOKUP(H55,'upload c51prpdc'!A:C,3,FALSE) -> P11AB | K55: =VLOOKUP($D55,'prosedur-2025'!$A:$H,3,FALSE) -> 185 | L55: =VLOOKUP($D55,'prosedur-2025'!$A:$H,4,FALSE) -> 91375186 | M55: =VLOOKUP($D55,'prosedur-2025'!$A:$H,5,FALSE) -> 71476844 | N55: =VLOOKUP($D55,'prosedur-2025'!$A:$H,6,FALSE) -> 92485620 | O55: =VLOOKUP($D55,'prosedur-2025'!$A:$H,7,FALSE) -> 108187010 | P55: =VLOOKUP($D55,'prosedur-2025'!$A:$H,8,FALSE) -> 124520887 | Q55: =K55*L55 -> 16904409480 | T55: =TEXT(VALUE(D55),"00.00") -> 81.35 | W55: =H55 -> 8135 | X55: 11 | Y55: =J55 -> P11AB | Z55: 1 | AA55: =I55 -> Complex Spinal Proc.
A56: PDC | B56: P11AD | C56: Complex Spinal Procedures | D56: 81.36 | E56: Refusion of lumbar and lumbosacral spine, anterior column, anterior technique | F56: =VLOOKUP($D56,proc!$A:$D,3,FALSE) -> 5 | G56: =VLOOKUP($D56,proc!$A:$D,4,FALSE) -> 0 | H56: =SUBSTITUTE(D56,".","") -> 8136 | I56: Complex Spinal Proc. | J56: =VLOOKUP(H56,'upload c51prpdc'!A:C,3,FALSE) -> P11AB | K56: =VLOOKUP($D56,'prosedur-2025'!$A:$H,3,FALSE) -> 14 | L56: =VLOOKUP($D56,'prosedur-2025'!$A:$H,4,FALSE) -> 74601905 | M56: =VLOOKUP($D56,'prosedur-2025'!$A:$H,5,FALSE) -> 48056191 | N56: =VLOOKUP($D56,'prosedur-2025'!$A:$H,6,FALSE) -> 78794765 | O56: =VLOOKUP($D56,'prosedur-2025'!$A:$H,7,FALSE) -> 100591222 | P56: =VLOOKUP($D56,'prosedur-2025'!$A:$H,8,FALSE) -> 107748085 | Q56: =K56*L56 -> 1044426669 | T56: =TEXT(VALUE(D56),"00.00") -> 81.36 | W56: =H56 -> 8136 | X56: 11 | Y56: =J56 -> P11AB | Z56: 1 | AA56: =I56 -> Complex Spinal Proc.
A57: PDC | B57: P11AD | C57: Complex Spinal Procedures | D57: 81.37 | E57: Refusion of lumbar and lumbosacral spine, posterior column, posterior technique | F57: =VLOOKUP($D57,proc!$A:$D,3,FALSE) -> 5 | G57: =VLOOKUP($D57,proc!$A:$D,4,FALSE) -> 0 | H57: =SUBSTITUTE(D57,".","") -> 8137 | I57: Complex Spinal Proc. | J57: =VLOOKUP(H57,'upload c51prpdc'!A:C,3,FALSE) -> P11AB | K57: =VLOOKUP($D57,'prosedur-2025'!$A:$H,3,FALSE) -> 9 | L57: =VLOOKUP($D57,'prosedur-2025'!$A:$H,4,FALSE) -> 1.0575249e+08 | M57: =VLOOKUP($D57,'prosedur-2025'!$A:$H,5,FALSE) -> 98390202 | N57: =VLOOKUP($D57,'prosedur-2025'!$A:$H,6,FALSE) -> 109876684 | O57: =VLOOKUP($D57,'prosedur-2025'!$A:$H,7,FALSE) -> 148569122 | P57: =VLOOKUP($D57,'prosedur-2025'!$A:$H,8,FALSE) -> 150380731 | Q57: =K57*L57 -> 951772405 | T57: =TEXT(VALUE(D57),"00.00") -> 81.37 | W57: =H57 -> 8137 | X57: 11 | Y57: =J57 -> P11AB | Z57: 1 | AA57: =I57 -> Complex Spinal Proc.
A58: PDC | B58: P11AD | C58: Complex Spinal Procedures | D58: 81.38 | E58: Refusion of lumbar and lumbosacral spine, anterior column, posterior technique | F58: =VLOOKUP($D58,proc!$A:$D,3,FALSE) -> 5 | G58: =VLOOKUP($D58,proc!$A:$D,4,FALSE) -> 0 | H58: =SUBSTITUTE(D58,".","") -> 8138 | I58: Complex Spinal Proc. | J58: =VLOOKUP(H58,'upload c51prpdc'!A:C,3,FALSE) -> P11AB | K58: =VLOOKUP($D58,'prosedur-2025'!$A:$H,3,FALSE) -> 135 | L58: =VLOOKUP($D58,'prosedur-2025'!$A:$H,4,FALSE) -> 76730268 | M58: =VLOOKUP($D58,'prosedur-2025'!$A:$H,5,FALSE) -> 45214948 | N58: =VLOOKUP($D58,'prosedur-2025'!$A:$H,6,FALSE) -> 85161186 | O58: =VLOOKUP($D58,'prosedur-2025'!$A:$H,7,FALSE) -> 104323910 | P58: =VLOOKUP($D58,'prosedur-2025'!$A:$H,8,FALSE) -> 126089406 | Q58: =K58*L58 -> 10358586246 | T58: =TEXT(VALUE(D58),"00.00") -> 81.38 | W58: =H58 -> 8138 | X58: 11 | Y58: =J58 -> P11AB | Z58: 1 | AA58: =I58 -> Complex Spinal Proc.
A59: PDC | B59: P11AD | C59: Complex Spinal Procedures | D59: 81.39 | E59: Refusion of spine, not elsewhere classified | F59: =VLOOKUP($D59,proc!$A:$D,3,FALSE) -> 4 | G59: =VLOOKUP($D59,proc!$A:$D,4,FALSE) -> 0 | H59: =SUBSTITUTE(D59,".","") -> 8139 | I59: Complex Spinal Proc. | J59: =VLOOKUP(H59,'upload c51prpdc'!A:C,3,FALSE) -> P11AB | K59: =VLOOKUP($D59,'prosedur-2025'!$A:$H,3,FALSE) -> 68 | L59: =VLOOKUP($D59,'prosedur-2025'!$A:$H,4,FALSE) -> 76808456 | M59: =VLOOKUP($D59,'prosedur-2025'!$A:$H,5,FALSE) -> 51487642 | N59: =VLOOKUP($D59,'prosedur-2025'!$A:$H,6,FALSE) -> 77173066 | O59: =VLOOKUP($D59,'prosedur-2025'!$A:$H,7,FALSE) -> 94742454 | P59: =VLOOKUP($D59,'prosedur-2025'!$A:$H,8,FALSE) -> 105626015 | Q59: =K59*L59 -> 5222974975 | T59: =TEXT(VALUE(D59),"00.00") -> 81.39 | W59: =H59 -> 8139 | X59: 11 | Y59: =J59 -> P11AB | Z59: 1 | AA59: =I59 -> Complex Spinal Proc.
A60: PDC | B60: P11AD | C60: Complex Spinal Procedures | D60: 81.66 | E60: Percutaneous vertebral augmentation | F60: =VLOOKUP($D60,proc!$A:$D,3,FALSE) -> 4 | G60: =VLOOKUP($D60,proc!$A:$D,4,FALSE) -> 0 | H60: =SUBSTITUTE(D60,".","") -> 8166 | I60: Moderate Spinal Proc. | J60: =VLOOKUP(H60,'upload c51prpdc'!A:C,3,FALSE) -> P11AJ | K60: =VLOOKUP($D60,'prosedur-2025'!$A:$H,3,FALSE) -> 666 | L60: =VLOOKUP($D60,'prosedur-2025'!$A:$H,4,FALSE) -> 47065309 | M60: =VLOOKUP($D60,'prosedur-2025'!$A:$H,5,FALSE) -> 31525400 | N60: =VLOOKUP($D60,'prosedur-2025'!$A:$H,6,FALSE) -> 42013112 | O60: =VLOOKUP($D60,'prosedur-2025'!$A:$H,7,FALSE) -> 57545001 | P60: =VLOOKUP($D60,'prosedur-2025'!$A:$H,8,FALSE) -> 75413325 | Q60: =K60*L60 -> 31345495792 | T60: =TEXT(VALUE(D60),"00.00") -> 81.66 | W60: =H60 -> 8166 | X60: 11 | Y60: =J60 -> P11AJ | Z60: 1 | AA60: =I60 -> Moderate Spinal Proc.
A61: PDC | B61: P11AD | C61: Complex Spinal Procedures | D61: 84.59 | E61: Insertion of other spinal devices | F61: =VLOOKUP($D61,proc!$A:$D,3,FALSE) -> 0 | G61: =VLOOKUP($D61,proc!$A:$D,4,FALSE) -> 0 | H61: =SUBSTITUTE(D61,".","") -> 8459 | I61: Moderate Spinal Proc. | J61: =VLOOKUP(H61,'upload c51prpdc'!A:C,3,FALSE) -> P11AJ | K61: =VLOOKUP($D61,'prosedur-2025'!$A:$H,3,FALSE) -> 88 | L61: =VLOOKUP($D61,'prosedur-2025'!$A:$H,4,FALSE) -> 63971686 | M61: =VLOOKUP($D61,'prosedur-2025'!$A:$H,5,FALSE) -> 34988684 | N61: =VLOOKUP($D61,'prosedur-2025'!$A:$H,6,FALSE) -> 44652176 | O61: =VLOOKUP($D61,'prosedur-2025'!$A:$H,7,FALSE) -> 70382521 | P61: =VLOOKUP($D61,'prosedur-2025'!$A:$H,8,FALSE) -> 128858971 | Q61: =K61*L61 -> 5629508395 | T61: =TEXT(VALUE(D61),"00.00") -> 84.59 | W61: =H61 -> 8459 | X61: 11 | Y61: =J61 -> P11AJ | Z61: 1 | AA61: =I61 -> Moderate Spinal Proc.
A62: PDC | B62: P11AD | C62: Complex Spinal Procedures | D62: 84.60 | E62: Insertion of spinal disc prosthesis, not otherwise specified | F62: =VLOOKUP($D62,proc!$A:$D,3,FALSE) -> 3 | G62: =VLOOKUP($D62,proc!$A:$D,4,FALSE) -> 0 | H62: =SUBSTITUTE(D62,".","") -> 8460 | I62: Complex Spinal Proc. | J62: =VLOOKUP(H62,'upload c51prpdc'!A:C,3,FALSE) -> P11AB | K62: =VLOOKUP($D62,'prosedur-2025'!$A:$H,3,FALSE) -> 4 | L62: =VLOOKUP($D62,'prosedur-2025'!$A:$H,4,FALSE) -> 94201396 | M62: =VLOOKUP($D62,'prosedur-2025'!$A:$H,5,FALSE) -> 14919275 | N62: =VLOOKUP($D62,'prosedur-2025'!$A:$H,6,FALSE) -> 54528657 | O62: =VLOOKUP($D62,'prosedur-2025'!$A:$H,7,FALSE) -> 125025777 | P62: =VLOOKUP($D62,'prosedur-2025'!$A:$H,8,FALSE) -> 182331876 | Q62: =K62*L62 -> 376805585 | T62: =TEXT(VALUE(D62),"00.00") -> 84.60 | W62: =H62 -> 8460 | X62: 11 | Y62: =J62 -> P11AB | Z62: 1 | AA62: =I62 -> Complex Spinal Proc.
A63: PDC | B63: P11AD | C63: Complex Spinal Procedures | D63: 84.61 | E63: Insertion of partial spinal disc prosthesis, cervical | F63: =VLOOKUP($D63,proc!$A:$D,3,FALSE) -> 3 | G63: =VLOOKUP($D63,proc!$A:$D,4,FALSE) -> 0 | H63: =SUBSTITUTE(D63,".","") -> 8461 | I63: Complex Spinal Proc. | J63: =VLOOKUP(H63,'upload c51prpdc'!A:C,3,FALSE) -> P11AB | K63: =VLOOKUP($D63,'prosedur-2025'!$A:$H,3,FALSE) -> 6 | L63: =VLOOKUP($D63,'prosedur-2025'!$A:$H,4,FALSE) -> 116184758 | M63: =VLOOKUP($D63,'prosedur-2025'!$A:$H,5,FALSE) -> 79665771 | N63: =VLOOKUP($D63,'prosedur-2025'!$A:$H,6,FALSE) -> 83597661 | O63: =VLOOKUP($D63,'prosedur-2025'!$A:$H,7,FALSE) -> 118980329 | P63: =VLOOKUP($D63,'prosedur-2025'!$A:$H,8,FALSE) -> 247386247 | Q63: =K63*L63 -> 697108548 | T63: =TEXT(VALUE(D63),"00.00") -> 84.61 | W63: =H63 -> 8461 | X63: 11 | Y63: =J63 -> P11AB | Z63: 1 | AA63: =I63 -> Complex Spinal Proc.
... A77: PDC | B77: P11AB | C77: Complex Craniotomy | D77: 01.14 | E77: Open biopsy of brain | F77: =VLOOKUP($D77,proc!$A:$D,3,FALSE) -> 6 | G77: =VLOOKUP($D77,proc!$A:$D,4,FALSE) -> 0 | H77: =SUBSTITUTE(D77,".","") -> 0114 | I77: Simple Craniotomy Proc. | J77: =VLOOKUP(H77,'upload c51prpdc'!A:C,3,FALSE) -> P11AF | K77: =VLOOKUP($D77,'prosedur-2025'!$A:$H,3,FALSE) -> 621 | L77: =VLOOKUP($D77,'prosedur-2025'!$A:$H,4,FALSE) -> 84531615 | M77: =VLOOKUP($D77,'prosedur-2025'!$A:$H,5,FALSE) -> 42187374 | N77: =VLOOKUP($D77,'prosedur-2025'!$A:$H,6,FALSE) -> 55413461 | O77: =VLOOKUP($D77,'prosedur-2025'!$A:$H,7,FALSE) -> 94412771 | P77: =VLOOKUP($D77,'prosedur-2025'!$A:$H,8,FALSE) -> 201536690 | Q77: =K77*L77 -> 52494133095 | T77: =TEXT(VALUE(D77),"00.00") -> 01.14 | W77: =H77 -> 0114 | X77: 11 | Y77: =J77 -> P11AF | Z77: 1 | AA77: =I77 -> Simple Craniotomy Proc.
A78: PDC | D78: 01.140 | E78: Awake Brain Biopsy (IM) | F78: 6 | G78: 1 | H78: =SUBSTITUTE(D78,".","") -> 01140 | I78: Simple Craniotomy Proc. | J78: P11AF | W78: =H78 -> 01140 | X78: 11 | Y78: =J78 -> P11AF | Z78: 1 | AA78: =I78 -> Simple Craniotomy Proc.
A79: PDC | B79: P11AB | C79: Complex Craniotomy | D79: 01.17 | E79: Brain temperature monitoring | F79: =VLOOKUP($D79,proc!$A:$D,3,FALSE) -> 5 | G79: =VLOOKUP($D79,proc!$A:$D,4,FALSE) -> 0 | H79: =SUBSTITUTE(D79,".","") -> 0117 | I79: Moderate Craniotomy Proc. | J79: =VLOOKUP(H79,'upload c51prpdc'!A:C,3,FALSE) -> P11AE | K79: =VLOOKUP($D79,'prosedur-2025'!$A:$H,3,FALSE) -> 1 | L79: =VLOOKUP($D79,'prosedur-2025'!$A:$H,4,FALSE) -> 74704100 | M79: =VLOOKUP($D79,'prosedur-2025'!$A:$H,5,FALSE) -> 74704100 | N79: =VLOOKUP($D79,'prosedur-2025'!$A:$H,6,FALSE) -> 74704100 | O79: =VLOOKUP($D79,'prosedur-2025'!$A:$H,7,FALSE) -> 74704100 | P79: =VLOOKUP($D79,'prosedur-2025'!$A:$H,8,FALSE) -> 74704100 | Q79: =K79*L79 -> 74704100 | T79: =TEXT(VALUE(D79),"00.00") -> 01.17 | W79: =H79 -> 0117 | X79: 11 | Y79: =J79 -> P11AE | Z79: 1 | AA79: =I79 -> Moderate Craniotomy Proc.
A80: PDC | B80: P11AB | C80: Complex Craniotomy | D80: 01.21 | E80: Incision and drainage of cranial sinus | F80: =VLOOKUP($D80,proc!$A:$D,3,FALSE) -> 4 | G80: =VLOOKUP($D80,proc!$A:$D,4,FALSE) -> 0 | H80: =SUBSTITUTE(D80,".","") -> 0121 | I80: Simple Craniotomy Proc. | J80: =VLOOKUP(H80,'upload c51prpdc'!A:C,3,FALSE) -> P11AF | K80: =VLOOKUP($D80,'prosedur-2025'!$A:$H,3,FALSE) -> 38 | L80: =VLOOKUP($D80,'prosedur-2025'!$A:$H,4,FALSE) -> 56019308 | M80: =VLOOKUP($D80,'prosedur-2025'!$A:$H,5,FALSE) -> 25604328 | N80: =VLOOKUP($D80,'prosedur-2025'!$A:$H,6,FALSE) -> 34788189 | O80: =VLOOKUP($D80,'prosedur-2025'!$A:$H,7,FALSE) -> 66430464 | P80: =VLOOKUP($D80,'prosedur-2025'!$A:$H,8,FALSE) -> 111097538 | Q80: =K80*L80 -> 2128733721 | T80: =TEXT(VALUE(D80),"00.00") -> 01.21 | W80: =H80 -> 0121 | X80: 11 | Y80: =J80 -> P11AF | Z80: 1 | AA80: =I80 -> Simple Craniotomy Proc.
A81: PDC | B81: P11AB | C81: Complex Craniotomy | D81: 01.23 | E81: Reopening of craniotomy site | F81: =VLOOKUP($D81,proc!$A:$D,3,FALSE) -> 6 | G81: =VLOOKUP($D81,proc!$A:$D,4,FALSE) -> 0 | H81: =SUBSTITUTE(D81,".","") -> 0123 | I81: Moderate Craniotomy Proc. | J81: =VLOOKUP(H81,'upload c51prpdc'!A:C,3,FALSE) -> P11AE | K81: =VLOOKUP($D81,'prosedur-2025'!$A:$H,3,FALSE) -> 385 | L81: =VLOOKUP($D81,'prosedur-2025'!$A:$H,4,FALSE) -> 64836067 | M81: =VLOOKUP($D81,'prosedur-2025'!$A:$H,5,FALSE) -> 26393956 | N81: =VLOOKUP($D81,'prosedur-2025'!$A:$H,6,FALSE) -> 45612332 | O81: =VLOOKUP($D81,'prosedur-2025'!$A:$H,7,FALSE) -> 84044650 | P81: =VLOOKUP($D81,'prosedur-2025'!$A:$H,8,FALSE) -> 140573443 | Q81: =K81*L81 -> 24961885858 | T81: =TEXT(VALUE(D81),"00.00") -> 01.23 | W81: =H81 -> 0123 | X81: 11 | Y81: =J81 -> P11AE | Z81: 1 | AA81: =I81 -> Moderate Craniotomy Proc.
A82: PDC | B82: P11AB | C82: Complex Craniotomy | D82: 01.25 | E82: Other craniectomy | F82: =VLOOKUP($D82,proc!$A:$D,3,FALSE) -> 5 | G82: =VLOOKUP($D82,proc!$A:$D,4,FALSE) -> 0 | H82: =SUBSTITUTE(D82,".","") -> 0125 | I82: Simple Craniotomy Proc. | J82: =VLOOKUP(H82,'upload c51prpdc'!A:C,3,FALSE) -> P11AF | K82: =VLOOKUP($D82,'prosedur-2025'!$A:$H,3,FALSE) -> 7467 | L82: =VLOOKUP($D82,'prosedur-2025'!$A:$H,4,FALSE) -> 78074736 | M82: =VLOOKUP($D82,'prosedur-2025'!$A:$H,5,FALSE) -> 37140700 | N82: =VLOOKUP($D82,'prosedur-2025'!$A:$H,6,FALSE) -> 58365135 | O82: =VLOOKUP($D82,'prosedur-2025'!$A:$H,7,FALSE) -> 95505892 | P82: =VLOOKUP($D82,'prosedur-2025'!$A:$H,8,FALSE) -> 152048474 | Q82: =K82*L82 -> 582984050594 | T82: =TEXT(VALUE(D82),"00.00") -> 01.25 | W82: =H82 -> 0125 | X82: 11 | Y82: =J82 -> P11AF | Z82: 1 | AA82: =I82 -> Simple Craniotomy Proc.
A83: PDC | D83: 01.250 | E83: Decompressive hemicraniectomy (IM) | F83: 5 | G83: 1 | H83: =SUBSTITUTE(D83,".","") -> 01250 | I83: Simple Craniotomy Proc. | J83: P11AF | W83: =H83 -> 01250 | X83: 11 | Y83: =J83 -> P11AF | Z83: 1 | AA83: =I83 -> Simple Craniotomy Proc.
A84: PDC | B84: P11AB | C84: Complex Craniotomy | D84: 01.31 | E84: Incision of cerebral meninges | F84: =VLOOKUP($D84,proc!$A:$D,3,FALSE) -> 5 | G84: =VLOOKUP($D84,proc!$A:$D,4,FALSE) -> 0 | H84: =SUBSTITUTE(D84,".","") -> 0131 | I84: Simple Craniotomy Proc. | J84: =VLOOKUP(H84,'upload c51prpdc'!A:C,3,FALSE) -> P11AF | K84: =VLOOKUP($D84,'prosedur-2025'!$A:$H,3,FALSE) -> 1370 | L84: =VLOOKUP($D84,'prosedur-2025'!$A:$H,4,FALSE) -> 70317775 | M84: =VLOOKUP($D84,'prosedur-2025'!$A:$H,5,FALSE) -> 33839988 | N84: =VLOOKUP($D84,'prosedur-2025'!$A:$H,6,FALSE) -> 49035090 | O84: =VLOOKUP($D84,'prosedur-2025'!$A:$H,7,FALSE) -> 83514873 | P84: =VLOOKUP($D84,'prosedur-2025'!$A:$H,8,FALSE) -> 138560234 | Q84: =K84*L84 -> 96335351096 | T84: =TEXT(VALUE(D84),"00.00") -> 01.31 | W84: =H84 -> 0131 | X84: 11 | Y84: =J84 -> P11AF | Z84: 1 | AA84: =I84 -> Simple Craniotomy Proc.
A85: PDC | D85: 01.310 | E85: Endoscopic assisted evacuation or aspiration of intracerebral hematoma (IM) | F85: 5 | G85: 1 | H85: =SUBSTITUTE(D85,".","") -> 01310 | I85: Simple Craniotomy Proc. | J85: P11AF | W85: =H85 -> 01310 | X85: 11 | Y85: =J85 -> P11AF | Z85: 1 | AA85: =I85 -> Simple Craniotomy Proc.
A86: PDC | D86: 01.311 | E86: Stereotactic assisted evacuation or aspiration of intracerebral hematoma (IM) | F86: 5 | G86: 1 | H86: =SUBSTITUTE(D86,".","") -> 01311 | I86: Simple Craniotomy Proc. | J86: P11AF | W86: =H86 -> 01311 | X86: 11 | Y86: =J86 -> P11AF | Z86: 1 | AA86: =I86 -> Simple Craniotomy Proc.
A87: PDC | B87: P11AB | C87: Complex Craniotomy | D87: 01.39 | E87: Other incision of brain | F87: =VLOOKUP($D87,proc!$A:$D,3,FALSE) -> 5 | G87: =VLOOKUP($D87,proc!$A:$D,4,FALSE) -> 0 | H87: =SUBSTITUTE(D87,".","") -> 0139 | I87: Moderate Craniotomy Proc. | J87: =VLOOKUP(H87,'upload c51prpdc'!A:C,3,FALSE) -> P11AE | K87: =VLOOKUP($D87,'prosedur-2025'!$A:$H,3,FALSE) -> 3142 | L87: =VLOOKUP($D87,'prosedur-2025'!$A:$H,4,FALSE) -> 77401427 | M87: =VLOOKUP($D87,'prosedur-2025'!$A:$H,5,FALSE) -> 35114119 | N87: =VLOOKUP($D87,'prosedur-2025'!$A:$H,6,FALSE) -> 51457480 | O87: =VLOOKUP($D87,'prosedur-2025'!$A:$H,7,FALSE) -> 88046886 | P87: =VLOOKUP($D87,'prosedur-2025'!$A:$H,8,FALSE) -> 159208215 | Q87: =K87*L87 -> 243195282977 | T87: =TEXT(VALUE(D87),"00.00") -> 01.39 | W87: =H87 -> 0139 | X87: 11 | Y87: =J87 -> P11AE | Z87: 1 | AA87: =I87 -> Moderate Craniotomy Proc.
A88: PDC | D88: 01.391 | E88: Evacuation or drainage of intracerebral hemorrhage (IM) | F88: 5 | G88: 1 | H88: =SUBSTITUTE(D88,".","") -> 01391 | I88: Moderate Craniotomy Proc. | J88: P11AE | W88: =H88 -> 01391 | X88: 11 | Y88: =J88 -> P11AE | Z88: 1 | AA88: =I88 -> Moderate Craniotomy Proc.
A89: PDC | D89: 01.392 | E89: Microscopic or endoscopic Evacuation of intracerebral hemorrhage (IM) | F89: 5 | G89: 1 | H89: =SUBSTITUTE(D89,".","") -> 01392 | I89: Moderate Craniotomy Proc. | J89: P11AE | W89: =H89 -> 01392 | X89: 11 | Y89: =J89 -> P11AE | Z89: 1 | AA89: =I89 -> Moderate Craniotomy Proc.
A90: PDC | D90: 01.393 | E90: Stereotactic evacuation or drainage of intracerebral hemorrhage (IM) | F90: 5 | G90: 1 | H90: =SUBSTITUTE(D90,".","") -> 01393 | I90: Moderate Craniotomy Proc. | J90: P11AE | W90: =H90 -> 01393 | X90: 11 | Y90: =J90 -> P11AE | Z90: 1 | AA90: =I90 -> Moderate Craniotomy Proc.
A91: PDC | B91: P11AB | C91: Complex Craniotomy | D91: 01.41 | E91: Operations on thalamus | F91: =VLOOKUP($D91,proc!$A:$D,3,FALSE) -> 5 | G91: =VLOOKUP($D91,proc!$A:$D,4,FALSE) -> 0 | H91: =SUBSTITUTE(D91,".","") -> 0141 | I91: Complex Craniotomy Proc. | J91: =VLOOKUP(H91,'upload c51prpdc'!A:C,3,FALSE) -> P11AC | K91: =VLOOKUP($D91,'prosedur-2025'!$A:$H,3,FALSE) -> 46 | L91: =VLOOKUP($D91,'prosedur-2025'!$A:$H,4,FALSE) -> 96694604 | M91: =VLOOKUP($D91,'prosedur-2025'!$A:$H,5,FALSE) -> 61201161 | N91: =VLOOKUP($D91,'prosedur-2025'!$A:$H,6,FALSE) -> 77727863 | O91: =VLOOKUP($D91,'prosedur-2025'!$A:$H,7,FALSE) -> 146952150 | P91: =VLOOKUP($D91,'prosedur-2025'!$A:$H,8,FALSE) -> 149614085 | Q91: =K91*L91 -> 4447951780 | T91: =TEXT(VALUE(D91),"00.00") -> 01.41 | W91: =H91 -> 0141 | X91: 11 | Y91: =J91 -> P11AC | Z91: 1 | AA91: =I91 -> Complex Craniotomy Proc.
A92: PDC | B92: P11AB | C92: Complex Craniotomy | D92: 01.42 | E92: Operations on globus pallidus | F92: =VLOOKUP($D92,proc!$A:$D,3,FALSE) -> 6 | G92: =VLOOKUP($D92,proc!$A:$D,4,FALSE) -> 0 | H92: =SUBSTITUTE(D92,".","") -> 0142 | I92: Complex Craniotomy Proc. | J92: =VLOOKUP(H92,'upload c51prpdc'!A:C,3,FALSE) -> P11AC | K92: =VLOOKUP($D92,'prosedur-2025'!$A:$H,3,FALSE) -> 15 | L92: =VLOOKUP($D92,'prosedur-2025'!$A:$H,4,FALSE) -> 72772346 | M92: =VLOOKUP($D92,'prosedur-2025'!$A:$H,5,FALSE) -> 35497749 | N92: =VLOOKUP($D92,'prosedur-2025'!$A:$H,6,FALSE) -> 65676868 | O92: =VLOOKUP($D92,'prosedur-2025'!$A:$H,7,FALSE) -> 85205288 | P92: =VLOOKUP($D92,'prosedur-2025'!$A:$H,8,FALSE) -> 146578731 | Q92: =K92*L92 -> 1091585195 | T92: =TEXT(VALUE(D92),"00.00") -> 01.42 | W92: =H92 -> 0142 | X92: 11 | Y92: =J92 -> P11AC | Z92: 1 | AA92: =I92 -> Complex Craniotomy Proc.
A93: PDC | B93: P11AB | C93: Complex Craniotomy | D93: 01.51 | E93: Excision of lesion or tissue of cerebral meninges | F93: =VLOOKUP($D93,proc!$A:$D,3,FALSE) -> 6 | G93: =VLOOKUP($D93,proc!$A:$D,4,FALSE) -> 0 | H93: =SUBSTITUTE(D93,".","") -> 0151 | I93: Moderate Craniotomy Proc. | J93: =VLOOKUP(H93,'upload c51prpdc'!A:C,3,FALSE) -> P11AE | K93: =VLOOKUP($D93,'prosedur-2025'!$A:$H,3,FALSE) -> 2551 | L93: =VLOOKUP($D93,'prosedur-2025'!$A:$H,4,FALSE) -> 77382110 | M93: =VLOOKUP($D93,'prosedur-2025'!$A:$H,5,FALSE) -> 38633734 | N93: =VLOOKUP($D93,'prosedur-2025'!$A:$H,6,FALSE) -> 54188460 | O93: =VLOOKUP($D93,'prosedur-2025'!$A:$H,7,FALSE) -> 95336655 | P93: =VLOOKUP($D93,'prosedur-2025'!$A:$H,8,FALSE) -> 156340846 | Q93: =K93*L93 -> 197401763615 | T93: =TEXT(VALUE(D93),"00.00") -> 01.51 | W93: =H93 -> 0151 | X93: 11 | Y93: =J93 -> P11AE | Z93: 1 | AA93: =I93 -> Moderate Craniotomy Proc.
A94: PDC | D94: 01.511 | E94: Excision of skullbase meningioma (IM) | F94: 6 | G94: 1 | H94: =SUBSTITUTE(D94,".","") -> 01511 | I94: Moderate Craniotomy Proc. | J94: P11AE | W94: =H94 -> 01511 | X94: 11 | Y94: =J94 -> P11AE | Z94: 1 | AA94: =I94 -> Moderate Craniotomy Proc.
A95: PDC | D95: 01.512 | E95: Excision of giant meningioma (IM) | F95: 6 | G95: c | H95: =SUBSTITUTE(D95,".","") -> 01512 | I95: Moderate Craniotomy Proc. | J95: P11AE | W95: =H95 -> 01512 | X95: 11 | Y95: =J95 -> P11AE | Z95: 1 | AA95: =I95 -> Moderate Craniotomy Proc.
A96: PDC | B96: P11AB | C96: Complex Craniotomy | D96: 01.52 | E96: Hemispherectomy | F96: =VLOOKUP($D96,proc!$A:$D,3,FALSE) -> 6 | G96: =VLOOKUP($D96,proc!$A:$D,4,FALSE) -> 0 | H96: =SUBSTITUTE(D96,".","") -> 0152 | I96: Moderate Craniotomy Proc. | J96: =VLOOKUP(H96,'upload c51prpdc'!A:C,3,FALSE) -> P11AE | K96: =VLOOKUP($D96,'prosedur-2025'!$A:$H,3,FALSE) -> 3 | L96: =VLOOKUP($D96,'prosedur-2025'!$A:$H,4,FALSE) -> 1.0796675e+08 | M96: =VLOOKUP($D96,'prosedur-2025'!$A:$H,5,FALSE) -> 18716286 | N96: =VLOOKUP($D96,'prosedur-2025'!$A:$H,6,FALSE) -> 112551763 | O96: =VLOOKUP($D96,'prosedur-2025'!$A:$H,7,FALSE) -> 192632202 | P96: =VLOOKUP($D96,'prosedur-2025'!$A:$H,8,FALSE) -> 192632202 | Q96: =K96*L96 -> 323900251 | T96: =TEXT(VALUE(D96),"00.00") -> 01.52 | W96: =H96 -> 0152 | X96: 11 | Y96: =J96 -> P11AE | Z96: 1 | AA96: =I96 -> Moderate Craniotomy Proc.
A97: PDC | B97: P11AB | C97: Complex Craniotomy | D97: 01.53 | E97: Lobectomy of brain | F97: =VLOOKUP($D97,proc!$A:$D,3,FALSE) -> 6 | G97: =VLOOKUP($D97,proc!$A:$D,4,FALSE) -> 0 | H97: =SUBSTITUTE(D97,".","") -> 0153 | I97: Moderate Craniotomy Proc. | J97: =VLOOKUP(H97,'upload c51prpdc'!A:C,3,FALSE) -> P11AE | K97: =VLOOKUP($D97,'prosedur-2025'!$A:$H,3,FALSE) -> 54 | L97: =VLOOKUP($D97,'prosedur-2025'!$A:$H,4,FALSE) -> 1.3090614e+08 | M97: =VLOOKUP($D97,'prosedur-2025'!$A:$H,5,FALSE) -> 63852106 | N97: =VLOOKUP($D97,'prosedur-2025'!$A:$H,6,FALSE) -> 113526005 | O97: =VLOOKUP($D97,'prosedur-2025'!$A:$H,7,FALSE) -> 170589836 | P97: =VLOOKUP($D97,'prosedur-2025'!$A:$H,8,FALSE) -> 205578204 | Q97: =K97*L97 -> 7068931717 | T97: =TEXT(VALUE(D97),"00.00") -> 01.53 | W97: =H97 -> 0153 | X97: 11 | Y97: =J97 -> P11AE | Z97: 1 | AA97: =I97 -> Moderate Craniotomy Proc.
A98: PDC | D98: 01.54 | E98: Awake Surgery Removal of brain tumor (IM) | F98: 6 | G98: 1 | H98: =SUBSTITUTE(D98,".","") -> 0154 | I98: Complex Craniotomy Proc. | J98: P11AC | W98: =H98 -> 0154 | X98: 11 | Y98: =J98 -> P11AC | Z98: 1 | AA98: =I98 -> Complex Craniotomy Proc.
A99: PDC | D99: 01.55 | E99: Awake Epilepsy Surgery (IM) | G99: 1 | H99: =SUBSTITUTE(D99,".","") -> 0155 | I99: Moderate Craniotomy Proc. | J99: P11AE | W99: =H99 -> 0155 | X99: 11 | Y99: =J99 -> P11AE | Z99: 1 | AA99: =I99 -> Moderate Craniotomy Proc.
A100: PDC | B100: P11AB | C100: Complex Craniotomy | D100: 01.59 | E100: Other excision or destruction of lesion or tissue of brain | F100: =VLOOKUP($D100,proc!$A:$D,3,FALSE) -> 6 | G100: =VLOOKUP($D100,proc!$A:$D,4,FALSE) -> 0 | H100: =SUBSTITUTE(D100,".","") -> 0159 | I100: Moderate Craniotomy Proc. | J100: =VLOOKUP(H100,'upload c51prpdc'!A:C,3,FALSE) -> P11AE | K100: =VLOOKUP($D100,'prosedur-2025'!$A:$H,3,FALSE) -> 5564 | L100: =VLOOKUP($D100,'prosedur-2025'!$A:$H,4,FALSE) -> 85330158 | M100: =VLOOKUP($D100,'prosedur-2025'!$A:$H,5,FALSE) -> 41554530 | N100: =VLOOKUP($D100,'prosedur-2025'!$A:$H,6,FALSE) -> 65234643 | O100: =VLOOKUP($D100,'prosedur-2025'!$A:$H,7,FALSE) -> 106846927 | P100: =VLOOKUP($D100,'prosedur-2025'!$A:$H,8,FALSE) -> 164868826 | Q100: =K100*L100 -> 474776996565 | T100: =TEXT(VALUE(D100),"00.00") -> 01.59 | W100: =H100 -> 0159 | X100: 11 | Y100: =J100 -> P11AE | Z100: 1 | AA100: =I100 -> Moderate Craniotomy Proc.
A101: PDC | D101: 01.590 | E101: Stereotactic Brain Lesioning (IM) | F101: 6 | G101: 1 | H101: =SUBSTITUTE(D101,".","") -> 01590 | I101: Moderate Craniotomy Proc. | J101: P11AE | W101: =H101 -> 01590 | X101: 11 | Y101: =J101 -> P11AE | Z101: 1 | AA101: =I101 -> Moderate Craniotomy Proc.
A102: PDC | D102: 01.591 | E102: Excision of complex malignant brain tumor (IM) | F102: 6 | G102: 1 | H102: =SUBSTITUTE(D102,".","") -> 01591 | I102: Moderate Craniotomy Proc. | J102: P11AE | W102: =H102 -> 01591 | X102: 11 | Y102: =J102 -> P11AE | Z102: 1 | AA102: =I102 -> Moderate Craniotomy Proc.
A103: PDC | D103: 01.592 | E103: Excision of complex malignant brain tumor, eloquent location (IM) | F103: 6 | G103: 1 | H103: =SUBSTITUTE(D103,".","") -> 01592 | I103: Moderate Craniotomy Proc. | J103: P11AE | W103: =H103 -> 01592 | X103: 11 | Y103: =J103 -> P11AE | Z103: 1 | AA103: =I103 -> Moderate Craniotomy Proc.
A104: PDC | D104: 01.593 | E104: Excision of complex benign brain tumor (IM) | F104: 6 | G104: 1 | H104: =SUBSTITUTE(D104,".","") -> 01593 | I104: Moderate Craniotomy Proc. | J104: P11AE | W104: =H104 -> 01593 | X104: 11 | Y104: =J104 -> P11AE | Z104: 1 | AA104: =I104 -> Moderate Craniotomy Proc.
A105: PDC | D105: 01.594 | E105: Excision of complex benign brain tumor, eloquent location (IM) | F105: 6 | G105: 1 | H105: =SUBSTITUTE(D105,".","") -> 01594 | I105: Moderate Craniotomy Proc. | J105: P11AE | W105: =H105 -> 01594 | X105: 11 | Y105: =J105 -> P11AE | Z105: 1 | AA105: =I105 -> Moderate Craniotomy Proc.
A106: PDC | D106: 01.595 | E106: Excision of brainstem lesion (IM) | F106: 6 | G106: 1 | H106: =SUBSTITUTE(D106,".","") -> 01595 | I106: Moderate Craniotomy Proc. | J106: P11AE | W106: =H106 -> 01595 | X106: 11 | Y106: =J106 -> P11AE | Z106: 1 | AA106: =I106 -> Moderate Craniotomy Proc.
A107: PDC | B107: P11AB | C107: Complex Craniotomy | D107: 02.11 | E107: Simple suture of dura mater of brain | F107: =VLOOKUP($D107,proc!$A:$D,3,FALSE) -> 4 | G107: =VLOOKUP($D107,proc!$A:$D,4,FALSE) -> 0 | H107: =SUBSTITUTE(D107,".","") -> 0211 | I107: Simple Craniotomy Proc. | J107: =VLOOKUP(H107,'upload c51prpdc'!A:C,3,FALSE) -> P11AF | K107: =VLOOKUP($D107,'prosedur-2025'!$A:$H,3,FALSE) -> 168 | L107: =VLOOKUP($D107,'prosedur-2025'!$A:$H,4,FALSE) -> 83566802 | M107: =VLOOKUP($D107,'prosedur-2025'!$A:$H,5,FALSE) -> 38488509 | N107: =VLOOKUP($D107,'prosedur-2025'!$A:$H,6,FALSE) -> 62071998 | O107: =VLOOKUP($D107,'prosedur-2025'!$A:$H,7,FALSE) -> 98169594 | P107: =VLOOKUP($D107,'prosedur-2025'!$A:$H,8,FALSE) -> 149328410 | Q107: =K107*L107 -> 14039222741 | T107: =TEXT(VALUE(D107),"00.00") -> 02.11 | W107: =H107 -> 0211 | X107: 11 | Y107: =J107 -> P11AF | Z107: 1 | AA107: =I107 -> Simple Craniotomy Proc.
A108: PDC | B108: P11AB | C108: Complex Craniotomy | D108: 02.12 | E108: Other repair of cerebral meninges | F108: =VLOOKUP($D108,proc!$A:$D,3,FALSE) -> 5 | G108: =VLOOKUP($D108,proc!$A:$D,4,FALSE) -> 0 | H108: =SUBSTITUTE(D108,".","") -> 0212 | I108: Simple Craniotomy Proc. | J108: =VLOOKUP(H108,'upload c51prpdc'!A:C,3,FALSE) -> P11AF | K108: =VLOOKUP($D108,'prosedur-2025'!$A:$H,3,FALSE) -> 1334 | L108: =VLOOKUP($D108,'prosedur-2025'!$A:$H,4,FALSE) -> 86322441 | M108: =VLOOKUP($D108,'prosedur-2025'!$A:$H,5,FALSE) -> 38650703 | N108: =VLOOKUP($D108,'prosedur-2025'!$A:$H,6,FALSE) -> 62737121 | O108: =VLOOKUP($D108,'prosedur-2025'!$A:$H,7,FALSE) -> 107853383 | P108: =VLOOKUP($D108,'prosedur-2025'!$A:$H,8,FALSE) -> 170626108 | Q108: =K108*L108 -> 115154136706 | T108: =TEXT(VALUE(D108),"00.00") -> 02.12 | W108: =H108 -> 0212 | X108: 11 | Y108: =J108 -> P11AF | Z108: 1 | AA108: =I108 -> Simple Craniotomy Proc.
A109: PDC | B109: P11AB | C109: Complex Craniotomy | D109: 02.14 | E109: Choroid plexectomy | F109: =VLOOKUP($D109,proc!$A:$D,3,FALSE) -> 6 | G109: =VLOOKUP($D109,proc!$A:$D,4,FALSE) -> 0 | H109: =SUBSTITUTE(D109,".","") -> 0214 | I109: Moderate Craniotomy Proc. | J109: =VLOOKUP(H109,'upload c51prpdc'!A:C,3,FALSE) -> P11AE | K109: =VLOOKUP($D109,'prosedur-2025'!$A:$H,3,FALSE) -> 21 | L109: =VLOOKUP($D109,'prosedur-2025'!$A:$H,4,FALSE) -> 62699190 | M109: =VLOOKUP($D109,'prosedur-2025'!$A:$H,5,FALSE) -> 31925200 | N109: =VLOOKUP($D109,'prosedur-2025'!$A:$H,6,FALSE) -> 59272164 | O109: =VLOOKUP($D109,'prosedur-2025'!$A:$H,7,FALSE) -> 79566841 | P109: =VLOOKUP($D109,'prosedur-2025'!$A:$H,8,FALSE) -> 99396992 | Q109: =K109*L109 -> 1316682998 | T109: =TEXT(VALUE(D109),"00.00") -> 02.14 | W109: =H109 -> 0214 | X109: 11 | Y109: =J109 -> P11AE | Z109: 1 | AA109: =I109 -> Moderate Craniotomy Proc.
A110: PDC | B110: P11AB | C110: Complex Craniotomy | D110: 02.92 | E110: Repair of brain | F110: =VLOOKUP($D110,proc!$A:$D,3,FALSE) -> 5 | G110: =VLOOKUP($D110,proc!$A:$D,4,FALSE) -> 0 | H110: =SUBSTITUTE(D110,".","") -> 0292 | I110: Moderate Craniotomy Proc. | J110: =VLOOKUP(H110,'upload c51prpdc'!A:C,3,FALSE) -> P11AE | K110: =VLOOKUP($D110,'prosedur-2025'!$A:$H,3,FALSE) -> 17 | L110: =VLOOKUP($D110,'prosedur-2025'!$A:$H,4,FALSE) -> 61465499 | M110: =VLOOKUP($D110,'prosedur-2025'!$A:$H,5,FALSE) -> 34307200 | N110: =VLOOKUP($D110,'prosedur-2025'!$A:$H,6,FALSE) -> 43086923 | O110: =VLOOKUP($D110,'prosedur-2025'!$A:$H,7,FALSE) -> 60466754 | P110: =VLOOKUP($D110,'prosedur-2025'!$A:$H,8,FALSE) -> 136878500 | Q110: =K110*L110 -> 1044913482 | T110: =TEXT(VALUE(D110),"00.00") -> 02.92 | W110: =H110 -> 0292 | X110: 11 | Y110: =J110 -> P11AE | Z110: 1 | AA110: =I110 -> Moderate Craniotomy Proc.
A111: PDC | B111: P11AP | C111: Neuromodulation | D111: 02.93 | E111: Implantation or replacement of intracranial neurostimulator lead(s) | F111: =VLOOKUP($D111,proc!$A:$D,3,FALSE) -> 5 | G111: =VLOOKUP($D111,proc!$A:$D,4,FALSE) -> 0 | H111: =SUBSTITUTE(D111,".","") -> 0293 | I111: Neuromodulation Proc. | J111: =VLOOKUP(H111,'upload c51prpdc'!A:C,3,FALSE) -> P11AP | K111: =VLOOKUP($D111,'prosedur-2025'!$A:$H,3,FALSE) -> 12 | L111: =VLOOKUP($D111,'prosedur-2025'!$A:$H,4,FALSE) -> 1.2191113e+08 | M111: =VLOOKUP($D111,'prosedur-2025'!$A:$H,5,FALSE) -> 18882640 | N111: =VLOOKUP($D111,'prosedur-2025'!$A:$H,6,FALSE) -> 36337421 | O111: =VLOOKUP($D111,'prosedur-2025'!$A:$H,7,FALSE) -> 170459548 | P111: =VLOOKUP($D111,'prosedur-2025'!$A:$H,8,FALSE) -> 287488076 | Q111: =K111*L111 -> 1462933521 | T111: =TEXT(VALUE(D111),"00.00") -> 02.93 | W111: =H111 -> 0293 | X111: 11 | Y111: =J111 -> P11AP | Z111: 1 | AA111: =I111 -> Neuromodulation Proc.
A112: PDC | B112: P11AP | C112: Neuromodulation | D112: 02.930 | E112: Implantation of neurostimulator lead into vagus nerve (IM) | F112: =VLOOKUP($D112,proc!$A:$D,3,FALSE) -> 5 | G112: =VLOOKUP($D112,proc!$A:$D,4,FALSE) -> 1 | H112: =SUBSTITUTE(D112,".","") -> 02930 | I112: Neuromodulation Proc. | J112: =VLOOKUP(H112,'upload c51prpdc'!A:C,3,FALSE) -> P11AP | T112: =TEXT(VALUE(D112),"00.00") -> 02.93 | W112: =H112 -> 02930 | X112: 11 | Y112: =J112 -> P11AP | Z112: 1 | AA112: =I112 -> Neuromodulation Proc.
