Workbook

Sheet ranap
A1: Cluster Code | B1: Cluster Description | C1: PD | D1: acasc
C2: PDC P17AA Pancreas, Liver Resection & Shunt Proc.
C3: 50.22 | D3: Partial hepatectomy
C4: 50.3 | D4: Lobectomy of liver
C5: 50.4 | D5: Total hepatectomy
C6: 50.51 | D6: Auxiliary liver transplant
C7: 50.59 | D7: Other transplant of liver
C8: 50.61 | D8: Closure of laceration of liver
C9: 50.69 | D9: Other repair of liver
C10: 50.93 | D10: Localized perfusion of liver
C11: 52.3 | D11: Marsupialization of pancreatic cyst
C12: 52.4 | D12: Internal drainage of pancreatic cyst
C13: 52.51 | D13: Proximal pancreatectomy
C14: 52.52 | D14: Distal pancreatectomy
... C26: 52.92 | D26: Cannulation of pancreatic duct
C27: PDC P17AB Biliary Tract Proc.
C28: 51.01 | D28: Percutaneous aspiration of gallbladder
C29: 51.31 | D29: Anastomosis of gallbladder to hepatic ducts
C30: 51.32 | D30: Anastomosis of gallbladder to intestine
C31: 51.33 | D31: Anastomosis of gallbladder to pancreas
C32: 51.34 | D32: Anastomosis of gallbladder to stomach
C33: 51.35 | D33: Other gallbladder anastomosis
C34: 51.36 | D34: Choledochoenterostomy
C35: 51.37 | D35: Anastomosis of hepatic duct to gastrointestinal tract
C36: 51.39 | D36: Other bile duct anastomosis
C37: 51.41 | D37: Common duct exploration for removal of calculus
C38: 51.42 | D38: Common duct exploration for relief of other obstruction
C39: 51.43 | D39: Insertion of choledochohepatic tube for decompression
... C55: 51.98 | D55: Other percutaneous procedures on biliary tract
C56: PDC P17AC Pancreas & Liver Proc. except Resection
C57: 17.63 | D57: Laser interstitial thermal therapy [LITT] of lesion or tissue of liver under guidance
C58: 50.14 | D58: Laparoscopic liver biopsy
C59: 50.21 | D59: Marsupialization of lesion of liver
C60: 50.23 | D60: Open ablation of liver lesion or tissue
C61: 50.24 | D61: Percutaneous ablation of liver lesion or tissue
C62: 50.25 | D62: Laparoscopic ablation of liver lesion or tissue
C63: 50.26 | D63: Other and unspecified ablation of liver lesion or tissue
C64: 50.29 | D64: Other destruction of lesion of liver
C65: 51.02 | D65: Trocar cholecystostomy
C66: 51.03 | D66: Other cholecystostomy
C67: 51.04 | D67: Other cholecystotomy
C68: 51.13 | D68: Open biopsy of gallbladder or bile ducts
C69: 51.19 | D69: Other diagnostic procedures on biliary tract
C70: PDC P17AD Laparoroscopic Cholecystectomy Proc.
C71: 51.23 | D71: Laparoscopic cholecystectomy
C72: 51.24 | D72: Laparoscopic partial cholecystectomy
C73: PDC P17AE Cholecystectomy Proc.
C74: 51.21 | D74: Other partial cholecystectomy
C75: 51.22 | D75: Cholecystectomy
C76: PDC P17AF Hepatobiliary Diagnostic Proc.
C77: 50.13 | D77: Transjugular liver biopsy
C78: 51.12 | D78: Percutaneous biopsy of gallbladder or bile ducts
C79: 52.11 | D79: Closed [aspiration] [needle] [percutaneous] biopsy of pancreas
C80: 52.12 | D80: Open biopsy of pancreas
C81: 52.19 | D81: Other diagnostic procedures on pancreas
C82: 87.53 | D82: Intraoperative cholangiogram
C83: PDC P17AG Other Hepatobiliary & Pancreas Proc.
C84: 38.86 | D84: Other surgical occlusion of vessels, abdominal arteries
C85: 50.0 | D85: Hepatotomy
C86: 50.11 | D86: Closed (percutaneous) [needle] biopsy of liver
C87: 50.12 | D87: Open biopsy of liver
C88: 50.19 | D88: Other diagnostic procedures on liver
C89: 50.91 | D89: Percutaneous aspiration of liver
C90: 50.92 | D90: Extracorporeal hepatic assistance
C91: 50.94 | D91: Other injection of therapeutic substance into liver
C92: 50.99 | D92: Other operations on liver
C93: 51.92 | D93: Closure of cholecystostomy
C94: 51.99 | D94: Other operations on biliary tract
C95: 52.01 | D95: Drainage of pancreatic cyst by catheter
... C106: 99.15 | D106: Parenteral infusion of concentrated nutritional substances
C107: PDC P17AH ERCP w Therapeutic Procedures
C108: 51.81 | D108: Dilation of sphincter of Oddi
C109: 51.82 | D109: Pancreatic sphincterotomy
C110: 51.83 | D110: Pancreatic sphincteroplasty
C111: 51.84 | D111: Endoscopic dilation of ampulla and biliary duct
C112: 51.85 | D112: Endoscopic sphincterotomy and papillotomy
C113: 51.86 | D113: Endoscopic insertion of nasobiliary drainage tube
C114: 51.87 | D114: Endoscopic insertion of stent (tube) into bile duct
C115: 51.88 | D115: Endoscopic removal of stone(s) from biliary tract
C116: 51.89 | D116: Other operations on sphincter of Oddi
C117: 51.95 | D117: Removal of prosthetic device from bile duct
C118: 52.21 | D118: Endoscopic excision or destruction of lesion or tissue of pancreatic duct
C119: 52.93 | D119: Endoscopic insertion of stent (tube) into pancreatic duct
... C124: 97.05 | D124: Replacement of stent (tube) in biliary or pancreatic duct
C125: PDC P17AJ ERCP Procedures
C126: 51.10 | D126: Endoscopic retrograde cholangiopancreatography [ERCP]
C127: 51.11 | D127: Endoscopic retrograde cholangiography [ERC]
C128: 51.14 | D128: Other closed [endoscopic] biopsy of biliary duct or sphincter of Oddi
C129: 51.15 | D129: Pressure measurement of sphincter of Oddi
C130: 52.13 | D130: Endoscopic retrograde pancreatography [ERP]
C131: 52.14 | D131: Closed [endoscopic] biopsy of pancreatic duct
C132: 46.21 | D132: Temporary ileostomy
C133: 46.22 | D133: Continent ileostomy
C134: 46.23 | D134: Other permanent ileostomy
C135: 46.50 | D135: Closure of intestinal stoma, not otherwise specified
C136: 46.51 | D136: Closure of stoma of small intestine
C137: 46.52 | D137: Closure of stoma of large intestine
... C218: 45.43 | D218: Endoscopic destruction of other lesion or tissue of large intestine
C219: PDC
C220: 45.02 | D220: Other incision of small intestine
...

Sheet rajal cluster icd10_web20260922
A1: Cluster Type | B1: Cluster Code | C1: Cluster Description | D1: ICD-10 Code | E1: ICD-10-Description
A2: PDC | B2: D17AA | C2: Chirosis And Alcholic Hepatitis | D2: ="K70.0" -> K70.0 | E2: Alcoholic fatty liver
A3: PDC | B3: D17AA | C3: Chirosis And Alcholic Hepatitis | D3: ="K70.1" -> K70.1 | E3: Alcoholic hepatitis
A4: PDC | B4: D17AA | C4: Chirosis And Alcholic Hepatitis | D4: ="K70.2" -> K70.2 | E4: Alcoholic fibrosis and sclerosis of liver
A5: PDC | B5: D17AA | C5: Chirosis And Alcholic Hepatitis | D5: ="K70.3" -> K70.3 | E5: Alcoholic cirrhosis of liver
A6: PDC | B6: D17AA | C6: Chirosis And Alcholic Hepatitis | D6: ="K70.4" -> K70.4 | E6: Alcoholic hepatic failure
A7: PDC | B7: D17AA | C7: Chirosis And Alcholic Hepatitis | D7: ="K70.9" -> K70.9 | E7: Alcoholic liver disease, unspecified
A8: PDC | B8: D17AA | C8: Chirosis And Alcholic Hepatitis | D8: ="K72.0" -> K72.0 | E8: Acute and subacute hepatic failure
A9: PDC | B9: D17AA | C9: Chirosis And Alcholic Hepatitis | D9: ="K72.1" -> K72.1 | E9: Chronic hepatic failure
A10: PDC | B10: D17AA | C10: Chirosis And Alcholic Hepatitis | D10: ="K72.9" -> K72.9 | E10: Hepatic failure, unspecified
A11: PDC | B11: D17AA | C11: Chirosis And Alcholic Hepatitis | D11: ="K74.0" -> K74.0 | E11: Hepatic fibrosis
A12: PDC | B12: D17AA | C12: Chirosis And Alcholic Hepatitis | D12: ="K74.1" -> K74.1 | E12: Hepatic sclerosis
A13: PDC | B13: D17AA | C13: Chirosis And Alcholic Hepatitis | D13: ="K74.2" -> K74.2 | E13: Hepatic fibrosis with hepatic sclerosis
A14: PDC | B14: D17AA | C14: Chirosis And Alcholic Hepatitis | D14: ="K74.3" -> K74.3 | E14: Primary biliary cirrhosis
A15: PDC | B15: D17AA | C15: Chirosis And Alcholic Hepatitis | D15: ="K74.4" -> K74.4 | E15: Secondary biliary cirrhosis
A16: PDC | B16: D17AA | C16: Chirosis And Alcholic Hepatitis | D16: ="K74.5" -> K74.5 | E16: Biliary cirrhosis, unspecified
A17: PDC | B17: D17AA | C17: Chirosis And Alcholic Hepatitis | D17: ="K74.6" -> K74.6 | E17: Other and unspecified cirrhosis of liver
A18: PDC | B18: D17AA | C18: Chirosis And Alcholic Hepatitis | D18: ="K76.6" -> K76.6 | E18: Portal hypertension
A19: PDC | B19: D17AA | C19: Chirosis And Alcholic Hepatitis | D19: ="K76.7" -> K76.7 | E19: Hepatorenal syndrome
A20: PDC | B20: D17AB | C20: Malignancy Of Hepatobiliary Or Pancreas | D20: ="C22.0" -> C22.0 | E20: Malignant neoplasm, liver cell carcinoma
A21: PDC | B21: D17AB | C21: Malignancy Of Hepatobiliary Or Pancreas | D21: ="C22.1" -> C22.1 | E21: Malignant neoplasm, intrahepatic bile duct carcinoma
A22: PDC | B22: D17AB | C22: Malignancy Of Hepatobiliary Or Pancreas | D22: ="C22.2" -> C22.2 | E22: Malignant neoplasm, hepatoblastoma
A23: PDC | B23: D17AB | C23: Malignancy Of Hepatobiliary Or Pancreas | D23: ="C22.3" -> C22.3 | E23: Malignant neoplasm, angiosarcoma of liver
A24: PDC | B24: D17AB | C24: Malignancy Of Hepatobiliary Or Pancreas | D24: ="C22.4" -> C22.4 | E24: Malignant neoplasm, other sarcomas of liver
A25: PDC | B25: D17AB | C25: Malignancy Of Hepatobiliary Or Pancreas | D25: ="C22.7" -> C22.7 | E25: Malignant neoplasm, other specified carcinomas of liver
A26: PDC | B26: D17AB | C26: Malignancy Of Hepatobiliary Or Pancreas | D26: ="C22.9" -> C22.9 | E26: Malignant neoplasm, liver, unspecified
A27: PDC | B27: D17AB | C27: Malignancy Of Hepatobiliary Or Pancreas | D27: ="C23" -> C23 | E27: Malignant neoplasm of gallbladder
A28: PDC | B28: D17AB | C28: Malignancy Of Hepatobiliary Or Pancreas | D28: ="C24.0" -> C24.0 | E28: Malignant neoplasm, extrahepatic bile duct
A29: PDC | B29: D17AB | C29: Malignancy Of Hepatobiliary Or Pancreas | D29: ="C24.1" -> C24.1 | E29: Malignant neoplasm, ampulla of vater
A30: PDC | B30: D17AB | C30: Malignancy Of Hepatobiliary Or Pancreas | D30: ="C24.8" -> C24.8 | E30: Malignant neoplasm, overlapping lesion of biliary tract
A31: PDC | B31: D17AB | C31: Malignancy Of Hepatobiliary Or Pancreas | D31: ="C24.9" -> C24.9 | E31: Malignant neoplasm, biliary tract, unspecified
A32: PDC | B32: D17AB | C32: Malignancy Of Hepatobiliary Or Pancreas | D32: ="C25.0" -> C25.0 | E32: Malignant neoplasm, head of pancreas
A33: PDC | B33: D17AB | C33: Malignancy Of Hepatobiliary Or Pancreas | D33: ="C25.1" -> C25.1 | E33: Malignant neoplasm, body of pancreas
A34: PDC | B34: D17AB | C34: Malignancy Of Hepatobiliary Or Pancreas | D34: ="C25.2" -> C25.2 | E34: Malignant neoplasm, tail of pancreas
A35: PDC | B35: D17AB | C35: Malignancy Of Hepatobiliary Or Pancreas | D35: ="C25.3" -> C25.3 | E35: Malignant neoplasm, pancreatic duct
A36: PDC | B36: D17AB | C36: Malignancy Of Hepatobiliary Or Pancreas | D36: ="C25.4" -> C25.4 | E36: Malignant neoplasm, endocrine pancreas
A37: PDC | B37: D17AB | C37: Malignancy Of Hepatobiliary Or Pancreas | D37: ="C25.7" -> C25.7 | E37: Malignant neoplasm, other parts of pancreas
A38: PDC | B38: D17AB | C38: Malignancy Of Hepatobiliary Or Pancreas | D38: ="C25.8" -> C25.8 | E38: Malignant neoplasm, overlapping lesion of pancreas
A39: PDC | B39: D17AB | C39: Malignancy Of Hepatobiliary Or Pancreas | D39: ="C25.9" -> C25.9 | E39: Malignant neoplasm, pancreas, unspecified
A40: PDC | B40: D17AB | C40: Malignancy Of Hepatobiliary Or Pancreas | D40: ="C78.7" -> C78.7 | E40: Secondary malignant neoplasm of liver
A41: PDC | B41: D17AB | C41: Malignancy Of Hepatobiliary Or Pancreas | D41: ="D01.5" -> D01.5 | E41: Carcinoma in situ of liver, gallbladder and bile ducts
A42: PDC | B42: D17AB | C42: Malignancy Of Hepatobiliary Or Pancreas | D42: ="D37.6" -> D37.6 | E42: Neoplasm of uncertain or unknown behaviour of liver, gallbladder and bile ducts
A43: PDC | B43: D17AC | C43: Disorder Of Pancreas, Except Malignancy | D43: ="B26.3" -> B26.3 | E43: Mumps pancreatitis
A44: PDC | B44: D17AC | C44: Disorder Of Pancreas, Except Malignancy | D44: ="D13.6" -> D13.6 | E44: Benign neoplasm, pancreas
A45: PDC | B45: D17AC | C45: Disorder Of Pancreas, Except Malignancy | D45: ="K85.0" -> K85.0 | E45: Idiopathic acute pancreatitis
A46: PDC | B46: D17AC | C46: Disorder Of Pancreas, Except Malignancy | D46: ="K85.1" -> K85.1 | E46: Biliary acute pancreatitis
A47: PDC | B47: D17AC | C47: Disorder Of Pancreas, Except Malignancy | D47: ="K85.2" -> K85.2 | E47: Alcohol-induced acute pancreatitis
A48: PDC | B48: D17AC | C48: Disorder Of Pancreas, Except Malignancy | D48: ="K85.3" -> K85.3 | E48: Drug-induced acute pancreatitis
A49: PDC | B49: D17AC | C49: Disorder Of Pancreas, Except Malignancy | D49: ="K85.8" -> K85.8 | E49: Other acute pancreatitis
A50: PDC | B50: D17AC | C50: Disorder Of Pancreas, Except Malignancy | D50: ="K85.9" -> K85.9 | E50: Acute pancreatitis, unspecified
A51: PDC | B51: D17AC | C51: Disorder Of Pancreas, Except Malignancy | D51: ="K86.0" -> K86.0 | E51: Alcohol-induced chronic pancreatitis
A52: PDC | B52: D17AC | C52: Disorder Of Pancreas, Except Malignancy | D52: ="K86.1" -> K86.1 | E52: Other chronic pancreatitis
A53: PDC | B53: D17AC | C53: Disorder Of Pancreas, Except Malignancy | D53: ="K86.2" -> K86.2 | E53: Cyst of pancreas
A54: PDC | B54: D17AC | C54: Disorder Of Pancreas, Except Malignancy | D54: ="K86.3" -> K86.3 | E54: Pseudocyst of pancreas
A55: PDC | B55: D17AC | C55: Disorder Of Pancreas, Except Malignancy | D55: ="K86.8" -> K86.8 | E55: Other specified diseases of pancreas
A56: PDC | B56: D17AC | C56: Disorder Of Pancreas, Except Malignancy | D56: ="K86.9" -> K86.9 | E56: Disease of pancreas, unspecified
A57: PDC | B57: D17AC | C57: Disorder Of Pancreas, Except Malignancy | D57: ="Q45.1" -> Q45.1 | E57: Annular pancreas
A58: PDC | B58: D17AC | C58: Disorder Of Pancreas, Except Malignancy | D58: ="Q45.2" -> Q45.2 | E58: Congenital pancreatic cyst
A59: PDC | B59: D17AC | C59: Disorder Of Pancreas, Except Malignancy | D59: ="S36.20" -> S36.20 | E59: Injury of pancreas, without open wound into cavity
A60: PDC | B60: D17AC | C60: Disorder Of Pancreas, Except Malignancy | D60: ="S36.21" -> S36.21 | E60: Injury of pancreas, with open wound into cavity
A61: PDC | B61: D17AD | C61: Disorder Of Liver, Except Malignancy , Cirhosis, Alcoholic Hepatitis | D61: ="A06.4" -> A06.4 | E61: Amoebic liver abscess
A62: PDC | B62: D17AD | C62: Disorder Of Liver, Except Malignancy , Cirhosis, Alcoholic Hepatitis | D62: ="B15.0" -> B15.0 | E62: Hepatitis a with hepatic coma
A63: PDC | B63: D17AD | C63: Disorder Of Liver, Except Malignancy , Cirhosis, Alcoholic Hepatitis | D63: ="B15.9" -> B15.9 | E63: Hepatitis a without hepatic coma
A64: PDC | B64: D17AD | C64: Disorder Of Liver, Except Malignancy , Cirhosis, Alcoholic Hepatitis | D64: ="B16.0" -> B16.0 | E64: Acute hepatitis b with delta-agent (coinfection) with hepatitis coma
A65: PDC | B65: D17AD | C65: Disorder Of Liver, Except Malignancy , Cirhosis, Alcoholic Hepatitis | D65: ="B16.1" -> B16.1 | E65: Acute hepatitis b with delta-agent (coinfection) without hepatitis coma
A66: PDC | B66: D17AD | C66: Disorder Of Liver, Except Malignancy , Cirhosis, Alcoholic Hepatitis | D66: ="B16.2" -> B16.2 | E66: Acute hepatitis b without delta-agent with hepatic coma
A67: PDC | B67: D17AD | C67: Disorder Of Liver, Except Malignancy , Cirhosis, Alcoholic Hepatitis | D67: ="B16.9" -> B16.9 | E67: Acute hepatitis b without delta-agent and without hepatatitis coma
A68: PDC | B68: D17AD | C68: Disorder Of Liver, Except Malignancy , Cirhosis, Alcoholic Hepatitis | D68: ="B17.0" -> B17.0 | E68: Acute delta-(super)infection of hepatitis b carrier
A69: PDC | B69: D17AD | C69: Disorder Of Liver, Except Malignancy , Cirhosis, Alcoholic Hepatitis | D69: ="B17.1" -> B17.1 | E69: Acute hepatitis c
A70: PDC | B70: D17AD | C70: Disorder Of Liver, Except Malignancy , Cirhosis, Alcoholic Hepatitis | D70: ="B17.2" -> B17.2 | E70: Acute hepatitis e
A71: PDC | B71: D17AD | C71: Disorder Of Liver, Except Malignancy , Cirhosis, Alcoholic Hepatitis | D71: ="B17.8" -> B17.8 | E71: Other specified acute viral hepatitis
A72: PDC | B72: D17AD | C72: Disorder Of Liver, Except Malignancy , Cirhosis, Alcoholic Hepatitis | D72: ="B17.9" -> B17.9 | E72: Acute viral hepatitis, unspecified
A73: PDC | B73: D17AD | C73: Disorder Of Liver, Except Malignancy , Cirhosis, Alcoholic Hepatitis | D73: ="B18.0" -> B18.0 | E73: Chronic viral hepatitis b with delta-agent
A74: PDC | B74: D17AD | C74: Disorder Of Liver, Except Malignancy , Cirhosis, Alcoholic Hepatitis | D74: ="B18.1" -> B18.1 | E74: Chronic viral hepatitis b without delta-agent
A75: PDC | B75: D17AD | C75: Disorder Of Liver, Except Malignancy , Cirhosis, Alcoholic Hepatitis | D75: ="B18.10" -> B18.10 | E75: Chronic viral hepatitis B without delta-agent (IM)
A76: PDC | B76: D17AD | C76: Disorder Of Liver, Except Malignancy , Cirhosis, Alcoholic Hepatitis | D76: ="B18.19" -> B18.19 | E76: Chronic hepatitis B, unspecified delta agent status (IM)
A77: PDC | B77: D17AD | C77: Disorder Of Liver, Except Malignancy , Cirhosis, Alcoholic Hepatitis | D77: ="B18.2" -> B18.2 | E77: Chronic viral hepatitis c
A78: PDC | B78: D17AD | C78: Disorder Of Liver, Except Malignancy , Cirhosis, Alcoholic Hepatitis | D78: ="B18.8" -> B18.8 | E78: Other chronic viral hepatitis
A79: PDC | B79: D17AD | C79: Disorder Of Liver, Except Malignancy , Cirhosis, Alcoholic Hepatitis | D79: ="B18.9" -> B18.9 | E79: Chronic viral hepatitis, unspecified
A80: PDC | B80: D17AD | C80: Disorder Of Liver, Except Malignancy , Cirhosis, Alcoholic Hepatitis | D80: ="B19.0" -> B19.0 | E80: Unspecified viral hepatitis hepatic with coma
A81: PDC | B81: D17AD | C81: Disorder Of Liver, Except Malignancy , Cirhosis, Alcoholic Hepatitis | D81: ="B19.9" -> B19.9 | E81: Unspecified viral hepatitis without hepatic coma
A82: PDC | B82: D17AD | C82: Disorder Of Liver, Except Malignancy , Cirhosis, Alcoholic Hepatitis | D82: ="B25.1" -> B25.1 | E82: Cytomegaloviral hepatitis
A83: PDC | B83: D17AD | C83: Disorder Of Liver, Except Malignancy , Cirhosis, Alcoholic Hepatitis | D83: ="B25.2" -> B25.2 | E83: Cytomegaloviral pancreatitis
A84: PDC | B84: D17AD | C84: Disorder Of Liver, Except Malignancy , Cirhosis, Alcoholic Hepatitis | D84: ="B58.1" -> B58.1 | E84: Toxoplasma hepatitis
A85: PDC | B85: D17AD | C85: Disorder Of Liver, Except Malignancy , Cirhosis, Alcoholic Hepatitis | D85: ="B65.1" -> B65.1 | E85: Schistosom due schis mansoni [intest schistosom]
A86: PDC | B86: D17AD | C86: Disorder Of Liver, Except Malignancy , Cirhosis, Alcoholic Hepatitis | D86: ="B66.0" -> B66.0 | E86: Opisthorchiasis
A87: PDC | B87: D17AD | C87: Disorder Of Liver, Except Malignancy , Cirhosis, Alcoholic Hepatitis | D87: ="B66.1" -> B66.1 | E87: Clonorchiasis
A88: PDC | B88: D17AD | C88: Disorder Of Liver, Except Malignancy , Cirhosis, Alcoholic Hepatitis | D88: ="B66.3" -> B66.3 | E88: Fascioliasis
A89: PDC | B89: D17AD | C89: Disorder Of Liver, Except Malignancy , Cirhosis, Alcoholic Hepatitis | D89: ="B66.5" -> B66.5 | E89: Fasciolopsiasis
A90: PDC | B90: D17AD | C90: Disorder Of Liver, Except Malignancy , Cirhosis, Alcoholic Hepatitis | D90: ="B67.0" -> B67.0 | E90: Echinococcus granulosus infection of liver
A91: PDC | B91: D17AD | C91: Disorder Of Liver, Except Malignancy , Cirhosis, Alcoholic Hepatitis | D91: ="B67.5" -> B67.5 | E91: Echinococcus multilocularis infection of liver
A92: PDC | B92: D17AD | C92: Disorder Of Liver, Except Malignancy , Cirhosis, Alcoholic Hepatitis | D92: ="B67.8" -> B67.8 | E92: Echinococcosis, unspecified, of liver
A93: PDC | B93: D17AD | C93: Disorder Of Liver, Except Malignancy , Cirhosis, Alcoholic Hepatitis | D93: ="D13.4" -> D13.4 | E93: Benign neoplasm, liver
A94: PDC | B94: D17AD | C94: Disorder Of Liver, Except Malignancy , Cirhosis, Alcoholic Hepatitis | D94: ="D18.02" -> D18.02 | E94: Haemangioma, liver (IM)
A95: PDC | B95: D17AD | C95: Disorder Of Liver, Except Malignancy , Cirhosis, Alcoholic Hepatitis | D95: ="E80.4" -> E80.4 | E95: Gilbert's syndrome
A96: PDC | B96: D17AD | C96: Disorder Of Liver, Except Malignancy , Cirhosis, Alcoholic Hepatitis | D96: ="E80.5" -> E80.5 | E96: Crigler-najjar syndrome
A97: PDC | B97: D17AD | C97: Disorder Of Liver, Except Malignancy , Cirhosis, Alcoholic Hepatitis | D97: ="E80.6" -> E80.6 | E97: Other disorders of bilirubin metabolism
A98: PDC | B98: D17AD | C98: Disorder Of Liver, Except Malignancy , Cirhosis, Alcoholic Hepatitis | D98: ="E80.7" -> E80.7 | E98: Disorder of bilirubin metabolism, unspecified
A99: PDC | B99: D17AD | C99: Disorder Of Liver, Except Malignancy , Cirhosis, Alcoholic Hepatitis | D99: ="I81" -> I81 | E99: Portal vein thrombosis
A100: PDC | B100: D17AD | C100: Disorder Of Liver, Except Malignancy , Cirhosis, Alcoholic Hepatitis | D100: ="I82.0" -> I82.0 | E100: Budd-chiari syndrome
...

Sheet rajal cluster icd9cm_web2026092
A1: Cluster Type | B1: Cluster Code | C1: Cluster Description | D1: ICD-9-CM Code | E1: ICD-9-CM Description
A2: PDC | B2: P17KL | C2: ERCP Diagnostic | D2: ="51.10" -> 51.10 | E2: Endoscopic retrograde cholangiopancreatography [ERCP]
A3: PDC | B3: P17KL | C3: ERCP Diagnostic | D3: ="51.11" -> 51.11 | E3: Endoscopic retrograde cholangiography [ERC]
A4: PDC | B4: P17KL | C4: ERCP Diagnostic | D4: ="51.14" -> 51.14 | E4: Other closed [endoscopic] biopsy of biliary duct or sphincter of Oddi
A5: PDC | B5: P17KL | C5: ERCP Diagnostic | D5: ="51.15" -> 51.15 | E5: Pressure measurement of sphincter of Oddi
A6: PDC | B6: P17KL | C6: ERCP Diagnostic | D6: ="52.13" -> 52.13 | E6: Endoscopic retrograde pancreatography [ERP]
A7: PDC | B7: P17KJ | C7: Other Hepatobiliary Major Proc. | D7: ="50.11" -> 50.11 | E7: Closed (percutaneous) [needle] biopsy of liver
A8: PDC | B8: P17KJ | C8: Other Hepatobiliary Major Proc. | D8: ="50.19" -> 50.19 | E8: Other diagnostic procedures on liver
A9: PDC | B9: P17KJ | C9: Other Hepatobiliary Major Proc. | D9: ="50.91" -> 50.91 | E9: Percutaneous aspiration of liver
A10: PDC | B10: P17KJ | C10: Other Hepatobiliary Major Proc. | D10: ="50.93" -> 50.93 | E10: Localized perfusion of liver
A11: PDC | B11: P17KJ | C11: Other Hepatobiliary Major Proc. | D11: ="50.94" -> 50.94 | E11: Other injection of therapeutic substance into liver
A12: PDC | B12: P17KJ | C12: Other Hepatobiliary Major Proc. | D12: ="51.01" -> 51.01 | E12: Percutaneous aspiration of gallbladder
A13: PDC | B13: P17KJ | C13: Other Hepatobiliary Major Proc. | D13: ="51.12" -> 51.12 | E13: Percutaneous biopsy of gallbladder or bile ducts
A14: PDC | B14: P17KJ | C14: Other Hepatobiliary Major Proc. | D14: ="51.19" -> 51.19 | E14: Other diagnostic procedures on biliary tract
A15: PDC | B15: P17KJ | C15: Other Hepatobiliary Major Proc. | D15: ="51.96" -> 51.96 | E15: Percutaneous extraction of common duct stones
A16: PDC | B16: P17KJ | C16: Other Hepatobiliary Major Proc. | D16: ="51.98" -> 51.98 | E16: Other percutaneous procedures on biliary tract
A17: PDC | B17: P17KJ | C17: Other Hepatobiliary Major Proc. | D17: ="52.11" -> 52.11 | E17: Closed [aspiration] [needle] [percutaneous] biopsy of pancreas
A18: PDC | B18: P17KJ | C18: Other Hepatobiliary Major Proc. | D18: ="52.14" -> 52.14 | E18: Closed [endoscopic] biopsy of pancreatic duct
A19: PDC | B19: P17KJ | C19: Other Hepatobiliary Major Proc. | D19: ="52.19" -> 52.19 | E19: Other diagnostic procedures on pancreas
A20: PDC | B20: P17KJ | C20: Other Hepatobiliary Major Proc. | D20: ="54.24" -> 54.24 | E20: Closed [percutaneous] [needle] biopsy of intra-abdominal mass
A21: PDC | B21: P17KJ | C21: Other Hepatobiliary Major Proc. | D21: ="87.53" -> 87.53 | E21: Intraoperative cholangiogram
A22: PDC | B22: P17KH | C22: Other Hepatobiliary Minor Proc. | D22: ="50.99" -> 50.99 | E22: Other operations on liver
A23: PDC | B23: P17KH | C23: Other Hepatobiliary Minor Proc. | D23: ="96.41" -> 96.41 | E23: Irrigation of cholecystostomy and other biliary tube
A24: PDC | B24: P17KH | C24: Other Hepatobiliary Minor Proc. | D24: ="96.42" -> 96.42 | E24: Irrigation of pancreatic tube
A25: PDC | B25: P17KH | C25: Other Hepatobiliary Minor Proc. | D25: ="97.54" -> 97.54 | E25: Removal of cholecystostomy tube
A26: PDC | B26: P17KH | C26: Other Hepatobiliary Minor Proc. | D26: ="97.55" -> 97.55 | E26: Removal of t-tube, other bile duct tube, or liver tube
A27: PDC | B27: P17KH | C27: Other Hepatobiliary Minor Proc. | D27: ="97.56" -> 97.56 | E27: Removal of pancreatic tube or drain
A28: AX | B28: 17PBX | C28: Laparoscopic Procedures | D28: ="50.40" -> 50.40 | E28: Laparoscopic liver resection (IM)
A29: AX | B29: 17PBX | C29: Laparoscopic Procedures | D29: ="52.50" -> 52.50 | E29: Laparoscopic partial pancreatectomy (IM)
A30: AX | B30: 17PBX | C30: Laparoscopic Procedures | D30: ="52.60" -> 52.60 | E30: Laparoscopic total pancreatectomy (IM)
A31: AX | B31: 17PBX | C31: Laparoscopic Procedures | D31: ="52.70" -> 52.70 | E31: Laparoscopic pancreaticoduodenectomy (IM)
A32: AX | B32: 17PCX | C32: Closed Common Duct Exploration Procedures | D32: ="51.10" -> 51.10 | E32: Endoscopic retrograde cholangiopancreatography [ERCP]
A33: AX | B33: 17PCX | C33: Closed Common Duct Exploration Procedures | D33: ="51.11" -> 51.11 | E33: Endoscopic retrograde cholangiography [ERC]
A34: AX | B34: 17PCX | C34: Closed Common Duct Exploration Procedures | D34: ="51.14" -> 51.14 | E34: Other closed [endoscopic] biopsy of biliary duct or sphincter of Oddi
A35: AX | B35: 17PCX | C35: Closed Common Duct Exploration Procedures | D35: ="51.15" -> 51.15 | E35: Pressure measurement of sphincter of Oddi
A36: AX | B36: 17PCX | C36: Closed Common Duct Exploration Procedures | D36: ="51.64" -> 51.64 | E36: Endoscopic excision or destruction of lesion of biliary ducts or sphincter of Oddi
A37: AX | B37: 17PCX | C37: Closed Common Duct Exploration Procedures | D37: ="51.84" -> 51.84 | E37: Endoscopic dilation of ampulla and biliary duct
A38: AX | B38: 17PCX | C38: Closed Common Duct Exploration Procedures | D38: ="51.85" -> 51.85 | E38: Endoscopic sphincterotomy and papillotomy
A39: AX | B39: 17PCX | C39: Closed Common Duct Exploration Procedures | D39: ="51.86" -> 51.86 | E39: Endoscopic insertion of nasobiliary drainage tube
A40: AX | B40: 17PCX | C40: Closed Common Duct Exploration Procedures | D40: ="51.87" -> 51.87 | E40: Endoscopic insertion of stent (tube) into bile duct
A41: AX | B41: 17PCX | C41: Closed Common Duct Exploration Procedures | D41: ="51.88" -> 51.88 | E41: Endoscopic removal of stone(s) from biliary tract
A42: AX | B42: 17PCX | C42: Closed Common Duct Exploration Procedures | D42: ="51.96" -> 51.96 | E42: Percutaneous extraction of common duct stones
A43: AX | B43: 17PCX | C43: Closed Common Duct Exploration Procedures | D43: ="51.98" -> 51.98 | E43: Other percutaneous procedures on biliary tract
A44: AX | B44: 17PDX | D44: ="54.21" -> 54.21 | E44: Laparoscopy
A45: AX | B45: 17PDX | D45: ="54.24" -> 54.24 | E45: Closed [percutaneous] [needle] biopsy of intra-abdominal mass
A46: AX | B46: 17PDX | D46: ="87.51" -> 87.51 | E46: Percutaneous hepatic cholangiogram
A47: AX | B47: 17PDX | D47: ="87.52" -> 87.52 | E47: Intravenous cholangiogram
A48: AX | B48: 17PDX | D48: ="87.54" -> 87.54 | E48: Other cholangiogram
A49: AX | B49: 17PDX | D49: ="87.59" -> 87.59 | E49: Other biliary tract x-ray
A50: AX | B50: 17PDX | D50: ="87.66" -> 87.66 | E50: Contrast pancreatogram
A51: AX | B51: 17PDX | D51: ="88.01" -> 88.01 | E51: Computerized axial tomography of abdomen
A52: AX | B52: 17PDX | D52: ="88.02" -> 88.02 | E52: Other abdomen tomography
A53: AX | B53: 17PDX | D53: ="88.04" -> 88.04 | E53: Abdominal lymphangiogram
A54: AX | B54: 17PDX | D54: ="88.47" -> 88.47 | E54: Arteriography of other intra-abdominal arteries
A55: AX | B55: 17PDX | D55: ="88.64" -> 88.64 | E55: Phlebography of the portal venous system using contrast material
A56: AX | B56: 17PDX | D56: ="88.74" -> 88.74 | E56: Diagnostic ultrasound of digestive system
A57: AX | B57: 17PDX | D57: ="88.97" -> 88.97 | E57: Magnetic resonance imaging of other and unspecified sites
A58: AX | B58: 17PDX | D58: ="92.02" -> 92.02 | E58: Liver scan and radioisotope function study
A59: AX | B59: 17PDX | D59: ="92.14" -> 92.14 | E59: Bone scan
A60: AX | B60: 17PDX | D60: ="92.18" -> 92.18 | E60: Total body scan

Sheet ranap cluster icd9cm_web2026092
A1: Cluster Type | B1: Cluster Code | C1: Cluster Description | D1: ICD-9-CM Code | E1: ICD-9-CM Description
A2: PDC | B2: P17AA | C2: Pancreas, Liver Resection & Shunt Proc. | D2: ="50.22" -> 50.22 | E2: Partial hepatectomy
A3: PDC | B3: P17AA | C3: Pancreas, Liver Resection & Shunt Proc. | D3: ="50.3" -> 50.3 | E3: Lobectomy of liver
A4: PDC | B4: P17AA | C4: Pancreas, Liver Resection & Shunt Proc. | D4: ="50.4" -> 50.4 | E4: Total hepatectomy
A5: PDC | B5: P17AA | C5: Pancreas, Liver Resection & Shunt Proc. | D5: ="50.51" -> 50.51 | E5: Auxiliary liver transplant
A6: PDC | B6: P17AA | C6: Pancreas, Liver Resection & Shunt Proc. | D6: ="50.59" -> 50.59 | E6: Other transplant of liver
A7: PDC | B7: P17AA | C7: Pancreas, Liver Resection & Shunt Proc. | D7: ="50.61" -> 50.61 | E7: Closure of laceration of liver
A8: PDC | B8: P17AA | C8: Pancreas, Liver Resection & Shunt Proc. | D8: ="50.69" -> 50.69 | E8: Other repair of liver
A9: PDC | B9: P17AA | C9: Pancreas, Liver Resection & Shunt Proc. | D9: ="50.93" -> 50.93 | E9: Localized perfusion of liver
A10: PDC | B10: P17AA | C10: Pancreas, Liver Resection & Shunt Proc. | D10: ="52.3" -> 52.3 | E10: Marsupialization of pancreatic cyst
A11: PDC | B11: P17AA | C11: Pancreas, Liver Resection & Shunt Proc. | D11: ="52.4" -> 52.4 | E11: Internal drainage of pancreatic cyst
A12: PDC | B12: P17AA | C12: Pancreas, Liver Resection & Shunt Proc. | D12: ="52.51" -> 52.51 | E12: Proximal pancreatectomy
A13: PDC | B13: P17AA | C13: Pancreas, Liver Resection & Shunt Proc. | D13: ="52.52" -> 52.52 | E13: Distal pancreatectomy
A14: PDC | B14: P17AA | C14: Pancreas, Liver Resection & Shunt Proc. | D14: ="52.53" -> 52.53 | E14: Radical subtotal pancreatectomy
A15: PDC | B15: P17AA | C15: Pancreas, Liver Resection & Shunt Proc. | D15: ="52.59" -> 52.59 | E15: Other partial pancreatectomy
A16: PDC | B16: P17AA | C16: Pancreas, Liver Resection & Shunt Proc. | D16: ="52.6" -> 52.6 | E16: Total pancreatectomy
A17: PDC | B17: P17AA | C17: Pancreas, Liver Resection & Shunt Proc. | D17: ="52.7" -> 52.7 | E17: Radical pancreaticoduodenectomy
A18: PDC | B18: P17AA | C18: Pancreas, Liver Resection & Shunt Proc. | D18: ="52.80" -> 52.80 | E18: Pancreatic transplant, not otherwise specified
A19: PDC | B19: P17AA | C19: Pancreas, Liver Resection & Shunt Proc. | D19: ="52.81" -> 52.81 | E19: Reimplantation of pancreatic tissue
A20: PDC | B20: P17AA | C20: Pancreas, Liver Resection & Shunt Proc. | D20: ="52.82" -> 52.82 | E20: Homotransplant of pancreas
A21: PDC | B21: P17AA | C21: Pancreas, Liver Resection & Shunt Proc. | D21: ="52.83" -> 52.83 | E21: Heterotransplant of pancreas
A22: PDC | B22: P17AA | C22: Pancreas, Liver Resection & Shunt Proc. | D22: ="52.84" -> 52.84 | E22: Autotransplantation of cells of Islets of Langerhans
A23: PDC | B23: P17AA | C23: Pancreas, Liver Resection & Shunt Proc. | D23: ="52.85" -> 52.85 | E23: Allotransplantation of cells of Islets of Langerhans
A24: PDC | B24: P17AA | C24: Pancreas, Liver Resection & Shunt Proc. | D24: ="52.86" -> 52.86 | E24: Transplantation of cells of Islets of Langerhans, not otherwise specified
A25: PDC | B25: P17AA | C25: Pancreas, Liver Resection & Shunt Proc. | D25: ="52.92" -> 52.92 | E25: Cannulation of pancreatic duct
A26: PDC | B26: P17AB | C26: Biliary Tract Proc. | D26: ="51.01" -> 51.01 | E26: Percutaneous aspiration of gallbladder
A27: PDC | B27: P17AB | C27: Biliary Tract Proc. | D27: ="51.31" -> 51.31 | E27: Anastomosis of gallbladder to hepatic ducts
A28: PDC | B28: P17AB | C28: Biliary Tract Proc. | D28: ="51.32" -> 51.32 | E28: Anastomosis of gallbladder to intestine
A29: PDC | B29: P17AB | C29: Biliary Tract Proc. | D29: ="51.33" -> 51.33 | E29: Anastomosis of gallbladder to pancreas
A30: PDC | B30: P17AB | C30: Biliary Tract Proc. | D30: ="51.34" -> 51.34 | E30: Anastomosis of gallbladder to stomach
A31: PDC | B31: P17AB | C31: Biliary Tract Proc. | D31: ="51.35" -> 51.35 | E31: Other gallbladder anastomosis
A32: PDC | B32: P17AB | C32: Biliary Tract Proc. | D32: ="51.36" -> 51.36 | E32: Choledochoenterostomy
A33: PDC | B33: P17AB | C33: Biliary Tract Proc. | D33: ="51.37" -> 51.37 | E33: Anastomosis of hepatic duct to gastrointestinal tract
A34: PDC | B34: P17AB | C34: Biliary Tract Proc. | D34: ="51.39" -> 51.39 | E34: Other bile duct anastomosis
A35: PDC | B35: P17AB | C35: Biliary Tract Proc. | D35: ="51.41" -> 51.41 | E35: Common duct exploration for removal of calculus
A36: PDC | B36: P17AB | C36: Biliary Tract Proc. | D36: ="51.42" -> 51.42 | E36: Common duct exploration for relief of other obstruction
A37: PDC | B37: P17AB | C37: Biliary Tract Proc. | D37: ="51.43" -> 51.43 | E37: Insertion of choledochohepatic tube for decompression
A38: PDC | B38: P17AB | C38: Biliary Tract Proc. | D38: ="51.49" -> 51.49 | E38: Incision of other bile ducts for relief of obstruction
A39: PDC | B39: P17AB | C39: Biliary Tract Proc. | D39: ="51.51" -> 51.51 | E39: Exploration of common duct
A40: PDC | B40: P17AB | C40: Biliary Tract Proc. | D40: ="51.59" -> 51.59 | E40: Other incision of other bile duct
A41: PDC | B41: P17AB | C41: Biliary Tract Proc. | D41: ="51.61" -> 51.61 | E41: Excision of cystic duct remnant
A42: PDC | B42: P17AB | C42: Biliary Tract Proc. | D42: ="51.62" -> 51.62 | E42: Excision of ampulla of vater (with reimplantation of common duct)
A43: PDC | B43: P17AB | C43: Biliary Tract Proc. | D43: ="51.63" -> 51.63 | E43: Other excision of common duct
A44: PDC | B44: P17AB | C44: Biliary Tract Proc. | D44: ="51.64" -> 51.64 | E44: Endoscopic excision or destruction of lesion of biliary ducts or sphincter of Oddi
A45: PDC | B45: P17AB | C45: Biliary Tract Proc. | D45: ="51.69" -> 51.69 | E45: Excision of other bile duct
A46: PDC | B46: P17AB | C46: Biliary Tract Proc. | D46: ="51.71" -> 51.71 | E46: Simple suture of common bile duct
A47: PDC | B47: P17AB | C47: Biliary Tract Proc. | D47: ="51.72" -> 51.72 | E47: Choledochoplasty
A48: PDC | B48: P17AB | C48: Biliary Tract Proc. | D48: ="51.79" -> 51.79 | E48: Repair of other bile ducts
A49: PDC | B49: P17AB | C49: Biliary Tract Proc. | D49: ="51.91" -> 51.91 | E49: Repair of laceration of gallbladder
A50: PDC | B50: P17AB | C50: Biliary Tract Proc. | D50: ="51.93" -> 51.93 | E50: Closure of other biliary fistula
A51: PDC | B51: P17AB | C51: Biliary Tract Proc. | D51: ="51.94" -> 51.94 | E51: Revision of anastomosis of biliary tract
A52: PDC | B52: P17AB | C52: Biliary Tract Proc. | D52: ="51.96" -> 51.96 | E52: Percutaneous extraction of common duct stones
A53: PDC | B53: P17AB | C53: Biliary Tract Proc. | D53: ="51.98" -> 51.98 | E53: Other percutaneous procedures on biliary tract
A54: PDC | B54: P17AC | C54: Pancreas & Liver Proc. except Resection | D54: ="17.63" -> 17.63 | E54: Laser interstitial thermal therapy [LITT] of lesion or tissue of liver under guidance
A55: PDC | B55: P17AC | C55: Pancreas & Liver Proc. except Resection | D55: ="50.14" -> 50.14 | E55: Laparoscopic liver biopsy
A56: PDC | B56: P17AC | C56: Pancreas & Liver Proc. except Resection | D56: ="50.21" -> 50.21 | E56: Marsupialization of lesion of liver
A57: PDC | B57: P17AC | C57: Pancreas & Liver Proc. except Resection | D57: ="50.23" -> 50.23 | E57: Open ablation of liver lesion or tissue
A58: PDC | B58: P17AC | C58: Pancreas & Liver Proc. except Resection | D58: ="50.24" -> 50.24 | E58: Percutaneous ablation of liver lesion or tissue
A59: PDC | B59: P17AC | C59: Pancreas & Liver Proc. except Resection | D59: ="50.25" -> 50.25 | E59: Laparoscopic ablation of liver lesion or tissue
A60: PDC | B60: P17AC | C60: Pancreas & Liver Proc. except Resection | D60: ="50.26" -> 50.26 | E60: Other and unspecified ablation of liver lesion or tissue
A61: PDC | B61: P17AC | C61: Pancreas & Liver Proc. except Resection | D61: ="50.29" -> 50.29 | E61: Other destruction of lesion of liver
A62: PDC | B62: P17AC | C62: Pancreas & Liver Proc. except Resection | D62: ="51.02" -> 51.02 | E62: Trocar cholecystostomy
A63: PDC | B63: P17AC | C63: Pancreas & Liver Proc. except Resection | D63: ="51.03" -> 51.03 | E63: Other cholecystostomy
A64: PDC | B64: P17AC | C64: Pancreas & Liver Proc. except Resection | D64: ="51.04" -> 51.04 | E64: Other cholecystotomy
A65: PDC | B65: P17AC | C65: Pancreas & Liver Proc. except Resection | D65: ="51.13" -> 51.13 | E65: Open biopsy of gallbladder or bile ducts
A66: PDC | B66: P17AC | C66: Pancreas & Liver Proc. except Resection | D66: ="51.19" -> 51.19 | E66: Other diagnostic procedures on biliary tract
A67: PDC | B67: P17AD | C67: Laparoroscopic Cholecystectomy Proc. | D67: ="51.23" -> 51.23 | E67: Laparoscopic cholecystectomy
A68: PDC | B68: P17AD | C68: Laparoroscopic Cholecystectomy Proc. | D68: ="51.24" -> 51.24 | E68: Laparoscopic partial cholecystectomy
A69: PDC | B69: P17AE | C69: Cholecystectomy Proc. | D69: ="51.21" -> 51.21 | E69: Other partial cholecystectomy
A70: PDC | B70: P17AE | C70: Cholecystectomy Proc. | D70: ="51.22" -> 51.22 | E70: Cholecystectomy
A71: PDC | B71: P17AF | C71: Hepatobiliary Diagnostic Proc. | D71: ="50.13" -> 50.13 | E71: Transjugular liver biopsy
A72: PDC | B72: P17AF | C72: Hepatobiliary Diagnostic Proc. | D72: ="51.12" -> 51.12 | E72: Percutaneous biopsy of gallbladder or bile ducts
A73: PDC | B73: P17AF | C73: Hepatobiliary Diagnostic Proc. | D73: ="52.11" -> 52.11 | E73: Closed [aspiration] [needle] [percutaneous] biopsy of pancreas
A74: PDC | B74: P17AF | C74: Hepatobiliary Diagnostic Proc. | D74: ="52.12" -> 52.12 | E74: Open biopsy of pancreas
A75: PDC | B75: P17AF | C75: Hepatobiliary Diagnostic Proc. | D75: ="52.19" -> 52.19 | E75: Other diagnostic procedures on pancreas
A76: PDC | B76: P17AF | C76: Hepatobiliary Diagnostic Proc. | D76: ="87.53" -> 87.53 | E76: Intraoperative cholangiogram
A77: PDC | B77: P17AG | C77: Other Hepatobiliary & Pancreas Proc. | D77: ="38.86" -> 38.86 | E77: Other surgical occlusion of vessels, abdominal arteries
A78: PDC | B78: P17AG | C78: Other Hepatobiliary & Pancreas Proc. | D78: ="50.0" -> 50.0 | E78: Hepatotomy
A79: PDC | B79: P17AG | C79: Other Hepatobiliary & Pancreas Proc. | D79: ="50.11" -> 50.11 | E79: Closed (percutaneous) [needle] biopsy of liver
A80: PDC | B80: P17AG | C80: Other Hepatobiliary & Pancreas Proc. | D80: ="50.12" -> 50.12 | E80: Open biopsy of liver
A81: PDC | B81: P17AG | C81: Other Hepatobiliary & Pancreas Proc. | D81: ="50.19" -> 50.19 | E81: Other diagnostic procedures on liver
A82: PDC | B82: P17AG | C82: Other Hepatobiliary & Pancreas Proc. | D82: ="50.91" -> 50.91 | E82: Percutaneous aspiration of liver
A83: PDC | B83: P17AG | C83: Other Hepatobiliary & Pancreas Proc. | D83: ="50.92" -> 50.92 | E83: Extracorporeal hepatic assistance
A84: PDC | B84: P17AG | C84: Other Hepatobiliary & Pancreas Proc. | D84: ="50.94" -> 50.94 | E84: Other injection of therapeutic substance into liver
A85: PDC | B85: P17AG | C85: Other Hepatobiliary & Pancreas Proc. | D85: ="50.99" -> 50.99 | E85: Other operations on liver
A86: PDC | B86: P17AG | C86: Other Hepatobiliary & Pancreas Proc. | D86: ="51.92" -> 51.92 | E86: Closure of cholecystostomy
A87: PDC | B87: P17AG | C87: Other Hepatobiliary & Pancreas Proc. | D87: ="51.99" -> 51.99 | E87: Other operations on biliary tract
A88: PDC | B88: P17AG | C88: Other Hepatobiliary & Pancreas Proc. | D88: ="52.01" -> 52.01 | E88: Drainage of pancreatic cyst by catheter
A89: PDC | B89: P17AG | C89: Other Hepatobiliary & Pancreas Proc. | D89: ="52.09" -> 52.09 | E89: Other pancreatotomy
A90: PDC | B90: P17AG | C90: Other Hepatobiliary & Pancreas Proc. | D90: ="52.22" -> 52.22 | E90: Other excision or destruction of lesion or tissue of pancreas or pancreatic duct
A91: PDC | B91: P17AG | C91: Other Hepatobiliary & Pancreas Proc. | D91: ="52.95" -> 52.95 | E91: Other repair of pancreas
A92: PDC | B92: P17AG | C92: Other Hepatobiliary & Pancreas Proc. | D92: ="52.99" -> 52.99 | E92: Other operations on pancreas
A93: PDC | B93: P17AG | C93: Other Hepatobiliary & Pancreas Proc. | D93: ="96.41" -> 96.41 | E93: Irrigation of cholecystostomy and other biliary tube
A94: PDC | B94: P17AG | C94: Other Hepatobiliary & Pancreas Proc. | D94: ="96.42" -> 96.42 | E94: Irrigation of pancreatic tube
A95: PDC | B95: P17AG | C95: Other Hepatobiliary & Pancreas Proc. | D95: ="97.54" -> 97.54 | E95: Removal of cholecystostomy tube
A96: PDC | B96: P17AG | C96: Other Hepatobiliary & Pancreas Proc. | D96: ="97.55" -> 97.55 | E96: Removal of t-tube, other bile duct tube, or liver tube
A97: PDC | B97: P17AG | C97: Other Hepatobiliary & Pancreas Proc. | D97: ="97.56" -> 97.56 | E97: Removal of pancreatic tube or drain
A98: PDC | B98: P17AG | C98: Other Hepatobiliary & Pancreas Proc. | D98: ="98.52" -> 98.52 | E98: Extracorporeal shockwave lithotripsy [ESWL] of the gallbladder and/or bile duct
A99: PDC | B99: P17AG | C99: Other Hepatobiliary & Pancreas Proc. | D99: ="99.15" -> 99.15 | E99: Parenteral infusion of concentrated nutritional substances
A100: PDC | B100: P17AH | C100: ERCP w Therapeutic Procedures | D100: ="51.81" -> 51.81 | E100: Dilation of sphincter of Oddi
...

Sheet ranap cluster icd10_web20260922
A1: Cluster Type | B1: Cluster Code | C1: Cluster Description | D1: ICD-10 Code | E1: ICD-10 Description
A2: PDC | B2: D17AA | C2: Chirosis And Alcholic Hepatitis | D2: ="K70.0" -> K70.0 | E2: Alcoholic fatty liver
A3: PDC | B3: D17AA | C3: Chirosis And Alcholic Hepatitis | D3: ="K70.1" -> K70.1 | E3: Alcoholic hepatitis
A4: PDC | B4: D17AA | C4: Chirosis And Alcholic Hepatitis | D4: ="K70.2" -> K70.2 | E4: Alcoholic fibrosis and sclerosis of liver
A5: PDC | B5: D17AA | C5: Chirosis And Alcholic Hepatitis | D5: ="K70.3" -> K70.3 | E5: Alcoholic cirrhosis of liver
A6: PDC | B6: D17AA | C6: Chirosis And Alcholic Hepatitis | D6: ="K70.4" -> K70.4 | E6: Alcoholic hepatic failure
A7: PDC | B7: D17AA | C7: Chirosis And Alcholic Hepatitis | D7: ="K70.9" -> K70.9 | E7: Alcoholic liver disease, unspecified
A8: PDC | B8: D17AA | C8: Chirosis And Alcholic Hepatitis | D8: ="K72.0" -> K72.0 | E8: Acute and subacute hepatic failure
A9: PDC | B9: D17AA | C9: Chirosis And Alcholic Hepatitis | D9: ="K72.1" -> K72.1 | E9: Chronic hepatic failure
A10: PDC | B10: D17AA | C10: Chirosis And Alcholic Hepatitis | D10: ="K72.9" -> K72.9 | E10: Hepatic failure, unspecified
A11: PDC | B11: D17AA | C11: Chirosis And Alcholic Hepatitis | D11: ="K74.0" -> K74.0 | E11: Hepatic fibrosis
A12: PDC | B12: D17AA | C12: Chirosis And Alcholic Hepatitis | D12: ="K74.1" -> K74.1 | E12: Hepatic sclerosis
A13: PDC | B13: D17AA | C13: Chirosis And Alcholic Hepatitis | D13: ="K74.2" -> K74.2 | E13: Hepatic fibrosis with hepatic sclerosis
A14: PDC | B14: D17AA | C14: Chirosis And Alcholic Hepatitis | D14: ="K74.3" -> K74.3 | E14: Primary biliary cirrhosis
A15: PDC | B15: D17AA | C15: Chirosis And Alcholic Hepatitis | D15: ="K74.4" -> K74.4 | E15: Secondary biliary cirrhosis
A16: PDC | B16: D17AA | C16: Chirosis And Alcholic Hepatitis | D16: ="K74.5" -> K74.5 | E16: Biliary cirrhosis, unspecified
A17: PDC | B17: D17AA | C17: Chirosis And Alcholic Hepatitis | D17: ="K74.6" -> K74.6 | E17: Other and unspecified cirrhosis of liver
A18: PDC | B18: D17AA | C18: Chirosis And Alcholic Hepatitis | D18: ="K76.6" -> K76.6 | E18: Portal hypertension
A19: PDC | B19: D17AA | C19: Chirosis And Alcholic Hepatitis | D19: ="K76.7" -> K76.7 | E19: Hepatorenal syndrome
A20: PDC | B20: D17AB | C20: Malignancy Of Hepatobiliary Or Pancreas | D20: ="C22.0" -> C22.0 | E20: Malignant neoplasm, liver cell carcinoma
A21: PDC | B21: D17AB | C21: Malignancy Of Hepatobiliary Or Pancreas | D21: ="C22.1" -> C22.1 | E21: Malignant neoplasm, intrahepatic bile duct carcinoma
A22: PDC | B22: D17AB | C22: Malignancy Of Hepatobiliary Or Pancreas | D22: ="C22.2" -> C22.2 | E22: Malignant neoplasm, hepatoblastoma
A23: PDC | B23: D17AB | C23: Malignancy Of Hepatobiliary Or Pancreas | D23: ="C22.3" -> C22.3 | E23: Malignant neoplasm, angiosarcoma of liver
A24: PDC | B24: D17AB | C24: Malignancy Of Hepatobiliary Or Pancreas | D24: ="C22.4" -> C22.4 | E24: Malignant neoplasm, other sarcomas of liver
A25: PDC | B25: D17AB | C25: Malignancy Of Hepatobiliary Or Pancreas | D25: ="C22.7" -> C22.7 | E25: Malignant neoplasm, other specified carcinomas of liver
A26: PDC | B26: D17AB | C26: Malignancy Of Hepatobiliary Or Pancreas | D26: ="C22.9" -> C22.9 | E26: Malignant neoplasm, liver, unspecified
A27: PDC | B27: D17AB | C27: Malignancy Of Hepatobiliary Or Pancreas | D27: ="C23" -> C23 | E27: Malignant neoplasm of gallbladder
A28: PDC | B28: D17AB | C28: Malignancy Of Hepatobiliary Or Pancreas | D28: ="C24.0" -> C24.0 | E28: Malignant neoplasm, extrahepatic bile duct
A29: PDC | B29: D17AB | C29: Malignancy Of Hepatobiliary Or Pancreas | D29: ="C24.1" -> C24.1 | E29: Malignant neoplasm, ampulla of vater
A30: PDC | B30: D17AB | C30: Malignancy Of Hepatobiliary Or Pancreas | D30: ="C24.8" -> C24.8 | E30: Malignant neoplasm, overlapping lesion of biliary tract
A31: PDC | B31: D17AB | C31: Malignancy Of Hepatobiliary Or Pancreas | D31: ="C24.9" -> C24.9 | E31: Malignant neoplasm, biliary tract, unspecified
A32: PDC | B32: D17AB | C32: Malignancy Of Hepatobiliary Or Pancreas | D32: ="C25.0" -> C25.0 | E32: Malignant neoplasm, head of pancreas
A33: PDC | B33: D17AB | C33: Malignancy Of Hepatobiliary Or Pancreas | D33: ="C25.1" -> C25.1 | E33: Malignant neoplasm, body of pancreas
A34: PDC | B34: D17AB | C34: Malignancy Of Hepatobiliary Or Pancreas | D34: ="C25.2" -> C25.2 | E34: Malignant neoplasm, tail of pancreas
A35: PDC | B35: D17AB | C35: Malignancy Of Hepatobiliary Or Pancreas | D35: ="C25.3" -> C25.3 | E35: Malignant neoplasm, pancreatic duct
A36: PDC | B36: D17AB | C36: Malignancy Of Hepatobiliary Or Pancreas | D36: ="C25.4" -> C25.4 | E36: Malignant neoplasm, endocrine pancreas
A37: PDC | B37: D17AB | C37: Malignancy Of Hepatobiliary Or Pancreas | D37: ="C25.7" -> C25.7 | E37: Malignant neoplasm, other parts of pancreas
A38: PDC | B38: D17AB | C38: Malignancy Of Hepatobiliary Or Pancreas | D38: ="C25.8" -> C25.8 | E38: Malignant neoplasm, overlapping lesion of pancreas
A39: PDC | B39: D17AB | C39: Malignancy Of Hepatobiliary Or Pancreas | D39: ="C25.9" -> C25.9 | E39: Malignant neoplasm, pancreas, unspecified
A40: PDC | B40: D17AB | C40: Malignancy Of Hepatobiliary Or Pancreas | D40: ="C78.7" -> C78.7 | E40: Secondary malignant neoplasm of liver
A41: PDC | B41: D17AB | C41: Malignancy Of Hepatobiliary Or Pancreas | D41: ="D01.5" -> D01.5 | E41: Carcinoma in situ of liver, gallbladder and bile ducts
A42: PDC | B42: D17AB | C42: Malignancy Of Hepatobiliary Or Pancreas | D42: ="D37.6" -> D37.6 | E42: Neoplasm of uncertain or unknown behaviour of liver, gallbladder and bile ducts
A43: PDC | B43: D17AC | C43: Disorder Of Pancreas, Except Malignancy | D43: ="B26.3" -> B26.3 | E43: Mumps pancreatitis
A44: PDC | B44: D17AC | C44: Disorder Of Pancreas, Except Malignancy | D44: ="D13.6" -> D13.6 | E44: Benign neoplasm, pancreas
A45: PDC | B45: D17AC | C45: Disorder Of Pancreas, Except Malignancy | D45: ="K85.0" -> K85.0 | E45: Idiopathic acute pancreatitis
A46: PDC | B46: D17AC | C46: Disorder Of Pancreas, Except Malignancy | D46: ="K85.1" -> K85.1 | E46: Biliary acute pancreatitis
A47: PDC | B47: D17AC | C47: Disorder Of Pancreas, Except Malignancy | D47: ="K85.2" -> K85.2 | E47: Alcohol-induced acute pancreatitis
A48: PDC | B48: D17AC | C48: Disorder Of Pancreas, Except Malignancy | D48: ="K85.3" -> K85.3 | E48: Drug-induced acute pancreatitis
A49: PDC | B49: D17AC | C49: Disorder Of Pancreas, Except Malignancy | D49: ="K85.8" -> K85.8 | E49: Other acute pancreatitis
A50: PDC | B50: D17AC | C50: Disorder Of Pancreas, Except Malignancy | D50: ="K85.9" -> K85.9 | E50: Acute pancreatitis, unspecified
A51: PDC | B51: D17AC | C51: Disorder Of Pancreas, Except Malignancy | D51: ="K86.0" -> K86.0 | E51: Alcohol-induced chronic pancreatitis
A52: PDC | B52: D17AC | C52: Disorder Of Pancreas, Except Malignancy | D52: ="K86.1" -> K86.1 | E52: Other chronic pancreatitis
A53: PDC | B53: D17AC | C53: Disorder Of Pancreas, Except Malignancy | D53: ="K86.2" -> K86.2 | E53: Cyst of pancreas
A54: PDC | B54: D17AC | C54: Disorder Of Pancreas, Except Malignancy | D54: ="K86.3" -> K86.3 | E54: Pseudocyst of pancreas
A55: PDC | B55: D17AC | C55: Disorder Of Pancreas, Except Malignancy | D55: ="K86.8" -> K86.8 | E55: Other specified diseases of pancreas
A56: PDC | B56: D17AC | C56: Disorder Of Pancreas, Except Malignancy | D56: ="K86.9" -> K86.9 | E56: Disease of pancreas, unspecified
A57: PDC | B57: D17AC | C57: Disorder Of Pancreas, Except Malignancy | D57: ="Q45.1" -> Q45.1 | E57: Annular pancreas
A58: PDC | B58: D17AC | C58: Disorder Of Pancreas, Except Malignancy | D58: ="Q45.2" -> Q45.2 | E58: Congenital pancreatic cyst
A59: PDC | B59: D17AC | C59: Disorder Of Pancreas, Except Malignancy | D59: ="S36.20" -> S36.20 | E59: Injury of pancreas, without open wound into cavity
A60: PDC | B60: D17AC | C60: Disorder Of Pancreas, Except Malignancy | D60: ="S36.21" -> S36.21 | E60: Injury of pancreas, with open wound into cavity
A61: PDC | B61: D17AD | C61: Disorder Of Liver, Except Malignancy , Cirhosis, Alcoholic Hepatitis | D61: ="A06.4" -> A06.4 | E61: Amoebic liver abscess
A62: PDC | B62: D17AD | C62: Disorder Of Liver, Except Malignancy , Cirhosis, Alcoholic Hepatitis | D62: ="B15.0" -> B15.0 | E62: Hepatitis a with hepatic coma
A63: PDC | B63: D17AD | C63: Disorder Of Liver, Except Malignancy , Cirhosis, Alcoholic Hepatitis | D63: ="B15.9" -> B15.9 | E63: Hepatitis a without hepatic coma
A64: PDC | B64: D17AD | C64: Disorder Of Liver, Except Malignancy , Cirhosis, Alcoholic Hepatitis | D64: ="B16.0" -> B16.0 | E64: Acute hepatitis b with delta-agent (coinfection) with hepatitis coma
A65: PDC | B65: D17AD | C65: Disorder Of Liver, Except Malignancy , Cirhosis, Alcoholic Hepatitis | D65: ="B16.1" -> B16.1 | E65: Acute hepatitis b with delta-agent (coinfection) without hepatitis coma
A66: PDC | B66: D17AD | C66: Disorder Of Liver, Except Malignancy , Cirhosis, Alcoholic Hepatitis | D66: ="B16.2" -> B16.2 | E66: Acute hepatitis b without delta-agent with hepatic coma
A67: PDC | B67: D17AD | C67: Disorder Of Liver, Except Malignancy , Cirhosis, Alcoholic Hepatitis | D67: ="B16.9" -> B16.9 | E67: Acute hepatitis b without delta-agent and without hepatatitis coma
A68: PDC | B68: D17AD | C68: Disorder Of Liver, Except Malignancy , Cirhosis, Alcoholic Hepatitis | D68: ="B17.0" -> B17.0 | E68: Acute delta-(super)infection of hepatitis b carrier
A69: PDC | B69: D17AD | C69: Disorder Of Liver, Except Malignancy , Cirhosis, Alcoholic Hepatitis | D69: ="B17.1" -> B17.1 | E69: Acute hepatitis c
A70: PDC | B70: D17AD | C70: Disorder Of Liver, Except Malignancy , Cirhosis, Alcoholic Hepatitis | D70: ="B17.2" -> B17.2 | E70: Acute hepatitis e
A71: PDC | B71: D17AD | C71: Disorder Of Liver, Except Malignancy , Cirhosis, Alcoholic Hepatitis | D71: ="B17.8" -> B17.8 | E71: Other specified acute viral hepatitis
A72: PDC | B72: D17AD | C72: Disorder Of Liver, Except Malignancy , Cirhosis, Alcoholic Hepatitis | D72: ="B17.9" -> B17.9 | E72: Acute viral hepatitis, unspecified
A73: PDC | B73: D17AD | C73: Disorder Of Liver, Except Malignancy , Cirhosis, Alcoholic Hepatitis | D73: ="B18.0" -> B18.0 | E73: Chronic viral hepatitis b with delta-agent
A74: PDC | B74: D17AD | C74: Disorder Of Liver, Except Malignancy , Cirhosis, Alcoholic Hepatitis | D74: ="B18.1" -> B18.1 | E74: Chronic viral hepatitis b without delta-agent
A75: PDC | B75: D17AD | C75: Disorder Of Liver, Except Malignancy , Cirhosis, Alcoholic Hepatitis | D75: ="B18.10" -> B18.10 | E75: Chronic viral hepatitis B without delta-agent (IM)
A76: PDC | B76: D17AD | C76: Disorder Of Liver, Except Malignancy , Cirhosis, Alcoholic Hepatitis | D76: ="B18.19" -> B18.19 | E76: Chronic hepatitis B, unspecified delta agent status (IM)
A77: PDC | B77: D17AD | C77: Disorder Of Liver, Except Malignancy , Cirhosis, Alcoholic Hepatitis | D77: ="B18.2" -> B18.2 | E77: Chronic viral hepatitis c
A78: PDC | B78: D17AD | C78: Disorder Of Liver, Except Malignancy , Cirhosis, Alcoholic Hepatitis | D78: ="B18.8" -> B18.8 | E78: Other chronic viral hepatitis
A79: PDC | B79: D17AD | C79: Disorder Of Liver, Except Malignancy , Cirhosis, Alcoholic Hepatitis | D79: ="B18.9" -> B18.9 | E79: Chronic viral hepatitis, unspecified
A80: PDC | B80: D17AD | C80: Disorder Of Liver, Except Malignancy , Cirhosis, Alcoholic Hepatitis | D80: ="B19.0" -> B19.0 | E80: Unspecified viral hepatitis hepatic with coma
A81: PDC | B81: D17AD | C81: Disorder Of Liver, Except Malignancy , Cirhosis, Alcoholic Hepatitis | D81: ="B19.9" -> B19.9 | E81: Unspecified viral hepatitis without hepatic coma
A82: PDC | B82: D17AD | C82: Disorder Of Liver, Except Malignancy , Cirhosis, Alcoholic Hepatitis | D82: ="B25.1" -> B25.1 | E82: Cytomegaloviral hepatitis
A83: PDC | B83: D17AD | C83: Disorder Of Liver, Except Malignancy , Cirhosis, Alcoholic Hepatitis | D83: ="B25.2" -> B25.2 | E83: Cytomegaloviral pancreatitis
A84: PDC | B84: D17AD | C84: Disorder Of Liver, Except Malignancy , Cirhosis, Alcoholic Hepatitis | D84: ="B58.1" -> B58.1 | E84: Toxoplasma hepatitis
A85: PDC | B85: D17AD | C85: Disorder Of Liver, Except Malignancy , Cirhosis, Alcoholic Hepatitis | D85: ="B65.1" -> B65.1 | E85: Schistosom due schis mansoni [intest schistosom]
A86: PDC | B86: D17AD | C86: Disorder Of Liver, Except Malignancy , Cirhosis, Alcoholic Hepatitis | D86: ="B66.0" -> B66.0 | E86: Opisthorchiasis
A87: PDC | B87: D17AD | C87: Disorder Of Liver, Except Malignancy , Cirhosis, Alcoholic Hepatitis | D87: ="B66.1" -> B66.1 | E87: Clonorchiasis
A88: PDC | B88: D17AD | C88: Disorder Of Liver, Except Malignancy , Cirhosis, Alcoholic Hepatitis | D88: ="B66.3" -> B66.3 | E88: Fascioliasis
A89: PDC | B89: D17AD | C89: Disorder Of Liver, Except Malignancy , Cirhosis, Alcoholic Hepatitis | D89: ="B66.5" -> B66.5 | E89: Fasciolopsiasis
A90: PDC | B90: D17AD | C90: Disorder Of Liver, Except Malignancy , Cirhosis, Alcoholic Hepatitis | D90: ="B67.0" -> B67.0 | E90: Echinococcus granulosus infection of liver
A91: PDC | B91: D17AD | C91: Disorder Of Liver, Except Malignancy , Cirhosis, Alcoholic Hepatitis | D91: ="B67.5" -> B67.5 | E91: Echinococcus multilocularis infection of liver
A92: PDC | B92: D17AD | C92: Disorder Of Liver, Except Malignancy , Cirhosis, Alcoholic Hepatitis | D92: ="B67.8" -> B67.8 | E92: Echinococcosis, unspecified, of liver
A93: PDC | B93: D17AD | C93: Disorder Of Liver, Except Malignancy , Cirhosis, Alcoholic Hepatitis | D93: ="D13.4" -> D13.4 | E93: Benign neoplasm, liver
A94: PDC | B94: D17AD | C94: Disorder Of Liver, Except Malignancy , Cirhosis, Alcoholic Hepatitis | D94: ="D18.02" -> D18.02 | E94: Haemangioma, liver (IM)
A95: PDC | B95: D17AD | C95: Disorder Of Liver, Except Malignancy , Cirhosis, Alcoholic Hepatitis | D95: ="E80.4" -> E80.4 | E95: Gilbert's syndrome
A96: PDC | B96: D17AD | C96: Disorder Of Liver, Except Malignancy , Cirhosis, Alcoholic Hepatitis | D96: ="E80.5" -> E80.5 | E96: Crigler-najjar syndrome
A97: PDC | B97: D17AD | C97: Disorder Of Liver, Except Malignancy , Cirhosis, Alcoholic Hepatitis | D97: ="E80.6" -> E80.6 | E97: Other disorders of bilirubin metabolism
A98: PDC | B98: D17AD | C98: Disorder Of Liver, Except Malignancy , Cirhosis, Alcoholic Hepatitis | D98: ="E80.7" -> E80.7 | E98: Disorder of bilirubin metabolism, unspecified
A99: PDC | B99: D17AD | C99: Disorder Of Liver, Except Malignancy , Cirhosis, Alcoholic Hepatitis | D99: ="I81" -> I81 | E99: Portal vein thrombosis
A100: PDC | B100: D17AD | C100: Disorder Of Liver, Except Malignancy , Cirhosis, Alcoholic Hepatitis | D100: ="I82.0" -> I82.0 | E100: Budd-chiari syndrome
...

Sheet rajal
A1: P15KH | B1: Peripheral Angioplasty Proc. | C1: PDC
C2: PDC P17KL ERCP Diagnostic
C3: 51.10 | D3: Endoscopic retrograde cholangiopancreatography [ERCP]
A4: P16KU | B4: Endoscopy of Upper Gastrointestinal Major Proc. | C4: PDC
C5: 51.11 | D5: Endoscopic retrograde cholangiography [ERC]
C6: 51.14 | D6: Other closed [endoscopic] biopsy of biliary duct or sphincter of Oddi
C7: 51.15 | D7: Pressure measurement of sphincter of Oddi
C8: 52.13 | D8: Endoscopic retrograde pancreatography [ERP]
C9: PDC P17KJ Other Hepatobiliary Major Proc.
C10: 50.11 | D10: Closed (percutaneous) [needle] biopsy of liver
C11: 50.19 | D11: Other diagnostic procedures on liver
C12: 50.91 | D12: Percutaneous aspiration of liver
C13: 50.93 | D13: Localized perfusion of liver
C14: 50.94 | D14: Other injection of therapeutic substance into liver
C15: 51.01 | D15: Percutaneous aspiration of gallbladder
C16: 51.12 | D16: Percutaneous biopsy of gallbladder or bile ducts
C17: 51.19 | D17: Other diagnostic procedures on biliary tract
A18: P16KT | B18: Colonoscopy Proc. | C18: PDC
C19: 51.96 | D19: Percutaneous extraction of common duct stones
C20: 51.98 | D20: Other percutaneous procedures on biliary tract
C21: 52.11 | D21: Closed [aspiration] [needle] [percutaneous] biopsy of pancreas
C22: 52.14 | D22: Closed [endoscopic] biopsy of pancreatic duct
A23: P16KX | B23: Major Biopsy for Digestive System | C23: PDC
C24: 52.19 | D24: Other diagnostic procedures on pancreas
C25: 54.24 | D25: Closed [percutaneous] [needle] biopsy of intra-abdominal mass
C26: 87.53 | D26: Intraoperative cholangiogram
C27: PDC P17KH Other Hepatobiliary Minor Proc.
C28: 50.99 | D28: Other operations on liver
A29: P16KY | B29: Moderate Biopsy for Digestive System | C29: PDC
C30: 96.41 | D30: Irrigation of cholecystostomy and other biliary tube
C31: 96.42 | D31: Irrigation of pancreatic tube
C32: 97.54 | D32: Removal of cholecystostomy tube
C33: 97.55 | D33: Removal of t-tube, other bile duct tube, or liver tube
C34: 97.56 | D34: Removal of pancreatic tube or drain
C35: 49.22 | D35: Biopsy of perianal tissue
A36: P16KV | B36: Endoscopy of Upper Gastrointestinal Minor Proc. | C36: PDC
C37: 42.22 | D37: Esophagoscopy through artificial stoma
C38: 42.23 | D38: Other esophagoscopy
C39: 44.11 | D39: Transabdominal gastroscopy
C40: 44.12 | D40: Gastroscopy through artificial stoma
C41: 44.13 | D41: Other gastroscopy
C42: 45.11 | D42: Transabdominal endoscopy of small intestine
C43: 45.12 | D43: Endoscopy of small intestine through artificial stoma
C44: 45.13 | D44: Other endoscopy of small intestine
A45: P16KE | B45: Hernia Proc. | C45: PDC
C46: 53.00 | D46: Unilateral repair of inguinal hernia, not otherwise specified
C47: 53.01 | D47: Other and open repair of direct inguinal hernia
C48: 53.02 | D48: Other and open repair of indirect inguinal hernia
C49: 53.03 | D49: Other and open repair of direct inguinal hernia with graft or prosthesis
C50: 53.04 | D50: Other and open repair of indirect inguinal hernia with graft or prosthesis
C51: 53.05 | D51: Repair of inguinal hernia with graft or prosthesis, not otherwise specified
C52: 53.10 | D52: Bilateral repair of inguinal hernia, not otherwise specified
C53: 53.11 | D53: Other and open bilateral repair of direct inguinal hernia
C54: 53.12 | D54: Other and open bilateral repair of indirect inguinal hernia
C55: 53.13 | D55: Other and open bilateral repair of inguinal hernia, one direct and one indirect
C56: 53.14 | D56: Other and open bilateral repair of direct inguinal hernia with graft or prosthesis
C57: 53.15 | D57: Other and open bilateral repair of indirect inguinal hernia with graft or prosthesis
... C75: 54.72 | D75: Other repair of abdominal wall
A76: P16KZ | B76: Minor Biopsy for Digestive System | C76: PDC
C77: 45.26 | D77: Open biopsy of large intestine
C78: 45.27 | D78: Intestinal biopsy, site unspecified
C79: 48.26 | D79: Biopsy of perirectal tissue
C80: 49.23 | D80: Biopsy of anus
C81: 54.22 | D81: Biopsy of abdominal wall or umbilicus
C82: 54.23 | D82: Biopsy of peritoneum
C83: 54.24 | D83: Closed [percutaneous] [needle] biopsy of intra-abdominal mass
A84: P16KM | B84: Hemorrhoid Proc. | C84: PDC
C85: 49.44 | D85: Destruction of hemorrhoids by cryotherapy
C86: 49.45 | D86: Ligation of hemorrhoids
C87: 49.46 | D87: Excision of hemorrhoids
C88: 49.49 | D88: Other procedures on hemorrhoids
A89: P16KN | B89: Rectum & Anal Moderate Proc. | C89: PDC
C90: 48.34 | D90: Destruction of rectal lesion or tissue by cryosurgery
C91: 48.35 | D91: Local excision of rectal lesion or tissue
C92: 48.71 | D92: Suture of laceration of rectum
C93: 48.73 | D93: Closure of other rectal fistula
C94: 48.76 | D94: Other proctopexy
C95: 48.79 | D95: Other repair of rectum
C96: 48.81 | D96: Incision of perirectal tissue
C97: 48.82 | D97: Excision of perirectal tissue
C98: 48.91 | D98: Incision of rectal stricture
C99: 48.92 | D99: Anorectal myectomy
C100: 48.93 | D100: Repair of perirectal fistula
C101: 49.11 | D101: Anal fistulotomy
... C106: 70.73 | D106: Repair of rectovaginal fistula
A107: P16KP | B107: Rectum & Anal Minor Proc. | C107: PDC
C108: 48.31 | D108: Radical electrocoagulation of rectal lesion or tissue
C109: 48.32 | D109: Other electrocoagulation of rectal lesion or tissue
C110: 48.33 | D110: Destruction of rectal lesion or tissue by laser
C111: 48.36 | D111: [Endoscopic] polypectomy of rectum
C112: 48.99 | D112: Other operations on rectum and perirectal tissue
C113: 49.01 | D113: Incision of perianal abscess
C114: 49.02 | D114: Other incision of perianal tissue
C115: 49.04 | D115: Other excision of perianal tissue
C116: 49.39 | D116: Other local excision or destruction of lesion or tissue of anus
C117: 49.51 | D117: Left lateral anal sphincterotomy
C118: 49.52 | D118: Posterior anal sphincterotomy
C119: 49.59 | D119: Other anal sphincterotomy
... C126: 49.99 | D126: Other operations on anus
A127: P16KQ | B127: Other Gastrointestinal Major Proc. | C127: PDC
...

Sheet ip op cluster
A1: Cluster Type | B1: PTD | C1: Cluster Code | D1: Cluster Description | E1: ICD9CM Code | F1: ICD9CM Description | G1: procgr | H1: New Cluster Descrirption | I1: New Cluster Code | J1: tarif iDRG | K1: tarif iDRG + AF | L1: tarif rs 2025 | M1: tarif rs uji coba | N1: Jumlah Kasus | O1: Total | P1: p25 uji coba | Q1: p50 uji coba | R1: p75 uji coba | S1: p90 uji coba | T1: Kompetensi | U1: Layanan
A2: PDC | B2: 1 | C2: P16AB | D2: Stomach, Esophagus & Duodenal Resection Procedures | E2: 41.5 | F2: Total splenectomy | G2: =VLOOKUP($E2,proc!$A:$D,3, FALSE) -> 4 | H2: =D2 -> Stomach, Esophagus & Duodenal Resection Procedures | I2: =C2 -> P16AB | J2: =VLOOKUP($C2,'tarif idrg'!$A:$O,11,FALSE) -> 18485238 | K2: =VLOOKUP($C2,'tarif idrg'!$A:$O,15,FALSE) -> 18485238 | L2: =VLOOKUP($E2,'ip prosedur-2025'!$A:$H,4,FALSE) -> 52429636 | M2: =VLOOKUP($E2,'ip prosedur-14 okt-15 juni 2026'!$A:$H,4,FALSE) -> 52865089 | N2: =VLOOKUP($E2,'ip prosedur-14 okt-15 juni 2026'!$A:$H,3, FALSE) -> 543 | O2: =M2*N2 -> 28705743414 | P2: =VLOOKUP($E2,'ip prosedur-14 okt-15 juni 2026'!$A:$H,5,FALSE) -> 24391385 | Q2: =VLOOKUP($E2,'ip prosedur-14 okt-15 juni 2026'!$A:$H,6,FALSE) -> 37323000 | R2: =VLOOKUP($E2,'ip prosedur-14 okt-15 juni 2026'!$A:$H,7,FALSE) -> 62092164 | S2: =VLOOKUP($E2,'ip prosedur-14 okt-15 juni 2026'!$A:$H,8,FALSE) -> 102438900
A3: PDC | B3: 1 | C3: P16AB | D3: Stomach, Esophagus & Duodenal Resection Procedures | E3: 42.41 | F3: Partial esophagectomy | G3: =VLOOKUP($E3,proc!$A:$D,3, FALSE) -> 6 | H3: =D3 -> Stomach, Esophagus & Duodenal Resection Procedures | I3: =C3 -> P16AB | J3: =VLOOKUP($C3,'tarif idrg'!$A:$O,11,FALSE) -> 18485238 | K3: =VLOOKUP($C3,'tarif idrg'!$A:$O,15,FALSE) -> 18485238 | L3: =VLOOKUP($E3,'ip prosedur-2025'!$A:$H,4,FALSE) -> 1.2611458e+08 | M3: =VLOOKUP($E3,'ip prosedur-14 okt-15 juni 2026'!$A:$H,4,FALSE) -> 1.1940485e+08 | N3: =VLOOKUP($E3,'ip prosedur-14 okt-15 juni 2026'!$A:$H,3, FALSE) -> 43 | O3: =M3*N3 -> 5134408520 | P3: =VLOOKUP($E3,'ip prosedur-14 okt-15 juni 2026'!$A:$H,5,FALSE) -> 53608899 | Q3: =VLOOKUP($E3,'ip prosedur-14 okt-15 juni 2026'!$A:$H,6,FALSE) -> 108589810 | R3: =VLOOKUP($E3,'ip prosedur-14 okt-15 juni 2026'!$A:$H,7,FALSE) -> 157989413 | S3: =VLOOKUP($E3,'ip prosedur-14 okt-15 juni 2026'!$A:$H,8,FALSE) -> 205202294
A4: PDC | B4: 1 | C4: P16AB | D4: Stomach, Esophagus & Duodenal Resection Procedures | E4: 42.42 | F4: Total esophagectomy | G4: =VLOOKUP($E4,proc!$A:$D,3, FALSE) -> 6 | H4: =D4 -> Stomach, Esophagus & Duodenal Resection Procedures | I4: =C4 -> P16AB | J4: =VLOOKUP($C4,'tarif idrg'!$A:$O,11,FALSE) -> 18485238 | K4: =VLOOKUP($C4,'tarif idrg'!$A:$O,15,FALSE) -> 18485238 | L4: =VLOOKUP($E4,'ip prosedur-2025'!$A:$H,4,FALSE) -> 1.1499459e+08 | M4: =VLOOKUP($E4,'ip prosedur-14 okt-15 juni 2026'!$A:$H,4,FALSE) -> 75994185 | N4: =VLOOKUP($E4,'ip prosedur-14 okt-15 juni 2026'!$A:$H,3, FALSE) -> 9 | O4: =M4*N4 -> 683947667 | P4: =VLOOKUP($E4,'ip prosedur-14 okt-15 juni 2026'!$A:$H,5,FALSE) -> 46214359 | Q4: =VLOOKUP($E4,'ip prosedur-14 okt-15 juni 2026'!$A:$H,6,FALSE) -> 69417899 | R4: =VLOOKUP($E4,'ip prosedur-14 okt-15 juni 2026'!$A:$H,7,FALSE) -> 101663598 | S4: =VLOOKUP($E4,'ip prosedur-14 okt-15 juni 2026'!$A:$H,8,FALSE) -> 167465700
A5: PDC | B5: 1 | C5: P16AB | D5: Stomach, Esophagus & Duodenal Resection Procedures | E5: 43.5 | F5: Partial gastrectomy with anastomosis to esophagus | G5: =VLOOKUP($E5,proc!$A:$D,3, FALSE) -> 5 | H5: =D5 -> Stomach, Esophagus & Duodenal Resection Procedures | I5: =C5 -> P16AB | J5: =VLOOKUP($C5,'tarif idrg'!$A:$O,11,FALSE) -> 18485238 | K5: =VLOOKUP($C5,'tarif idrg'!$A:$O,15,FALSE) -> 18485238 | L5: =VLOOKUP($E5,'ip prosedur-2025'!$A:$H,4,FALSE) -> 98744188 | M5: =VLOOKUP($E5,'ip prosedur-14 okt-15 juni 2026'!$A:$H,4,FALSE) -> 94617269 | N5: =VLOOKUP($E5,'ip prosedur-14 okt-15 juni 2026'!$A:$H,3, FALSE) -> 53 | O5: =M5*N5 -> 5014715278 | P5: =VLOOKUP($E5,'ip prosedur-14 okt-15 juni 2026'!$A:$H,5,FALSE) -> 42753297 | Q5: =VLOOKUP($E5,'ip prosedur-14 okt-15 juni 2026'!$A:$H,6,FALSE) -> 79648401 | R5: =VLOOKUP($E5,'ip prosedur-14 okt-15 juni 2026'!$A:$H,7,FALSE) -> 126490623 | S5: =VLOOKUP($E5,'ip prosedur-14 okt-15 juni 2026'!$A:$H,8,FALSE) -> 200440522
A6: PDC | B6: 1 | C6: P16AB | D6: Stomach, Esophagus & Duodenal Resection Procedures | E6: 43.6 | F6: Partial gastrectomy with anastomosis to duodenum | G6: =VLOOKUP($E6,proc!$A:$D,3, FALSE) -> 5 | H6: =D6 -> Stomach, Esophagus & Duodenal Resection Procedures | I6: =C6 -> P16AB | J6: =VLOOKUP($C6,'tarif idrg'!$A:$O,11,FALSE) -> 18485238 | K6: =VLOOKUP($C6,'tarif idrg'!$A:$O,15,FALSE) -> 18485238 | L6: =VLOOKUP($E6,'ip prosedur-2025'!$A:$H,4,FALSE) -> 75277649 | M6: =VLOOKUP($E6,'ip prosedur-14 okt-15 juni 2026'!$A:$H,4,FALSE) -> 72766392 | N6: =VLOOKUP($E6,'ip prosedur-14 okt-15 juni 2026'!$A:$H,3, FALSE) -> 58 | O6: =M6*N6 -> 4220450728 | P6: =VLOOKUP($E6,'ip prosedur-14 okt-15 juni 2026'!$A:$H,5,FALSE) -> 40672345 | Q6: =VLOOKUP($E6,'ip prosedur-14 okt-15 juni 2026'!$A:$H,6,FALSE) -> 58786202 | R6: =VLOOKUP($E6,'ip prosedur-14 okt-15 juni 2026'!$A:$H,7,FALSE) -> 91531996 | S6: =VLOOKUP($E6,'ip prosedur-14 okt-15 juni 2026'!$A:$H,8,FALSE) -> 148960900
A7: PDC | B7: 1 | C7: P16AB | D7: Stomach, Esophagus & Duodenal Resection Procedures | E7: 43.7 | F7: Partial gastrectomy with anastomosis to jejunum | G7: =VLOOKUP($E7,proc!$A:$D,3, FALSE) -> 6 | H7: =D7 -> Stomach, Esophagus & Duodenal Resection Procedures | I7: =C7 -> P16AB | J7: =VLOOKUP($C7,'tarif idrg'!$A:$O,11,FALSE) -> 18485238 | K7: =VLOOKUP($C7,'tarif idrg'!$A:$O,15,FALSE) -> 18485238 | L7: =VLOOKUP($E7,'ip prosedur-2025'!$A:$H,4,FALSE) -> 74462792 | M7: =VLOOKUP($E7,'ip prosedur-14 okt-15 juni 2026'!$A:$H,4,FALSE) -> 74421012 | N7: =VLOOKUP($E7,'ip prosedur-14 okt-15 juni 2026'!$A:$H,3, FALSE) -> 231 | O7: =M7*N7 -> 17191253712 | P7: =VLOOKUP($E7,'ip prosedur-14 okt-15 juni 2026'!$A:$H,5,FALSE) -> 34708610 | Q7: =VLOOKUP($E7,'ip prosedur-14 okt-15 juni 2026'!$A:$H,6,FALSE) -> 60993125 | R7: =VLOOKUP($E7,'ip prosedur-14 okt-15 juni 2026'!$A:$H,7,FALSE) -> 92240100 | S7: =VLOOKUP($E7,'ip prosedur-14 okt-15 juni 2026'!$A:$H,8,FALSE) -> 135701622
A8: PDC | B8: 1 | C8: P16AB | D8: Stomach, Esophagus & Duodenal Resection Procedures | E8: 43.81 | F8: Partial gastrectomy with jejunal transposition | G8: =VLOOKUP($E8,proc!$A:$D,3, FALSE) -> 6 | H8: =D8 -> Stomach, Esophagus & Duodenal Resection Procedures | I8: =C8 -> P16AB | J8: =VLOOKUP($C8,'tarif idrg'!$A:$O,11,FALSE) -> 18485238 | K8: =VLOOKUP($C8,'tarif idrg'!$A:$O,15,FALSE) -> 18485238 | L8: =VLOOKUP($E8,'ip prosedur-2025'!$A:$H,4,FALSE) -> 80525516 | M8: =VLOOKUP($E8,'ip prosedur-14 okt-15 juni 2026'!$A:$H,4,FALSE) -> 73089081 | N8: =VLOOKUP($E8,'ip prosedur-14 okt-15 juni 2026'!$A:$H,3, FALSE) -> 5 | O8: =M8*N8 -> 365445407 | P8: =VLOOKUP($E8,'ip prosedur-14 okt-15 juni 2026'!$A:$H,5,FALSE) -> 63276121 | Q8: =VLOOKUP($E8,'ip prosedur-14 okt-15 juni 2026'!$A:$H,6,FALSE) -> 70513922 | R8: =VLOOKUP($E8,'ip prosedur-14 okt-15 juni 2026'!$A:$H,7,FALSE) -> 82309664 | S8: =VLOOKUP($E8,'ip prosedur-14 okt-15 juni 2026'!$A:$H,8,FALSE) -> 104230307
A9: PDC | B9: 1 | C9: P16AB | D9: Stomach, Esophagus & Duodenal Resection Procedures | E9: 43.89 | F9: Other partial gastrectomy | G9: =VLOOKUP($E9,proc!$A:$D,3, FALSE) -> 5 | H9: =D9 -> Stomach, Esophagus & Duodenal Resection Procedures | I9: =C9 -> P16AB | J9: =VLOOKUP($C9,'tarif idrg'!$A:$O,11,FALSE) -> 18485238 | K9: =VLOOKUP($C9,'tarif idrg'!$A:$O,15,FALSE) -> 18485238 | L9: =VLOOKUP($E9,'ip prosedur-2025'!$A:$H,4,FALSE) -> 52574054 | M9: =VLOOKUP($E9,'ip prosedur-14 okt-15 juni 2026'!$A:$H,4,FALSE) -> 53324980 | N9: =VLOOKUP($E9,'ip prosedur-14 okt-15 juni 2026'!$A:$H,3, FALSE) -> 350 | O9: =M9*N9 -> 18663743053 | P9: =VLOOKUP($E9,'ip prosedur-14 okt-15 juni 2026'!$A:$H,5,FALSE) -> 20792502 | Q9: =VLOOKUP($E9,'ip prosedur-14 okt-15 juni 2026'!$A:$H,6,FALSE) -> 32577345 | R9: =VLOOKUP($E9,'ip prosedur-14 okt-15 juni 2026'!$A:$H,7,FALSE) -> 65702614 | S9: =VLOOKUP($E9,'ip prosedur-14 okt-15 juni 2026'!$A:$H,8,FALSE) -> 101884136
A10: PDC | B10: 1 | C10: P16AB | D10: Stomach, Esophagus & Duodenal Resection Procedures | E10: 43.91 | F10: Total gastrectomy with intestinal interposition | G10: =VLOOKUP($E10,proc!$A:$D,3, FALSE) -> 6 | H10: =D10 -> Stomach, Esophagus & Duodenal Resection Procedures | I10: =C10 -> P16AB | J10: =VLOOKUP($C10,'tarif idrg'!$A:$O,11,FALSE) -> 18485238 | K10: =VLOOKUP($C10,'tarif idrg'!$A:$O,15,FALSE) -> 18485238 | L10: =VLOOKUP($E10,'ip prosedur-2025'!$A:$H,4,FALSE) -> 1.1919652e+08 | M10: =VLOOKUP($E10,'ip prosedur-14 okt-15 juni 2026'!$A:$H,4,FALSE) -> 1.4422502e+08 | N10: =VLOOKUP($E10,'ip prosedur-14 okt-15 juni 2026'!$A:$H,3, FALSE) -> 10 | O10: =M10*N10 -> 1442250236 | P10: =VLOOKUP($E10,'ip prosedur-14 okt-15 juni 2026'!$A:$H,5,FALSE) -> 85870232 | Q10: =VLOOKUP($E10,'ip prosedur-14 okt-15 juni 2026'!$A:$H,6,FALSE) -> 92324883 | R10: =VLOOKUP($E10,'ip prosedur-14 okt-15 juni 2026'!$A:$H,7,FALSE) -> 151293741 | S10: =VLOOKUP($E10,'ip prosedur-14 okt-15 juni 2026'!$A:$H,8,FALSE) -> 205202294
A11: PDC | B11: 1 | C11: P16AB | D11: Stomach, Esophagus & Duodenal Resection Procedures | E11: 43.99 | F11: Other total gastrectomy | G11: =VLOOKUP($E11,proc!$A:$D,3, FALSE) -> 6 | H11: =D11 -> Stomach, Esophagus & Duodenal Resection Procedures | I11: =C11 -> P16AB | J11: =VLOOKUP($C11,'tarif idrg'!$A:$O,11,FALSE) -> 18485238 | K11: =VLOOKUP($C11,'tarif idrg'!$A:$O,15,FALSE) -> 18485238 | L11: =VLOOKUP($E11,'ip prosedur-2025'!$A:$H,4,FALSE) -> 87655495 | M11: =VLOOKUP($E11,'ip prosedur-14 okt-15 juni 2026'!$A:$H,4,FALSE) -> 1.1048437e+08 | N11: =VLOOKUP($E11,'ip prosedur-14 okt-15 juni 2026'!$A:$H,3, FALSE) -> 45 | O11: =M11*N11 -> 4971796542 | P11: =VLOOKUP($E11,'ip prosedur-14 okt-15 juni 2026'!$A:$H,5,FALSE) -> 43422908 | Q11: =VLOOKUP($E11,'ip prosedur-14 okt-15 juni 2026'!$A:$H,6,FALSE) -> 91403368 | R11: =VLOOKUP($E11,'ip prosedur-14 okt-15 juni 2026'!$A:$H,7,FALSE) -> 122210336 | S11: =VLOOKUP($E11,'ip prosedur-14 okt-15 juni 2026'!$A:$H,8,FALSE) -> 234211982
A12: PDC | B12: 1 | C12: P16AD | D12: Rectal Resection Procedures | E12: 48.0 | F12: Proctotomy | G12: =VLOOKUP($E12,proc!$A:$D,3, FALSE) -> 4 | H12: =D12 -> Rectal Resection Procedures | I12: =C12 -> P16AD | J12: =VLOOKUP($C12,'tarif idrg'!$A:$O,11,FALSE) -> 19047832 | K12: =VLOOKUP($C12,'tarif idrg'!$A:$O,15,FALSE) -> 19047832 | L12: =VLOOKUP($E12,'ip prosedur-2025'!$A:$H,4,FALSE) -> 19959087 | M12: =VLOOKUP($E12,'ip prosedur-14 okt-15 juni 2026'!$A:$H,4,FALSE) -> 17114671 | N12: =VLOOKUP($E12,'ip prosedur-14 okt-15 juni 2026'!$A:$H,3, FALSE) -> 30 | O12: =M12*N12 -> 513440133 | P12: =VLOOKUP($E12,'ip prosedur-14 okt-15 juni 2026'!$A:$H,5,FALSE) -> 7283797 | Q12: =VLOOKUP($E12,'ip prosedur-14 okt-15 juni 2026'!$A:$H,6,FALSE) -> 13968995 | R12: =VLOOKUP($E12,'ip prosedur-14 okt-15 juni 2026'!$A:$H,7,FALSE) -> 25205333 | S12: =VLOOKUP($E12,'ip prosedur-14 okt-15 juni 2026'!$A:$H,8,FALSE) -> 32847476
A13: PDC | B13: 1 | C13: P16AD | D13: Rectal Resection Procedures | E13: 48.40 | F13: Pull-through resection of rectum, not otherwise specified | G13: =VLOOKUP($E13,proc!$A:$D,3, FALSE) -> 5 | H13: =D13 -> Rectal Resection Procedures | I13: =C13 -> P16AD | J13: =VLOOKUP($C13,'tarif idrg'!$A:$O,11,FALSE) -> 19047832 | K13: =VLOOKUP($C13,'tarif idrg'!$A:$O,15,FALSE) -> 19047832 | L13: =VLOOKUP($E13,'ip prosedur-2025'!$A:$H,4,FALSE) -> 40360689 | M13: =VLOOKUP($E13,'ip prosedur-14 okt-15 juni 2026'!$A:$H,4,FALSE) -> 34725012 | N13: =VLOOKUP($E13,'ip prosedur-14 okt-15 juni 2026'!$A:$H,3, FALSE) -> 132 | O13: =M13*N13 -> 4583701558 | P13: =VLOOKUP($E13,'ip prosedur-14 okt-15 juni 2026'!$A:$H,5,FALSE) -> 15014000 | Q13: =VLOOKUP($E13,'ip prosedur-14 okt-15 juni 2026'!$A:$H,6,FALSE) -> 23447487 | R13: =VLOOKUP($E13,'ip prosedur-14 okt-15 juni 2026'!$A:$H,7,FALSE) -> 33824388 | S13: =VLOOKUP($E13,'ip prosedur-14 okt-15 juni 2026'!$A:$H,8,FALSE) -> 57323242
... A218: PDC | B218: 1 | C218: P16AR | D218: Complex Therapeutic Colonoscopy | E218: 45.43 | F218: Endoscopic destruction of other lesion or tissue of large intestine | G218: =VLOOKUP($E218,proc!$A:$D,3, FALSE) -> 0 | H218: =D218 -> Complex Therapeutic Colonoscopy | I218: =C218 -> P16AR | J218: =VLOOKUP($C218,'tarif idrg'!$A:$O,11,FALSE) -> 4822236 | K218: =VLOOKUP($C218,'tarif idrg'!$A:$O,15,FALSE) -> 4822236 | L218: =VLOOKUP($E218,'ip prosedur-2025'!$A:$H,4,FALSE) -> 22653031 | M218: =VLOOKUP($E218,'ip prosedur-14 okt-15 juni 2026'!$A:$H,4,FALSE) -> 23169771 | N218: =VLOOKUP($E218,'ip prosedur-14 okt-15 juni 2026'!$A:$H,3, FALSE) -> 149 | O218: =M218*N218 -> 3452295822 | P218: =VLOOKUP($E218,'ip prosedur-14 okt-15 juni 2026'!$A:$H,5,FALSE) -> 7029841 | Q218: =VLOOKUP($E218,'ip prosedur-14 okt-15 juni 2026'!$A:$H,6,FALSE) -> 17173400 | R218: =VLOOKUP($E218,'ip prosedur-14 okt-15 juni 2026'!$A:$H,7,FALSE) -> 31940856 | S218: =VLOOKUP($E218,'ip prosedur-14 okt-15 juni 2026'!$A:$H,8,FALSE) -> 39472470
A219: PDC | B219: 1 | C219: P16AJ | D219: Minor Small and Large Bowel Procedures | E219: PDC | G219: =VLOOKUP($E219,proc!$A:$D,3, FALSE) -> #N/A | H219: =D219 -> Minor Small and Large Bowel Procedures | I219: =C219 -> P16AJ | J219: =VLOOKUP($C219,'tarif idrg'!$A:$O,11,FALSE) -> #N/A | K219: =VLOOKUP($C219,'tarif idrg'!$A:$O,15,FALSE) -> #N/A | L219: =VLOOKUP($E219,'ip prosedur-2025'!$A:$H,4,FALSE) -> #N/A | M219: =VLOOKUP($E219,'ip prosedur-14 okt-15 juni 2026'!$A:$H,4,FALSE) -> #N/A | N219: =VLOOKUP($E219,'ip prosedur-14 okt-15 juni 2026'!$A:$H,3, FALSE) -> #N/A | O219: =M219*N219 -> #N/A | P219: =VLOOKUP($E219,'ip prosedur-14 okt-15 juni 2026'!$A:$H,5,FALSE) -> #N/A | Q219: =VLOOKUP($E219,'ip prosedur-14 okt-15 juni 2026'!$A:$H,6,FALSE) -> #N/A | R219: =VLOOKUP($E219,'ip prosedur-14 okt-15 juni 2026'!$A:$H,7,FALSE) -> #N/A | S219: =VLOOKUP($E219,'ip prosedur-14 okt-15 juni 2026'!$A:$H,8,FALSE) -> #N/A
A220: PDC | B220: 1 | C220: P16AJ | D220: Minor Small and Large Bowel Procedures | E220: 45.02 | F220: Other incision of small intestine | G220: =VLOOKUP($E220,proc!$A:$D,3, FALSE) -> 4 | H220: =D220 -> Minor Small and Large Bowel Procedures | I220: =C220 -> P16AJ | J220: =VLOOKUP($C220,'tarif idrg'!$A:$O,11,FALSE) -> #N/A | K220: =VLOOKUP($C220,'tarif idrg'!$A:$O,15,FALSE) -> #N/A | L220: =VLOOKUP($E220,'ip prosedur-2025'!$A:$H,4,FALSE) -> 47327291 | M220: =VLOOKUP($E220,'ip prosedur-14 okt-15 juni 2026'!$A:$H,4,FALSE) -> 54690432 | N220: =VLOOKUP($E220,'ip prosedur-14 okt-15 juni 2026'!$A:$H,3, FALSE) -> 94 | O220: =M220*N220 -> 5140900608 | P220: =VLOOKUP($E220,'ip prosedur-14 okt-15 juni 2026'!$A:$H,5,FALSE) -> 17362785 | Q220: =VLOOKUP($E220,'ip prosedur-14 okt-15 juni 2026'!$A:$H,6,FALSE) -> 32814821 | R220: =VLOOKUP($E220,'ip prosedur-14 okt-15 juni 2026'!$A:$H,7,FALSE) -> 66778900 | S220: =VLOOKUP($E220,'ip prosedur-14 okt-15 juni 2026'!$A:$H,8,FALSE) -> 121182345
A221: PDC | B221: 1 | C221: P16AJ | D221: Minor Small and Large Bowel Procedures | E221: 45.03 | F221: Incision of large intestine | G221: =VLOOKUP($E221,proc!$A:$D,3, FALSE) -> 4 | H221: =D221 -> Minor Small and Large Bowel Procedures | I221: =C221 -> P16AJ | J221: =VLOOKUP($C221,'tarif idrg'!$A:$O,11,FALSE) -> #N/A | K221: =VLOOKUP($C221,'tarif idrg'!$A:$O,15,FALSE) -> #N/A | L221: =VLOOKUP($E221,'ip prosedur-2025'!$A:$H,4,FALSE) -> 56875818 | M221: =VLOOKUP($E221,'ip prosedur-14 okt-15 juni 2026'!$A:$H,4,FALSE) -> 44744856 | N221: =VLOOKUP($E221,'ip prosedur-14 okt-15 juni 2026'!$A:$H,3, FALSE) -> 108 | O221: =M221*N221 -> 4832444400 | P221: =VLOOKUP($E221,'ip prosedur-14 okt-15 juni 2026'!$A:$H,5,FALSE) -> 19368463 | Q221: =VLOOKUP($E221,'ip prosedur-14 okt-15 juni 2026'!$A:$H,6,FALSE) -> 32688098 | R221: =VLOOKUP($E221,'ip prosedur-14 okt-15 juni 2026'!$A:$H,7,FALSE) -> 51267949 | S221: =VLOOKUP($E221,'ip prosedur-14 okt-15 juni 2026'!$A:$H,8,FALSE) -> 92616208
A222: PDC | B222: 1 | C222: P16AJ | D222: Minor Small and Large Bowel Procedures | E222: 45.11 | F222: Transabdominal endoscopy of small intestine | G222: =VLOOKUP($E222,proc!$A:$D,3, FALSE) -> 0 | H222: =D222 -> Minor Small and Large Bowel Procedures | I222: =C222 -> P16AJ | J222: =VLOOKUP($C222,'tarif idrg'!$A:$O,11,FALSE) -> #N/A | K222: =VLOOKUP($C222,'tarif idrg'!$A:$O,15,FALSE) -> #N/A | L222: =VLOOKUP($E222,'ip prosedur-2025'!$A:$H,4,FALSE) -> 19692268 | M222: =VLOOKUP($E222,'ip prosedur-14 okt-15 juni 2026'!$A:$H,4,FALSE) -> 34061280 | N222: =VLOOKUP($E222,'ip prosedur-14 okt-15 juni 2026'!$A:$H,3, FALSE) -> 17 | O222: =M222*N222 -> 579041759 | P222: =VLOOKUP($E222,'ip prosedur-14 okt-15 juni 2026'!$A:$H,5,FALSE) -> 12377427 | Q222: =VLOOKUP($E222,'ip prosedur-14 okt-15 juni 2026'!$A:$H,6,FALSE) -> 15374613 | R222: =VLOOKUP($E222,'ip prosedur-14 okt-15 juni 2026'!$A:$H,7,FALSE) -> 44843982 | S222: =VLOOKUP($E222,'ip prosedur-14 okt-15 juni 2026'!$A:$H,8,FALSE) -> 88059127
A223: PDC | B223: 1 | C223: P16AJ | D223: Minor Small and Large Bowel Procedures | E223: 45.15 | F223: Open biopsy of small intestine | G223: =VLOOKUP($E223,proc!$A:$D,3, FALSE) -> 4 | H223: =D223 -> Minor Small and Large Bowel Procedures | I223: =C223 -> P16AJ | J223: =VLOOKUP($C223,'tarif idrg'!$A:$O,11,FALSE) -> #N/A | K223: =VLOOKUP($C223,'tarif idrg'!$A:$O,15,FALSE) -> #N/A | L223: =VLOOKUP($E223,'ip prosedur-2025'!$A:$H,4,FALSE) -> 33645451 | M223: =VLOOKUP($E223,'ip prosedur-14 okt-15 juni 2026'!$A:$H,4,FALSE) -> 35811168 | N223: =VLOOKUP($E223,'ip prosedur-14 okt-15 juni 2026'!$A:$H,3, FALSE) -> 396 | O223: =M223*N223 -> 14181222425 | P223: =VLOOKUP($E223,'ip prosedur-14 okt-15 juni 2026'!$A:$H,5,FALSE) -> 15015039 | Q223: =VLOOKUP($E223,'ip prosedur-14 okt-15 juni 2026'!$A:$H,6,FALSE) -> 23930024 | R223: =VLOOKUP($E223,'ip prosedur-14 okt-15 juni 2026'!$A:$H,7,FALSE) -> 43515833 | S223: =VLOOKUP($E223,'ip prosedur-14 okt-15 juni 2026'!$A:$H,8,FALSE) -> 73132299
A224: PDC | B224: 1 | C224: P16AJ | D224: Minor Small and Large Bowel Procedures | E224: 45.19 | F224: Other diagnostic procedures on small intestine | G224: =VLOOKUP($E224,proc!$A:$D,3, FALSE) -> 0 | H224: =D224 -> Minor Small and Large Bowel Procedures | I224: =C224 -> P16AJ | J224: =VLOOKUP($C224,'tarif idrg'!$A:$O,11,FALSE) -> #N/A | K224: =VLOOKUP($C224,'tarif idrg'!$A:$O,15,FALSE) -> #N/A | L224: =VLOOKUP($E224,'ip prosedur-2025'!$A:$H,4,FALSE) -> 30629622 | M224: =VLOOKUP($E224,'ip prosedur-14 okt-15 juni 2026'!$A:$H,4,FALSE) -> 31869876 | N224: =VLOOKUP($E224,'ip prosedur-14 okt-15 juni 2026'!$A:$H,3, FALSE) -> 22 | O224: =M224*N224 -> 701137279 | P224: =VLOOKUP($E224,'ip prosedur-14 okt-15 juni 2026'!$A:$H,5,FALSE) -> 11035132 | Q224: =VLOOKUP($E224,'ip prosedur-14 okt-15 juni 2026'!$A:$H,6,FALSE) -> 15911016 | R224: =VLOOKUP($E224,'ip prosedur-14 okt-15 juni 2026'!$A:$H,7,FALSE) -> 29372655 | S224: =VLOOKUP($E224,'ip prosedur-14 okt-15 juni 2026'!$A:$H,8,FALSE) -> 56264468
A225: PDC | B225: 1 | C225: P16AJ | D225: Minor Small and Large Bowel Procedures | E225: 45.26 | F225: Open biopsy of large intestine | G225: =VLOOKUP($E225,proc!$A:$D,3, FALSE) -> 4 | H225: =D225 -> Minor Small and Large Bowel Procedures | I225: =C225 -> P16AJ | J225: =VLOOKUP($C225,'tarif idrg'!$A:$O,11,FALSE) -> #N/A | K225: =VLOOKUP($C225,'tarif idrg'!$A:$O,15,FALSE) -> #N/A | L225: =VLOOKUP($E225,'ip prosedur-2025'!$A:$H,4,FALSE) -> 28311589 | M225: =VLOOKUP($E225,'ip prosedur-14 okt-15 juni 2026'!$A:$H,4,FALSE) -> 28227707 | N225: =VLOOKUP($E225,'ip prosedur-14 okt-15 juni 2026'!$A:$H,3, FALSE) -> 1532 | O225: =M225*N225 -> 43244847078 | P225: =VLOOKUP($E225,'ip prosedur-14 okt-15 juni 2026'!$A:$H,5,FALSE) -> 13812279 | Q225: =VLOOKUP($E225,'ip prosedur-14 okt-15 juni 2026'!$A:$H,6,FALSE) -> 19752805 | R225: =VLOOKUP($E225,'ip prosedur-14 okt-15 juni 2026'!$A:$H,7,FALSE) -> 30867651 | S225: =VLOOKUP($E225,'ip prosedur-14 okt-15 juni 2026'!$A:$H,8,FALSE) -> 52640969
A226: PDC | B226: 1 | C226: P16AJ | D226: Minor Small and Large Bowel Procedures | E226: 45.27 | F226: Intestinal biopsy, site unspecified | G226: =VLOOKUP($E226,proc!$A:$D,3, FALSE) -> 0 | H226: =D226 -> Minor Small and Large Bowel Procedures | I226: =C226 -> P16AJ | J226: =VLOOKUP($C226,'tarif idrg'!$A:$O,11,FALSE) -> #N/A | K226: =VLOOKUP($C226,'tarif idrg'!$A:$O,15,FALSE) -> #N/A | L226: =VLOOKUP($E226,'ip prosedur-2025'!$A:$H,4,FALSE) -> 26523378 | M226: =VLOOKUP($E226,'ip prosedur-14 okt-15 juni 2026'!$A:$H,4,FALSE) -> 25600631 | N226: =VLOOKUP($E226,'ip prosedur-14 okt-15 juni 2026'!$A:$H,3, FALSE) -> 136 | O226: =M226*N226 -> 3481685755 | P226: =VLOOKUP($E226,'ip prosedur-14 okt-15 juni 2026'!$A:$H,5,FALSE) -> 14368033 | Q226: =VLOOKUP($E226,'ip prosedur-14 okt-15 juni 2026'!$A:$H,6,FALSE) -> 19608499 | R226: =VLOOKUP($E226,'ip prosedur-14 okt-15 juni 2026'!$A:$H,7,FALSE) -> 32608965 | S226: =VLOOKUP($E226,'ip prosedur-14 okt-15 juni 2026'!$A:$H,8,FALSE) -> 45232826
A227: PDC | B227: 1 | C227: P16AJ | D227: Minor Small and Large Bowel Procedures | E227: 45.28 | F227: Other diagnostic procedures on large intestine | G227: =VLOOKUP($E227,proc!$A:$D,3, FALSE) -> 0 | H227: =D227 -> Minor Small and Large Bowel Procedures | I227: =C227 -> P16AJ | J227: =VLOOKUP($C227,'tarif idrg'!$A:$O,11,FALSE) -> #N/A | K227: =VLOOKUP($C227,'tarif idrg'!$A:$O,15,FALSE) -> #N/A | L227: =VLOOKUP($E227,'ip prosedur-2025'!$A:$H,4,FALSE) -> 25116833 | M227: =VLOOKUP($E227,'ip prosedur-14 okt-15 juni 2026'!$A:$H,4,FALSE) -> 17245994 | N227: =VLOOKUP($E227,'ip prosedur-14 okt-15 juni 2026'!$A:$H,3, FALSE) -> 6 | O227: =M227*N227 -> 103475964 | P227: =VLOOKUP($E227,'ip prosedur-14 okt-15 juni 2026'!$A:$H,5,FALSE) -> 3638415 | Q227: =VLOOKUP($E227,'ip prosedur-14 okt-15 juni 2026'!$A:$H,6,FALSE) -> 8176357 | R227: =VLOOKUP($E227,'ip prosedur-14 okt-15 juni 2026'!$A:$H,7,FALSE) -> 17306350 | S227: =VLOOKUP($E227,'ip prosedur-14 okt-15 juni 2026'!$A:$H,8,FALSE) -> 59574775
A228: PDC | B228: 1 | C228: P16AJ | D228: Minor Small and Large Bowel Procedures | E228: 45.34 | F228: Other destruction of lesion of small intestine, except duodenum | G228: =VLOOKUP($E228,proc!$A:$D,3, FALSE) -> 4 | H228: =D228 -> Minor Small and Large Bowel Procedures | I228: =C228 -> P16AJ | J228: =VLOOKUP($C228,'tarif idrg'!$A:$O,11,FALSE) -> #N/A | K228: =VLOOKUP($C228,'tarif idrg'!$A:$O,15,FALSE) -> #N/A | L228: =VLOOKUP($E228,'ip prosedur-2025'!$A:$H,4,FALSE) -> 39306713 | M228: =VLOOKUP($E228,'ip prosedur-14 okt-15 juni 2026'!$A:$H,4,FALSE) -> 56542585 | N228: =VLOOKUP($E228,'ip prosedur-14 okt-15 juni 2026'!$A:$H,3, FALSE) -> 39 | O228: =M228*N228 -> 2205160798 | P228: =VLOOKUP($E228,'ip prosedur-14 okt-15 juni 2026'!$A:$H,5,FALSE) -> 16913293 | Q228: =VLOOKUP($E228,'ip prosedur-14 okt-15 juni 2026'!$A:$H,6,FALSE) -> 25618104 | R228: =VLOOKUP($E228,'ip prosedur-14 okt-15 juni 2026'!$A:$H,7,FALSE) -> 62026445 | S228: =VLOOKUP($E228,'ip prosedur-14 okt-15 juni 2026'!$A:$H,8,FALSE) -> 152417404
A229: PDC | B229: 1 | C229: P16AJ | D229: Minor Small and Large Bowel Procedures | E229: 45.49 | F229: Other destruction of lesion of large intestine | G229: =VLOOKUP($E229,proc!$A:$D,3, FALSE) -> 4 | H229: =D229 -> Minor Small and Large Bowel Procedures | I229: =C229 -> P16AJ | J229: =VLOOKUP($C229,'tarif idrg'!$A:$O,11,FALSE) -> #N/A | K229: =VLOOKUP($C229,'tarif idrg'!$A:$O,15,FALSE) -> #N/A | L229: =VLOOKUP($E229,'ip prosedur-2025'!$A:$H,4,FALSE) -> 30218864 | M229: =VLOOKUP($E229,'ip prosedur-14 okt-15 juni 2026'!$A:$H,4,FALSE) -> 44598676 | N229: =VLOOKUP($E229,'ip prosedur-14 okt-15 juni 2026'!$A:$H,3, FALSE) -> 56 | O229: =M229*N229 -> 2497525866 | P229: =VLOOKUP($E229,'ip prosedur-14 okt-15 juni 2026'!$A:$H,5,FALSE) -> 15186078 | Q229: =VLOOKUP($E229,'ip prosedur-14 okt-15 juni 2026'!$A:$H,6,FALSE) -> 25649925 | R229: =VLOOKUP($E229,'ip prosedur-14 okt-15 juni 2026'!$A:$H,7,FALSE) -> 57426200 | S229: =VLOOKUP($E229,'ip prosedur-14 okt-15 juni 2026'!$A:$H,8,FALSE) -> 101155350
A230: PDC | B230: 1 | C230: P16AJ | D230: Minor Small and Large Bowel Procedures | E230: 45.50 | F230: Isolation of intestinal segment, not otherwise specified | G230: =VLOOKUP($E230,proc!$A:$D,3, FALSE) -> 5 | H230: =D230 -> Minor Small and Large Bowel Procedures | I230: =C230 -> P16AJ | J230: =VLOOKUP($C230,'tarif idrg'!$A:$O,11,FALSE) -> #N/A | K230: =VLOOKUP($C230,'tarif idrg'!$A:$O,15,FALSE) -> #N/A | L230: =VLOOKUP($E230,'ip prosedur-2025'!$A:$H,4,FALSE) -> 1.705323e+08 | M230: =VLOOKUP($E230,'ip prosedur-14 okt-15 juni 2026'!$A:$H,4,FALSE) -> 42031596 | N230: =VLOOKUP($E230,'ip prosedur-14 okt-15 juni 2026'!$A:$H,3, FALSE) -> 7 | O230: =M230*N230 -> 294221171 | P230: =VLOOKUP($E230,'ip prosedur-14 okt-15 juni 2026'!$A:$H,5,FALSE) -> 8756700 | Q230: =VLOOKUP($E230,'ip prosedur-14 okt-15 juni 2026'!$A:$H,6,FALSE) -> 30049243 | R230: =VLOOKUP($E230,'ip prosedur-14 okt-15 juni 2026'!$A:$H,7,FALSE) -> 40729704 | S230: =VLOOKUP($E230,'ip prosedur-14 okt-15 juni 2026'!$A:$H,8,FALSE) -> 150314277
A231: PDC | B231: 1 | C231: P16AJ | D231: Minor Small and Large Bowel Procedures | E231: 46.60 | F231: Fixation of intestine, not otherwise specified | G231: =VLOOKUP($E231,proc!$A:$D,3, FALSE) -> 3 | H231: =D231 -> Minor Small and Large Bowel Procedures | I231: =C231 -> P16AJ | J231: =VLOOKUP($C231,'tarif idrg'!$A:$O,11,FALSE) -> #N/A | K231: =VLOOKUP($C231,'tarif idrg'!$A:$O,15,FALSE) -> #N/A | L231: =VLOOKUP($E231,'ip prosedur-2025'!$A:$H,4,FALSE) -> 42958161 | M231: =VLOOKUP($E231,'ip prosedur-14 okt-15 juni 2026'!$A:$H,4,FALSE) -> 30529292 | N231: =VLOOKUP($E231,'ip prosedur-14 okt-15 juni 2026'!$A:$H,3, FALSE) -> 9 | O231: =M231*N231 -> 274763628 | P231: =VLOOKUP($E231,'ip prosedur-14 okt-15 juni 2026'!$A:$H,5,FALSE) -> 12105065 | Q231: =VLOOKUP($E231,'ip prosedur-14 okt-15 juni 2026'!$A:$H,6,FALSE) -> 15846995 | R231: =VLOOKUP($E231,'ip prosedur-14 okt-15 juni 2026'!$A:$H,7,FALSE) -> 28243600 | S231: =VLOOKUP($E231,'ip prosedur-14 okt-15 juni 2026'!$A:$H,8,FALSE) -> 94674006
... A618: PDC | B618: 2 | C618: P16KW | D618: Other Gastrointestinal Minor Proc. | E618: 99.93 | F618: Rectal massage (for levator spasm) | G618: =VLOOKUP($E618,proc!$A:$D,3, FALSE) -> 0 | H618: =D618 -> Other Gastrointestinal Minor Proc. | I618: =C618 -> P16KW | J618: =VLOOKUP($C618,'tarif idrg'!$A:$O,11,FALSE) -> 406097 | K618: =VLOOKUP($C618,'tarif idrg'!$A:$O,15,FALSE) -> 406097 | L618: =VLOOKUP($E618,'ip prosedur-2025'!$A:$H,4,FALSE) -> 8114314.6 | M618: =VLOOKUP($E618,'ip prosedur-14 okt-15 juni 2026'!$A:$H,4,FALSE) -> 9015433.5 | N618: =VLOOKUP($E618,'ip prosedur-14 okt-15 juni 2026'!$A:$H,3, FALSE) -> 13 | O618: =M618*N618 -> 117200635 | P618: =VLOOKUP($E618,'ip prosedur-14 okt-15 juni 2026'!$A:$H,5,FALSE) -> 3443578 | Q618: =VLOOKUP($E618,'ip prosedur-14 okt-15 juni 2026'!$A:$H,6,FALSE) -> 7922125 | R618: =VLOOKUP($E618,'ip prosedur-14 okt-15 juni 2026'!$A:$H,7,FALSE) -> 13353121 | S618: =VLOOKUP($E618,'ip prosedur-14 okt-15 juni 2026'!$A:$H,8,FALSE) -> 17433656

Sheet ranap cluster
A1: Cluster Type | B1: Cluster Code | C1: Cluster Description | D1: ICD9CM Code | E1: ICD9CM Description | F1: procgr | G1: New Cluster Descrirption | H1: New Cluster Code | I1: Action | J1: Notes | K1: tarif iDRG | L1: tarif iDRG + AF | M1: Check rajal | N1: Check Changes | O1: tarif rs 2025 | P1: tarif rs uji coba | Q1: Jumlah Kasus | R1: Total | S1: p25 uji coba | T1: p50 uji coba | U1: p75 uji coba | V1: p90 uji coba | W1: Kompetensi | X1: Layanan
A2: PDC | B2: P16AB | C2: Stomach, Esophagus & Duodenal Resection Procedures | D2: 41.5 | E2: Total splenectomy | F2: =VLOOKUP($D2,proc!$A:$D,3, FALSE) -> 4 | G2: =C2 -> Stomach, Esophagus & Duodenal Resection Procedures | H2: =B2 -> P16AB | K2: =VLOOKUP($B2,'tarif idrg'!$A:$O,11,FALSE) -> 18485238 | L2: =VLOOKUP($B2,'tarif idrg'!$A:$O,15,FALSE) -> 18485238 | N2: =IF(C2<>G2,"Change","-") -> - | O2: =VLOOKUP($D2,'ip prosedur-2025'!$A:$H,4,FALSE) -> 52429636 | P2: =VLOOKUP($D2,'ip prosedur-14 okt-15 juni 2026'!$A:$H,4,FALSE) -> 52865089 | Q2: =VLOOKUP($D2,'ip prosedur-14 okt-15 juni 2026'!$A:$H,3, FALSE) -> 543 | R2: =P2*Q2 -> 28705743414 | S2: =VLOOKUP($D2,'ip prosedur-14 okt-15 juni 2026'!$A:$H,5,FALSE) -> 24391385 | T2: =VLOOKUP($D2,'ip prosedur-14 okt-15 juni 2026'!$A:$H,6,FALSE) -> 37323000 | U2: =VLOOKUP($D2,'ip prosedur-14 okt-15 juni 2026'!$A:$H,7,FALSE) -> 62092164 | V2: =VLOOKUP($D2,'ip prosedur-14 okt-15 juni 2026'!$A:$H,8,FALSE) -> 102438900
A3: PDC | B3: P16AB | C3: Stomach, Esophagus & Duodenal Resection Procedures | D3: 42.41 | E3: Partial esophagectomy | F3: =VLOOKUP($D3,proc!$A:$D,3, FALSE) -> 6 | G3: =C3 -> Stomach, Esophagus & Duodenal Resection Procedures | H3: =B3 -> P16AB | K3: =VLOOKUP($B3,'tarif idrg'!$A:$O,11,FALSE) -> 18485238 | L3: =VLOOKUP($B3,'tarif idrg'!$A:$O,15,FALSE) -> 18485238 | N3: =IF(C3<>G3,"Change","-") -> - | O3: =VLOOKUP($D3,'ip prosedur-2025'!$A:$H,4,FALSE) -> 1.2611458e+08 | P3: =VLOOKUP($D3,'ip prosedur-14 okt-15 juni 2026'!$A:$H,4,FALSE) -> 1.1940485e+08 | Q3: =VLOOKUP($D3,'ip prosedur-14 okt-15 juni 2026'!$A:$H,3, FALSE) -> 43 | R3: =P3*Q3 -> 5134408520 | S3: =VLOOKUP($D3,'ip prosedur-14 okt-15 juni 2026'!$A:$H,5,FALSE) -> 53608899 | T3: =VLOOKUP($D3,'ip prosedur-14 okt-15 juni 2026'!$A:$H,6,FALSE) -> 108589810 | U3: =VLOOKUP($D3,'ip prosedur-14 okt-15 juni 2026'!$A:$H,7,FALSE) -> 157989413 | V3: =VLOOKUP($D3,'ip prosedur-14 okt-15 juni 2026'!$A:$H,8,FALSE) -> 205202294
A4: PDC | B4: P16AB | C4: Stomach, Esophagus & Duodenal Resection Procedures | D4: 42.42 | E4: Total esophagectomy | F4: =VLOOKUP($D4,proc!$A:$D,3, FALSE) -> 6 | G4: =C4 -> Stomach, Esophagus & Duodenal Resection Procedures | H4: =B4 -> P16AB | K4: =VLOOKUP($B4,'tarif idrg'!$A:$O,11,FALSE) -> 18485238 | L4: =VLOOKUP($B4,'tarif idrg'!$A:$O,15,FALSE) -> 18485238 | N4: =IF(C4<>G4,"Change","-") -> - | O4: =VLOOKUP($D4,'ip prosedur-2025'!$A:$H,4,FALSE) -> 1.1499459e+08 | P4: =VLOOKUP($D4,'ip prosedur-14 okt-15 juni 2026'!$A:$H,4,FALSE) -> 75994185 | Q4: =VLOOKUP($D4,'ip prosedur-14 okt-15 juni 2026'!$A:$H,3, FALSE) -> 9 | R4: =P4*Q4 -> 683947667 | S4: =VLOOKUP($D4,'ip prosedur-14 okt-15 juni 2026'!$A:$H,5,FALSE) -> 46214359 | T4: =VLOOKUP($D4,'ip prosedur-14 okt-15 juni 2026'!$A:$H,6,FALSE) -> 69417899 | U4: =VLOOKUP($D4,'ip prosedur-14 okt-15 juni 2026'!$A:$H,7,FALSE) -> 101663598 | V4: =VLOOKUP($D4,'ip prosedur-14 okt-15 juni 2026'!$A:$H,8,FALSE) -> 167465700
A5: PDC | B5: P16AB | C5: Stomach, Esophagus & Duodenal Resection Procedures | D5: 43.5 | E5: Partial gastrectomy with anastomosis to esophagus | F5: =VLOOKUP($D5,proc!$A:$D,3, FALSE) -> 5 | G5: =C5 -> Stomach, Esophagus & Duodenal Resection Procedures | H5: =B5 -> P16AB | K5: =VLOOKUP($B5,'tarif idrg'!$A:$O,11,FALSE) -> 18485238 | L5: =VLOOKUP($B5,'tarif idrg'!$A:$O,15,FALSE) -> 18485238 | N5: =IF(C5<>G5,"Change","-") -> - | O5: =VLOOKUP($D5,'ip prosedur-2025'!$A:$H,4,FALSE) -> 98744188 | P5: =VLOOKUP($D5,'ip prosedur-14 okt-15 juni 2026'!$A:$H,4,FALSE) -> 94617269 | Q5: =VLOOKUP($D5,'ip prosedur-14 okt-15 juni 2026'!$A:$H,3, FALSE) -> 53 | R5: =P5*Q5 -> 5014715278 | S5: =VLOOKUP($D5,'ip prosedur-14 okt-15 juni 2026'!$A:$H,5,FALSE) -> 42753297 | T5: =VLOOKUP($D5,'ip prosedur-14 okt-15 juni 2026'!$A:$H,6,FALSE) -> 79648401 | U5: =VLOOKUP($D5,'ip prosedur-14 okt-15 juni 2026'!$A:$H,7,FALSE) -> 126490623 | V5: =VLOOKUP($D5,'ip prosedur-14 okt-15 juni 2026'!$A:$H,8,FALSE) -> 200440522
A6: PDC | B6: P16AB | C6: Stomach, Esophagus & Duodenal Resection Procedures | D6: 43.6 | E6: Partial gastrectomy with anastomosis to duodenum | F6: =VLOOKUP($D6,proc!$A:$D,3, FALSE) -> 5 | G6: =C6 -> Stomach, Esophagus & Duodenal Resection Procedures | H6: =B6 -> P16AB | K6: =VLOOKUP($B6,'tarif idrg'!$A:$O,11,FALSE) -> 18485238 | L6: =VLOOKUP($B6,'tarif idrg'!$A:$O,15,FALSE) -> 18485238 | N6: =IF(C6<>G6,"Change","-") -> - | O6: =VLOOKUP($D6,'ip prosedur-2025'!$A:$H,4,FALSE) -> 75277649 | P6: =VLOOKUP($D6,'ip prosedur-14 okt-15 juni 2026'!$A:$H,4,FALSE) -> 72766392 | Q6: =VLOOKUP($D6,'ip prosedur-14 okt-15 juni 2026'!$A:$H,3, FALSE) -> 58 | R6: =P6*Q6 -> 4220450728 | S6: =VLOOKUP($D6,'ip prosedur-14 okt-15 juni 2026'!$A:$H,5,FALSE) -> 40672345 | T6: =VLOOKUP($D6,'ip prosedur-14 okt-15 juni 2026'!$A:$H,6,FALSE) -> 58786202 | U6: =VLOOKUP($D6,'ip prosedur-14 okt-15 juni 2026'!$A:$H,7,FALSE) -> 91531996 | V6: =VLOOKUP($D6,'ip prosedur-14 okt-15 juni 2026'!$A:$H,8,FALSE) -> 148960900
A7: PDC | B7: P16AB | C7: Stomach, Esophagus & Duodenal Resection Procedures | D7: 43.7 | E7: Partial gastrectomy with anastomosis to jejunum | F7: =VLOOKUP($D7,proc!$A:$D,3, FALSE) -> 6 | G7: =C7 -> Stomach, Esophagus & Duodenal Resection Procedures | H7: =B7 -> P16AB | K7: =VLOOKUP($B7,'tarif idrg'!$A:$O,11,FALSE) -> 18485238 | L7: =VLOOKUP($B7,'tarif idrg'!$A:$O,15,FALSE) -> 18485238 | N7: =IF(C7<>G7,"Change","-") -> - | O7: =VLOOKUP($D7,'ip prosedur-2025'!$A:$H,4,FALSE) -> 74462792 | P7: =VLOOKUP($D7,'ip prosedur-14 okt-15 juni 2026'!$A:$H,4,FALSE) -> 74421012 | Q7: =VLOOKUP($D7,'ip prosedur-14 okt-15 juni 2026'!$A:$H,3, FALSE) -> 231 | R7: =P7*Q7 -> 17191253712 | S7: =VLOOKUP($D7,'ip prosedur-14 okt-15 juni 2026'!$A:$H,5,FALSE) -> 34708610 | T7: =VLOOKUP($D7,'ip prosedur-14 okt-15 juni 2026'!$A:$H,6,FALSE) -> 60993125 | U7: =VLOOKUP($D7,'ip prosedur-14 okt-15 juni 2026'!$A:$H,7,FALSE) -> 92240100 | V7: =VLOOKUP($D7,'ip prosedur-14 okt-15 juni 2026'!$A:$H,8,FALSE) -> 135701622
A8: PDC | B8: P16AB | C8: Stomach, Esophagus & Duodenal Resection Procedures | D8: 43.81 | E8: Partial gastrectomy with jejunal transposition | F8: =VLOOKUP($D8,proc!$A:$D,3, FALSE) -> 6 | G8: =C8 -> Stomach, Esophagus & Duodenal Resection Procedures | H8: =B8 -> P16AB | K8: =VLOOKUP($B8,'tarif idrg'!$A:$O,11,FALSE) -> 18485238 | L8: =VLOOKUP($B8,'tarif idrg'!$A:$O,15,FALSE) -> 18485238 | N8: =IF(C8<>G8,"Change","-") -> - | O8: =VLOOKUP($D8,'ip prosedur-2025'!$A:$H,4,FALSE) -> 80525516 | P8: =VLOOKUP($D8,'ip prosedur-14 okt-15 juni 2026'!$A:$H,4,FALSE) -> 73089081 | Q8: =VLOOKUP($D8,'ip prosedur-14 okt-15 juni 2026'!$A:$H,3, FALSE) -> 5 | R8: =P8*Q8 -> 365445407 | S8: =VLOOKUP($D8,'ip prosedur-14 okt-15 juni 2026'!$A:$H,5,FALSE) -> 63276121 | T8: =VLOOKUP($D8,'ip prosedur-14 okt-15 juni 2026'!$A:$H,6,FALSE) -> 70513922 | U8: =VLOOKUP($D8,'ip prosedur-14 okt-15 juni 2026'!$A:$H,7,FALSE) -> 82309664 | V8: =VLOOKUP($D8,'ip prosedur-14 okt-15 juni 2026'!$A:$H,8,FALSE) -> 104230307
A9: PDC | B9: P16AB | C9: Stomach, Esophagus & Duodenal Resection Procedures | D9: 43.89 | E9: Other partial gastrectomy | F9: =VLOOKUP($D9,proc!$A:$D,3, FALSE) -> 5 | G9: =C9 -> Stomach, Esophagus & Duodenal Resection Procedures | H9: =B9 -> P16AB | K9: =VLOOKUP($B9,'tarif idrg'!$A:$O,11,FALSE) -> 18485238 | L9: =VLOOKUP($B9,'tarif idrg'!$A:$O,15,FALSE) -> 18485238 | N9: =IF(C9<>G9,"Change","-") -> - | O9: =VLOOKUP($D9,'ip prosedur-2025'!$A:$H,4,FALSE) -> 52574054 | P9: =VLOOKUP($D9,'ip prosedur-14 okt-15 juni 2026'!$A:$H,4,FALSE) -> 53324980 | Q9: =VLOOKUP($D9,'ip prosedur-14 okt-15 juni 2026'!$A:$H,3, FALSE) -> 350 | R9: =P9*Q9 -> 18663743053 | S9: =VLOOKUP($D9,'ip prosedur-14 okt-15 juni 2026'!$A:$H,5,FALSE) -> 20792502 | T9: =VLOOKUP($D9,'ip prosedur-14 okt-15 juni 2026'!$A:$H,6,FALSE) -> 32577345 | U9: =VLOOKUP($D9,'ip prosedur-14 okt-15 juni 2026'!$A:$H,7,FALSE) -> 65702614 | V9: =VLOOKUP($D9,'ip prosedur-14 okt-15 juni 2026'!$A:$H,8,FALSE) -> 101884136
A10: PDC | B10: P16AB | C10: Stomach, Esophagus & Duodenal Resection Procedures | D10: 43.91 | E10: Total gastrectomy with intestinal interposition | F10: =VLOOKUP($D10,proc!$A:$D,3, FALSE) -> 6 | G10: =C10 -> Stomach, Esophagus & Duodenal Resection Procedures | H10: =B10 -> P16AB | K10: =VLOOKUP($B10,'tarif idrg'!$A:$O,11,FALSE) -> 18485238 | L10: =VLOOKUP($B10,'tarif idrg'!$A:$O,15,FALSE) -> 18485238 | N10: =IF(C10<>G10,"Change","-") -> - | O10: =VLOOKUP($D10,'ip prosedur-2025'!$A:$H,4,FALSE) -> 1.1919652e+08 | P10: =VLOOKUP($D10,'ip prosedur-14 okt-15 juni 2026'!$A:$H,4,FALSE) -> 1.4422502e+08 | Q10: =VLOOKUP($D10,'ip prosedur-14 okt-15 juni 2026'!$A:$H,3, FALSE) -> 10 | R10: =P10*Q10 -> 1442250236 | S10: =VLOOKUP($D10,'ip prosedur-14 okt-15 juni 2026'!$A:$H,5,FALSE) -> 85870232 | T10: =VLOOKUP($D10,'ip prosedur-14 okt-15 juni 2026'!$A:$H,6,FALSE) -> 92324883 | U10: =VLOOKUP($D10,'ip prosedur-14 okt-15 juni 2026'!$A:$H,7,FALSE) -> 151293741 | V10: =VLOOKUP($D10,'ip prosedur-14 okt-15 juni 2026'!$A:$H,8,FALSE) -> 205202294
A11: PDC | B11: P16AB | C11: Stomach, Esophagus & Duodenal Resection Procedures | D11: 43.99 | E11: Other total gastrectomy | F11: =VLOOKUP($D11,proc!$A:$D,3, FALSE) -> 6 | G11: =C11 -> Stomach, Esophagus & Duodenal Resection Procedures | H11: =B11 -> P16AB | K11: =VLOOKUP($B11,'tarif idrg'!$A:$O,11,FALSE) -> 18485238 | L11: =VLOOKUP($B11,'tarif idrg'!$A:$O,15,FALSE) -> 18485238 | N11: =IF(C11<>G11,"Change","-") -> - | O11: =VLOOKUP($D11,'ip prosedur-2025'!$A:$H,4,FALSE) -> 87655495 | P11: =VLOOKUP($D11,'ip prosedur-14 okt-15 juni 2026'!$A:$H,4,FALSE) -> 1.1048437e+08 | Q11: =VLOOKUP($D11,'ip prosedur-14 okt-15 juni 2026'!$A:$H,3, FALSE) -> 45 | R11: =P11*Q11 -> 4971796542 | S11: =VLOOKUP($D11,'ip prosedur-14 okt-15 juni 2026'!$A:$H,5,FALSE) -> 43422908 | T11: =VLOOKUP($D11,'ip prosedur-14 okt-15 juni 2026'!$A:$H,6,FALSE) -> 91403368 | U11: =VLOOKUP($D11,'ip prosedur-14 okt-15 juni 2026'!$A:$H,7,FALSE) -> 122210336 | V11: =VLOOKUP($D11,'ip prosedur-14 okt-15 juni 2026'!$A:$H,8,FALSE) -> 234211982
A12: PDC | B12: P16AD | C12: Rectal Resection Procedures | D12: 48.0 | E12: Proctotomy | F12: =VLOOKUP($D12,proc!$A:$D,3, FALSE) -> 4 | G12: =C12 -> Rectal Resection Procedures | H12: =B12 -> P16AD | K12: =VLOOKUP($B12,'tarif idrg'!$A:$O,11,FALSE) -> 19047832 | L12: =VLOOKUP($B12,'tarif idrg'!$A:$O,15,FALSE) -> 19047832 | N12: =IF(C12<>G12,"Change","-") -> - | O12: =VLOOKUP($D12,'ip prosedur-2025'!$A:$H,4,FALSE) -> 19959087 | P12: =VLOOKUP($D12,'ip prosedur-14 okt-15 juni 2026'!$A:$H,4,FALSE) -> 17114671 | Q12: =VLOOKUP($D12,'ip prosedur-14 okt-15 juni 2026'!$A:$H,3, FALSE) -> 30 | R12: =P12*Q12 -> 513440133 | S12: =VLOOKUP($D12,'ip prosedur-14 okt-15 juni 2026'!$A:$H,5,FALSE) -> 7283797 | T12: =VLOOKUP($D12,'ip prosedur-14 okt-15 juni 2026'!$A:$H,6,FALSE) -> 13968995 | U12: =VLOOKUP($D12,'ip prosedur-14 okt-15 juni 2026'!$A:$H,7,FALSE) -> 25205333 | V12: =VLOOKUP($D12,'ip prosedur-14 okt-15 juni 2026'!$A:$H,8,FALSE) -> 32847476
A13: PDC | B13: P16AD | C13: Rectal Resection Procedures | D13: 48.40 | E13: Pull-through resection of rectum, not otherwise specified | F13: =VLOOKUP($D13,proc!$A:$D,3, FALSE) -> 5 | G13: =C13 -> Rectal Resection Procedures | H13: =B13 -> P16AD | K13: =VLOOKUP($B13,'tarif idrg'!$A:$O,11,FALSE) -> 19047832 | L13: =VLOOKUP($B13,'tarif idrg'!$A:$O,15,FALSE) -> 19047832 | N13: =IF(C13<>G13,"Change","-") -> - | O13: =VLOOKUP($D13,'ip prosedur-2025'!$A:$H,4,FALSE) -> 40360689 | P13: =VLOOKUP($D13,'ip prosedur-14 okt-15 juni 2026'!$A:$H,4,FALSE) -> 34725012 | Q13: =VLOOKUP($D13,'ip prosedur-14 okt-15 juni 2026'!$A:$H,3, FALSE) -> 132 | R13: =P13*Q13 -> 4583701558 | S13: =VLOOKUP($D13,'ip prosedur-14 okt-15 juni 2026'!$A:$H,5,FALSE) -> 15014000 | T13: =VLOOKUP($D13,'ip prosedur-14 okt-15 juni 2026'!$A:$H,6,FALSE) -> 23447487 | U13: =VLOOKUP($D13,'ip prosedur-14 okt-15 juni 2026'!$A:$H,7,FALSE) -> 33824388 | V13: =VLOOKUP($D13,'ip prosedur-14 okt-15 juni 2026'!$A:$H,8,FALSE) -> 57323242
... A218: PDC | B218: P16AR | C218: Complex Therapeutic Colonoscopy | D218: 45.43 | E218: Endoscopic destruction of other lesion or tissue of large intestine | F218: =VLOOKUP($D218,proc!$A:$D,3, FALSE) -> 0 | G218: =C218 -> Complex Therapeutic Colonoscopy | H218: =B218 -> P16AR | K218: =VLOOKUP($B218,'tarif idrg'!$A:$O,11,FALSE) -> 4822236 | L218: =VLOOKUP($B218,'tarif idrg'!$A:$O,15,FALSE) -> 4822236 | N218: =IF(C218<>G218,"Change","-") -> - | O218: =VLOOKUP($D218,'ip prosedur-2025'!$A:$H,4,FALSE) -> 22653031 | P218: =VLOOKUP($D218,'ip prosedur-14 okt-15 juni 2026'!$A:$H,4,FALSE) -> 23169771 | Q218: =VLOOKUP($D218,'ip prosedur-14 okt-15 juni 2026'!$A:$H,3, FALSE) -> 149 | R218: =P218*Q218 -> 3452295822 | S218: =VLOOKUP($D218,'ip prosedur-14 okt-15 juni 2026'!$A:$H,5,FALSE) -> 7029841 | T218: =VLOOKUP($D218,'ip prosedur-14 okt-15 juni 2026'!$A:$H,6,FALSE) -> 17173400 | U218: =VLOOKUP($D218,'ip prosedur-14 okt-15 juni 2026'!$A:$H,7,FALSE) -> 31940856 | V218: =VLOOKUP($D218,'ip prosedur-14 okt-15 juni 2026'!$A:$H,8,FALSE) -> 39472470
A219: PDC | B219: P16AJ | C219: Minor Small and Large Bowel Procedures | D219: PDC | F219: =VLOOKUP($D219,proc!$A:$D,3, FALSE) -> #N/A | G219: =C219 -> Minor Small and Large Bowel Procedures | H219: =B219 -> P16AJ | K219: =VLOOKUP($B219,'tarif idrg'!$A:$O,11,FALSE) -> #N/A | L219: =VLOOKUP($B219,'tarif idrg'!$A:$O,15,FALSE) -> #N/A | N219: =IF(C219<>G219,"Change","-") -> - | O219: =VLOOKUP($D219,'ip prosedur-2025'!$A:$H,4,FALSE) -> #N/A | P219: =VLOOKUP($D219,'ip prosedur-14 okt-15 juni 2026'!$A:$H,4,FALSE) -> #N/A | Q219: =VLOOKUP($D219,'ip prosedur-14 okt-15 juni 2026'!$A:$H,3, FALSE) -> #N/A | R219: =P219*Q219 -> #N/A | S219: =VLOOKUP($D219,'ip prosedur-14 okt-15 juni 2026'!$A:$H,5,FALSE) -> #N/A | T219: =VLOOKUP($D219,'ip prosedur-14 okt-15 juni 2026'!$A:$H,6,FALSE) -> #N/A | U219: =VLOOKUP($D219,'ip prosedur-14 okt-15 juni 2026'!$A:$H,7,FALSE) -> #N/A | V219: =VLOOKUP($D219,'ip prosedur-14 okt-15 juni 2026'!$A:$H,8,FALSE) -> #N/A
A220: PDC | B220: P16AJ | C220: Minor Small and Large Bowel Procedures | D220: 45.02 | E220: Other incision of small intestine | F220: =VLOOKUP($D220,proc!$A:$D,3, FALSE) -> 4 | G220: =C220 -> Minor Small and Large Bowel Procedures | H220: =B220 -> P16AJ | K220: =VLOOKUP($B220,'tarif idrg'!$A:$O,11,FALSE) -> #N/A | L220: =VLOOKUP($B220,'tarif idrg'!$A:$O,15,FALSE) -> #N/A | N220: =IF(C220<>G220,"Change","-") -> - | O220: =VLOOKUP($D220,'ip prosedur-2025'!$A:$H,4,FALSE) -> 47327291 | P220: =VLOOKUP($D220,'ip prosedur-14 okt-15 juni 2026'!$A:$H,4,FALSE) -> 54690432 | Q220: =VLOOKUP($D220,'ip prosedur-14 okt-15 juni 2026'!$A:$H,3, FALSE) -> 94 | R220: =P220*Q220 -> 5140900608 | S220: =VLOOKUP($D220,'ip prosedur-14 okt-15 juni 2026'!$A:$H,5,FALSE) -> 17362785 | T220: =VLOOKUP($D220,'ip prosedur-14 okt-15 juni 2026'!$A:$H,6,FALSE) -> 32814821 | U220: =VLOOKUP($D220,'ip prosedur-14 okt-15 juni 2026'!$A:$H,7,FALSE) -> 66778900 | V220: =VLOOKUP($D220,'ip prosedur-14 okt-15 juni 2026'!$A:$H,8,FALSE) -> 121182345
A221: PDC | B221: P16AJ | C221: Minor Small and Large Bowel Procedures | D221: 45.03 | E221: Incision of large intestine | F221: =VLOOKUP($D221,proc!$A:$D,3, FALSE) -> 4 | G221: =C221 -> Minor Small and Large Bowel Procedures | H221: =B221 -> P16AJ | K221: =VLOOKUP($B221,'tarif idrg'!$A:$O,11,FALSE) -> #N/A | L221: =VLOOKUP($B221,'tarif idrg'!$A:$O,15,FALSE) -> #N/A | N221: =IF(C221<>G221,"Change","-") -> - | O221: =VLOOKUP($D221,'ip prosedur-2025'!$A:$H,4,FALSE) -> 56875818 | P221: =VLOOKUP($D221,'ip prosedur-14 okt-15 juni 2026'!$A:$H,4,FALSE) -> 44744856 | Q221: =VLOOKUP($D221,'ip prosedur-14 okt-15 juni 2026'!$A:$H,3, FALSE) -> 108 | R221: =P221*Q221 -> 4832444400 | S221: =VLOOKUP($D221,'ip prosedur-14 okt-15 juni 2026'!$A:$H,5,FALSE) -> 19368463 | T221: =VLOOKUP($D221,'ip prosedur-14 okt-15 juni 2026'!$A:$H,6,FALSE) -> 32688098 | U221: =VLOOKUP($D221,'ip prosedur-14 okt-15 juni 2026'!$A:$H,7,FALSE) -> 51267949 | V221: =VLOOKUP($D221,'ip prosedur-14 okt-15 juni 2026'!$A:$H,8,FALSE) -> 92616208
A222: PDC | B222: P16AJ | C222: Minor Small and Large Bowel Procedures | D222: 45.11 | E222: Transabdominal endoscopy of small intestine | F222: =VLOOKUP($D222,proc!$A:$D,3, FALSE) -> 0 | G222: =C222 -> Minor Small and Large Bowel Procedures | H222: =B222 -> P16AJ | K222: =VLOOKUP($B222,'tarif idrg'!$A:$O,11,FALSE) -> #N/A | L222: =VLOOKUP($B222,'tarif idrg'!$A:$O,15,FALSE) -> #N/A | N222: =IF(C222<>G222,"Change","-") -> - | O222: =VLOOKUP($D222,'ip prosedur-2025'!$A:$H,4,FALSE) -> 19692268 | P222: =VLOOKUP($D222,'ip prosedur-14 okt-15 juni 2026'!$A:$H,4,FALSE) -> 34061280 | Q222: =VLOOKUP($D222,'ip prosedur-14 okt-15 juni 2026'!$A:$H,3, FALSE) -> 17 | R222: =P222*Q222 -> 579041759 | S222: =VLOOKUP($D222,'ip prosedur-14 okt-15 juni 2026'!$A:$H,5,FALSE) -> 12377427 | T222: =VLOOKUP($D222,'ip prosedur-14 okt-15 juni 2026'!$A:$H,6,FALSE) -> 15374613 | U222: =VLOOKUP($D222,'ip prosedur-14 okt-15 juni 2026'!$A:$H,7,FALSE) -> 44843982 | V222: =VLOOKUP($D222,'ip prosedur-14 okt-15 juni 2026'!$A:$H,8,FALSE) -> 88059127
A223: PDC | B223: P16AJ | C223: Minor Small and Large Bowel Procedures | D223: 45.15 | E223: Open biopsy of small intestine | F223: =VLOOKUP($D223,proc!$A:$D,3, FALSE) -> 4 | G223: =C223 -> Minor Small and Large Bowel Procedures | H223: =B223 -> P16AJ | K223: =VLOOKUP($B223,'tarif idrg'!$A:$O,11,FALSE) -> #N/A | L223: =VLOOKUP($B223,'tarif idrg'!$A:$O,15,FALSE) -> #N/A | N223: =IF(C223<>G223,"Change","-") -> - | O223: =VLOOKUP($D223,'ip prosedur-2025'!$A:$H,4,FALSE) -> 33645451 | P223: =VLOOKUP($D223,'ip prosedur-14 okt-15 juni 2026'!$A:$H,4,FALSE) -> 35811168 | Q223: =VLOOKUP($D223,'ip prosedur-14 okt-15 juni 2026'!$A:$H,3, FALSE) -> 396 | R223: =P223*Q223 -> 14181222425 | S223: =VLOOKUP($D223,'ip prosedur-14 okt-15 juni 2026'!$A:$H,5,FALSE) -> 15015039 | T223: =VLOOKUP($D223,'ip prosedur-14 okt-15 juni 2026'!$A:$H,6,FALSE) -> 23930024 | U223: =VLOOKUP($D223,'ip prosedur-14 okt-15 juni 2026'!$A:$H,7,FALSE) -> 43515833 | V223: =VLOOKUP($D223,'ip prosedur-14 okt-15 juni 2026'!$A:$H,8,FALSE) -> 73132299
A224: PDC | B224: P16AJ | C224: Minor Small and Large Bowel Procedures | D224: 45.19 | E224: Other diagnostic procedures on small intestine | F224: =VLOOKUP($D224,proc!$A:$D,3, FALSE) -> 0 | G224: =C224 -> Minor Small and Large Bowel Procedures | H224: =B224 -> P16AJ | K224: =VLOOKUP($B224,'tarif idrg'!$A:$O,11,FALSE) -> #N/A | L224: =VLOOKUP($B224,'tarif idrg'!$A:$O,15,FALSE) -> #N/A | N224: =IF(C224<>G224,"Change","-") -> - | O224: =VLOOKUP($D224,'ip prosedur-2025'!$A:$H,4,FALSE) -> 30629622 | P224: =VLOOKUP($D224,'ip prosedur-14 okt-15 juni 2026'!$A:$H,4,FALSE) -> 31869876 | Q224: =VLOOKUP($D224,'ip prosedur-14 okt-15 juni 2026'!$A:$H,3, FALSE) -> 22 | R224: =P224*Q224 -> 701137279 | S224: =VLOOKUP($D224,'ip prosedur-14 okt-15 juni 2026'!$A:$H,5,FALSE) -> 11035132 | T224: =VLOOKUP($D224,'ip prosedur-14 okt-15 juni 2026'!$A:$H,6,FALSE) -> 15911016 | U224: =VLOOKUP($D224,'ip prosedur-14 okt-15 juni 2026'!$A:$H,7,FALSE) -> 29372655 | V224: =VLOOKUP($D224,'ip prosedur-14 okt-15 juni 2026'!$A:$H,8,FALSE) -> 56264468
A225: PDC | B225: P16AJ | C225: Minor Small and Large Bowel Procedures | D225: 45.26 | E225: Open biopsy of large intestine | F225: =VLOOKUP($D225,proc!$A:$D,3, FALSE) -> 4 | G225: =C225 -> Minor Small and Large Bowel Procedures | H225: =B225 -> P16AJ | K225: =VLOOKUP($B225,'tarif idrg'!$A:$O,11,FALSE) -> #N/A | L225: =VLOOKUP($B225,'tarif idrg'!$A:$O,15,FALSE) -> #N/A | N225: =IF(C225<>G225,"Change","-") -> - | O225: =VLOOKUP($D225,'ip prosedur-2025'!$A:$H,4,FALSE) -> 28311589 | P225: =VLOOKUP($D225,'ip prosedur-14 okt-15 juni 2026'!$A:$H,4,FALSE) -> 28227707 | Q225: =VLOOKUP($D225,'ip prosedur-14 okt-15 juni 2026'!$A:$H,3, FALSE) -> 1532 | R225: =P225*Q225 -> 43244847078 | S225: =VLOOKUP($D225,'ip prosedur-14 okt-15 juni 2026'!$A:$H,5,FALSE) -> 13812279 | T225: =VLOOKUP($D225,'ip prosedur-14 okt-15 juni 2026'!$A:$H,6,FALSE) -> 19752805 | U225: =VLOOKUP($D225,'ip prosedur-14 okt-15 juni 2026'!$A:$H,7,FALSE) -> 30867651 | V225: =VLOOKUP($D225,'ip prosedur-14 okt-15 juni 2026'!$A:$H,8,FALSE) -> 52640969
A226: PDC | B226: P16AJ | C226: Minor Small and Large Bowel Procedures | D226: 45.27 | E226: Intestinal biopsy, site unspecified | F226: =VLOOKUP($D226,proc!$A:$D,3, FALSE) -> 0 | G226: =C226 -> Minor Small and Large Bowel Procedures | H226: =B226 -> P16AJ | K226: =VLOOKUP($B226,'tarif idrg'!$A:$O,11,FALSE) -> #N/A | L226: =VLOOKUP($B226,'tarif idrg'!$A:$O,15,FALSE) -> #N/A | N226: =IF(C226<>G226,"Change","-") -> - | O226: =VLOOKUP($D226,'ip prosedur-2025'!$A:$H,4,FALSE) -> 26523378 | P226: =VLOOKUP($D226,'ip prosedur-14 okt-15 juni 2026'!$A:$H,4,FALSE) -> 25600631 | Q226: =VLOOKUP($D226,'ip prosedur-14 okt-15 juni 2026'!$A:$H,3, FALSE) -> 136 | R226: =P226*Q226 -> 3481685755 | S226: =VLOOKUP($D226,'ip prosedur-14 okt-15 juni 2026'!$A:$H,5,FALSE) -> 14368033 | T226: =VLOOKUP($D226,'ip prosedur-14 okt-15 juni 2026'!$A:$H,6,FALSE) -> 19608499 | U226: =VLOOKUP($D226,'ip prosedur-14 okt-15 juni 2026'!$A:$H,7,FALSE) -> 32608965 | V226: =VLOOKUP($D226,'ip prosedur-14 okt-15 juni 2026'!$A:$H,8,FALSE) -> 45232826
A227: PDC | B227: P16AJ | C227: Minor Small and Large Bowel Procedures | D227: 45.28 | E227: Other diagnostic procedures on large intestine | F227: =VLOOKUP($D227,proc!$A:$D,3, FALSE) -> 0 | G227: =C227 -> Minor Small and Large Bowel Procedures | H227: =B227 -> P16AJ | K227: =VLOOKUP($B227,'tarif idrg'!$A:$O,11,FALSE) -> #N/A | L227: =VLOOKUP($B227,'tarif idrg'!$A:$O,15,FALSE) -> #N/A | N227: =IF(C227<>G227,"Change","-") -> - | O227: =VLOOKUP($D227,'ip prosedur-2025'!$A:$H,4,FALSE) -> 25116833 | P227: =VLOOKUP($D227,'ip prosedur-14 okt-15 juni 2026'!$A:$H,4,FALSE) -> 17245994 | Q227: =VLOOKUP($D227,'ip prosedur-14 okt-15 juni 2026'!$A:$H,3, FALSE) -> 6 | R227: =P227*Q227 -> 103475964 | S227: =VLOOKUP($D227,'ip prosedur-14 okt-15 juni 2026'!$A:$H,5,FALSE) -> 3638415 | T227: =VLOOKUP($D227,'ip prosedur-14 okt-15 juni 2026'!$A:$H,6,FALSE) -> 8176357 | U227: =VLOOKUP($D227,'ip prosedur-14 okt-15 juni 2026'!$A:$H,7,FALSE) -> 17306350 | V227: =VLOOKUP($D227,'ip prosedur-14 okt-15 juni 2026'!$A:$H,8,FALSE) -> 59574775
A228: PDC | B228: P16AJ | C228: Minor Small and Large Bowel Procedures | D228: 45.34 | E228: Other destruction of lesion of small intestine, except duodenum | F228: =VLOOKUP($D228,proc!$A:$D,3, FALSE) -> 4 | G228: =C228 -> Minor Small and Large Bowel Procedures | H228: =B228 -> P16AJ | K228: =VLOOKUP($B228,'tarif idrg'!$A:$O,11,FALSE) -> #N/A | L228: =VLOOKUP($B228,'tarif idrg'!$A:$O,15,FALSE) -> #N/A | N228: =IF(C228<>G228,"Change","-") -> - | O228: =VLOOKUP($D228,'ip prosedur-2025'!$A:$H,4,FALSE) -> 39306713 | P228: =VLOOKUP($D228,'ip prosedur-14 okt-15 juni 2026'!$A:$H,4,FALSE) -> 56542585 | Q228: =VLOOKUP($D228,'ip prosedur-14 okt-15 juni 2026'!$A:$H,3, FALSE) -> 39 | R228: =P228*Q228 -> 2205160798 | S228: =VLOOKUP($D228,'ip prosedur-14 okt-15 juni 2026'!$A:$H,5,FALSE) -> 16913293 | T228: =VLOOKUP($D228,'ip prosedur-14 okt-15 juni 2026'!$A:$H,6,FALSE) -> 25618104 | U228: =VLOOKUP($D228,'ip prosedur-14 okt-15 juni 2026'!$A:$H,7,FALSE) -> 62026445 | V228: =VLOOKUP($D228,'ip prosedur-14 okt-15 juni 2026'!$A:$H,8,FALSE) -> 152417404
A229: PDC | B229: P16AJ | C229: Minor Small and Large Bowel Procedures | D229: 45.49 | E229: Other destruction of lesion of large intestine | F229: =VLOOKUP($D229,proc!$A:$D,3, FALSE) -> 4 | G229: =C229 -> Minor Small and Large Bowel Procedures | H229: =B229 -> P16AJ | K229: =VLOOKUP($B229,'tarif idrg'!$A:$O,11,FALSE) -> #N/A | L229: =VLOOKUP($B229,'tarif idrg'!$A:$O,15,FALSE) -> #N/A | N229: =IF(C229<>G229,"Change","-") -> - | O229: =VLOOKUP($D229,'ip prosedur-2025'!$A:$H,4,FALSE) -> 30218864 | P229: =VLOOKUP($D229,'ip prosedur-14 okt-15 juni 2026'!$A:$H,4,FALSE) -> 44598676 | Q229: =VLOOKUP($D229,'ip prosedur-14 okt-15 juni 2026'!$A:$H,3, FALSE) -> 56 | R229: =P229*Q229 -> 2497525866 | S229: =VLOOKUP($D229,'ip prosedur-14 okt-15 juni 2026'!$A:$H,5,FALSE) -> 15186078 | T229: =VLOOKUP($D229,'ip prosedur-14 okt-15 juni 2026'!$A:$H,6,FALSE) -> 25649925 | U229: =VLOOKUP($D229,'ip prosedur-14 okt-15 juni 2026'!$A:$H,7,FALSE) -> 57426200 | V229: =VLOOKUP($D229,'ip prosedur-14 okt-15 juni 2026'!$A:$H,8,FALSE) -> 101155350
A230: PDC | B230: P16AJ | C230: Minor Small and Large Bowel Procedures | D230: 45.50 | E230: Isolation of intestinal segment, not otherwise specified | F230: =VLOOKUP($D230,proc!$A:$D,3, FALSE) -> 5 | G230: =C230 -> Minor Small and Large Bowel Procedures | H230: =B230 -> P16AJ | K230: =VLOOKUP($B230,'tarif idrg'!$A:$O,11,FALSE) -> #N/A | L230: =VLOOKUP($B230,'tarif idrg'!$A:$O,15,FALSE) -> #N/A | N230: =IF(C230<>G230,"Change","-") -> - | O230: =VLOOKUP($D230,'ip prosedur-2025'!$A:$H,4,FALSE) -> 1.705323e+08 | P230: =VLOOKUP($D230,'ip prosedur-14 okt-15 juni 2026'!$A:$H,4,FALSE) -> 42031596 | Q230: =VLOOKUP($D230,'ip prosedur-14 okt-15 juni 2026'!$A:$H,3, FALSE) -> 7 | R230: =P230*Q230 -> 294221171 | S230: =VLOOKUP($D230,'ip prosedur-14 okt-15 juni 2026'!$A:$H,5,FALSE) -> 8756700 | T230: =VLOOKUP($D230,'ip prosedur-14 okt-15 juni 2026'!$A:$H,6,FALSE) -> 30049243 | U230: =VLOOKUP($D230,'ip prosedur-14 okt-15 juni 2026'!$A:$H,7,FALSE) -> 40729704 | V230: =VLOOKUP($D230,'ip prosedur-14 okt-15 juni 2026'!$A:$H,8,FALSE) -> 150314277
A231: PDC | B231: P16AJ | C231: Minor Small and Large Bowel Procedures | D231: 46.60 | E231: Fixation of intestine, not otherwise specified | F231: =VLOOKUP($D231,proc!$A:$D,3, FALSE) -> 3 | G231: =C231 -> Minor Small and Large Bowel Procedures | H231: =B231 -> P16AJ | K231: =VLOOKUP($B231,'tarif idrg'!$A:$O,11,FALSE) -> #N/A | L231: =VLOOKUP($B231,'tarif idrg'!$A:$O,15,FALSE) -> #N/A | N231: =IF(C231<>G231,"Change","-") -> - | O231: =VLOOKUP($D231,'ip prosedur-2025'!$A:$H,4,FALSE) -> 42958161 | P231: =VLOOKUP($D231,'ip prosedur-14 okt-15 juni 2026'!$A:$H,4,FALSE) -> 30529292 | Q231: =VLOOKUP($D231,'ip prosedur-14 okt-15 juni 2026'!$A:$H,3, FALSE) -> 9 | R231: =P231*Q231 -> 274763628 | S231: =VLOOKUP($D231,'ip prosedur-14 okt-15 juni 2026'!$A:$H,5,FALSE) -> 12105065 | T231: =VLOOKUP($D231,'ip prosedur-14 okt-15 juni 2026'!$A:$H,6,FALSE) -> 15846995 | U231: =VLOOKUP($D231,'ip prosedur-14 okt-15 juni 2026'!$A:$H,7,FALSE) -> 28243600 | V231: =VLOOKUP($D231,'ip prosedur-14 okt-15 juni 2026'!$A:$H,8,FALSE) -> 94674006
... A413: PDC | B413: P16AN | C413: Hernia Procedures | D413: 84.91 | E413: Amputation, not otherwise specified | F413: =VLOOKUP($D413,proc!$A:$D,3, FALSE) -> 2 | G413: =C413 -> Hernia Procedures | H413: =B413 -> P16AN | K413: =VLOOKUP($B413,'tarif idrg'!$A:$O,11,FALSE) -> 6349277 | L413: =VLOOKUP($B413,'tarif idrg'!$A:$O,15,FALSE) -> 5777842 | N413: =IF(C413<>G413,"Change","-") -> - | O413: =VLOOKUP($D413,'ip prosedur-2025'!$A:$H,4,FALSE) -> 17864290 | P413: =VLOOKUP($D413,'ip prosedur-14 okt-15 juni 2026'!$A:$H,4,FALSE) -> 13007112 | Q413: =VLOOKUP($D413,'ip prosedur-14 okt-15 juni 2026'!$A:$H,3, FALSE) -> 94 | R413: =P413*Q413 -> 1222668572 | S413: =VLOOKUP($D413,'ip prosedur-14 okt-15 juni 2026'!$A:$H,5,FALSE) -> 6864419 | T413: =VLOOKUP($D413,'ip prosedur-14 okt-15 juni 2026'!$A:$H,6,FALSE) -> 10200000 | U413: =VLOOKUP($D413,'ip prosedur-14 okt-15 juni 2026'!$A:$H,7,FALSE) -> 12961192 | V413: =VLOOKUP($D413,'ip prosedur-14 okt-15 juni 2026'!$A:$H,8,FALSE) -> 25126586
C414: TOTAL | G414: TOTAL | H414: =B414 | Q414: =SUBTOTAL(9, Q2:Q413) -> #N/A | R414: =SUBTOTAL(9, R2:R413) -> #N/A | S414: =R414/Q414 -> #N/A

Sheet rajal cluster
A1: Cluster Type | B1: Cluster Code | C1: Cluster Description | D1: ICD9CM Code | E1: ICD9CM Description | F1: procgr | G1: New Cluster Descrirption | H1: New Cluster Code | I1: Action | J1: Notes | K1: tarif iDRG | L1: tarif iDRG + AF | M1: Check rajal | N1: Check Changes | O1: tarif rs 2025 | P1: tarif rs uji coba | Q1: Jumlah Kasus | R1: Total | S1: p25 uji coba | T1: p50 uji coba | U1: p75 uji coba | V1: p90 uji coba
A2: PDC | B2: P16LC | C2: Large Intestine Proc. | D2: 45.42 | E2: Endoscopic polypectomy of large intestine | F2: =VLOOKUP($D2,proc!$A:$D,3, FALSE) -> 0 | G2: =C2 -> Large Intestine Proc. | H2: =B2 -> P16LC | K2: =VLOOKUP($B2,'tarif idrg'!$A:$O,11,FALSE) -> 2538107 | L2: =VLOOKUP($B2,'tarif idrg'!$A:$O,15,FALSE) -> 2538107 | N2: =IF(C2<>G2,"Change","-") -> - | O2: =VLOOKUP($D2,'ip prosedur-2025'!$A:$H,4,FALSE) -> 18426257 | P2: =VLOOKUP($D2,'ip prosedur-14 okt-15 juni 2026'!$A:$H,4,FALSE) -> 18889854 | Q2: =VLOOKUP($D2,'ip prosedur-14 okt-15 juni 2026'!$A:$H,3, FALSE) -> 398 | R2: =P2*Q2 -> 7518162007 | S2: =VLOOKUP($D2,'ip prosedur-14 okt-15 juni 2026'!$A:$H,5,FALSE) -> 9487446 | T2: =VLOOKUP($D2,'ip prosedur-14 okt-15 juni 2026'!$A:$H,6,FALSE) -> 15191567 | U2: =VLOOKUP($D2,'ip prosedur-14 okt-15 juni 2026'!$A:$H,7,FALSE) -> 22151886 | V2: =VLOOKUP($D2,'ip prosedur-14 okt-15 juni 2026'!$A:$H,8,FALSE) -> 37480651
A3: PDC | B3: P16LC | C3: Large Intestine Proc. | D3: 45.43 | E3: Endoscopic destruction of other lesion or tissue of large intestine | F3: =VLOOKUP($D3,proc!$A:$D,3, FALSE) -> 0 | G3: =C3 -> Large Intestine Proc. | H3: =B3 -> P16LC | K3: =VLOOKUP($B3,'tarif idrg'!$A:$O,11,FALSE) -> 2538107 | L3: =VLOOKUP($B3,'tarif idrg'!$A:$O,15,FALSE) -> 2538107 | N3: =IF(C3<>G3,"Change","-") -> - | O3: =VLOOKUP($D3,'ip prosedur-2025'!$A:$H,4,FALSE) -> 22653031 | P3: =VLOOKUP($D3,'ip prosedur-14 okt-15 juni 2026'!$A:$H,4,FALSE) -> 23169771 | Q3: =VLOOKUP($D3,'ip prosedur-14 okt-15 juni 2026'!$A:$H,3, FALSE) -> 149 | R3: =P3*Q3 -> 3452295822 | S3: =VLOOKUP($D3,'ip prosedur-14 okt-15 juni 2026'!$A:$H,5,FALSE) -> 7029841 | T3: =VLOOKUP($D3,'ip prosedur-14 okt-15 juni 2026'!$A:$H,6,FALSE) -> 17173400 | U3: =VLOOKUP($D3,'ip prosedur-14 okt-15 juni 2026'!$A:$H,7,FALSE) -> 31940856 | V3: =VLOOKUP($D3,'ip prosedur-14 okt-15 juni 2026'!$A:$H,8,FALSE) -> 39472470
A4: PDC | B4: P16KU | C4: Endoscopy of Upper Gastrointestinal Major Proc. | D4: 42.21 | E4: Operative esophagoscopy by incision | F4: =VLOOKUP($D4,proc!$A:$D,3, FALSE) -> 0 | G4: =C4 -> Endoscopy of Upper Gastrointestinal Major Proc. | H4: =B4 -> P16KU | K4: =VLOOKUP($B4,'tarif idrg'!$A:$O,11,FALSE) -> 2168928 | L4: =VLOOKUP($B4,'tarif idrg'!$A:$O,15,FALSE) -> 2168928 | N4: =IF(C4<>G4,"Change","-") -> - | O4: =VLOOKUP($D4,'ip prosedur-2025'!$A:$H,4,FALSE) -> 46257832 | P4: =VLOOKUP($D4,'ip prosedur-14 okt-15 juni 2026'!$A:$H,4,FALSE) -> 47671641 | Q4: =VLOOKUP($D4,'ip prosedur-14 okt-15 juni 2026'!$A:$H,3, FALSE) -> 48 | R4: =P4*Q4 -> 2288238776 | S4: =VLOOKUP($D4,'ip prosedur-14 okt-15 juni 2026'!$A:$H,5,FALSE) -> 15417285 | T4: =VLOOKUP($D4,'ip prosedur-14 okt-15 juni 2026'!$A:$H,6,FALSE) -> 60921721 | U4: =VLOOKUP($D4,'ip prosedur-14 okt-15 juni 2026'!$A:$H,7,FALSE) -> 72585433 | V4: =VLOOKUP($D4,'ip prosedur-14 okt-15 juni 2026'!$A:$H,8,FALSE) -> 85224767
A5: PDC | B5: P16KU | C5: Endoscopy of Upper Gastrointestinal Major Proc. | D5: 42.29 | E5: Other diagnostic procedures on esophagus | F5: =VLOOKUP($D5,proc!$A:$D,3, FALSE) -> 0 | G5: =C5 -> Endoscopy of Upper Gastrointestinal Major Proc. | H5: =B5 -> P16KU | K5: =VLOOKUP($B5,'tarif idrg'!$A:$O,11,FALSE) -> 2168928 | L5: =VLOOKUP($B5,'tarif idrg'!$A:$O,15,FALSE) -> 2168928 | N5: =IF(C5<>G5,"Change","-") -> - | O5: =VLOOKUP($D5,'ip prosedur-2025'!$A:$H,4,FALSE) -> 22892120 | P5: =VLOOKUP($D5,'ip prosedur-14 okt-15 juni 2026'!$A:$H,4,FALSE) -> 26465628 | Q5: =VLOOKUP($D5,'ip prosedur-14 okt-15 juni 2026'!$A:$H,3, FALSE) -> 16 | R5: =P5*Q5 -> 423450055 | S5: =VLOOKUP($D5,'ip prosedur-14 okt-15 juni 2026'!$A:$H,5,FALSE) -> 3514487 | T5: =VLOOKUP($D5,'ip prosedur-14 okt-15 juni 2026'!$A:$H,6,FALSE) -> 17436164 | U5: =VLOOKUP($D5,'ip prosedur-14 okt-15 juni 2026'!$A:$H,7,FALSE) -> 29075709 | V5: =VLOOKUP($D5,'ip prosedur-14 okt-15 juni 2026'!$A:$H,8,FALSE) -> 77578955
A6: PDC | B6: P16KU | C6: Endoscopy of Upper Gastrointestinal Major Proc. | D6: 42.33 | E6: Endoscopic excision or destruction of lesion or tissue of esophagus | F6: =VLOOKUP($D6,proc!$A:$D,3, FALSE) -> 0 | G6: =C6 -> Endoscopy of Upper Gastrointestinal Major Proc. | H6: =B6 -> P16KU | K6: =VLOOKUP($B6,'tarif idrg'!$A:$O,11,FALSE) -> 2168928 | L6: =VLOOKUP($B6,'tarif idrg'!$A:$O,15,FALSE) -> 2168928 | N6: =IF(C6<>G6,"Change","-") -> - | O6: =VLOOKUP($D6,'ip prosedur-2025'!$A:$H,4,FALSE) -> 18993436 | P6: =VLOOKUP($D6,'ip prosedur-14 okt-15 juni 2026'!$A:$H,4,FALSE) -> 18413547 | Q6: =VLOOKUP($D6,'ip prosedur-14 okt-15 juni 2026'!$A:$H,3, FALSE) -> 3363 | R6: =P6*Q6 -> 61924758830 | S6: =VLOOKUP($D6,'ip prosedur-14 okt-15 juni 2026'!$A:$H,5,FALSE) -> 8559723 | T6: =VLOOKUP($D6,'ip prosedur-14 okt-15 juni 2026'!$A:$H,6,FALSE) -> 14636951 | U6: =VLOOKUP($D6,'ip prosedur-14 okt-15 juni 2026'!$A:$H,7,FALSE) -> 22943523 | V6: =VLOOKUP($D6,'ip prosedur-14 okt-15 juni 2026'!$A:$H,8,FALSE) -> 34779292
A7: PDC | B7: P16KU | C7: Endoscopy of Upper Gastrointestinal Major Proc. | D7: 42.81 | E7: Insertion of permanent tube into esophagus | F7: =VLOOKUP($D7,proc!$A:$D,3, FALSE) -> 4 | G7: =C7 -> Endoscopy of Upper Gastrointestinal Major Proc. | H7: =B7 -> P16KU | K7: =VLOOKUP($B7,'tarif idrg'!$A:$O,11,FALSE) -> 2168928 | L7: =VLOOKUP($B7,'tarif idrg'!$A:$O,15,FALSE) -> 2168928 | N7: =IF(C7<>G7,"Change","-") -> - | O7: =VLOOKUP($D7,'ip prosedur-2025'!$A:$H,4,FALSE) -> 40301831 | P7: =VLOOKUP($D7,'ip prosedur-14 okt-15 juni 2026'!$A:$H,4,FALSE) -> 70550089 | Q7: =VLOOKUP($D7,'ip prosedur-14 okt-15 juni 2026'!$A:$H,3, FALSE) -> 13 | R7: =P7*Q7 -> 917151154 | S7: =VLOOKUP($D7,'ip prosedur-14 okt-15 juni 2026'!$A:$H,5,FALSE) -> 22702113 | T7: =VLOOKUP($D7,'ip prosedur-14 okt-15 juni 2026'!$A:$H,6,FALSE) -> 38835233 | U7: =VLOOKUP($D7,'ip prosedur-14 okt-15 juni 2026'!$A:$H,7,FALSE) -> 56934105 | V7: =VLOOKUP($D7,'ip prosedur-14 okt-15 juni 2026'!$A:$H,8,FALSE) -> 85553694
A8: PDC | B8: P16KU | C8: Endoscopy of Upper Gastrointestinal Major Proc. | D8: 43.11 | E8: Percutaneous [endoscopic] gastrostomy [PEG] | F8: =VLOOKUP($D8,proc!$A:$D,3, FALSE) -> 0 | G8: =C8 -> Endoscopy of Upper Gastrointestinal Major Proc. | H8: =B8 -> P16KU | K8: =VLOOKUP($B8,'tarif idrg'!$A:$O,11,FALSE) -> 2168928 | L8: =VLOOKUP($B8,'tarif idrg'!$A:$O,15,FALSE) -> 2168928 | N8: =IF(C8<>G8,"Change","-") -> - | O8: =VLOOKUP($D8,'ip prosedur-2025'!$A:$H,4,FALSE) -> 37934611 | P8: =VLOOKUP($D8,'ip prosedur-14 okt-15 juni 2026'!$A:$H,4,FALSE) -> 37881149 | Q8: =VLOOKUP($D8,'ip prosedur-14 okt-15 juni 2026'!$A:$H,3, FALSE) -> 132 | R8: =P8*Q8 -> 5000311723 | S8: =VLOOKUP($D8,'ip prosedur-14 okt-15 juni 2026'!$A:$H,5,FALSE) -> 14822395 | T8: =VLOOKUP($D8,'ip prosedur-14 okt-15 juni 2026'!$A:$H,6,FALSE) -> 21139652 | U8: =VLOOKUP($D8,'ip prosedur-14 okt-15 juni 2026'!$A:$H,7,FALSE) -> 37927061 | V8: =VLOOKUP($D8,'ip prosedur-14 okt-15 juni 2026'!$A:$H,8,FALSE) -> 67030428
A9: PDC | B9: P16KU | C9: Endoscopy of Upper Gastrointestinal Major Proc. | D9: 43.41 | E9: Endoscopic excision or destruction of lesion or tissue of stomach | F9: =VLOOKUP($D9,proc!$A:$D,3, FALSE) -> 0 | G9: =C9 -> Endoscopy of Upper Gastrointestinal Major Proc. | H9: =B9 -> P16KU | K9: =VLOOKUP($B9,'tarif idrg'!$A:$O,11,FALSE) -> 2168928 | L9: =VLOOKUP($B9,'tarif idrg'!$A:$O,15,FALSE) -> 2168928 | N9: =IF(C9<>G9,"Change","-") -> - | O9: =VLOOKUP($D9,'ip prosedur-2025'!$A:$H,4,FALSE) -> 19775994 | P9: =VLOOKUP($D9,'ip prosedur-14 okt-15 juni 2026'!$A:$H,4,FALSE) -> 18895515 | Q9: =VLOOKUP($D9,'ip prosedur-14 okt-15 juni 2026'!$A:$H,3, FALSE) -> 177 | R9: =P9*Q9 -> 3344506167 | S9: =VLOOKUP($D9,'ip prosedur-14 okt-15 juni 2026'!$A:$H,5,FALSE) -> 10412973 | T9: =VLOOKUP($D9,'ip prosedur-14 okt-15 juni 2026'!$A:$H,6,FALSE) -> 15661826 | U9: =VLOOKUP($D9,'ip prosedur-14 okt-15 juni 2026'!$A:$H,7,FALSE) -> 22553300 | V9: =VLOOKUP($D9,'ip prosedur-14 okt-15 juni 2026'!$A:$H,8,FALSE) -> 35693290
A10: PDC | B10: P16KU | C10: Endoscopy of Upper Gastrointestinal Major Proc. | D10: 44.19 | E10: Other diagnostic procedures on stomach | F10: =VLOOKUP($D10,proc!$A:$D,3, FALSE) -> 0 | G10: =C10 -> Endoscopy of Upper Gastrointestinal Major Proc. | H10: =B10 -> P16KU | K10: =VLOOKUP($B10,'tarif idrg'!$A:$O,11,FALSE) -> 2168928 | L10: =VLOOKUP($B10,'tarif idrg'!$A:$O,15,FALSE) -> 2168928 | N10: =IF(C10<>G10,"Change","-") -> - | O10: =VLOOKUP($D10,'ip prosedur-2025'!$A:$H,4,FALSE) -> 32841857 | P10: =VLOOKUP($D10,'ip prosedur-14 okt-15 juni 2026'!$A:$H,4,FALSE) -> 29376722 | Q10: =VLOOKUP($D10,'ip prosedur-14 okt-15 juni 2026'!$A:$H,3, FALSE) -> 8 | R10: =P10*Q10 -> 235013780 | S10: =VLOOKUP($D10,'ip prosedur-14 okt-15 juni 2026'!$A:$H,5,FALSE) -> 14351357 | T10: =VLOOKUP($D10,'ip prosedur-14 okt-15 juni 2026'!$A:$H,6,FALSE) -> 17654972 | U10: =VLOOKUP($D10,'ip prosedur-14 okt-15 juni 2026'!$A:$H,7,FALSE) -> 32955274 | V10: =VLOOKUP($D10,'ip prosedur-14 okt-15 juni 2026'!$A:$H,8,FALSE) -> 84789974
A11: PDC | B11: P16KU | C11: Endoscopy of Upper Gastrointestinal Major Proc. | D11: 44.22 | E11: Endoscopic dilation of pylorus | F11: =VLOOKUP($D11,proc!$A:$D,3, FALSE) -> 0 | G11: =C11 -> Endoscopy of Upper Gastrointestinal Major Proc. | H11: =B11 -> P16KU | K11: =VLOOKUP($B11,'tarif idrg'!$A:$O,11,FALSE) -> 2168928 | L11: =VLOOKUP($B11,'tarif idrg'!$A:$O,15,FALSE) -> 2168928 | N11: =IF(C11<>G11,"Change","-") -> - | O11: =VLOOKUP($D11,'ip prosedur-2025'!$A:$H,4,FALSE) -> 33030318 | P11: =VLOOKUP($D11,'ip prosedur-14 okt-15 juni 2026'!$A:$H,4,FALSE) -> 41361428 | Q11: =VLOOKUP($D11,'ip prosedur-14 okt-15 juni 2026'!$A:$H,3, FALSE) -> 21 | R11: =P11*Q11 -> 868589993 | S11: =VLOOKUP($D11,'ip prosedur-14 okt-15 juni 2026'!$A:$H,5,FALSE) -> 24212760 | T11: =VLOOKUP($D11,'ip prosedur-14 okt-15 juni 2026'!$A:$H,6,FALSE) -> 27401971 | U11: =VLOOKUP($D11,'ip prosedur-14 okt-15 juni 2026'!$A:$H,7,FALSE) -> 58458806 | V11: =VLOOKUP($D11,'ip prosedur-14 okt-15 juni 2026'!$A:$H,8,FALSE) -> 80579607
A12: PDC | B12: P16KU | C12: Endoscopy of Upper Gastrointestinal Major Proc. | D12: 44.43 | E12: Endoscopic control of gastric or duodenal bleeding | F12: =VLOOKUP($D12,proc!$A:$D,3, FALSE) -> 0 | G12: =C12 -> Endoscopy of Upper Gastrointestinal Major Proc. | H12: =B12 -> P16KU | K12: =VLOOKUP($B12,'tarif idrg'!$A:$O,11,FALSE) -> 2168928 | L12: =VLOOKUP($B12,'tarif idrg'!$A:$O,15,FALSE) -> 2168928 | N12: =IF(C12<>G12,"Change","-") -> - | O12: =VLOOKUP($D12,'ip prosedur-2025'!$A:$H,4,FALSE) -> 26982567 | P12: =VLOOKUP($D12,'ip prosedur-14 okt-15 juni 2026'!$A:$H,4,FALSE) -> 32266276 | Q12: =VLOOKUP($D12,'ip prosedur-14 okt-15 juni 2026'!$A:$H,3, FALSE) -> 75 | R12: =P12*Q12 -> 2419970715 | S12: =VLOOKUP($D12,'ip prosedur-14 okt-15 juni 2026'!$A:$H,5,FALSE) -> 10805734 | T12: =VLOOKUP($D12,'ip prosedur-14 okt-15 juni 2026'!$A:$H,6,FALSE) -> 19221164 | U12: =VLOOKUP($D12,'ip prosedur-14 okt-15 juni 2026'!$A:$H,7,FALSE) -> 29172026 | V12: =VLOOKUP($D12,'ip prosedur-14 okt-15 juni 2026'!$A:$H,8,FALSE) -> 65204939
A13: PDC | B13: P16KU | C13: Endoscopy of Upper Gastrointestinal Major Proc. | D13: 44.93 | E13: Insertion of gastric bubble (balloon) | F13: =VLOOKUP($D13,proc!$A:$D,3, FALSE) -> 0 | G13: =C13 -> Endoscopy of Upper Gastrointestinal Major Proc. | H13: =B13 -> P16KU | K13: =VLOOKUP($B13,'tarif idrg'!$A:$O,11,FALSE) -> 2168928 | L13: =VLOOKUP($B13,'tarif idrg'!$A:$O,15,FALSE) -> 2168928 | N13: =IF(C13<>G13,"Change","-") -> - | O13: =VLOOKUP($D13,'ip prosedur-2025'!$A:$H,4,FALSE) -> 18098464 | P13: =VLOOKUP($D13,'ip prosedur-14 okt-15 juni 2026'!$A:$H,4,FALSE) -> 61934696 | Q13: =VLOOKUP($D13,'ip prosedur-14 okt-15 juni 2026'!$A:$H,3, FALSE) -> 8 | R13: =P13*Q13 -> 495477567 | S13: =VLOOKUP($D13,'ip prosedur-14 okt-15 juni 2026'!$A:$H,5,FALSE) -> 22915101 | T13: =VLOOKUP($D13,'ip prosedur-14 okt-15 juni 2026'!$A:$H,6,FALSE) -> 31752954 | U13: =VLOOKUP($D13,'ip prosedur-14 okt-15 juni 2026'!$A:$H,7,FALSE) -> 62582877 | V13: =VLOOKUP($D13,'ip prosedur-14 okt-15 juni 2026'!$A:$H,8,FALSE) -> 152810539
... A206: PDC | B206: P16KW | C206: Other Gastrointestinal Minor Proc. | D206: 99.93 | E206: Rectal massage (for levator spasm) | F206: =VLOOKUP($D206,proc!$A:$D,3, FALSE) -> 0 | G206: =C206 -> Other Gastrointestinal Minor Proc. | H206: =B206 -> P16KW | K206: =VLOOKUP($B206,'tarif idrg'!$A:$O,11,FALSE) -> 406097 | L206: =VLOOKUP($B206,'tarif idrg'!$A:$O,15,FALSE) -> 406097 | N206: =IF(C206<>G206,"Change","-") -> - | O206: =VLOOKUP($D206,'ip prosedur-2025'!$A:$H,4,FALSE) -> 8114314.6 | P206: =VLOOKUP($D206,'ip prosedur-14 okt-15 juni 2026'!$A:$H,4,FALSE) -> 9015433.5 | Q206: =VLOOKUP($D206,'ip prosedur-14 okt-15 juni 2026'!$A:$H,3, FALSE) -> 13 | R206: =P206*Q206 -> 117200635 | S206: =VLOOKUP($D206,'ip prosedur-14 okt-15 juni 2026'!$A:$H,5,FALSE) -> 3443578 | T206: =VLOOKUP($D206,'ip prosedur-14 okt-15 juni 2026'!$A:$H,6,FALSE) -> 7922125 | U206: =VLOOKUP($D206,'ip prosedur-14 okt-15 juni 2026'!$A:$H,7,FALSE) -> 13353121 | V206: =VLOOKUP($D206,'ip prosedur-14 okt-15 juni 2026'!$A:$H,8,FALSE) -> 17433656
C207: TOTAL | G207: TOTAL | H207: =B207 | Q207: =SUBTOTAL(9, Q2:Q206) -> #N/A | R207: =SUBTOTAL(9, R2:R206) -> #N/A | S207: =R207/Q207 -> #N/A

Sheet ip prosedur-14 okt-15 juni 2026
A1: cdx | B1: desc_icd | C1: jml_kasus | D1: mean_billing | E1: p25 | F1: p50 | G1: p75 | H1: p90
A2: 00.01 | B2: Therapeutic ultrasound of vessels of head and neck | C2: 121 | D2: 8198795.9 | E2: 2771300 | F2: 5036518 | G2: 7738910 | H2: 16838068
A3: 00.02 | B3: Therapeutic ultrasound of heart | C3: 59 | D3: 11879608 | E3: 3935625 | F3: 8051726 | G3: 13041200 | H3: 22807945
A4: 00.03 | B4: Therapeutic ultrasound of peripheral vascular vessels | C4: 74 | D4: 18773372 | E4: 6066481 | F4: 10166392 | G4: 20911630 | H4: 39865131
A5: 00.09 | B5: Other therapeutic ultrasound | C5: 322 | D5: 24288937 | E5: 7185658 | F5: 11694335 | G5: 19454891 | H5: 35131990
A6: 00.10 | B6: Implantation of chemotherapeutic agent | C6: 45 | D6: 21885231 | E6: 11494450 | F6: 19871243 | G6: 31499126 | H6: 37648530
A7: 00.11 | B7: Infusion of drotrecogin alfa (activated) | C7: 21 | D7: 6843764.7 | E7: 3356630 | F7: 4726774 | G7: 5797569 | H7: 9585444
A8: 00.12 | B8: Administration of inhaled nitric oxide | C8: 1286 | D8: 14839660 | E8: 4539625 | F8: 7099387 | G8: 15339294 | H8: 30812073
A9: 00.13 | B9: Injection or infusion of nesiritide | C9: 30 | D9: 7189237 | E9: 2316250 | F9: 4657594 | G9: 7127522 | H9: 14787300
A10: 00.14 | B10: Injection or infusion of oxazolidinone class of antibiotics | C10: 156 | D10: 7052252.6 | E10: 3591378 | F10: 4657394 | G10: 6841648 | H10: 14283701
A11: 00.15 | B11: High-dose infusion interleukin-2 [IL-2] | C11: 2 | D11: 5006900 | E11: 3140000 | F11: 3140000 | G11: 6873800 | H11: 6873800
A12: 00.16 | B12: Pressurized treatment of venous bypass graft [conduit] with pharmaceutical substance | C12: 16 | D12: 2.1475718e+08 | E12: 2874150 | F12: 75423001 | G12: 295359561 | H12: 545026548
A13: 00.17 | B13: Infusion of vasopressor agent | C13: 10914 | D13: 22423039 | E13: 6178075 | F13: 10572459 | G13: 20968010 | H13: 47691808
... A15072: S02.411 | B15072: Open Fracture of malar bone [zygoma] (IM) | C15072: 247 | D15072: 35655612 | E15072: 19199161 | F15072: 29153226 | G15072: 43575521 | H15072: 66646866
A15073: S02.417 | C15073: 1 | D15073: 15587252 | E15073: 15587252 | F15073: 15587252 | G15073: 15587252 | H15073: 15587252
A15074: S02.420 | B15074: Closed Fracture of maxillary bones (IM) | C15074: 559 | D15074: 30834752 | E15074: 11420311 | F15074: 22247726 | G15074: 37147813 | H15074: 66944571
A15075: S02.421 | B15075: Open Fracture of maxillary bones (IM) | C15075: 133 | D15075: 34794999 | E15075: 12569132 | F15075: 24443366 | G15075: 40985904 | H15075: 65805557
A15076: S02.470 | B15076: Multiple closed fracture of malar and maxillary bones (IM) | C15076: 236 | D15076: 36063670 | E15076: 18664353 | F15076: 31251271 | G15076: 47133004 | H15076: 70593098
A15077: S02.471 | B15077: Multiple open fracture of malar and maxillary bones (IM) | C15077: 106 | D15077: 36399572 | E15077: 15693196 | F15077: 30178373 | G15077: 50449024 | H15077: 72048112
A15078: S02.5 | B15078: Fracture of tooth | C15078: 729 | D15078: 16122923 | E15078: 6265533 | F15078: 10582490 | G15078: 19924032 | H15078: 34362047
A15079: S02.50 | B15079: Fracture of tooth, closed | C15079: 501 | D15079: 25077974 | E15079: 8230355 | F15079: 15173750 | G15079: 31988137 | H15079: 56620555
A15080: S02.51 | B15080: Fracture of tooth, open | C15080: 161 | D15080: 18122462 | E15080: 7617017 | F15080: 12793788 | G15080: 22672599 | H15080: 33698586
A15081: S02.6 | B15081: Fracture of mandible | C15081: 2258 | D15081: 30278394 | E15081: 11095009 | F15081: 23047134 | G15081: 38277992 | H15081: 63846633
A15082: S02.60 | B15082: Fracture of mandible, closed | C15082: 245 | D15082: 56170104 | E15082: 25884329 | F15082: 46317551 | G15082: 72845319 | H15082: 115645351
A15083: S02.601 | B15083: Open Fracture of alveolar process (IM) | C15083: 755 | D15083: 36426542 | E15083: 13948534 | F15083: 26328746 | G15083: 46878400 | H15083: 79779746
A15084: S02.61 | B15084: Fracture of mandible, open | C15084: 40 | D15084: 58527956 | E15084: 22419872 | F15084: 42537500 | G15084: 67322166 | H15084: 115285000
A15085: S02.610 | B15085: Closed Fracture of body of mandible (IM) | C15085: 605 | D15085: 33850533 | E15085: 15921531 | F15085: 25740978 | G15085: 44170786 | H15085: 66711584
... A25996: Z99.9 | B25996: Dependence on unspecified enabling machine and device | C25996: 3 | D25996: 73278243 | E25996: 5443284 | F25996: 79807776 | G25996: 134583668 | H25996: 134583668

Sheet ip prosedur-2025
A1: cdx | B1: deskripsi | C1: jumlah | D1: mean_billing | E1: p25 | F1: p50 | G1: p75 | H1: p90
A2: 00.01 | B2: Therapeutic ultrasound of vessels of head and neck | C2: 72 | D2: 8373869.9 | E2: 2557732 | F2: 5558121 | G2: 10294589 | H2: 21248293
A3: 00.02 | B3: Therapeutic ultrasound of heart | C3: 61 | D3: 20642282 | E3: 4846922 | F3: 7823264 | G3: 20199122 | H3: 67678954
A4: 00.03 | B4: Therapeutic ultrasound of peripheral vascular vessels | C4: 54 | D4: 20291542 | E4: 6040977 | F4: 10626387 | G4: 20309321 | H4: 43190773
A5: 00.09 | B5: Other therapeutic ultrasound | C5: 433 | D5: 14627902 | E5: 6531234 | F5: 10533631 | G5: 15770329 | H5: 26819422
A6: 00.10 | B6: Implantation of chemotherapeutic agent | C6: 18 | D6: 17080110 | E6: 10433142 | F6: 16911961 | G6: 21051924 | H6: 29931624
A7: 00.11 | B7: Infusion of drotrecogin alfa (activated) | C7: 10 | D7: 8717115.9 | E7: 3200480 | F7: 4592879 | G7: 9082551 | H7: 12746316
A8: 00.12 | B8: Administration of inhaled nitric oxide | C8: 1358 | D8: 15011075 | E8: 4277582 | F8: 7300332 | G8: 17554127 | H8: 35177534
A9: 00.13 | B9: Injection or infusion of nesiritide | C9: 38 | D9: 7519967.5 | E9: 2316250 | F9: 4423700 | G9: 8600415 | H9: 15044023
A10: 00.14 | B10: Injection or infusion of oxazolidinone class of antibiotics | C10: 337 | D10: 5832730.1 | E10: 3503559 | F10: 4440845 | G10: 6176964 | H10: 9641362
A11: 00.15 | B11: High-dose infusion interleukin-2 [IL-2] | C11: 4 | D11: 21163456 | E11: 3221782 | F11: 6976225 | G11: 27518632 | H11: 46937184
A12: 00.16 | B12: Pressurized treatment of venous bypass graft [conduit] with pharmaceutical substance | C12: 13 | D12: 1.8471565e+08 | E12: 24611600 | F12: 194165580 | G12: 209439500 | H12: 543226600
A13: 00.17 | B13: Infusion of vasopressor agent | C13: 11858 | D13: 19854354 | E13: 5973679 | F13: 10150920 | G13: 19662833 | H13: 43819856
... A3945: Z48.0 | B3945: Attention to surgical dressings and sutures | C3945: 1 | D3945: 3117238 | E3945: 3117238 | F3945: 3117238 | G3945: 3117238 | H3945: 3117238

Sheet proc
A1: CODE | B1: STR | C1: procgr | D1: im
A2: 00.01 | B2: Therapeutic ultrasound of vessels of head and neck | C2: 0 | D2: 0
A3: 00.02 | B3: Therapeutic ultrasound of heart | C3: 0 | D3: 0
A4: 00.03 | B4: Therapeutic ultrasound of peripheral vascular vessels | C4: 0 | D4: 0
A5: 00.09 | B5: Other therapeutic ultrasound | C5: 0 | D5: 0
A6: 00.10 | B6: Implantation of chemotherapeutic agent | C6: 0 | D6: 0
A7: 00.11 | B7: Infusion of drotrecogin alfa (activated) | C7: 0 | D7: 0
A8: 00.12 | B8: Administration of inhaled nitric oxide | C8: 0 | D8: 0
A9: 00.13 | B9: Injection or infusion of nesiritide | C9: 0 | D9: 0
A10: 00.14 | B10: Injection or infusion of oxazolidinone class of antibiotics | C10: 0 | D10: 0
A11: 00.15 | B11: High-dose infusion interleukin-2 [IL-2] | C11: 0 | D11: 0
A12: 00.16 | B12: Pressurized treatment of venous bypass graft [conduit] with pharmaceutical substance | C12: 0 | D12: 0
... A3943: 29.13 | B3943: Flexible endoscopic evaluation of swallowing (FEES) (IM) | C3943: 0 | D3943: 1
A3944: 29.3 | B3944: Excision or destruction of lesion or tissue of pharynx | D3944: 0
A3945: 29.910 | B3945: Repair of choanal atresia intranasal (IM) | C3945: 0 | D3945: 1
A3946: 29.911 | B3946: Repair of choanal atresia transpalatal (IM) | C3946: 0 | D3946: 1
A3947: 31.420 | B3947: Stroboscopy (IM) | C3947: 0 | D3947: 1
A3948: 76.32 | B3948: Partial maxillectomy/open medial maxillectomy (IM) | C3948: 4 | D3948: 1
A3949: 76.33 | B3949: Total maxillectomy (IM) | C3949: 4 | D3949: 1
A3950: 76.34 | B3950: Endoscopic medial maxillectomy (IM) | C3950: 4 | D3950: 1
A3951: 86.12 | B3951: Skin prick test (IM) | C3951: 0 | D3951: 1
A3952: 86.13 | B3952: Skin end-point titration test (IM) | C3952: 0 | D3952: 1
A3953: 93.390 | B3953: Vestibular rehabilitation therapy (IM) | C3953: 0 | D3953: 1
A3954: 93.391 | B3954: Canalith repositioning therapy (IM) | C3954: 0 | D3954: 1
A3955: 95.410 | B3955: Pure tone audiometry (IM) | C3955: 0 | D3955: 1
A3956: 95.411 | B3956: Speech audiometry (IM) | C3956: 0 | D3956: 1
... A3970: 95.465 | B3970: Vestibular evoked myogenic potential (IM) | C3970: 0 | D3970: 1
A3971: 78.3 | B3971: Limb lengthening procedures | D3971: 0
A3972: 78.4 | B3972: Other repair or plastic operations on bone | D3972: 0
A3973: 79.4 | B3973: Closed reduction of separated epiphysis | D3973: 0
A3974: 79.5 | B3974: Open reduction of separated epiphysis | D3974: 0
A3975: 79.8 | B3975: Open reduction of dislocation | D3975: 0
A3976: 32.27 | B3976: Bronchoscopic bronchial thermoplasty, ablation of airway smooth muscle | C3976: 0 | D3976: 0
A3977: 33.94 | B3977: Bronchial dilatation with bronchoscopy (rigid) with or without baloon (IM) | C3977: 0 | D3977: 1
A3978: 78.0 | B3978: Bone graft | D3978: 0
A3979: 78.2 | B3979: Limb shortening procedures | D3979: 0
A3980: 33.95 | B3980: Insertion or replacement of bronchial stent using bronchoscopy (IM) | C3980: 0 | D3980: 1
A3981: 33.240 | B3981: Endobronchoscopy ultrasound during bronchoscopic theurapetic intervention or diagnostic (IM) | C3981: 0 | D3981: 1
A3982: 71.6 | B3982: Other vulvectomy | D3982: 0
A3983: 78.1 | B3983: Application of external fixation device | D3983: 0
A3984: 79.1 | B3984: Closed reduction of fracture with internal fixation | D3984: 0
A3985: 79.2 | B3985: Open reduction of fracture without internal fixation | D3985: 0
A3986: 79.3 | B3986: Open reduction of fracture with internal fixation | D3986: 0
A3987: 79.9 | B3987: Unspecified operation on bone injury | D3987: 0
A3988: 92.150 | B3988: Lung perfusion scan (IM) | C3988: 0 | D3988: 1
A3989: 83.15 | B3989: Escharotomy (IM) | C3989: 4 | D3989: 1
A3990: 48.632 | B3990: Laparoscopic low anterior resection of rectum (IM) | C3990: 5 | D3990: 1
A3991: 12.75 | B3991: Glaucoma implant (IM) | C3991: 2 | D3991: 1
A3992: 89.380 | B3992: Cardio pulmonary exercise test (IM) | C3992: 0 | D3992: 1
A3993: 89.381 | B3993: Difusion lung capacity test (IM) | C3993: 0 | D3993: 1
A3994: 89.370 | B3994: Six minute walking test (IM) | C3994: 0 | D3994: 1
A3995: 89.390 | B3995: Bronchial provocation test (IM) | C3995: 0 | D3995: 1
A3996: 89.391 | B3996: Exhaled substance breath test (IM) | C3996: 0 | D3996: 1
A3997: 22.200 | B3997: Uncinectomy sinistra (IM) | C3997: 4 | D3997: 1
A3998: 22.201 | B3998: Uncinectomy dextra (IM) | C3998: 4 | D3998: 1
A3999: 22.410 | B3999: Frontal sinusotomy sinistra (IM) | C3999: 4 | D3999: 1
... A4011: 21.23 | B4011: Nasoendoskopi (IM) | C4011: 0 | D4011: 1
A4012: 23.0 | B4012: Forceps extraction of tooth | D4012: 0
A4013: 23.1 | B4013: Surgical removal of tooth | C4013: 0 | D4013: 0
A4014: 23.12 | B4014: Odontectomy NOS (IM) | C4014: 0 | D4014: 1
A4015: 23.13 | B4015: Removal of impacted tooth (IM) | C4015: 0 | D4015: 1
A4016: 23.14 | B4016: Tooth extraction with elevationof mucoperiosteal flap (IM) | C4016: 0 | D4016: 1
A4017: 94.270 | B4017: Electroconvulsive therapy (ECT), conventional (IM) | C4017: 0 | D4017: 1
A4018: 94.271 | B4018: Electroconvulsive therapy (ECT), with premedication (IM) | C4018: 0 | D4018: 1
A4019: 94.28 | B4019: Transcranial magnetic stimulation (TMS) (IM) | C4019: 0 | D4019: 1
A4020: 68.4 | B4020: Total abdominal hysterectomy | C4020: 4 | D4020: 0
A4021: 69.90 | B4021: Uterine compression suture (B-Lynch) (IM) | C4021: 0 | D4021: 1
A4022: 66.03 | B4022: Laparoscopy salpingotomy (IM) | C4022: 3 | D4022: 1
A4023: 66.04 | B4023: Laparoscopy salpingostomy (IM) | C4023: 3 | D4023: 1
A4024: 66.18 | B4024: Laparoscopy, other diagnostic procedures on fallopian tubes (IM) | C4024: 2 | D4024: 1
... A4616: NULL | B4616: NULL | C4616: 6 | D4616: NULL
A4617: NULL | B4617: NULL | D4617: NULL
A4618: NULL | B4618: NULL | C4618: 5 | D4618: NULL
A4619: NULL | B4619: NULL | C4619: 5 | D4619: NULL
A4620: NULL | B4620: NULL | C4620: 5 | D4620: NULL
A4621: NULL | B4621: NULL | C4621: 5 | D4621: NULL
A4622: NULL | B4622: NULL | C4622: 5 | D4622: NULL
A4623: 89.070 | B4623: Other Specialist Pre-operative Consultation (IM) | C4623: 0 | D4623: 1
A4624: 89.071 | B4624: Other Specialist Consultation (IM) | C4624: 0 | D4624: 1
A4625: 92.50 | B4625: Non-Imaging Nuclear Medicine Thyroid Function Test (IM) | C4625: 0 | D4625: 1
A4626: 92.51 | B4626: Non-Imaging Nuclear Medicine Thyroid Cancer Marker (IM) | C4626: 0 | D4626: 1
A4627: 92.52 | B4627: Non-Imaging Nuclear Medicine Thyroid Antibody Test (IM) | C4627: 0 | D4627: 1
A4628: 31.421 | B4628: Microlaryngoscopy (IM) | C4628: 0 | D4628: 1
A4629: 37.340 | B4629: Catheter based invasive electrophysiologic 3-dimensional cryo-ablation (IM) | C4629: 6 | D4629: 1
... A4879: KND0203 | B4879: Other Pharmaceuticals | C4879: 0 | D4879: 1

Sheet tarif idrg
I1: Tarif iDRG tanpa Adjustment Factor | L1: Tarif dengan Adjustment Factor
A2: pdc | B2: deskripsi pdc | C2: PTD | D2: MDC | E2: DC | F2: DRG | G2: Deskripsi DRG | H2: Jumlah Kasus | I2: NBR | J2: Cost Weight | K2: Tarif iDRG | L2: NBR | M2: Cost Weight | N2: Adjustment Factor | O2: Tarif iDRG | P2: Total Biaya INACBG | Q2: Total Biaya iDRG | R2: Selisih Biaya | S2: % Selisih Biaya | T2: pdc | U2: deskripsi pdc
A3: =T3 -> 00CX | B3: =U3 -> Liver Transplant | C3: =MID(F3,6,1) -> 1 | D3: =LEFT(F3,2) -> 10 | E3: =LEFT(F3,5) -> 10011 | F3: 1001119 | G3: Liver Transplant | H3: 5 | I3: 8037060 | J3: 48.89 | K3: 392931863 | L3: 8037060 | M3: 48.89 | N3: 1 | O3: 392931863 | P3: 1839518700 | Q3: 1975609317 | R3: 136090617 | S3: 0.074 | T3: {=INDEX(Sheet10!D:D,MATCH(C3&E3,INDEX(Sheet10!A:A&Sheet10!B:B,0),0))} -> 00CX | U3: =VLOOKUP(T3,Sheet10!D:E,2,FALSE) -> Liver Transplant
A4: =T4 -> 00DX | B4: =U4 -> Heart-Lung Transplant | C4: =MID(F4,6,1) -> 1 | D4: =LEFT(F4,2) -> 10 | E4: =LEFT(F4,5) -> 10021 | F4: 1002119 | G4: Heart-Lung Transplant | H4: #N/A | I4: 8037060 | J4: 57.86 | K4: 465024292 | L4: 8037060 | M4: 57.86 | N4: 1 | O4: 465024292 | P4: #N/A | Q4: #N/A | R4: #N/A | S4: #N/A | T4: {=INDEX(Sheet10!D:D,MATCH(C4&E4,INDEX(Sheet10!A:A&Sheet10!B:B,0),0))} -> 00DX | U4: =VLOOKUP(T4,Sheet10!D:E,2,FALSE) -> Heart-Lung Transplant
A5: =T5 -> 00EX | B5: =U5 -> Bone Marrow Transplant | C5: =MID(F5,6,1) -> 1 | D5: =LEFT(F5,2) -> 10 | E5: =LEFT(F5,5) -> 10031 | F5: 1003119 | G5: Bone Marrow Transplant | H5: 4 | I5: 8037060 | J5: 15.26 | K5: 122645536 | L5: 8037060 | M5: 15.26 | N5: 1 | O5: 122645536 | P5: 297932400 | Q5: 492794142 | R5: 194861742 | S5: 0.654 | T5: {=INDEX(Sheet10!D:D,MATCH(C5&E5,INDEX(Sheet10!A:A&Sheet10!B:B,0),0))} -> 00EX | U5: =VLOOKUP(T5,Sheet10!D:E,2,FALSE) -> Bone Marrow Transplant
A6: =T6 -> 99PCX | B6: =U6 -> Trach w Mech Vent Support 96+ Hr w LOS 21+ days | C6: =MID(F6,6,1) -> 1 | D6: =LEFT(F6,2) -> 10 | E6: =LEFT(F6,5) -> 10111 | F6: 1011110 | G6: Trach w Mech Vent Support 96+ Hr w LOS 21+ days w/ No CC | H6: 385 | I6: 8037060 | J6: 15.16 | K6: 121841830 | L6: 8037060 | M6: 15.16 | N6: 1 | O6: 121841830 | P6: 35446310800 | Q6: 47212869396 | R6: 11766558596 | S6: 0.332 | T6: {=INDEX(Sheet10!D:D,MATCH(C6&E6,INDEX(Sheet10!A:A&Sheet10!B:B,0),0))} -> 99PCX | U6: =VLOOKUP(T6,Sheet10!D:E,2,FALSE) -> Trach w Mech Vent Support 96+ Hr w LOS 21+ days
A7: =T7 -> 99PCX | B7: =U7 -> Trach w Mech Vent Support 96+ Hr w LOS 21+ days | C7: =MID(F7,6,1) -> 1 | D7: =LEFT(F7,2) -> 10 | E7: =LEFT(F7,5) -> 10111 | F7: 1011111 | G7: Trach w Mech Vent Support 96+ Hr w LOS 21+ days w/ Mild CC | H7: 4817 | I7: 8037060 | J7: 17.87 | K7: 143622262 | L7: 8037060 | M7: 17.87 | N7: 0.93 | O7: 133568704 | P7: 604742956900 | Q7: 647975312926 | R7: 43232356026 | S7: 0.071 | T7: {=INDEX(Sheet10!D:D,MATCH(C7&E7,INDEX(Sheet10!A:A&Sheet10!B:B,0),0))} -> 99PCX | U7: =VLOOKUP(T7,Sheet10!D:E,2,FALSE) -> Trach w Mech Vent Support 96+ Hr w LOS 21+ days
A8: =T8 -> 99PCX | B8: =U8 -> Trach w Mech Vent Support 96+ Hr w LOS 21+ days | C8: =MID(F8,6,1) -> 1 | D8: =LEFT(F8,2) -> 10 | E8: =LEFT(F8,5) -> 10111 | F8: 1011112 | G8: Trach w Mech Vent Support 96+ Hr w LOS 21+ days w/ Moderate CC | H8: 1150 | I8: 8037060 | J8: 26.65 | K8: 214187649 | L8: 8037060 | M8: 26.65 | N8: 0.74 | O8: 158498860 | P8: 172169274000 | Q8: 183685979299 | R8: 11516705299 | S8: 0.067 | T8: {=INDEX(Sheet10!D:D,MATCH(C8&E8,INDEX(Sheet10!A:A&Sheet10!B:B,0),0))} -> 99PCX | U8: =VLOOKUP(T8,Sheet10!D:E,2,FALSE) -> Trach w Mech Vent Support 96+ Hr w LOS 21+ days
A9: =T9 -> 99PCX | B9: =U9 -> Trach w Mech Vent Support 96+ Hr w LOS 21+ days | C9: =MID(F9,6,1) -> 1 | D9: =LEFT(F9,2) -> 10 | E9: =LEFT(F9,5) -> 10112 | F9: 1011210 | G9: Mech Vent Support 96+ Hr w LOS 21+ days w/ No CC | H9: 5731 | I9: 8037060 | J9: 12.87 | K9: 103436962 | L9: 8037060 | M9: 12.87 | N9: 0.86 | O9: 88955787 | P9: 339380358600 | Q9: 513539874359 | R9: 174159515759 | S9: 0.513 | T9: {=INDEX(Sheet10!D:D,MATCH(C9&E9,INDEX(Sheet10!A:A&Sheet10!B:B,0),0))} -> 99PCX | U9: =VLOOKUP(T9,Sheet10!D:E,2,FALSE) -> Trach w Mech Vent Support 96+ Hr w LOS 21+ days
A10: =T10 -> 99PCX | B10: =U10 -> Trach w Mech Vent Support 96+ Hr w LOS 21+ days | C10: =MID(F10,6,1) -> 1 | D10: =LEFT(F10,2) -> 10 | E10: =LEFT(F10,5) -> 10112 | F10: 1011211 | G10: Mech Vent Support 96+ Hr w LOS 21+ days w/ Mild CC | H10: 4134 | I10: 8037060 | J10: 14.76 | K10: 118627006 | L10: 8037060 | M10: 14.76 | N10: 0.93 | O10: 110323115 | P10: 338040611300 | Q10: 459799647479 | R10: 121759036179 | S10: 0.36 | T10: {=INDEX(Sheet10!D:D,MATCH(C10&E10,INDEX(Sheet10!A:A&Sheet10!B:B,0),0))} -> 99PCX | U10: =VLOOKUP(T10,Sheet10!D:E,2,FALSE) -> Trach w Mech Vent Support 96+ Hr w LOS 21+ days
A11: =T11 -> 99PCX | B11: =U11 -> Trach w Mech Vent Support 96+ Hr w LOS 21+ days | C11: =MID(F11,6,1) -> 1 | D11: =LEFT(F11,2) -> 10 | E11: =LEFT(F11,5) -> 10112 | F11: 1011212 | G11: Mech Vent Support 96+ Hr w LOS 21+ days w/ Moderate CC | H11: 1069 | I11: 8037060 | J11: 18.25 | K11: 146676345 | L11: 8037060 | M11: 18.25 | N11: 1 | O11: 146676345 | P11: 105546058200 | Q11: 158185302857 | R11: 52639244657 | S11: 0.499 | T11: {=INDEX(Sheet10!D:D,MATCH(C11&E11,INDEX(Sheet10!A:A&Sheet10!B:B,0),0))} -> 99PCX | U11: =VLOOKUP(T11,Sheet10!D:E,2,FALSE) -> Trach w Mech Vent Support 96+ Hr w LOS 21+ days
A12: =T12 -> 99PCX | B12: =U12 -> Trach w Mech Vent Support 96+ Hr w LOS 21+ days | C12: =MID(F12,6,1) -> 1 | D12: =LEFT(F12,2) -> 10 | E12: =LEFT(F12,5) -> 10121 | F12: 1012110 | G12: Trach w Mech Vent Support 96+ Hr w/ No CC | H12: 1160 | I12: 8037060 | J12: 9.12 | K12: 73297987 | L12: 8037060 | M12: 9.12 | N12: 1.12 | O12: 82093746 | P12: 95287761100 | Q12: 95576904970 | R12: 289143870 | S12: 0.003 | T12: {=INDEX(Sheet10!D:D,MATCH(C12&E12,INDEX(Sheet10!A:A&Sheet10!B:B,0),0))} -> 99PCX | U12: =VLOOKUP(T12,Sheet10!D:E,2,FALSE) -> Trach w Mech Vent Support 96+ Hr w LOS 21+ days
A13: =T13 -> 99PCX | B13: =U13 -> Trach w Mech Vent Support 96+ Hr w LOS 21+ days | C13: =MID(F13,6,1) -> 1 | D13: =LEFT(F13,2) -> 10 | E13: =LEFT(F13,5) -> 10121 | F13: 1012111 | G13: Trach w Mech Vent Support 96+ Hr w/ Mild CC | H13: 6672 | I13: 8037060 | J13: 11.64 | K13: 93551378 | L13: 8037060 | M13: 11.64 | N13: 1.16 | O13: 108519599 | P13: 725462123900 | Q13: 726269884154 | R13: 807760254 | S13: 0.001 | T13: {=INDEX(Sheet10!D:D,MATCH(C13&E13,INDEX(Sheet10!A:A&Sheet10!B:B,0),0))} -> 99PCX | U13: =VLOOKUP(T13,Sheet10!D:E,2,FALSE) -> Trach w Mech Vent Support 96+ Hr w LOS 21+ days
A14: =T14 -> 99PCX | B14: =U14 -> Trach w Mech Vent Support 96+ Hr w LOS 21+ days | C14: =MID(F14,6,1) -> 1 | D14: =LEFT(F14,2) -> 10 | E14: =LEFT(F14,5) -> 10121 | F14: 1012112 | G14: Trach w Mech Vent Support 96+ Hr w/ Moderate CC | H14: 904 | I14: 8037060 | J14: 15.49 | K14: 124494059 | L14: 8037060 | M14: 15.49 | N14: 1.08 | O14: 134453584 | P14: 121391894300 | Q14: 121962140073 | R14: 570245773 | S14: 0.005 | T14: {=INDEX(Sheet10!D:D,MATCH(C14&E14,INDEX(Sheet10!A:A&Sheet10!B:B,0),0))} -> 99PCX | U14: =VLOOKUP(T14,Sheet10!D:E,2,FALSE) -> Trach w Mech Vent Support 96+ Hr w LOS 21+ days
A15: =T15 -> 99PCX | B15: =U15 -> Trach w Mech Vent Support 96+ Hr w LOS 21+ days | C15: =MID(F15,6,1) -> 1 | D15: =LEFT(F15,2) -> 10 | E15: =LEFT(F15,5) -> 10122 | F15: 1012210 | G15: Mech Vent Support 96+ Hr w/ No CC | H15: 53018 | I15: 8037060 | J15: 6.11 | K15: 49106437 | L15: 8037060 | M15: 6.11 | N15: 1.18 | O15: 57945595 | P15: 3064224963800 | Q15: 3085276774359 | R15: 21051810559 | S15: 0.007 | T15: {=INDEX(Sheet10!D:D,MATCH(C15&E15,INDEX(Sheet10!A:A&Sheet10!B:B,0),0))} -> 99PCX | U15: =VLOOKUP(T15,Sheet10!D:E,2,FALSE) -> Trach w Mech Vent Support 96+ Hr w LOS 21+ days
A16: =T16 -> 99PCX | B16: =U16 -> Trach w Mech Vent Support 96+ Hr w LOS 21+ days | C16: =MID(F16,6,1) -> 1 | D16: =LEFT(F16,2) -> 10 | E16: =LEFT(F16,5) -> 10122 | F16: 1012211 | G16: Mech Vent Support 96+ Hr w/ Mild CC | H16: 4174 | I16: 8037060 | J16: 9.23 | K16: 74182064 | L16: 8037060 | M16: 9.23 | N16: 1.07 | O16: 79374808 | P16: 330750364000 | Q16: 332562126702 | R16: 1811762702 | S16: 0.005 | T16: {=INDEX(Sheet10!D:D,MATCH(C16&E16,INDEX(Sheet10!A:A&Sheet10!B:B,0),0))} -> 99PCX | U16: =VLOOKUP(T16,Sheet10!D:E,2,FALSE) -> Trach w Mech Vent Support 96+ Hr w LOS 21+ days
... A170: =T170 -> D14AB | B170: =U170 -> Pulmonary Edema dan Respiratory Distress | C170: =MID(F170,6,1) -> 1 | D170: =LEFT(F170,2) -> 14 | E170: =LEFT(F170,5) -> 14621 | F170: 1462111 | G170: Pulmonary Edema dan Respiratory Distress w/ Mild CC | H170: 27038 | I170: 8037060 | J170: 0.84 | K170: 6751130 | L170: 8037060 | M170: 0.84 | N170: 0.87 | O170: 5873483 | P170: 149673675000 | Q170: 161435691467 | R170: 11762016467 | S170: 0.079 | T170: {=INDEX(Sheet10!D:D,MATCH(C170&E170,INDEX(Sheet10!A:A&Sheet10!B:B,0),0))} -> D14AB | U170: =VLOOKUP(T170,Sheet10!D:E,2,FALSE) -> Pulmonary Edema dan Respiratory Distress
A171: =T171 -> 14BX | B171: =U171 -> Respiratory Drug Resistance TB | C171: =MID(F171,6,1) -> 1 | D171: =LEFT(F171,2) -> 14 | E171: =LEFT(F171,5) -> 14631 | F171: 1463119 | G171: Respiratory Drug Resistance TB | H171: #N/A | I171: 8037060 | J171: 0.86 | K171: 6911872 | L171: 8037060 | M171: 0.86 | N171: 1 | O171: 6911872 | P171: #N/A | Q171: #N/A | R171: #N/A | S171: #N/A | T171: {=INDEX(Sheet10!D:D,MATCH(C171&E171,INDEX(Sheet10!A:A&Sheet10!B:B,0),0))} -> 14BX | U171: =VLOOKUP(T171,Sheet10!D:E,2,FALSE) -> Respiratory Drug Resistance TB
A172: =T172 -> 14CX | B172: =U172 -> Respiratory Drug Resistance TB | C172: =MID(F172,6,1) -> 1 | D172: =LEFT(F172,2) -> 14 | E172: =LEFT(F172,5) -> 14632 | F172: 1463219 | G172: Respiratory Drug Resistance | H172: #N/A | I172: 8037060 | J172: 0.83 | K172: 6670760 | L172: 8037060 | M172: 0.83 | N172: 1 | O172: 6670760 | P172: #N/A | Q172: #N/A | R172: #N/A | S172: #N/A | T172: {=INDEX(Sheet10!D:D,MATCH(C172&E172,INDEX(Sheet10!A:A&Sheet10!B:B,0),0))} -> 14CX | U172: =VLOOKUP(T172,Sheet10!D:E,2,FALSE) -> Respiratory Drug Resistance TB
A173: =T173 -> D14AD | B173: =U173 -> Respiratory System Neoplasms | C173: =MID(F173,6,1) -> 1 | D173: =LEFT(F173,2) -> 14 | E173: =LEFT(F173,5) -> 14641 | F173: 1464110 | G173: Respiratory System Neoplasms w/ No CC | H173: 16874 | I173: 8037060 | J173: 0.75 | K173: 6027795 | L173: 8037060 | M173: 0.75 | N173: 1 | O173: 6027795 | P173: 76615997500 | Q173: 103314903330 | R173: 26698905830 | S173: 0.348 | T173: {=INDEX(Sheet10!D:D,MATCH(C173&E173,INDEX(Sheet10!A:A&Sheet10!B:B,0),0))} -> D14AD | U173: =VLOOKUP(T173,Sheet10!D:E,2,FALSE) -> Respiratory System Neoplasms
A174: =T174 -> D14AD | B174: =U174 -> Respiratory System Neoplasms | C174: =MID(F174,6,1) -> 1 | D174: =LEFT(F174,2) -> 14 | E174: =LEFT(F174,5) -> 14641 | F174: 1464111 | G174: Respiratory System Neoplasms w/ Mild CC | H174: 9966 | I174: 8037060 | J174: 1.2 | K174: 9644472 | L174: 8037060 | M174: 1.2 | N174: 1 | O174: 9644472 | P174: 90078221600 | Q174: 97554151544 | R174: 7475929944 | S174: 0.083 | T174: {=INDEX(Sheet10!D:D,MATCH(C174&E174,INDEX(Sheet10!A:A&Sheet10!B:B,0),0))} -> D14AD | U174: =VLOOKUP(T174,Sheet10!D:E,2,FALSE) -> Respiratory System Neoplasms
A175: =T175 -> D14AD | B175: =U175 -> Respiratory System Neoplasms | C175: =MID(F175,6,1) -> 1 | D175: =LEFT(F175,2) -> 14 | E175: =LEFT(F175,5) -> 14641 | F175: 1464112 | G175: Respiratory System Neoplasms w/ Moderate CC | H175: 3165 | I175: 8037060 | J175: 1.73 | K175: 13904114 | L175: 8037060 | M175: 1.73 | N175: 1 | O175: 13904114 | P175: 36252794200 | Q175: 44636342566 | R175: 8383548366 | S175: 0.231 | T175: {=INDEX(Sheet10!D:D,MATCH(C175&E175,INDEX(Sheet10!A:A&Sheet10!B:B,0),0))} -> D14AD | U175: =VLOOKUP(T175,Sheet10!D:E,2,FALSE) -> Respiratory System Neoplasms
A176: =T176 -> D14AE | B176: =U176 -> Pneumothorax | C176: =MID(F176,6,1) -> 1 | D176: =LEFT(F176,2) -> 14 | E176: =LEFT(F176,5) -> 14651 | F176: 1465110 | G176: Pneumothorax w/ No CC | H176: 659 | I176: 8037060 | J176: 0.68 | K176: 5465201 | L176: 8037060 | M176: 0.68 | N176: 1 | O176: 5465201 | P176: 3151176000 | Q176: 3643062327 | R176: 491886327 | S176: 0.156 | T176: {=INDEX(Sheet10!D:D,MATCH(C176&E176,INDEX(Sheet10!A:A&Sheet10!B:B,0),0))} -> D14AE | U176: =VLOOKUP(T176,Sheet10!D:E,2,FALSE) -> Pneumothorax
A177: =T177 -> D14AE | B177: =U177 -> Pneumothorax | C177: =MID(F177,6,1) -> 1 | D177: =LEFT(F177,2) -> 14 | E177: =LEFT(F177,5) -> 14651 | F177: 1465111 | G177: Pneumothorax w/ Mild CC | H177: 295 | I177: 8037060 | J177: 1.01 | K177: 8117431 | L177: 8037060 | M177: 1.01 | N177: 1 | O177: 8117431 | P177: 2125122500 | Q177: 2423379527 | R177: 298257027 | S177: 0.14 | T177: {=INDEX(Sheet10!D:D,MATCH(C177&E177,INDEX(Sheet10!A:A&Sheet10!B:B,0),0))} -> D14AE | U177: =VLOOKUP(T177,Sheet10!D:E,2,FALSE) -> Pneumothorax
A178: =T178 -> D14AF | B178: =U178 -> Pleural Effusion | C178: =MID(F178,6,1) -> 1 | D178: =LEFT(F178,2) -> 14 | E178: =LEFT(F178,5) -> 14661 | F178: 1466110 | G178: Pleural Effusion w/ No CC | H178: 5431 | I178: 8037060 | J178: 0.71 | K178: 5706313 | L178: 8037060 | M178: 0.71 | N178: 1 | O178: 5706313 | P178: 25130230300 | Q178: 31477001731 | R178: 6346771431 | S178: 0.253 | T178: {=INDEX(Sheet10!D:D,MATCH(C178&E178,INDEX(Sheet10!A:A&Sheet10!B:B,0),0))} -> D14AF | U178: =VLOOKUP(T178,Sheet10!D:E,2,FALSE) -> Pleural Effusion
A179: =T179 -> D14AF | B179: =U179 -> Pleural Effusion | C179: =MID(F179,6,1) -> 1 | D179: =LEFT(F179,2) -> 14 | E179: =LEFT(F179,5) -> 14661 | F179: 1466111 | G179: Pleural Effusion w/ Mild CC | H179: 2557 | I179: 8037060 | J179: 1.05 | K179: 8438913 | L179: 8037060 | M179: 1.05 | N179: 1 | O179: 8438913 | P179: 17018941500 | Q179: 21872928541 | R179: 4853987041 | S179: 0.285 | T179: {=INDEX(Sheet10!D:D,MATCH(C179&E179,INDEX(Sheet10!A:A&Sheet10!B:B,0),0))} -> D14AF | U179: =VLOOKUP(T179,Sheet10!D:E,2,FALSE) -> Pleural Effusion
A180: =T180 -> D14AG | B180: =U180 -> Respiratory Drug Resistance TB | C180: =MID(F180,6,1) -> 1 | D180: =LEFT(F180,2) -> 14 | E180: =LEFT(F180,5) -> 14671 | F180: 1467110 | G180: Respiratory Tuberculosis w/ No CC | H180: 170384 | I180: 8037060 | J180: 0.68 | K180: 5465201 | L180: 8037060 | M180: 0.68 | N180: 0.91 | O180: 4973333 | P180: 803667378000 | Q180: 858271616528 | R180: 54604238528 | S180: 0.068 | T180: {=INDEX(Sheet10!D:D,MATCH(C180&E180,INDEX(Sheet10!A:A&Sheet10!B:B,0),0))} -> D14AG | U180: =VLOOKUP(T180,Sheet10!D:E,2,FALSE) -> Respiratory Drug Resistance TB
A181: =T181 -> D14AG | B181: =U181 -> Respiratory Drug Resistance TB | C181: =MID(F181,6,1) -> 1 | D181: =LEFT(F181,2) -> 14 | E181: =LEFT(F181,5) -> 14671 | F181: 1467111 | G181: Respiratory Tuberculosis w/ Mild CC | H181: 62781 | I181: 8037060 | J181: 1.09 | K181: 8760395 | L181: 8037060 | M181: 1.09 | N181: 0.75 | O181: 6570297 | P181: 387190049800 | Q181: 417390577714 | R181: 30200527914 | S181: 0.078 | T181: {=INDEX(Sheet10!D:D,MATCH(C181&E181,INDEX(Sheet10!A:A&Sheet10!B:B,0),0))} -> D14AG | U181: =VLOOKUP(T181,Sheet10!D:E,2,FALSE) -> Respiratory Drug Resistance TB
A182: =T182 -> D14AG | B182: =U182 -> Respiratory Drug Resistance TB | C182: =MID(F182,6,1) -> 1 | D182: =LEFT(F182,2) -> 14 | E182: =LEFT(F182,5) -> 14671 | F182: 1467112 | G182: Respiratory Tuberculosis w/ Moderate CC | H182: 18 | I182: 8037060 | J182: 2.26 | K182: 18163756 | L182: 8037060 | M182: 2.26 | N182: 1 | O182: 18163756 | P182: 175767700 | Q182: 332422601 | R182: 156654901 | S182: 0.891 | T182: {=INDEX(Sheet10!D:D,MATCH(C182&E182,INDEX(Sheet10!A:A&Sheet10!B:B,0),0))} -> D14AG | U182: =VLOOKUP(T182,Sheet10!D:E,2,FALSE) -> Respiratory Drug Resistance TB
A183: =T183 -> D14AH | B183: =U183 -> Respiratory Infections and Inflammation | C183: =MID(F183,6,1) -> 1 | D183: =LEFT(F183,2) -> 14 | E183: =LEFT(F183,5) -> 14681 | F183: 1468110 | G183: Respiratory Infections and Inflammation w/ No CC | H183: 1020145 | I183: 8037060 | J183: 0.57 | K183: 4581124 | L183: 8037060 | M183: 0.57 | N183: 0.87 | O183: 3985578 | P183: 3838968760100 | Q183: 4205224951898 | R183: 366256191798 | S183: 0.095 | T183: {=INDEX(Sheet10!D:D,MATCH(C183&E183,INDEX(Sheet10!A:A&Sheet10!B:B,0),0))} -> D14AH | U183: =VLOOKUP(T183,Sheet10!D:E,2,FALSE) -> Respiratory Infections and Inflammation
A184: =T184 -> D14AH | B184: =U184 -> Respiratory Infections and Inflammation | C184: =MID(F184,6,1) -> 1 | D184: =LEFT(F184,2) -> 14 | E184: =LEFT(F184,5) -> 14681 | F184: 1468111 | G184: Respiratory Infections and Inflammation w/ Mild CC | H184: 246193 | I184: 8037060 | J184: 0.76 | K184: 6108166 | L184: 8037060 | M184: 0.76 | N184: 0.93 | O184: 5680594 | P184: 1314202793900 | Q184: 1430172000612 | R184: 115969206712 | S184: 0.088 | T184: {=INDEX(Sheet10!D:D,MATCH(C184&E184,INDEX(Sheet10!A:A&Sheet10!B:B,0),0))} -> D14AH | U184: =VLOOKUP(T184,Sheet10!D:E,2,FALSE) -> Respiratory Infections and Inflammation
... A225: =T225 -> P15AM | B225: =U225 -> Permanent Pacemaker Insertion | C225: =MID(F225,6,1) -> 1 | D225: =LEFT(F225,2) -> 15 | E225: =LEFT(F225,5) -> 15141 | F225: 1514119 | G225: Permanent Pacemaker Insertion | H225: 2381 | I225: 8037060 | J225: 5.91 | K225: 47499025 | L225: 8037060 | M225: 5.91 | N225: 1.01 | O225: 47974015 | P225: 114741652400 | Q225: 114829430848 | R225: 87778448 | S225: 0.001 | T225: {=INDEX(Sheet10!D:D,MATCH(C225&E225,INDEX(Sheet10!A:A&Sheet10!B:B,0),0))} -> P15AM | U225: =VLOOKUP(T225,Sheet10!D:E,2,FALSE) -> Permanent Pacemaker Insertion
A226: =T226 -> P15AN | B226: =U226 -> Major Cardiac Electrophysiologic Proc. | C226: =MID(F226,6,1) -> 1 | D226: =LEFT(F226,2) -> 15 | E226: =LEFT(F226,5) -> 15151 | F226: 1515119 | G226: Major Cardiac Electrophysiologic Proc. | H226: #N/A | I226: 8037060 | J226: 4.19 | K226: 33675281 | L226: 8037060 | M226: 4.19 | N226: 1 | O226: 33675281 | P226: #N/A | Q226: #N/A | R226: #N/A | S226: #N/A | T226: {=INDEX(Sheet10!D:D,MATCH(C226&E226,INDEX(Sheet10!A:A&Sheet10!B:B,0),0))} -> P15AN | U226: =VLOOKUP(T226,Sheet10!D:E,2,FALSE) -> Major Cardiac Electrophysiologic Proc.
A227: =T227 -> 15PLX | B227: =U227 -> Acute MI w PTCA w (+Stent) | C227: =MID(F227,6,1) -> 1 | D227: =LEFT(F227,2) -> 15 | E227: =LEFT(F227,5) -> 15163 | F227: 1516319 | G227: PTCA (+Stent) | H227: 17993 | I227: 8037060 | J227: 4.74 | K227: 38095664 | L227: 8037060 | M227: 4.74 | N227: 1 | O227: 38095664 | P227: 679130659800 | Q227: 688228677049 | R227: 9098017249 | S227: 0.013 | T227: {=INDEX(Sheet10!D:D,MATCH(C227&E227,INDEX(Sheet10!A:A&Sheet10!B:B,0),0))} -> 15PLX | U227: =VLOOKUP(T227,Sheet10!D:E,2,FALSE) -> Acute MI w PTCA w (+Stent)
A228: =T228 -> P15AP | B228: =U228 -> Acute MI w PTCA w (+Stent) | C228: =MID(F228,6,1) -> 1 | D228: =LEFT(F228,2) -> 15 | E228: =LEFT(F228,5) -> 15164 | F228: 1516410 | G228: PTCA w/ No CC | H228: 1657 | I228: 8037060 | J228: 3.82 | K228: 30701569 | L228: 8037060 | M228: 3.82 | N228: 1 | O228: 30701569 | P228: 36675952300 | Q228: 51146630164 | R228: 14470677864 | S228: 0.395 | T228: {=INDEX(Sheet10!D:D,MATCH(C228&E228,INDEX(Sheet10!A:A&Sheet10!B:B,0),0))} -> P15AP | U228: =VLOOKUP(T228,Sheet10!D:E,2,FALSE) -> Acute MI w PTCA w (+Stent)
A229: =T229 -> P15AP | B229: =U229 -> Acute MI w PTCA w (+Stent) | C229: =MID(F229,6,1) -> 1 | D229: =LEFT(F229,2) -> 15 | E229: =LEFT(F229,5) -> 15164 | F229: 1516411 | G229: PTCA w/ Mild CC | H229: 876 | I229: 8037060 | J229: 4.31 | K229: 34639729 | L229: 8037060 | M229: 4.31 | N229: 1.25 | O229: 43299661 | P229: 37786295300 | Q229: 38091638817 | R229: 305343517 | S229: 0.008 | T229: {=INDEX(Sheet10!D:D,MATCH(C229&E229,INDEX(Sheet10!A:A&Sheet10!B:B,0),0))} -> P15AP | U229: =VLOOKUP(T229,Sheet10!D:E,2,FALSE) -> Acute MI w PTCA w (+Stent)
A230: =T230 -> 15PJX | B230: =U230 -> PTA (+Stent) | C230: =MID(F230,6,1) -> 1 | D230: =LEFT(F230,2) -> 15 | E230: =LEFT(F230,5) -> 15171 | F230: 1517119 | G230: PTA (+Stent) | H230: 98 | I230: 8037060 | J230: 6.23 | K230: 50070884 | L230: 8037060 | M230: 6.23 | N230: 1 | O230: 50070884 | P230: 4111175500 | Q230: 4934930612 | R230: 823755112 | S230: 0.2 | T230: {=INDEX(Sheet10!D:D,MATCH(C230&E230,INDEX(Sheet10!A:A&Sheet10!B:B,0),0))} -> 15PJX | U230: =VLOOKUP(T230,Sheet10!D:E,2,FALSE) -> PTA (+Stent)
A231: =T231 -> P15AQ | B231: =U231 -> PTA (+Stent) | C231: =MID(F231,6,1) -> 1 | D231: =LEFT(F231,2) -> 15 | E231: =LEFT(F231,5) -> 15172 | F231: 1517219 | G231: PTA | H231: 2887 | I231: 8037060 | J231: 4.76 | K231: 38256406 | L231: 8037060 | M231: 4.76 | N231: 1 | O231: 38256406 | P231: 72094724600 | Q231: 110983380967 | R231: 38888656367 | S231: 0.539 | T231: {=INDEX(Sheet10!D:D,MATCH(C231&E231,INDEX(Sheet10!A:A&Sheet10!B:B,0),0))} -> P15AQ | U231: =VLOOKUP(T231,Sheet10!D:E,2,FALSE) -> PTA (+Stent)
A232: =T232 -> P15AR | B232: =U232 -> Permanent Pacemaker Revision | C232: =MID(F232,6,1) -> 1 | D232: =LEFT(F232,2) -> 15 | E232: =LEFT(F232,5) -> 15181 | F232: 1518119 | G232: Permanent Pacemaker Revision | H232: 127 | I232: 8037060 | J232: 5.08 | K232: 40828265 | L232: 8037060 | M232: 5.08 | N232: 1 | O232: 40828265 | P232: 4575369000 | Q232: 5220521630 | R232: 645152630 | S232: 0.141 | T232: {=INDEX(Sheet10!D:D,MATCH(C232&E232,INDEX(Sheet10!A:A&Sheet10!B:B,0),0))} -> P15AR | U232: =VLOOKUP(T232,Sheet10!D:E,2,FALSE) -> Permanent Pacemaker Revision
A233: =T233 -> P15AS | B233: =U233 -> Permanent Pacemaker Replacement | C233: =MID(F233,6,1) -> 1 | D233: =LEFT(F233,2) -> 15 | E233: =LEFT(F233,5) -> 15191 | F233: 1519119 | G233: Permanent Pacemaker Replacement | H233: 265 | I233: 8037060 | J233: 5.59 | K233: 44927165 | L233: 8037060 | M233: 5.59 | N233: 1 | O233: 44927165 | P233: 9537074300 | Q233: 11980623831 | R233: 2443549531 | S233: 0.256 | T233: {=INDEX(Sheet10!D:D,MATCH(C233&E233,INDEX(Sheet10!A:A&Sheet10!B:B,0),0))} -> P15AS | U233: =VLOOKUP(T233,Sheet10!D:E,2,FALSE) -> Permanent Pacemaker Replacement
A234: =T234 -> P15AT | B234: =U234 -> Minor Cardiac Electrophysiologic Proc. | C234: =MID(F234,6,1) -> 1 | D234: =LEFT(F234,2) -> 15 | E234: =LEFT(F234,5) -> 15201 | F234: 1520119 | G234: Minor Cardiac Electrophysiologic Proc. | H234: 1500 | I234: 8037060 | J234: 3.46 | K234: 27808228 | L234: 8037060 | M234: 3.46 | N234: 1 | O234: 27808228 | P234: 35588351900 | Q234: 41952791400 | R234: 6364439500 | S234: 0.179 | T234: {=INDEX(Sheet10!D:D,MATCH(C234&E234,INDEX(Sheet10!A:A&Sheet10!B:B,0),0))} -> P15AT | U234: =VLOOKUP(T234,Sheet10!D:E,2,FALSE) -> Minor Cardiac Electrophysiologic Proc.
A235: =T235 -> P15AU | B235: =U235 -> Major Cardiac Diagnostic Procedures | C235: =MID(F235,6,1) -> 1 | D235: =LEFT(F235,2) -> 15 | E235: =LEFT(F235,5) -> 15211 | F235: 1521119 | G235: Major Cardiac Diagnostic Procedures | H235: 28 | I235: 8037060 | J235: 4.17 | K235: 33514540 | L235: 8037060 | M235: 4.17 | N235: 1 | O235: 33514540 | P235: 940786800 | Q235: 944117626 | R235: 3330826 | S235: 0.004 | T235: {=INDEX(Sheet10!D:D,MATCH(C235&E235,INDEX(Sheet10!A:A&Sheet10!B:B,0),0))} -> P15AU | U235: =VLOOKUP(T235,Sheet10!D:E,2,FALSE) -> Major Cardiac Diagnostic Procedures
A236: =T236 -> P15AV | B236: =U236 -> Other Vascular Procedures | C236: =MID(F236,6,1) -> 1 | D236: =LEFT(F236,2) -> 15 | E236: =LEFT(F236,5) -> 15221 | F236: 1522110 | G236: Other Vascular Procedures w/ No CC | H236: 8715 | I236: 8037060 | J236: 1.96 | K236: 15752638 | L236: 8037060 | M236: 1.96 | N236: 1.27 | O236: 20005850 | P236: 175040673100 | Q236: 175474620548 | R236: 433947448 | S236: 0.002 | T236: {=INDEX(Sheet10!D:D,MATCH(C236&E236,INDEX(Sheet10!A:A&Sheet10!B:B,0),0))} -> P15AV | U236: =VLOOKUP(T236,Sheet10!D:E,2,FALSE) -> Other Vascular Procedures
A237: =T237 -> P15AV | B237: =U237 -> Other Vascular Procedures | C237: =MID(F237,6,1) -> 1 | D237: =LEFT(F237,2) -> 15 | E237: =LEFT(F237,5) -> 15221 | F237: 1522111 | G237: Other Vascular Procedures w/ Mild CC | H237: 3745 | I237: 8037060 | J237: 2.68 | K237: 21539321 | L237: 8037060 | M237: 2.68 | N237: 1.23 | O237: 26493365 | P237: 99820999700 | Q237: 99968113285 | R237: 147113585 | S237: 0.001 | T237: {=INDEX(Sheet10!D:D,MATCH(C237&E237,INDEX(Sheet10!A:A&Sheet10!B:B,0),0))} -> P15AV | U237: =VLOOKUP(T237,Sheet10!D:E,2,FALSE) -> Other Vascular Procedures
A238: =T238 -> P15AV | B238: =U238 -> Other Vascular Procedures | C238: =MID(F238,6,1) -> 1 | D238: =LEFT(F238,2) -> 15 | E238: =LEFT(F238,5) -> 15221 | F238: 1522112 | G238: Other Vascular Procedures w/ Moderate CC | H238: 1401 | I238: 8037060 | J238: 3.82 | K238: 30701569 | L238: 8037060 | M238: 3.82 | N238: 1.01 | O238: 31008585 | P238: 43807735100 | Q238: 44141028811 | R238: 333293711 | S238: 0.008 | T238: {=INDEX(Sheet10!D:D,MATCH(C238&E238,INDEX(Sheet10!A:A&Sheet10!B:B,0),0))} -> P15AV | U238: =VLOOKUP(T238,Sheet10!D:E,2,FALSE) -> Other Vascular Procedures
... A550: =T550 -> 99PZX | B550: =U550 -> Kidney Transplant Proc. | C550: =MID(F550,6,1) -> 1 | D550: =LEFT(F550,2) -> 21 | E550: =LEFT(F550,5) -> 21011 | F550: 2101119 | G550: Kidney Transplant Proc. | H550: 113 | I550: 8037060 | J550: 37.32 | K550: 299943079 | L550: 8037060 | M550: 37.32 | N550: 1.28 | O550: 383927141 | P550: 43386356100 | Q550: 43515688975 | R550: 129332875 | S550: 0.003 | T550: {=INDEX(Sheet10!D:D,MATCH(C550&E550,INDEX(Sheet10!A:A&Sheet10!B:B,0),0))} -> 99PZX | U550: =VLOOKUP(T550,Sheet10!D:E,2,FALSE) -> Kidney Transplant Proc.
A551: =T551 -> 21BX | B551: =U551 -> Kidney Donor Proc. | C551: =MID(F551,6,1) -> 1 | D551: =LEFT(F551,2) -> 21 | E551: =LEFT(F551,5) -> 21021 | F551: 2102119 | G551: Kidney Donor Proc. | H551: #N/A | I551: 8037060 | J551: 2.29 | K551: 18404867 | L551: 8037060 | M551: 2.29 | N551: 1 | O551: 18404867 | P551: #N/A | Q551: #N/A | R551: #N/A | S551: #N/A | T551: {=INDEX(Sheet10!D:D,MATCH(C551&E551,INDEX(Sheet10!A:A&Sheet10!B:B,0),0))} -> 21BX | U551: =VLOOKUP(T551,Sheet10!D:E,2,FALSE) -> Kidney Donor Proc.
A552: =T552 -> D21AD | B552: =U552 -> Kidney, Ureter and Bladder - Major Proc. w/ Neoplasms | C552: =MID(F552,6,1) -> 1 | D552: =LEFT(F552,2) -> 21 | E552: =LEFT(F552,5) -> 21041 | F552: 2104110 | G552: Kidney, Ureter and Bladder - Major Proc. w/ Neoplasms w/ No CC | H552: 598 | I552: 8037060 | J552: 2.37 | K552: 19047832 | L552: 8037060 | M552: 2.37 | N552: 1 | O552: 19047832 | P552: 9775595900 | Q552: 11529670339 | R552: 1754074439 | S552: 0.179 | T552: {=INDEX(Sheet10!D:D,MATCH(C552&E552,INDEX(Sheet10!A:A&Sheet10!B:B,0),0))} -> D21AD | U552: =VLOOKUP(T552,Sheet10!D:E,2,FALSE) -> Kidney, Ureter and Bladder - Major Proc. w/ Neoplasms
A553: =T553 -> D21AD | B553: =U553 -> Kidney, Ureter and Bladder - Major Proc. w/ Neoplasms | C553: =MID(F553,6,1) -> 1 | D553: =LEFT(F553,2) -> 21 | E553: =LEFT(F553,5) -> 21041 | F553: 2104111 | G553: Kidney, Ureter and Bladder - Major Proc. w/ Neoplasms w/ Mild CC | H553: 457 | I553: 8037060 | J553: 3.4 | K553: 27326004 | L553: 8037060 | M553: 3.4 | N553: 1 | O553: 27326004 | P553: 9938584900 | Q553: 12591301328 | R553: 2652716428 | S553: 0.267 | T553: {=INDEX(Sheet10!D:D,MATCH(C553&E553,INDEX(Sheet10!A:A&Sheet10!B:B,0),0))} -> D21AD | U553: =VLOOKUP(T553,Sheet10!D:E,2,FALSE) -> Kidney, Ureter and Bladder - Major Proc. w/ Neoplasms
A554: =T554 -> D21AD | B554: =U554 -> Kidney, Ureter and Bladder - Major Proc. w/ Neoplasms | C554: =MID(F554,6,1) -> 1 | D554: =LEFT(F554,2) -> 21 | E554: =LEFT(F554,5) -> 21041 | F554: 2104112 | G554: Kidney, Ureter and Bladder - Major Proc. w/ Neoplasms w/ Moderate CC | H554: 210 | I554: 8037060 | J554: 5.42 | K554: 43560865 | L554: 8037060 | M554: 5.42 | N554: 1 | O554: 43560865 | P554: 5605567300 | Q554: 9215713692 | R554: 3610146392 | S554: 0.644 | T554: {=INDEX(Sheet10!D:D,MATCH(C554&E554,INDEX(Sheet10!A:A&Sheet10!B:B,0),0))} -> D21AD | U554: =VLOOKUP(T554,Sheet10!D:E,2,FALSE) -> Kidney, Ureter and Bladder - Major Proc. w/ Neoplasms
A555: =T555 -> P21AC | B555: =U555 -> Kidney, Ureter and Bladder - Major Proc. w/ Neoplasms | C555: =MID(F555,6,1) -> 1 | D555: =LEFT(F555,2) -> 21 | E555: =LEFT(F555,5) -> 21042 | F555: 2104219 | G555: Kidney, Ureter and Bladder - Major Proc. | H555: 7191 | I555: 8037060 | J555: 2.29 | K555: 18404867 | L555: 8037060 | M555: 2.29 | N555: 0.9 | O555: 16564381 | P555: 111941136100 | Q555: 120322568009 | R555: 8381431909 | S555: 0.075 | T555: {=INDEX(Sheet10!D:D,MATCH(C555&E555,INDEX(Sheet10!A:A&Sheet10!B:B,0),0))} -> P21AC | U555: =VLOOKUP(T555,Sheet10!D:E,2,FALSE) -> Kidney, Ureter and Bladder - Major Proc. w/ Neoplasms
A556: =T556 -> D21AD | B556: =U556 -> Kidney, Ureter and Bladder - Major Proc. w/ Neoplasms | C556: =MID(F556,6,1) -> 1 | D556: =LEFT(F556,2) -> 21 | E556: =LEFT(F556,5) -> 21051 | F556: 2105119 | G556: Kidney, Ureter and Bladder - Moderate Proc. w/ Neoplasms | H556: 305 | I556: 8037060 | J556: 2.88 | K556: 23146733 | L556: 8037060 | M556: 2.88 | N556: 1 | O556: 23146733 | P556: 6149807600 | Q556: 7120816004 | R556: 971008404 | S556: 0.158 | T556: {=INDEX(Sheet10!D:D,MATCH(C556&E556,INDEX(Sheet10!A:A&Sheet10!B:B,0),0))} -> D21AD | U556: =VLOOKUP(T556,Sheet10!D:E,2,FALSE) -> Kidney, Ureter and Bladder - Major Proc. w/ Neoplasms
A557: =T557 -> P21AN | B557: =U557 -> Kidney, Ureter and Bladder - Moderate Proc. w/ Neoplasms | C557: =MID(F557,6,1) -> 1 | D557: =LEFT(F557,2) -> 21 | E557: =LEFT(F557,5) -> 21052 | F557: 2105210 | G557: Kidney, Ureter and Bladder - Moderate Proc. w/ No CC | H557: 14050 | I557: 8037060 | J557: 1.27 | K557: 10207066 | L557: 8037060 | M557: 1.27 | N557: 1.26 | O557: 12860903 | P557: 181189585200 | Q557: 182542870939 | R557: 1353285739 | S557: 0.007 | T557: {=INDEX(Sheet10!D:D,MATCH(C557&E557,INDEX(Sheet10!A:A&Sheet10!B:B,0),0))} -> P21AN | U557: =VLOOKUP(T557,Sheet10!D:E,2,FALSE) -> Kidney, Ureter and Bladder - Moderate Proc. w/ Neoplasms
A558: =T558 -> P21AN | B558: =U558 -> Kidney, Ureter and Bladder - Moderate Proc. w/ Neoplasms | C558: =MID(F558,6,1) -> 1 | D558: =LEFT(F558,2) -> 21 | E558: =LEFT(F558,5) -> 21052 | F558: 2105211 | G558: Kidney, Ureter and Bladder - Moderate Proc. w/ Mild CC | H558: 2540 | I558: 8037060 | J558: 1.97 | K558: 15833008 | L558: 8037060 | M558: 1.97 | N558: 1.2 | O558: 18999610 | P558: 48312317700 | Q558: 48733662994 | R558: 421345294 | S558: 0.009 | T558: {=INDEX(Sheet10!D:D,MATCH(C558&E558,INDEX(Sheet10!A:A&Sheet10!B:B,0),0))} -> P21AN | U558: =VLOOKUP(T558,Sheet10!D:E,2,FALSE) -> Kidney, Ureter and Bladder - Moderate Proc. w/ Neoplasms
A559: =T559 -> P21AD | B559: =U559 -> Operative Insertion of Peritoneal Catheter for Dialysis | C559: =MID(F559,6,1) -> 1 | D559: =LEFT(F559,2) -> 21 | E559: =LEFT(F559,5) -> 21061 | F559: 2106119 | G559: Operative Insertion of Peritoneal Catheter for Dialysis | H559: 195 | I559: 8037060 | J559: 2.51 | K559: 20173021 | L559: 8037060 | M559: 2.51 | N559: 1 | O559: 20173021 | P559: 2831520800 | Q559: 3973918517 | R559: 1142397717 | S559: 0.403 | T559: {=INDEX(Sheet10!D:D,MATCH(C559&E559,INDEX(Sheet10!A:A&Sheet10!B:B,0),0))} -> P21AD | U559: =VLOOKUP(T559,Sheet10!D:E,2,FALSE) -> Operative Insertion of Peritoneal Catheter for Dialysis
A560: =T560 -> P21AE | B560: =U560 -> Transurethral Prostatectomy | C560: =MID(F560,6,1) -> 1 | D560: =LEFT(F560,2) -> 21 | E560: =LEFT(F560,5) -> 21071 | F560: 2107119 | G560: Transurethral Prostatectomy | H560: 1607 | I560: 8037060 | J560: 1.32 | K560: 10608919 | L560: 8037060 | M560: 1.32 | N560: 1 | O560: 10608919 | P560: 15795501000 | Q560: 17249447154 | R560: 1453946154 | S560: 0.092 | T560: {=INDEX(Sheet10!D:D,MATCH(C560&E560,INDEX(Sheet10!A:A&Sheet10!B:B,0),0))} -> P21AE | U560: =VLOOKUP(T560,Sheet10!D:E,2,FALSE) -> Transurethral Prostatectomy
A561: =T561 -> D21AD | B561: =U561 -> Kidney, Ureter and Bladder - Major Proc. w/ Neoplasms | C561: =MID(F561,6,1) -> 1 | D561: =LEFT(F561,2) -> 21 | E561: =LEFT(F561,5) -> 21081 | F561: 2108110 | G561: Other Kidney and Urinary Tract OR Proc. w/ Neoplasms w/ No CC | H561: 46 | I561: 8037060 | J561: 1.67 | K561: 13421890 | L561: 8037060 | M561: 1.67 | N561: 1 | O561: 13421890 | P561: 556748100 | Q561: 624893449 | R561: 68145349 | S561: 0.122 | T561: {=INDEX(Sheet10!D:D,MATCH(C561&E561,INDEX(Sheet10!A:A&Sheet10!B:B,0),0))} -> D21AD | U561: =VLOOKUP(T561,Sheet10!D:E,2,FALSE) -> Kidney, Ureter and Bladder - Major Proc. w/ Neoplasms
A562: =T562 -> D21AD | B562: =U562 -> Kidney, Ureter and Bladder - Major Proc. w/ Neoplasms | C562: =MID(F562,6,1) -> 1 | D562: =LEFT(F562,2) -> 21 | E562: =LEFT(F562,5) -> 21081 | F562: 2108111 | G562: Other Kidney and Urinary Tract OR Proc. w/ Neoplasms w/ Mild CC | H562: 1 | I562: 8037060 | J562: 2.51 | K562: 20173021 | L562: 8037060 | M562: 2.51 | N562: 1 | O562: 20173021 | P562: 7992300 | Q562: 20173021 | R562: 12180721 | S562: 1.524 | T562: {=INDEX(Sheet10!D:D,MATCH(C562&E562,INDEX(Sheet10!A:A&Sheet10!B:B,0),0))} -> D21AD | U562: =VLOOKUP(T562,Sheet10!D:E,2,FALSE) -> Kidney, Ureter and Bladder - Major Proc. w/ Neoplasms
A563: =T563 -> D21AD | B563: =U563 -> Kidney, Ureter and Bladder - Major Proc. w/ Neoplasms | C563: =MID(F563,6,1) -> 1 | D563: =LEFT(F563,2) -> 21 | E563: =LEFT(F563,5) -> 21081 | F563: 2108112 | G563: Other Kidney and Urinary Tract OR Proc. w/ Neoplasms w/ Moderate CC | H563: 44 | I563: 8037060 | J563: 3.09 | K563: 24834515 | L563: 8037060 | M563: 3.09 | N563: 1 | O563: 24834515 | P563: 748297000 | Q563: 1101881178 | R563: 353584178 | S563: 0.473 | T563: {=INDEX(Sheet10!D:D,MATCH(C563&E563,INDEX(Sheet10!A:A&Sheet10!B:B,0),0))} -> D21AD | U563: =VLOOKUP(T563,Sheet10!D:E,2,FALSE) -> Kidney, Ureter and Bladder - Major Proc. w/ Neoplasms
... A596: =T596 -> D21AL | B596: =U596 -> Urethral Stricture | C596: =MID(F596,6,1) -> 1 | D596: =LEFT(F596,2) -> 21 | E596: =LEFT(F596,5) -> 21711 | F596: 2171111 | G596: Urethral Stricture w/ Mild CC | H596: 1192 | I596: 8037060 | J596: 1.13 | K596: 9081878 | L596: 8037060 | M596: 1.13 | N596: 1.2 | O596: 10898253 | P596: 13032570000 | Q596: 13140938005 | R596: 108368005 | S596: 0.008 | T596: {=INDEX(Sheet10!D:D,MATCH(C596&E596,INDEX(Sheet10!A:A&Sheet10!B:B,0),0))} -> D21AL | U596: =VLOOKUP(T596,Sheet10!D:E,2,FALSE) -> Urethral Stricture
A597: =T597 -> 22PBX | B597: =U597 -> Radical Prostatectomy Proc. w Laparascopy | C597: =MID(F597,6,1) -> 1 | D597: =LEFT(F597,2) -> 22 | E597: =LEFT(F597,5) -> 22011 | F597: 2201119 | G597: Radical Prostatectomy Proc. w Laparascopy | H597: #N/A | I597: 8037060 | J597: 1.45 | K597: 11653737 | L597: 8037060 | M597: 1.45 | N597: 1 | O597: 11653737 | P597: #N/A | Q597: #N/A | R597: #N/A | S597: #N/A | T597: {=INDEX(Sheet10!D:D,MATCH(C597&E597,INDEX(Sheet10!A:A&Sheet10!B:B,0),0))} -> 22PBX | U597: =VLOOKUP(T597,Sheet10!D:E,2,FALSE) -> Radical Prostatectomy Proc. w Laparascopy
A598: =T598 -> P22AA | B598: =U598 -> Radical Prostatectomy Proc. w Laparascopy | C598: =MID(F598,6,1) -> 1 | D598: =LEFT(F598,2) -> 22 | E598: =LEFT(F598,5) -> 22012 | F598: 2201219 | G598: Radical Prostatectomy Proc. | H598: 63 | I598: 8037060 | J598: 1.24 | K598: 9965954 | L598: 8037060 | M598: 1.24 | N598: 1 | O598: 9965954 | P598: 531632600 | Q598: 642702127 | R598: 111069527 | S598: 0.209 | T598: {=INDEX(Sheet10!D:D,MATCH(C598&E598,INDEX(Sheet10!A:A&Sheet10!B:B,0),0))} -> P22AA | U598: =VLOOKUP(T598,Sheet10!D:E,2,FALSE) -> Radical Prostatectomy Proc. w Laparascopy
A599: =T599 -> 22BX | B599: =U599 -> Male Reproductive Minimal Invasive Proc. w Neoplasms | C599: =MID(F599,6,1) -> 1 | D599: =LEFT(F599,2) -> 22 | E599: =LEFT(F599,5) -> 22031 | F599: 2203119 | G599: Male Reproductive Minimal Invasive Proc. w Neoplasms | H599: 383 | I599: 8037060 | J599: 1.08 | K599: 8680025 | L599: 8037060 | M599: 1.08 | N599: 1.04 | O599: 9027226 | P599: 3464009200 | Q599: 3494227478 | R599: 30218278 | S599: 0.009 | T599: {=INDEX(Sheet10!D:D,MATCH(C599&E599,INDEX(Sheet10!A:A&Sheet10!B:B,0),0))} -> 22BX | U599: =VLOOKUP(T599,Sheet10!D:E,2,FALSE) -> Male Reproductive Minimal Invasive Proc. w Neoplasms
A600: =T600 -> P22AC | B600: =U600 -> Male Reproductive Minimal Invasive Proc. w Neoplasms | C600: =MID(F600,6,1) -> 1 | D600: =LEFT(F600,2) -> 22 | E600: =LEFT(F600,5) -> 22032 | F600: 2203219 | G600: Male Reproductive Minimal Invasive Proc. | H600: 578 | I600: 8037060 | J600: 1 | K600: 8037060 | L600: 8037060 | M600: 1 | N600: 1.15 | O600: 9242619 | P600: 5355115500 | Q600: 5403151782 | R600: 48036282 | S600: 0.009 | T600: {=INDEX(Sheet10!D:D,MATCH(C600&E600,INDEX(Sheet10!A:A&Sheet10!B:B,0),0))} -> P22AC | U600: =VLOOKUP(T600,Sheet10!D:E,2,FALSE) -> Male Reproductive Minimal Invasive Proc. w Neoplasms
A601: =T601 -> P22AD | B601: =U601 -> Transurethral Prostatectomy Proc. | C601: =MID(F601,6,1) -> 1 | D601: =LEFT(F601,2) -> 22 | E601: =LEFT(F601,5) -> 22042 | F601: 2204210 | G601: Transurethral Prostatectomy Proc. w/ No CC | H601: 57089 | I601: 8037060 | J601: 1.25 | K601: 10046325 | L601: 8037060 | M601: 1.25 | N601: 0.9 | O601: 9041693 | P601: 489620530700 | Q601: 521329641133 | R601: 31709110433 | S601: 0.065 | T601: {=INDEX(Sheet10!D:D,MATCH(C601&E601,INDEX(Sheet10!A:A&Sheet10!B:B,0),0))} -> P22AD | U601: =VLOOKUP(T601,Sheet10!D:E,2,FALSE) -> Transurethral Prostatectomy Proc.
A602: =T602 -> P22AD | B602: =U602 -> Transurethral Prostatectomy Proc. | C602: =MID(F602,6,1) -> 1 | D602: =LEFT(F602,2) -> 22 | E602: =LEFT(F602,5) -> 22042 | F602: 2204211 | G602: Transurethral Prostatectomy Proc. w/ Mild CC | H602: 12055 | I602: 8037060 | J602: 1.66 | K602: 13341520 | L602: 8037060 | M602: 1.66 | N602: 1 | O602: 13341520 | P602: 157142184100 | Q602: 162280263778 | R602: 5138079678 | S602: 0.033 | T602: {=INDEX(Sheet10!D:D,MATCH(C602&E602,INDEX(Sheet10!A:A&Sheet10!B:B,0),0))} -> P22AD | U602: =VLOOKUP(T602,Sheet10!D:E,2,FALSE) -> Transurethral Prostatectomy Proc.
A603: =T603 -> P22AE | B603: =U603 -> Scrotal, Inguinal, and Testis Minimal Invasive Proc. | C603: =MID(F603,6,1) -> 1 | D603: =LEFT(F603,2) -> 22 | E603: =LEFT(F603,5) -> 22051 | F603: 2205110 | G603: Scrotal, Inguinal, and Testis Minimal Invasive Proc. w/ No CC | H603: 286 | I603: 8037060 | J603: 0.89 | K603: 7152983 | L603: 8037060 | M603: 0.89 | N603: 1 | O603: 7152983 | P603: 1901378700 | Q603: 2096631752 | R603: 195253052 | S603: 0.103 | T603: {=INDEX(Sheet10!D:D,MATCH(C603&E603,INDEX(Sheet10!A:A&Sheet10!B:B,0),0))} -> P22AE | U603: =VLOOKUP(T603,Sheet10!D:E,2,FALSE) -> Scrotal, Inguinal, and Testis Minimal Invasive Proc.
A604: =T604 -> P22AE | B604: =U604 -> Scrotal, Inguinal, and Testis Minimal Invasive Proc. | C604: =MID(F604,6,1) -> 1 | D604: =LEFT(F604,2) -> 22 | E604: =LEFT(F604,5) -> 22051 | F604: 2205111 | G604: Scrotal, Inguinal, and Testis Minimal Invasive Proc. w/ Mild CC | H604: 176 | I604: 8037060 | J604: 1.67 | K604: 13421890 | L604: 8037060 | M604: 1.67 | N604: 1.16 | O604: 15569393 | P604: 2730909200 | Q604: 2788569103 | R604: 57659903 | S604: 0.021 | T604: {=INDEX(Sheet10!D:D,MATCH(C604&E604,INDEX(Sheet10!A:A&Sheet10!B:B,0),0))} -> P22AE | U604: =VLOOKUP(T604,Sheet10!D:E,2,FALSE) -> Scrotal, Inguinal, and Testis Minimal Invasive Proc.
A605: =T605 -> P22AF | B605: =U605 -> Open Prostatectomy Proc. | C605: =MID(F605,6,1) -> 1 | D605: =LEFT(F605,2) -> 22 | E605: =LEFT(F605,5) -> 22061 | F605: 2206110 | G605: Open Prostatectomy Proc. w/ No CC | H605: 2229 | I605: 8037060 | J605: 1.1 | K605: 8840766 | L605: 8037060 | M605: 1.1 | N605: 1 | O605: 8840766 | P605: 12722593900 | Q605: 19876569414 | R605: 7153975514 | S605: 0.562 | T605: {=INDEX(Sheet10!D:D,MATCH(C605&E605,INDEX(Sheet10!A:A&Sheet10!B:B,0),0))} -> P22AF | U605: =VLOOKUP(T605,Sheet10!D:E,2,FALSE) -> Open Prostatectomy Proc.
A606: =T606 -> P22AF | B606: =U606 -> Open Prostatectomy Proc. | C606: =MID(F606,6,1) -> 1 | D606: =LEFT(F606,2) -> 22 | E606: =LEFT(F606,5) -> 22061 | F606: 2206111 | G606: Open Prostatectomy Proc. w/ Mild CC | H606: 683 | I606: 8037060 | J606: 1.48 | K606: 11894849 | L606: 8037060 | M606: 1.48 | N606: 1 | O606: 11894849 | P606: 6098170500 | Q606: 8189530730 | R606: 2091360230 | S606: 0.343 | T606: {=INDEX(Sheet10!D:D,MATCH(C606&E606,INDEX(Sheet10!A:A&Sheet10!B:B,0),0))} -> P22AF | U606: =VLOOKUP(T606,Sheet10!D:E,2,FALSE) -> Open Prostatectomy Proc.
A607: =T607 -> P22AB | B607: =U607 -> Major Penis Proc. | C607: =MID(F607,6,1) -> 1 | D607: =LEFT(F607,2) -> 22 | E607: =LEFT(F607,5) -> 22071 | F607: 2207119 | G607: Major Penis Proc. | H607: 5871 | I607: 8037060 | J607: 1.27 | K607: 10207066 | L607: 8037060 | M607: 1.27 | N607: 1.08 | O607: 11023631 | P607: 64505190900 | Q607: 65552834513 | R607: 1047643613 | S607: 0.016 | T607: {=INDEX(Sheet10!D:D,MATCH(C607&E607,INDEX(Sheet10!A:A&Sheet10!B:B,0),0))} -> P22AB | U607: =VLOOKUP(T607,Sheet10!D:E,2,FALSE) -> Major Penis Proc.
A608: =T608 -> 22BX | B608: =U608 -> Male Reproductive Minimal Invasive Proc. w Neoplasms | C608: =MID(F608,6,1) -> 1 | D608: =LEFT(F608,2) -> 22 | E608: =LEFT(F608,5) -> 22081 | F608: 2208119 | G608: Male Reproductive Open Proc. w Neoplasms | H608: 178 | I608: 8037060 | J608: 1.43 | K608: 11492996 | L608: 8037060 | M608: 1.43 | N608: 1 | O608: 11492996 | P608: 1411240900 | Q608: 2073210752 | R608: 661969852 | S608: 0.469 | T608: {=INDEX(Sheet10!D:D,MATCH(C608&E608,INDEX(Sheet10!A:A&Sheet10!B:B,0),0))} -> 22BX | U608: =VLOOKUP(T608,Sheet10!D:E,2,FALSE) -> Male Reproductive Minimal Invasive Proc. w Neoplasms
A609: =T609 -> P22AH | B609: =U609 -> Male Reproductive Open Proc. w Neoplasms | C609: =MID(F609,6,1) -> 1 | D609: =LEFT(F609,2) -> 22 | E609: =LEFT(F609,5) -> 22082 | F609: 2208210 | G609: Male Reproductive Open Proc. w/ No CC | H609: 22033 | I609: 8037060 | J609: 0.95 | K609: 7635207 | L609: 8037060 | M609: 0.95 | N609: 1.06 | O609: 8093319 | P609: 177632749300 | Q609: 180544356781 | R609: 2911607481 | S609: 0.016 | T609: {=INDEX(Sheet10!D:D,MATCH(C609&E609,INDEX(Sheet10!A:A&Sheet10!B:B,0),0))} -> P22AH | U609: =VLOOKUP(T609,Sheet10!D:E,2,FALSE) -> Male Reproductive Open Proc. w Neoplasms
... A696: =T696 -> 24CX | B696: =U696 -> Ectopic Pregnancy w/ OR Proc. w/ Shock | C696: =MID(F696,6,1) -> 1 | D696: =LEFT(F696,2) -> 24 | E696: =LEFT(F696,5) -> 24112 | F696: 2411219 | G696: Ectopic Pregnancy w/ OR Proc. w/ Shock | H696: 314 | I696: 8037060 | J696: 2.1 | K696: 16877826 | L696: 8037060 | M696: 2.1 | N696: 1 | O696: 16877826 | P696: 4890867400 | Q696: 5326160364 | R696: 435292964 | S696: 0.089 | T696: {=INDEX(Sheet10!D:D,MATCH(C696&E696,INDEX(Sheet10!A:A&Sheet10!B:B,0),0))} -> 24CX | U696: =VLOOKUP(T696,Sheet10!D:E,2,FALSE) -> Ectopic Pregnancy w/ OR Proc. w/ Shock
A697: =T697 -> 24PCX | B697: =U697 -> Ectopic Pregnancy w/ Laparoscopic OR Proc. | C697: =MID(F697,6,1) -> 1 | D697: =LEFT(F697,2) -> 24 | E697: =LEFT(F697,5) -> 24121 | F697: 2412119 | G697: Ectopic Pregnancy w/ Laparoscopic OR Proc. | H697: #N/A | I697: 8037060 | J697: 1.38 | K697: 11091143 | L697: 8037060 | M697: 1.38 | N697: 1 | O697: 11091143 | P697: #N/A | Q697: #N/A | R697: #N/A | S697: #N/A | T697: {=INDEX(Sheet10!D:D,MATCH(C697&E697,INDEX(Sheet10!A:A&Sheet10!B:B,0),0))} -> 24PCX | U697: =VLOOKUP(T697,Sheet10!D:E,2,FALSE) -> Ectopic Pregnancy w/ Laparoscopic OR Proc.
A698: =T698 -> 24PDX | B698: =U698 -> Abdominal Histerectomy/Histerotomy for Abortion | C698: =MID(F698,6,1) -> 1 | D698: =LEFT(F698,2) -> 24 | E698: =LEFT(F698,5) -> 24141 | F698: 2414119 | G698: Abdominal Histerectomy/Histerotomy for Abortion | H698: 301 | I698: 8037060 | J698: 1.73 | K698: 13904114 | L698: 8037060 | M698: 1.73 | N698: 1 | O698: 13904114 | P698: 3105619800 | Q698: 4208403254 | R698: 1102783454 | S698: 0.355 | T698: {=INDEX(Sheet10!D:D,MATCH(C698&E698,INDEX(Sheet10!A:A&Sheet10!B:B,0),0))} -> 24PDX | U698: =VLOOKUP(T698,Sheet10!D:E,2,FALSE) -> Abdominal Histerectomy/Histerotomy for Abortion
A699: =T699 -> 24PEX | B699: =U699 -> Dilatation & Curettage, Aspiration Curettage for Uncomplicated Abortion | C699: =MID(F699,6,1) -> 1 | D699: =LEFT(F699,2) -> 24 | E699: =LEFT(F699,5) -> 24151 | F699: 2415119 | G699: Dilatation & Curettage, Aspiration Curettage for Uncomplicated Abortion | H699: 151319 | I699: 8037060 | J699: 0.41 | K699: 3295195 | L699: 8037060 | M699: 0.41 | N699: 0.88 | O699: 2899771 | P699: 415987534000 | Q699: 447179270476 | R699: 31191736476 | S699: 0.075 | T699: {=INDEX(Sheet10!D:D,MATCH(C699&E699,INDEX(Sheet10!A:A&Sheet10!B:B,0),0))} -> 24PEX | U699: =VLOOKUP(T699,Sheet10!D:E,2,FALSE) -> Dilatation & Curettage, Aspiration Curettage for Uncomplicated Abortion
A700: =T700 -> 24PEX | B700: =U700 -> Dilatation & Curettage, Aspiration Curettage for Uncomplicated Abortion | C700: =MID(F700,6,1) -> 1 | D700: =LEFT(F700,2) -> 24 | E700: =LEFT(F700,5) -> 24161 | F700: 2416119 | G700: Dilatation & Curettage, Aspiration Curettage for Complicated Abortion | H700: 38022 | I700: 8037060 | J700: 0.43 | K700: 3455936 | L700: 8037060 | M700: 0.43 | N700: 1 | O700: 3455936 | P700: 104999883500 | Q700: 133625066488 | R700: 28625182988 | S700: 0.273 | T700: {=INDEX(Sheet10!D:D,MATCH(C700&E700,INDEX(Sheet10!A:A&Sheet10!B:B,0),0))} -> 24PEX | U700: =VLOOKUP(T700,Sheet10!D:E,2,FALSE) -> Dilatation & Curettage, Aspiration Curettage for Uncomplicated Abortion
A701: =T701 -> 24PEX | B701: =U701 -> Dilatation & Curettage, Aspiration Curettage for Uncomplicated Abortion | C701: =MID(F701,6,1) -> 1 | D701: =LEFT(F701,2) -> 24 | E701: =LEFT(F701,5) -> 24171 | F701: 2417119 | G701: Dilatation & Curettage, Aspiration Curettage for Molar Pregnancy | H701: 5090 | I701: 8037060 | J701: 0.77 | K701: 6188536 | L701: 8037060 | M701: 0.77 | N701: 1 | O701: 6188536 | P701: 15778198000 | Q701: 31737147258 | R701: 15958949258 | S701: 1.011 | T701: {=INDEX(Sheet10!D:D,MATCH(C701&E701,INDEX(Sheet10!A:A&Sheet10!B:B,0),0))} -> 24PEX | U701: =VLOOKUP(T701,Sheet10!D:E,2,FALSE) -> Dilatation & Curettage, Aspiration Curettage for Uncomplicated Abortion
A702: =T702 -> 24PBX | B702: =U702 -> Ectopic Pregnancy w/ OR Proc. | C702: =MID(F702,6,1) -> 1 | D702: =LEFT(F702,2) -> 24 | E702: =LEFT(F702,5) -> 24181 | F702: 2418119 | G702: Pregnancy & Antenatal OR Proc. | H702: 1344 | I702: 8037060 | J702: 1.11 | K702: 8921137 | L702: 8037060 | M702: 1.11 | N702: 1 | O702: 8921137 | P702: 10816971700 | Q702: 12117757590 | R702: 1300785890 | S702: 0.12 | T702: {=INDEX(Sheet10!D:D,MATCH(C702&E702,INDEX(Sheet10!A:A&Sheet10!B:B,0),0))} -> 24PBX | U702: =VLOOKUP(T702,Sheet10!D:E,2,FALSE) -> Ectopic Pregnancy w/ OR Proc.
A703: =T703 -> ~24PQX | B703: =U703 -> OR Proc. Level 4 or 5 or 6 w/ Delivery | C703: =MID(F703,6,1) -> 1 | D703: =LEFT(F703,2) -> 24 | E703: =LEFT(F703,5) -> 24192 | F703: 2419219 | G703: OR Proc. Level 4 or 5 or 6 w/ Delivery | H703: 4240 | I703: 8037060 | J703: 1.31 | K703: 10528549 | L703: 8037060 | M703: 1.31 | N703: 1 | O703: 10528549 | P703: 42780582500 | Q703: 45061571064 | R703: 2280988564 | S703: 0.053 | T703: {=INDEX(Sheet10!D:D,MATCH(C703&E703,INDEX(Sheet10!A:A&Sheet10!B:B,0),0))} -> ~24PQX | U703: =VLOOKUP(T703,Sheet10!D:E,2,FALSE) -> OR Proc. Level 4 or 5 or 6 w/ Delivery
A704: =T704 -> ~24PQX | B704: =U704 -> OR Proc. Level 4 or 5 or 6 w/ Delivery | C704: =MID(F704,6,1) -> 1 | D704: =LEFT(F704,2) -> 24 | E704: =LEFT(F704,5) -> 24193 | F704: 2419319 | G704: OR Proc. Level 3 w/ Delivery | H704: 422 | I704: 8037060 | J704: 0.71 | K704: 5706313 | L704: 8037060 | M704: 0.71 | N704: 1 | O704: 5706313 | P704: 1482195300 | Q704: 2423855917 | R704: 941660617 | S704: 0.635 | T704: {=INDEX(Sheet10!D:D,MATCH(C704&E704,INDEX(Sheet10!A:A&Sheet10!B:B,0),0))} -> ~24PQX | U704: =VLOOKUP(T704,Sheet10!D:E,2,FALSE) -> OR Proc. Level 4 or 5 or 6 w/ Delivery
A705: =T705 -> ~24PQX | B705: =U705 -> OR Proc. Level 4 or 5 or 6 w/ Delivery | C705: =MID(F705,6,1) -> 1 | D705: =LEFT(F705,2) -> 24 | E705: =LEFT(F705,5) -> 24194 | F705: 2419419 | G705: OR Proc. Level 2 w/ Delivery | H705: 37 | I705: 8037060 | J705: 0.62 | K705: 4982977 | L705: 8037060 | M705: 0.62 | N705: 1 | O705: 4982977 | P705: 241569900 | Q705: 187115656 | R705: -54454244 | S705: -0.225 | T705: {=INDEX(Sheet10!D:D,MATCH(C705&E705,INDEX(Sheet10!A:A&Sheet10!B:B,0),0))} -> ~24PQX | U705: =VLOOKUP(T705,Sheet10!D:E,2,FALSE) -> OR Proc. Level 4 or 5 or 6 w/ Delivery
A706: =T706 -> ~24PQX | B706: =U706 -> OR Proc. Level 4 or 5 or 6 w/ Delivery | C706: =MID(F706,6,1) -> 1 | D706: =LEFT(F706,2) -> 24 | E706: =LEFT(F706,5) -> 24195 | F706: 2419519 | G706: OR Proc. Level 1 w/ Delivery | H706: 3 | I706: 8037060 | J706: 0.44 | K706: 3536306 | L706: 8037060 | M706: 0.44 | N706: 1 | O706: 3536306 | P706: 24083100 | Q706: 10728419 | R706: -13354681 | S706: -0.555 | T706: {=INDEX(Sheet10!D:D,MATCH(C706&E706,INDEX(Sheet10!A:A&Sheet10!B:B,0),0))} -> ~24PQX | U706: =VLOOKUP(T706,Sheet10!D:E,2,FALSE) -> OR Proc. Level 4 or 5 or 6 w/ Delivery
A707: =T707 -> ~24PQX | B707: =U707 -> OR Proc. Level 4 or 5 or 6 w/ Delivery | C707: =MID(F707,6,1) -> 1 | D707: =LEFT(F707,2) -> 24 | E707: =LEFT(F707,5) -> 24201 | F707: 2420119 | G707: OR Proc. Level 5 or 6 w/ Pregnancy & Antenatal | H707: 400 | I707: 8037060 | J707: 4.06 | K707: 32630464 | L707: 8037060 | M707: 4.06 | N707: 1 | O707: 32630464 | P707: 9310081600 | Q707: 13136951940 | R707: 3826870340 | S707: 0.411 | T707: {=INDEX(Sheet10!D:D,MATCH(C707&E707,INDEX(Sheet10!A:A&Sheet10!B:B,0),0))} -> ~24PQX | U707: =VLOOKUP(T707,Sheet10!D:E,2,FALSE) -> OR Proc. Level 4 or 5 or 6 w/ Delivery
A708: =T708 -> ~24PQX | B708: =U708 -> OR Proc. Level 4 or 5 or 6 w/ Delivery | C708: =MID(F708,6,1) -> 1 | D708: =LEFT(F708,2) -> 24 | E708: =LEFT(F708,5) -> 24202 | F708: 2420219 | G708: OR Proc. Level 4 w/ Pregnancy & Antenatal | H708: 441 | I708: 8037060 | J708: 1.2 | K708: 9644472 | L708: 8037060 | M708: 1.2 | N708: 1 | O708: 9644472 | P708: 3890506800 | Q708: 4306044152 | R708: 415537352 | S708: 0.107 | T708: {=INDEX(Sheet10!D:D,MATCH(C708&E708,INDEX(Sheet10!A:A&Sheet10!B:B,0),0))} -> ~24PQX | U708: =VLOOKUP(T708,Sheet10!D:E,2,FALSE) -> OR Proc. Level 4 or 5 or 6 w/ Delivery
A709: =T709 -> ~24PQX | B709: =U709 -> OR Proc. Level 4 or 5 or 6 w/ Delivery | C709: =MID(F709,6,1) -> 1 | D709: =LEFT(F709,2) -> 24 | E709: =LEFT(F709,5) -> 24203 | F709: 2420319 | G709: OR Proc. Level 3 w/ Pregnancy & Antenatal | H709: 5541 | I709: 8037060 | J709: 0.9 | K709: 7233354 | L709: 8037060 | M709: 0.9 | N709: 1 | O709: 7233354 | P709: 38582753900 | Q709: 40654903014 | R709: 2072149114 | S709: 0.054 | T709: {=INDEX(Sheet10!D:D,MATCH(C709&E709,INDEX(Sheet10!A:A&Sheet10!B:B,0),0))} -> ~24PQX | U709: =VLOOKUP(T709,Sheet10!D:E,2,FALSE) -> OR Proc. Level 4 or 5 or 6 w/ Delivery
... A857: =T857 -> D28AM | B857: =U857 -> Mycobacteriosis, Adult | C857: =MID(F857,6,1) -> 1 | D857: =LEFT(F857,2) -> 28 | E857: =LEFT(F857,5) -> 28722 | F857: 2872211 | G857: Mycobacteriosis, Child w/ Mild CC | H857: 358 | I857: 8037060 | J857: 0.77 | K857: 6188536 | L857: 8037060 | M857: 0.77 | N857: 1.03 | O857: 6374192 | P857: 2281989600 | Q857: 2317438838 | R857: 35449238 | S857: 0.016 | T857: {=INDEX(Sheet10!D:D,MATCH(C857&E857,INDEX(Sheet10!A:A&Sheet10!B:B,0),0))} -> D28AM | U857: =VLOOKUP(T857,Sheet10!D:E,2,FALSE) -> Mycobacteriosis, Adult
A858: =T858 -> 28CX | B858: =U858 -> COVID-19, Confirmed | C858: =MID(F858,6,1) -> 1 | D858: =LEFT(F858,2) -> 28 | E858: =LEFT(F858,5) -> 28731 | F858: 2873110 | G858: COVID-19, Confirmed w/ No CC | H858: #N/A | I858: 8037060 | J858: 1.62 | K858: 13020037 | L858: 8037060 | M858: 1.62 | N858: 1 | O858: 13020037 | P858: #N/A | Q858: #N/A | R858: #N/A | S858: #N/A | T858: {=INDEX(Sheet10!D:D,MATCH(C858&E858,INDEX(Sheet10!A:A&Sheet10!B:B,0),0))} -> 28CX | U858: =VLOOKUP(T858,Sheet10!D:E,2,FALSE) -> COVID-19, Confirmed
A859: =T859 -> 28CX | B859: =U859 -> COVID-19, Confirmed | C859: =MID(F859,6,1) -> 1 | D859: =LEFT(F859,2) -> 28 | E859: =LEFT(F859,5) -> 28731 | F859: 2873111 | G859: COVID-19, Confirmed w/ Mild CC | H859: #N/A | I859: 8037060 | J859: 2.01 | K859: 16154491 | L859: 8037060 | M859: 2.01 | N859: 1 | O859: 16154491 | P859: #N/A | Q859: #N/A | R859: #N/A | S859: #N/A | T859: {=INDEX(Sheet10!D:D,MATCH(C859&E859,INDEX(Sheet10!A:A&Sheet10!B:B,0),0))} -> 28CX | U859: =VLOOKUP(T859,Sheet10!D:E,2,FALSE) -> COVID-19, Confirmed
A860: =T860 -> 28CX | B860: =U860 -> COVID-19, Confirmed | C860: =MID(F860,6,1) -> 1 | D860: =LEFT(F860,2) -> 28 | E860: =LEFT(F860,5) -> 28731 | F860: 2873112 | G860: COVID-19, Confirmed w/ Moderate CC | H860: #N/A | I860: 8037060 | J860: 2.69 | K860: 21619691 | L860: 8037060 | M860: 2.69 | N860: 1 | O860: 21619691 | P860: #N/A | Q860: #N/A | R860: #N/A | S860: #N/A | T860: {=INDEX(Sheet10!D:D,MATCH(C860&E860,INDEX(Sheet10!A:A&Sheet10!B:B,0),0))} -> 28CX | U860: =VLOOKUP(T860,Sheet10!D:E,2,FALSE) -> COVID-19, Confirmed
A861: =T861 -> ~28CX | B861: =U861 -> COVID-19, Suspected | C861: =MID(F861,6,1) -> 1 | D861: =LEFT(F861,2) -> 28 | E861: =LEFT(F861,5) -> 28741 | F861: 2874110 | G861: COVID-19, Suspected w/ No CC | H861: #N/A | I861: 8037060 | J861: 0.94 | K861: 7554836 | L861: 8037060 | M861: 0.94 | N861: 1 | O861: 7554836 | P861: #N/A | Q861: #N/A | R861: #N/A | S861: #N/A | T861: {=INDEX(Sheet10!D:D,MATCH(C861&E861,INDEX(Sheet10!A:A&Sheet10!B:B,0),0))} -> ~28CX | U861: =VLOOKUP(T861,Sheet10!D:E,2,FALSE) -> COVID-19, Suspected
A862: =T862 -> ~28CX | B862: =U862 -> COVID-19, Suspected | C862: =MID(F862,6,1) -> 1 | D862: =LEFT(F862,2) -> 28 | E862: =LEFT(F862,5) -> 28741 | F862: 2874111 | G862: COVID-19, Suspected w/ Mild CC | H862: #N/A | I862: 8037060 | J862: 1.17 | K862: 9403360 | L862: 8037060 | M862: 1.17 | N862: 1 | O862: 9403360 | P862: #N/A | Q862: #N/A | R862: #N/A | S862: #N/A | T862: {=INDEX(Sheet10!D:D,MATCH(C862&E862,INDEX(Sheet10!A:A&Sheet10!B:B,0),0))} -> ~28CX | U862: =VLOOKUP(T862,Sheet10!D:E,2,FALSE) -> COVID-19, Suspected
A863: =T863 -> D28AP | B863: =U863 -> Leprosy, Adult - Chronic | C863: =MID(F863,6,1) -> 1 | D863: =LEFT(F863,2) -> 28 | E863: =LEFT(F863,5) -> 28751 | F863: 2875119 | G863: Leprosy, Adult - Chronic | H863: #N/A | I863: 8037060 | J863: 0.51 | K863: 4098901 | L863: 8037060 | M863: 0.51 | N863: 1 | O863: 4098901 | P863: #N/A | Q863: #N/A | R863: #N/A | S863: #N/A | T863: {=INDEX(Sheet10!D:D,MATCH(C863&E863,INDEX(Sheet10!A:A&Sheet10!B:B,0),0))} -> D28AP | U863: =VLOOKUP(T863,Sheet10!D:E,2,FALSE) -> Leprosy, Adult - Chronic
A864: =T864 -> D28AP | B864: =U864 -> Leprosy, Adult - Chronic | C864: =MID(F864,6,1) -> 1 | D864: =LEFT(F864,2) -> 28 | E864: =LEFT(F864,5) -> 28752 | F864: 2875219 | G864: Leprosy, Adult - Sub Acute | H864: #N/A | I864: 8037060 | J864: 0.51 | K864: 4098901 | L864: 8037060 | M864: 0.51 | N864: 1 | O864: 4098901 | P864: #N/A | Q864: #N/A | R864: #N/A | S864: #N/A | T864: {=INDEX(Sheet10!D:D,MATCH(C864&E864,INDEX(Sheet10!A:A&Sheet10!B:B,0),0))} -> D28AP | U864: =VLOOKUP(T864,Sheet10!D:E,2,FALSE) -> Leprosy, Adult - Chronic
A865: =T865 -> D28AP | B865: =U865 -> Leprosy, Adult - Chronic | C865: =MID(F865,6,1) -> 1 | D865: =LEFT(F865,2) -> 28 | E865: =LEFT(F865,5) -> 28753 | F865: 2875319 | G865: Leprosy, Adult | H865: 2482 | I865: 8037060 | J865: 0.51 | K865: 4098901 | L865: 8037060 | M865: 0.51 | N865: 1 | O865: 4098901 | P865: 7147797700 | Q865: 10298607289 | R865: 3150809589 | S865: 0.441 | T865: {=INDEX(Sheet10!D:D,MATCH(C865&E865,INDEX(Sheet10!A:A&Sheet10!B:B,0),0))} -> D28AP | U865: =VLOOKUP(T865,Sheet10!D:E,2,FALSE) -> Leprosy, Adult - Chronic
A866: =T866 -> D28AP | B866: =U866 -> Leprosy, Adult - Chronic | C866: =MID(F866,6,1) -> 1 | D866: =LEFT(F866,2) -> 28 | E866: =LEFT(F866,5) -> 28761 | F866: 2876119 | G866: Leprosy, Child - Chronic | H866: #N/A | I866: 8037060 | J866: 0.5 | K866: 4018530 | L866: 8037060 | M866: 0.5 | N866: 1 | O866: 4018530 | P866: #N/A | Q866: #N/A | R866: #N/A | S866: #N/A | T866: {=INDEX(Sheet10!D:D,MATCH(C866&E866,INDEX(Sheet10!A:A&Sheet10!B:B,0),0))} -> D28AP | U866: =VLOOKUP(T866,Sheet10!D:E,2,FALSE) -> Leprosy, Adult - Chronic
A867: =T867 -> D28AP | B867: =U867 -> Leprosy, Adult - Chronic | C867: =MID(F867,6,1) -> 1 | D867: =LEFT(F867,2) -> 28 | E867: =LEFT(F867,5) -> 28762 | F867: 2876219 | G867: Leprosy, Child - Sub Acute | H867: #N/A | I867: 8037060 | J867: 0.5 | K867: 4018530 | L867: 8037060 | M867: 0.5 | N867: 1 | O867: 4018530 | P867: #N/A | Q867: #N/A | R867: #N/A | S867: #N/A | T867: {=INDEX(Sheet10!D:D,MATCH(C867&E867,INDEX(Sheet10!A:A&Sheet10!B:B,0),0))} -> D28AP | U867: =VLOOKUP(T867,Sheet10!D:E,2,FALSE) -> Leprosy, Adult - Chronic
A868: =T868 -> D28AP | B868: =U868 -> Leprosy, Adult - Chronic | C868: =MID(F868,6,1) -> 1 | D868: =LEFT(F868,2) -> 28 | E868: =LEFT(F868,5) -> 28763 | F868: 2876319 | G868: Leprosy, Child | H868: 151 | I868: 8037060 | J868: 0.5 | K868: 4018530 | L868: 8037060 | M868: 0.5 | N868: 1 | O868: 4018530 | P868: 474539700 | Q868: 612068030 | R868: 137528330 | S868: 0.29 | T868: {=INDEX(Sheet10!D:D,MATCH(C868&E868,INDEX(Sheet10!A:A&Sheet10!B:B,0),0))} -> D28AP | U868: =VLOOKUP(T868,Sheet10!D:E,2,FALSE) -> Leprosy, Adult - Chronic
A869: =T869 -> D29AA | B869: =U869 -> Dementia and Other Organic Disorders - Chronic | C869: =MID(F869,6,1) -> 1 | D869: =LEFT(F869,2) -> 29 | E869: =LEFT(F869,5) -> 29611 | F869: 2961110 | G869: Dementia and Other Organic Disorders - Chronic w/ No CC | H869: 16 | I869: 8037060 | J869: 0.97 | K869: 7795948 | L869: 8037060 | M869: 0.97 | N869: 1 | O869: 7795948 | P869: 364036000 | Q869: 393385371 | R869: 29349371 | S869: 0.081 | T869: {=INDEX(Sheet10!D:D,MATCH(C869&E869,INDEX(Sheet10!A:A&Sheet10!B:B,0),0))} -> D29AA | U869: =VLOOKUP(T869,Sheet10!D:E,2,FALSE) -> Dementia and Other Organic Disorders - Chronic
...

Sheet Sheet10
A1: ptd | B1: dc | C1: dc_name v 3mei | D1: code diag/proc | E1: dc_name v 3mei
A2: 1 | B2: 10011 | C2: Liver Transplant | D2: 00CX | E2: Liver Transplant
A3: 1 | B3: 10011 | C3: Liver Transplant | D3: 0PA | E3: Liver Transplant
A4: 1 | B4: 10021 | C4: Heart-Lung Transplant | D4: 00DX | E4: Heart-Lung Transplant
A5: 1 | B5: 10021 | C5: Heart-Lung Transplant | D5: 0PB | E5: Heart-Lung Transplant
A6: 1 | B6: 10031 | C6: Bone Marrow Transplant | D6: 00EX | E6: Bone Marrow Transplant
A7: 1 | B7: 10031 | C7: Bone Marrow Transplant | D7: 0PD | E7: Bone Marrow Transplant
